Workbook

Sheet 1-产品总表
A1: 1-产品总表
A2: 产品编码 | B2: 类目 | C2: 产品名称 | D2: 图片链接 | E2: SKU | F2: SKU编码 | G2: 上架状态 | H2: 产品文案介绍 | I2: 主材介绍 | J2: 辅材介绍 | K2: 尺寸明细 | L2: 定制范围 | M2: 备注 | N2: 导入校验 | O2: ⚠️问题标注
A3: PPS26330070320 | B3: 卧室-床 | C3: 畔色榉木无边床 |榉木金属腿床 | D3: https://img.alicdn.com/imgextra/i1/2215699812811/O1CN01weGhhJ1WdUTWXDll4_!!2215699812811.jpg | E3: 榉木无边床-1.2米-榉木铺板 | F3: PPS2633007032011 | G3: 在售 | H3: 德国进口AA级榉木：清新木色纹路。拒绝贴皮拒绝甲醛，安心呼吸整夜安睡。 10°床头舒适倾角：一体床架超静音。久靠也舒适，惬意倚靠感。 无边窄体设计：侧边无床沿。大幅拓宽床尾过道，更省空间。 超厚超密床铺板：承重强度MAX。抗弯曲防变形，保护床垫弹簧。 全床静音系统：龙骨静音贴处理。安心翻身无异响，助你好眠。 镜面不锈钢金属腿：0.1mm精度定制。科学力学结构，稳固承托更耐久。 床腿内收设计：避开踢脚线。轻盈不磕碰，床体贴合墙面。 预留透气孔：双排通风设计。防潮透气，床体会"呼吸"。 | I3: 德国进口AA级榉木 | J3: 床铺板：德国进口AA级榉木/新西兰松木；床腿；不锈钢 | K3: 宽度：1200mm；长度：2115mm；高度860 | L3: 床头高度可任意定制；床长度支持1800mm-2500mm定制；床宽度支持1000mm-2200mm定制；超出范围转人工 | M3: . | N3: ✅ 可导入 | O3: ✓
A4: PPS26330070320 | B4: 卧室-床 | C4: 畔色榉木无边床 |榉木金属腿床 | D4: https://img.alicdn.com/imgextra/i1/2215699812811/O1CN01weGhhJ1WdUTWXDll4_!!2215699812811.jpg | E4: 榉木无边床-1.35米-榉木铺板 | F4: PPS2633007032012 | G4: 在售 | H4: 德国进口AA级榉木：清新木色纹路。拒绝贴皮拒绝甲醛，安心呼吸整夜安睡。 10°床头舒适倾角：一体床架超静音。久靠也舒适，惬意倚靠感。 无边窄体设计：侧边无床沿。大幅拓宽床尾过道，更省空间。 超厚超密床铺板：承重强度MAX。抗弯曲防变形，保护床垫弹簧。 全床静音系统：龙骨静音贴处理。安心翻身无异响，助你好眠。 镜面不锈钢金属腿：0.1mm精度定制。科学力学结构，稳固承托更耐久。 床腿内收设计：避开踢脚线。轻盈不磕碰，床体贴合墙面。 预留透气孔：双排通风设计。防潮透气，床体会"呼吸"。 | I4: 德国进口AA级榉木 | J4: 床铺板：德国进口AA级榉木/新西兰松木；床腿；不锈钢 | K4: 宽度：1350mm；长度：2115mm；高度860 | L4: 床头高度可任意定制；床长度支持1800mm-2500mm定制；床宽度支持1000mm-2200mm定制；超出范围转人工 | M4: . | N4: ✅ 可导入 | O4: ✓
A5: PPS26330070320 | B5: 卧室-床 | C5: 畔色榉木无边床 |榉木金属腿床 | D5: https://img.alicdn.com/imgextra/i1/2215699812811/O1CN01weGhhJ1WdUTWXDll4_!!2215699812811.jpg | E5: 榉木无边床-1.5米-榉木铺板 | F5: PPS2633007032013 | G5: 在售 | H5: 德国进口AA级榉木：清新木色纹路。拒绝贴皮拒绝甲醛，安心呼吸整夜安睡。 10°床头舒适倾角：一体床架超静音。久靠也舒适，惬意倚靠感。 无边窄体设计：侧边无床沿。大幅拓宽床尾过道，更省空间。 超厚超密床铺板：承重强度MAX。抗弯曲防变形，保护床垫弹簧。 全床静音系统：龙骨静音贴处理。安心翻身无异响，助你好眠。 镜面不锈钢金属腿：0.1mm精度定制。科学力学结构，稳固承托更耐久。 床腿内收设计：避开踢脚线。轻盈不磕碰，床体贴合墙面。 预留透气孔：双排通风设计。防潮透气，床体会"呼吸"。 | I5: 德国进口AA级榉木 | J5: 床铺板：德国进口AA级榉木/新西兰松木；床腿；不锈钢 | K5: 宽度：1500mm；长度：2115mm；高度860 | L5: 床头高度可任意定制；床长度支持1800mm-2500mm定制；床宽度支持1000mm-2200mm定制；超出范围转人工 | M5: . | N5: ✅ 可导入 | O5: ✓
A6: PPS26330070320 | B6: 卧室-床 | C6: 畔色榉木无边床 |榉木金属腿床 | D6: https://img.alicdn.com/imgextra/i1/2215699812811/O1CN01weGhhJ1WdUTWXDll4_!!2215699812811.jpg | E6: 榉木无边床-1.8米-榉木铺板 | F6: PPS2633007032014 | G6: 在售 | H6: 德国进口AA级榉木：清新木色纹路。拒绝贴皮拒绝甲醛，安心呼吸整夜安睡。 10°床头舒适倾角：一体床架超静音。久靠也舒适，惬意倚靠感。 无边窄体设计：侧边无床沿。大幅拓宽床尾过道，更省空间。 超厚超密床铺板：承重强度MAX。抗弯曲防变形，保护床垫弹簧。 全床静音系统：龙骨静音贴处理。安心翻身无异响，助你好眠。 镜面不锈钢金属腿：0.1mm精度定制。科学力学结构，稳固承托更耐久。 床腿内收设计：避开踢脚线。轻盈不磕碰，床体贴合墙面。 预留透气孔：双排通风设计。防潮透气，床体会"呼吸"。 | I6: 德国进口AA级榉木 | J6: 床铺板：德国进口AA级榉木/新西兰松木；床腿；不锈钢 | K6: 宽度：1800mm；长度：2115mm；高度860 | L6: 床头高度可任意定制；床长度支持1800mm-2500mm定制；床宽度支持1000mm-2200mm定制；超出范围转人工 | N6: ✅ 可导入 | O6: ✓
A7: PPS26330070320 | B7: 卧室-床 | C7: 畔色榉木无边床 |榉木金属腿床 | D7: https://img.alicdn.com/imgextra/i1/2215699812811/O1CN01weGhhJ1WdUTWXDll4_!!2215699812811.jpg | E7: 榉木无边床-1.2米-松木铺板 | F7: PPS2633007032015 | G7: 在售 | H7: 德国进口AA级榉木：清新木色纹路。拒绝贴皮拒绝甲醛，安心呼吸整夜安睡。 10°床头舒适倾角：一体床架超静音。久靠也舒适，惬意倚靠感。 无边窄体设计：侧边无床沿。大幅拓宽床尾过道，更省空间。 超厚超密床铺板：承重强度MAX。抗弯曲防变形，保护床垫弹簧。 全床静音系统：龙骨静音贴处理。安心翻身无异响，助你好眠。 镜面不锈钢金属腿：0.1mm精度定制。科学力学结构，稳固承托更耐久。 床腿内收设计：避开踢脚线。轻盈不磕碰，床体贴合墙面。 预留透气孔：双排通风设计。防潮透气，床体会"呼吸"。 | I7: 德国进口AA级榉木 | J7: 床铺板：德国进口AA级榉木/新西兰松木；床腿；不锈钢 | K7: 宽度：1200mm；长度：2115mm；高度860 | L7: 床头高度可任意定制；床长度支持1800mm-2500mm定制；床宽度支持1000mm-2200mm定制；超出范围转人工 | M7: . | N7: ✅ 可导入 | O7: ✓
A8: PPS26330070320 | B8: 卧室-床 | C8: 畔色榉木无边床 |榉木金属腿床 | D8: https://img.alicdn.com/imgextra/i1/2215699812811/O1CN01weGhhJ1WdUTWXDll4_!!2215699812811.jpg | E8: 榉木无边床-1.35米-松木铺板 | F8: PPS2633007032016 | G8: 在售 | H8: 德国进口AA级榉木：清新木色纹路。拒绝贴皮拒绝甲醛，安心呼吸整夜安睡。 10°床头舒适倾角：一体床架超静音。久靠也舒适，惬意倚靠感。 无边窄体设计：侧边无床沿。大幅拓宽床尾过道，更省空间。 超厚超密床铺板：承重强度MAX。抗弯曲防变形，保护床垫弹簧。 全床静音系统：龙骨静音贴处理。安心翻身无异响，助你好眠。 镜面不锈钢金属腿：0.1mm精度定制。科学力学结构，稳固承托更耐久。 床腿内收设计：避开踢脚线。轻盈不磕碰，床体贴合墙面。 预留透气孔：双排通风设计。防潮透气，床体会"呼吸"。 | I8: 德国进口AA级榉木 | J8: 床铺板：德国进口AA级榉木/新西兰松木；床腿；不锈钢 | K8: 宽度：1350mm；长度：2115mm；高度860 | L8: 床头高度可任意定制；床长度支持1800mm-2500mm定制；床宽度支持1000mm-2200mm定制；超出范围转人工 | M8: . | N8: ✅ 可导入 | O8: ✓
A9: PPS26330070320 | B9: 卧室-床 | C9: 畔色榉木无边床 |榉木金属腿床 | D9: https://img.alicdn.com/imgextra/i1/2215699812811/O1CN01weGhhJ1WdUTWXDll4_!!2215699812811.jpg | E9: 榉木无边床-1.5米-松木铺板 | F9: PPS2633007032017 | G9: 在售 | H9: 德国进口AA级榉木：清新木色纹路。拒绝贴皮拒绝甲醛，安心呼吸整夜安睡。 10°床头舒适倾角：一体床架超静音。久靠也舒适，惬意倚靠感。 无边窄体设计：侧边无床沿。大幅拓宽床尾过道，更省空间。 超厚超密床铺板：承重强度MAX。抗弯曲防变形，保护床垫弹簧。 全床静音系统：龙骨静音贴处理。安心翻身无异响，助你好眠。 镜面不锈钢金属腿：0.1mm精度定制。科学力学结构，稳固承托更耐久。 床腿内收设计：避开踢脚线。轻盈不磕碰，床体贴合墙面。 预留透气孔：双排通风设计。防潮透气，床体会"呼吸"。 | I9: 德国进口AA级榉木 | J9: 床铺板：德国进口AA级榉木/新西兰松木；床腿；不锈钢 | K9: 宽度：1500mm；长度：2115mm；高度860 | L9: 床头高度可任意定制；床长度支持1800mm-2500mm定制；床宽度支持1000mm-2200mm定制；超出范围转人工 | M9: . | N9: ✅ 可导入 | O9: ✓
A10: PPS26330070320 | B10: 卧室-床 | C10: 畔色榉木无边床 |榉木金属腿床 | D10: https://img.alicdn.com/imgextra/i1/2215699812811/O1CN01weGhhJ1WdUTWXDll4_!!2215699812811.jpg | E10: 榉木无边床-1.8米-松木铺板 | F10: PPS2633007032018 | G10: 在售 | H10: 德国进口AA级榉木：清新木色纹路。拒绝贴皮拒绝甲醛，安心呼吸整夜安睡。 10°床头舒适倾角：一体床架超静音。久靠也舒适，惬意倚靠感。 无边窄体设计：侧边无床沿。大幅拓宽床尾过道，更省空间。 超厚超密床铺板：承重强度MAX。抗弯曲防变形，保护床垫弹簧。 全床静音系统：龙骨静音贴处理。安心翻身无异响，助你好眠。 镜面不锈钢金属腿：0.1mm精度定制。科学力学结构，稳固承托更耐久。 床腿内收设计：避开踢脚线。轻盈不磕碰，床体贴合墙面。 预留透气孔：双排通风设计。防潮透气，床体会"呼吸"。 | I10: 德国进口AA级榉木 | J10: 床铺板：德国进口AA级榉木/新西兰松木；床腿；不锈钢 | K10: 宽度：1800mm；长度：2115mm；高度860 | L10: 床头高度可任意定制；床长度支持1800mm-2500mm定制；床宽度支持1000mm-2200mm定制；超出范围转人工 | M10: . | N10: ✅ 可导入 | O10: ✓
A11: PPS26330080322 | B11: 卧室-床 | C11: 畔色榉木柔光双人床 |榉木小灯床 | D11: https://img.alicdn.com/imgextra/i3/2215699812811/O1CN011b8ljX1WdUTWEOKNH_!!2215699812811.jpg | E11: 榉木柔光床-1.2米-榉木铺板 | F11: PPS2633008032211 | G11: 在售 | H11: 德国进口AA级榉木：清新木色纹路。轻盈设计，自然和煦。 柔光磨砂床头灯：微光潺潺。细腻光线流淌，点亮美好夜晚。 悬浮空气感设计：让卧室清新自然。用光线勾勒美好形体。 薄床头设计：卧室空间节省10%。床尾走道宽松，更多收纳空间。 超高落地床头：从头到腰全方位舒适。大板直拼，舒畅木纹。 预设床头灯：轻按即亮。节省床头空间，无线开关位置随心。 360°床体倒圆：无惧磕碰。贴心友好，舒适亲肤。 床底挑空设计：扫地机清扫无忧。通风且清爽，方便打理。 | I11: 德国进口AA级榉木 | J11: 床铺板：德国进口AA级榉木/新西兰松木；床头灯：亚克力 | K11: 宽度：1250mm；长度：2100mm；高度880 | L11: 床头高度可任意定制；床长度支持1800mm-2500mm定制；床宽度支持1000mm-2200mm定制；超出范围转人工 | M11: . | N11: ✅ 可导入 | O11: ✓
A12: PPS26330080322 | B12: 卧室-床 | C12: 畔色榉木柔光双人床 |榉木小灯床 | D12: https://img.alicdn.com/imgextra/i3/2215699812811/O1CN011b8ljX1WdUTWEOKNH_!!2215699812811.jpg | E12: 榉木柔光床-1.35米-榉木铺板 | F12: PPS2633008032212 | G12: 在售 | H12: 德国进口AA级榉木：清新木色纹路。轻盈设计，自然和煦。 柔光磨砂床头灯：微光潺潺。细腻光线流淌，点亮美好夜晚。 悬浮空气感设计：让卧室清新自然。用光线勾勒美好形体。 薄床头设计：卧室空间节省10%。床尾走道宽松，更多收纳空间。 超高落地床头：从头到腰全方位舒适。大板直拼，舒畅木纹。 预设床头灯：轻按即亮。节省床头空间，无线开关位置随心。 360°床体倒圆：无惧磕碰。贴心友好，舒适亲肤。 床底挑空设计：扫地机清扫无忧。通风且清爽，方便打理。 | I12: 德国进口AA级榉木 | J12: 床铺板：德国进口AA级榉木/新西兰松木；床头灯：亚克力 | K12: 宽度：1400mm；长度：2100mm；高度880 | L12: 床头高度可任意定制；床长度支持1800mm-2500mm定制；床宽度支持1000mm-2200mm定制；超出范围转人工 | M12: . | N12: ✅ 可导入 | O12: ✓
A13: PPS26330080322 | B13: 卧室-床 | C13: 畔色榉木柔光双人床 |榉木小灯床 | D13: https://img.alicdn.com/imgextra/i3/2215699812811/O1CN011b8ljX1WdUTWEOKNH_!!2215699812811.jpg | E13: 榉木柔光床-1.5米-榉木铺板 | F13: PPS2633008032213 | G13: 在售 | H13: 德国进口AA级榉木：清新木色纹路。轻盈设计，自然和煦。 柔光磨砂床头灯：微光潺潺。细腻光线流淌，点亮美好夜晚。 悬浮空气感设计：让卧室清新自然。用光线勾勒美好形体。 薄床头设计：卧室空间节省10%。床尾走道宽松，更多收纳空间。 超高落地床头：从头到腰全方位舒适。大板直拼，舒畅木纹。 预设床头灯：轻按即亮。节省床头空间，无线开关位置随心。 360°床体倒圆：无惧磕碰。贴心友好，舒适亲肤。 床底挑空设计：扫地机清扫无忧。通风且清爽，方便打理。 | I13: 德国进口AA级榉木 | J13: 床铺板：德国进口AA级榉木/新西兰松木；床头灯：亚克力 | K13: 宽度：1550mm；长度：2100mm；高度880 | L13: 床头高度可任意定制；床长度支持1800mm-2500mm定制；床宽度支持1000mm-2200mm定制；超出范围转人工 | M13: . | N13: ✅ 可导入 | O13: ✓
A14: PPS26330080322 | B14: 卧室-床 | C14: 畔色榉木柔光双人床 |榉木小灯床 | D14: https://img.alicdn.com/imgextra/i3/2215699812811/O1CN011b8ljX1WdUTWEOKNH_!!2215699812811.jpg | E14: 榉木柔光床-1.8米-榉木铺板 | F14: PPS2633008032214 | G14: 在售 | H14: 德国进口AA级榉木：清新木色纹路。轻盈设计，自然和煦。 柔光磨砂床头灯：微光潺潺。细腻光线流淌，点亮美好夜晚。 悬浮空气感设计：让卧室清新自然。用光线勾勒美好形体。 薄床头设计：卧室空间节省10%。床尾走道宽松，更多收纳空间。 超高落地床头：从头到腰全方位舒适。大板直拼，舒畅木纹。 预设床头灯：轻按即亮。节省床头空间，无线开关位置随心。 360°床体倒圆：无惧磕碰。贴心友好，舒适亲肤。 床底挑空设计：扫地机清扫无忧。通风且清爽，方便打理。 | I14: 德国进口AA级榉木 | J14: 床铺板：德国进口AA级榉木/新西兰松木；床头灯：亚克力 | K14: 宽度：1850mm；长度：2100mm；高度880 | L14: 床头高度可任意定制；床长度支持1800mm-2500mm定制；床宽度支持1000mm-2200mm定制；超出范围转人工 | M14: . | N14: ✅ 可导入 | O14: ✓
A15: PPS26330080322 | B15: 卧室-床 | C15: 畔色榉木柔光双人床 |榉木小灯床 | D15: https://img.alicdn.com/imgextra/i3/2215699812811/O1CN011b8ljX1WdUTWEOKNH_!!2215699812811.jpg | E15: 榉木柔光床-1.2米-松木铺板 | F15: PPS2633008032215 | G15: 在售 | H15: 德国进口AA级榉木：清新木色纹路。轻盈设计，自然和煦。 柔光磨砂床头灯：微光潺潺。细腻光线流淌，点亮美好夜晚。 悬浮空气感设计：让卧室清新自然。用光线勾勒美好形体。 薄床头设计：卧室空间节省10%。床尾走道宽松，更多收纳空间。 超高落地床头：从头到腰全方位舒适。大板直拼，舒畅木纹。 预设床头灯：轻按即亮。节省床头空间，无线开关位置随心。 360°床体倒圆：无惧磕碰。贴心友好，舒适亲肤。 床底挑空设计：扫地机清扫无忧。通风且清爽，方便打理。 | I15: 德国进口AA级榉木 | J15: 床铺板：德国进口AA级榉木/新西兰松木；床头灯：亚克力 | K15: 宽度：1250mm；长度：2100mm；高度880 | L15: 床头高度可任意定制；床长度支持1800mm-2500mm定制；床宽度支持1000mm-2200mm定制；超出范围转人工 | M15: . | N15: ✅ 可导入 | O15: ✓
A16: PPS26330080322 | B16: 卧室-床 | C16: 畔色榉木柔光双人床 |榉木小灯床 | D16: https://img.alicdn.com/imgextra/i3/2215699812811/O1CN011b8ljX1WdUTWEOKNH_!!2215699812811.jpg | E16: 榉木柔光床-1.35米-松木铺板 | F16: PPS2633008032216 | G16: 在售 | H16: 德国进口AA级榉木：清新木色纹路。轻盈设计，自然和煦。 柔光磨砂床头灯：微光潺潺。细腻光线流淌，点亮美好夜晚。 悬浮空气感设计：让卧室清新自然。用光线勾勒美好形体。 薄床头设计：卧室空间节省10%。床尾走道宽松，更多收纳空间。 超高落地床头：从头到腰全方位舒适。大板直拼，舒畅木纹。 预设床头灯：轻按即亮。节省床头空间，无线开关位置随心。 360°床体倒圆：无惧磕碰。贴心友好，舒适亲肤。 床底挑空设计：扫地机清扫无忧。通风且清爽，方便打理。 | I16: 德国进口AA级榉木 | J16: 床铺板：德国进口AA级榉木/新西兰松木；床头灯：亚克力 | K16: 宽度：1400mm；长度：2100mm；高度880 | L16: 床头高度可任意定制；床长度支持1800mm-2500mm定制；床宽度支持1000mm-2200mm定制；超出范围转人工 | M16: . | N16: ✅ 可导入 | O16: ✓
A17: PPS26330080322 | B17: 卧室-床 | C17: 畔色榉木柔光双人床 |榉木小灯床 | D17: https://img.alicdn.com/imgextra/i3/2215699812811/O1CN011b8ljX1WdUTWEOKNH_!!2215699812811.jpg | E17: 榉木柔光床-1.5米-松木铺板 | F17: PPS2633008032217 | G17: 在售 | H17: 德国进口AA级榉木：清新木色纹路。轻盈设计，自然和煦。 柔光磨砂床头灯：微光潺潺。细腻光线流淌，点亮美好夜晚。 悬浮空气感设计：让卧室清新自然。用光线勾勒美好形体。 薄床头设计：卧室空间节省10%。床尾走道宽松，更多收纳空间。 超高落地床头：从头到腰全方位舒适。大板直拼，舒畅木纹。 预设床头灯：轻按即亮。节省床头空间，无线开关位置随心。 360°床体倒圆：无惧磕碰。贴心友好，舒适亲肤。 床底挑空设计：扫地机清扫无忧。通风且清爽，方便打理。 | I17: 德国进口AA级榉木 | J17: 床铺板：德国进口AA级榉木/新西兰松木；床头灯：亚克力 | K17: 宽度：1550mm；长度：2100mm；高度880 | L17: 床头高度可任意定制；床长度支持1800mm-2500mm定制；床宽度支持1000mm-2200mm定制；超出范围转人工 | M17: . | N17: ✅ 可导入 | O17: ✓
A18: PPS26330080322 | B18: 卧室-床 | C18: 畔色榉木柔光双人床 |榉木小灯床 | D18: https://img.alicdn.com/imgextra/i3/2215699812811/O1CN011b8ljX1WdUTWEOKNH_!!2215699812811.jpg | E18: 榉木柔光床-1.8米-松木铺板 | F18: PPS2633008032218 | G18: 在售 | H18: 德国进口AA级榉木：清新木色纹路。轻盈设计，自然和煦。 柔光磨砂床头灯：微光潺潺。细腻光线流淌，点亮美好夜晚。 悬浮空气感设计：让卧室清新自然。用光线勾勒美好形体。 薄床头设计：卧室空间节省10%。床尾走道宽松，更多收纳空间。 超高落地床头：从头到腰全方位舒适。大板直拼，舒畅木纹。 预设床头灯：轻按即亮。节省床头空间，无线开关位置随心。 360°床体倒圆：无惧磕碰。贴心友好，舒适亲肤。 床底挑空设计：扫地机清扫无忧。通风且清爽，方便打理。 | I18: 德国进口AA级榉木 | J18: 床铺板：德国进口AA级榉木/新西兰松木；床头灯：亚克力 | K18: 宽度：1850mm；长度：2100mm；高度880 | L18: 床头高度可任意定制；床长度支持1800mm-2500mm定制；床宽度支持1000mm-2200mm定制；超出范围转人工 | M18: . | N18: ✅ 可导入 | O18: ✓
... A71: PPS26330140117 | B71: 卧室-床 | C71: 畔色黑胡桃木软包双人床 |黑胡桃木落地大软包床 | D71: https://img.alicdn.com/imgextra/i4/2215699812811/O1CN01eDD7Xt1WdUTbnanUa_!!2215699812811.jpg | E71: 黑胡桃木软包床-1.8米-松木铺板 | F71: PPS2633014011718 | G71: 在售 | H71: 北美进口FAS级黑胡桃木：沙发级缓释靠包。重磅用料，SPA级舒睡体验。 丰满灯芯绒面料：温柔厚重抚触感。厚重舒适耐磨抗皱，可机洗。 沙发级填充结构：云般包裹体验。饱满充盈倚靠感，5A级鹅绒。 超高靠背：从腰部到颈部多点支撑。提供多层次缓释支撑。 建筑式块状承托腿：沉稳厚重倍支撑力。全床均匀受力，长久使用不变形。 悬浮感设计：释放卧室呼吸感。床下可储物，视觉通透。 平整车线工艺：线条利落有序。光线下的慵懒色泽，内敛贵族质感。 板式床腿内缩：日常行走不磕碰。全床圆润边角，舒适亲肤。 | I71: 北美进口FAS级黑胡桃木 | J71: 床铺板：德国进口AA级榉木/新西兰松木；床头软包：灯芯绒 | K71: 宽度：1890mm；长度：2270mm；高度880 | L71: 床头高度可任意定制；床长度支持1800mm-2500mm定制；床宽度支持1000mm-2200mm定制；超出范围转人工 | M71: . | N71: ✅ 可导入 | O71: ✓
A72: PPS26330140117 | B72: 卧室-床 | C72: 畔色黑胡桃木软包双人床 |黑胡桃木落地大软包床 | D72: https://img.alicdn.com/imgextra/i4/2215699812811/O1CN01eDD7Xt1WdUTbnanUa_!!2215699812811.jpg | E72: 黑胡桃木榻榻米（无床头）-1.2米-榉木铺板 | F72: PPS2633014011719 | G72: 在售 | H72: 北美进口FAS级黑胡桃木：沙发级缓释靠包。重磅用料，SPA级舒睡体验。 丰满灯芯绒面料：温柔厚重抚触感。厚重舒适耐磨抗皱，可机洗。 沙发级填充结构：云般包裹体验。饱满充盈倚靠感，5A级鹅绒。 超高靠背：从腰部到颈部多点支撑。提供多层次缓释支撑。 建筑式块状承托腿：沉稳厚重倍支撑力。全床均匀受力，长久使用不变形。 悬浮感设计：释放卧室呼吸感。床下可储物，视觉通透。 平整车线工艺：线条利落有序。光线下的慵懒色泽，内敛贵族质感。 板式床腿内缩：日常行走不磕碰。全床圆润边角，舒适亲肤。 | I72: 北美进口FAS级黑胡桃木 | J72: 床铺板：德国进口AA级榉木/新西兰松木；床头软包：灯芯绒 | K72: 宽度：1290mm；长度：2270mm；高度235 | L72: 床头高度可任意定制；床长度支持1800mm-2500mm定制；床宽度支持1000mm-2200mm定制；超出范围转人工 | N72: ✅ 可导入 | O72: ✓
A73: PPS26330140117 | B73: 卧室-床 | C73: 畔色黑胡桃木软包双人床 |黑胡桃木落地大软包床 | D73: https://img.alicdn.com/imgextra/i4/2215699812811/O1CN01eDD7Xt1WdUTbnanUa_!!2215699812811.jpg | E73: 黑胡桃木榻榻米（无床头）-1.35米-榉木铺板 | F73: PPS2633014011720 | G73: 在售 | H73: 北美进口FAS级黑胡桃木：沙发级缓释靠包。重磅用料，SPA级舒睡体验。 丰满灯芯绒面料：温柔厚重抚触感。厚重舒适耐磨抗皱，可机洗。 沙发级填充结构：云般包裹体验。饱满充盈倚靠感，5A级鹅绒。 超高靠背：从腰部到颈部多点支撑。提供多层次缓释支撑。 建筑式块状承托腿：沉稳厚重倍支撑力。全床均匀受力，长久使用不变形。 悬浮感设计：释放卧室呼吸感。床下可储物，视觉通透。 平整车线工艺：线条利落有序。光线下的慵懒色泽，内敛贵族质感。 板式床腿内缩：日常行走不磕碰。全床圆润边角，舒适亲肤。 | I73: 北美进口FAS级黑胡桃木 | J73: 床铺板：德国进口AA级榉木/新西兰松木；床头软包：灯芯绒 | K73: 宽度：1440mm；长度：2270mm；高度235 | L73: 床头高度可任意定制；床长度支持1800mm-2500mm定制；床宽度支持1000mm-2200mm定制；超出范围转人工 | N73: ✅ 可导入 | O73: ✓
A74: PPS26330140117 | B74: 卧室-床 | C74: 畔色黑胡桃木软包双人床 |黑胡桃木落地大软包床 | D74: https://img.alicdn.com/imgextra/i4/2215699812811/O1CN01eDD7Xt1WdUTbnanUa_!!2215699812811.jpg | E74: 黑胡桃木榻榻米（无床头）-1.5米-榉木铺板 | F74: PPS2633014011721 | G74: 在售 | H74: 北美进口FAS级黑胡桃木：沙发级缓释靠包。重磅用料，SPA级舒睡体验。 丰满灯芯绒面料：温柔厚重抚触感。厚重舒适耐磨抗皱，可机洗。 沙发级填充结构：云般包裹体验。饱满充盈倚靠感，5A级鹅绒。 超高靠背：从腰部到颈部多点支撑。提供多层次缓释支撑。 建筑式块状承托腿：沉稳厚重倍支撑力。全床均匀受力，长久使用不变形。 悬浮感设计：释放卧室呼吸感。床下可储物，视觉通透。 平整车线工艺：线条利落有序。光线下的慵懒色泽，内敛贵族质感。 板式床腿内缩：日常行走不磕碰。全床圆润边角，舒适亲肤。 | I74: 北美进口FAS级黑胡桃木 | J74: 床铺板：德国进口AA级榉木/新西兰松木；床头软包：灯芯绒 | K74: 宽度：1590mm；长度：2270mm；高度235 | L74: 床头高度可任意定制；床长度支持1800mm-2500mm定制；床宽度支持1000mm-2200mm定制；超出范围转人工 | N74: ✅ 可导入 | O74: ✓
A75: PPS26330140117 | B75: 卧室-床 | C75: 畔色黑胡桃木软包双人床 |黑胡桃木落地大软包床 | D75: https://img.alicdn.com/imgextra/i4/2215699812811/O1CN01eDD7Xt1WdUTbnanUa_!!2215699812811.jpg | E75: 黑胡桃木榻榻米（无床头）-1.8米-榉木铺板 | F75: PPS2633014011722 | G75: 在售 | H75: 北美进口FAS级黑胡桃木：沙发级缓释靠包。重磅用料，SPA级舒睡体验。 丰满灯芯绒面料：温柔厚重抚触感。厚重舒适耐磨抗皱，可机洗。 沙发级填充结构：云般包裹体验。饱满充盈倚靠感，5A级鹅绒。 超高靠背：从腰部到颈部多点支撑。提供多层次缓释支撑。 建筑式块状承托腿：沉稳厚重倍支撑力。全床均匀受力，长久使用不变形。 悬浮感设计：释放卧室呼吸感。床下可储物，视觉通透。 平整车线工艺：线条利落有序。光线下的慵懒色泽，内敛贵族质感。 板式床腿内缩：日常行走不磕碰。全床圆润边角，舒适亲肤。 | I75: 北美进口FAS级黑胡桃木 | J75: 床铺板：德国进口AA级榉木/新西兰松木；床头软包：灯芯绒 | K75: 宽度：1890mm；长度：2270mm；高度235 | L75: 床头高度可任意定制；床长度支持1800mm-2500mm定制；床宽度支持1000mm-2200mm定制；超出范围转人工 | N75: ✅ 可导入 | O75: ✓
A76: PPS26330150118 | B76: 卧室-床 | C76: 畔色黑胡桃木悬浮双人床 |黑胡桃木标准床 | D76: https://img.alicdn.com/imgextra/i4/2215699812811/O1CN015fCgsq1WdUTgF91sN_!!2215699812811.jpg | E76: 黑胡桃木悬浮床-1.2米-榉木铺板 | F76: PPS2633015011811 | G76: 在售 | H76: 暂无北美进口FAS级黑胡桃木：大板直拼流畅木纹。悬浮空气设计，云端睡卧感。 悬浮透光背板：点亮温馨夜晚。无线开关，无极亮暗调节。 床头预设电力插座：舒适不断线。床头背板可置物，兼具储物功能。 加厚圆墩象腿：强力稳固支撑。建筑式块状承托，沉稳厚重。 悬浮内收床腿：不磕碰。悬浮视感，放大卧室空间。 薄床头设计：卧室空间节省10%。窄体设计，床尾走道宽松。 超高落地床头：从头到腰的整体支撑。大板直拼舒畅木纹。 全床静音系统：安静安心。德国榉木双龙骨，10点支撑。 | I76: 北美进口FAS级黑胡桃木 | J76: 床铺板：德国进口AA级榉木/新西兰松木 | K76: 宽度：1250mm；长度：2100mm；高度950 | L76: 床头高度可任意定制；床长度支持1800mm-2500mm定制；床宽度支持1000mm-2200mm定制；超出范围转人工 | M76: . | N76: ✅ 可导入 | O76: ✓
A77: PPS26330150118 | B77: 卧室-床 | C77: 畔色黑胡桃木悬浮双人床 |黑胡桃木标准床 | D77: https://img.alicdn.com/imgextra/i4/2215699812811/O1CN015fCgsq1WdUTgF91sN_!!2215699812811.jpg | E77: 黑胡桃木悬浮床-1.35米-榉木铺板 | F77: PPS2633015011812 | G77: 在售 | H77: 暂无北美进口FAS级黑胡桃木：大板直拼流畅木纹。悬浮空气设计，云端睡卧感。 悬浮透光背板：点亮温馨夜晚。无线开关，无极亮暗调节。 床头预设电力插座：舒适不断线。床头背板可置物，兼具储物功能。 加厚圆墩象腿：强力稳固支撑。建筑式块状承托，沉稳厚重。 悬浮内收床腿：不磕碰。悬浮视感，放大卧室空间。 薄床头设计：卧室空间节省10%。窄体设计，床尾走道宽松。 超高落地床头：从头到腰的整体支撑。大板直拼舒畅木纹。 全床静音系统：安静安心。德国榉木双龙骨，10点支撑。 | I77: 北美进口FAS级黑胡桃木 | J77: 床铺板：德国进口AA级榉木/新西兰松木 | K77: 宽度：1400mm；长度：2100mm；高度950 | L77: 床头高度可任意定制；床长度支持1800mm-2500mm定制；床宽度支持1000mm-2200mm定制；超出范围转人工 | M77: . | N77: ✅ 可导入 | O77: ✓
A78: PPS26330150118 | B78: 卧室-床 | C78: 畔色黑胡桃木悬浮双人床 |黑胡桃木标准床 | D78: https://img.alicdn.com/imgextra/i4/2215699812811/O1CN015fCgsq1WdUTgF91sN_!!2215699812811.jpg | E78: 黑胡桃木悬浮床-1.5米-榉木铺板 | F78: PPS2633015011813 | G78: 在售 | H78: 暂无北美进口FAS级黑胡桃木：大板直拼流畅木纹。悬浮空气设计，云端睡卧感。 悬浮透光背板：点亮温馨夜晚。无线开关，无极亮暗调节。 床头预设电力插座：舒适不断线。床头背板可置物，兼具储物功能。 加厚圆墩象腿：强力稳固支撑。建筑式块状承托，沉稳厚重。 悬浮内收床腿：不磕碰。悬浮视感，放大卧室空间。 薄床头设计：卧室空间节省10%。窄体设计，床尾走道宽松。 超高落地床头：从头到腰的整体支撑。大板直拼舒畅木纹。 全床静音系统：安静安心。德国榉木双龙骨，10点支撑。 | I78: 北美进口FAS级黑胡桃木 | J78: 床铺板：德国进口AA级榉木/新西兰松木 | K78: 宽度：1550mm；长度：2100mm；高度950 | L78: 床头高度可任意定制；床长度支持1800mm-2500mm定制；床宽度支持1000mm-2200mm定制；超出范围转人工 | M78: . | N78: ✅ 可导入 | O78: ✓
A79: PPS26330150118 | B79: 卧室-床 | C79: 畔色黑胡桃木悬浮双人床 |黑胡桃木标准床 | D79: https://img.alicdn.com/imgextra/i4/2215699812811/O1CN015fCgsq1WdUTgF91sN_!!2215699812811.jpg | E79: 黑胡桃木悬浮床-1.8米-榉木铺板 | F79: PPS2633015011814 | G79: 在售 | H79: 暂无北美进口FAS级黑胡桃木：大板直拼流畅木纹。悬浮空气设计，云端睡卧感。 悬浮透光背板：点亮温馨夜晚。无线开关，无极亮暗调节。 床头预设电力插座：舒适不断线。床头背板可置物，兼具储物功能。 加厚圆墩象腿：强力稳固支撑。建筑式块状承托，沉稳厚重。 悬浮内收床腿：不磕碰。悬浮视感，放大卧室空间。 薄床头设计：卧室空间节省10%。窄体设计，床尾走道宽松。 超高落地床头：从头到腰的整体支撑。大板直拼舒畅木纹。 全床静音系统：安静安心。德国榉木双龙骨，10点支撑。 | I79: 北美进口FAS级黑胡桃木 | J79: 床铺板：德国进口AA级榉木/新西兰松木 | K79: 宽度：1850mm；长度：2100mm；高度950 | L79: 床头高度可任意定制；床长度支持1800mm-2500mm定制；床宽度支持1000mm-2200mm定制；超出范围转人工 | M79: . | N79: ✅ 可导入 | O79: ✓
A80: PPS26330150118 | B80: 卧室-床 | C80: 畔色黑胡桃木悬浮双人床 |黑胡桃木标准床 | D80: https://img.alicdn.com/imgextra/i4/2215699812811/O1CN015fCgsq1WdUTgF91sN_!!2215699812811.jpg | E80: 黑胡桃木悬浮床-1.2米-松木铺板 | F80: PPS2633015011815 | G80: 在售 | H80: 暂无北美进口FAS级黑胡桃木：大板直拼流畅木纹。悬浮空气设计，云端睡卧感。 悬浮透光背板：点亮温馨夜晚。无线开关，无极亮暗调节。 床头预设电力插座：舒适不断线。床头背板可置物，兼具储物功能。 加厚圆墩象腿：强力稳固支撑。建筑式块状承托，沉稳厚重。 悬浮内收床腿：不磕碰。悬浮视感，放大卧室空间。 薄床头设计：卧室空间节省10%。窄体设计，床尾走道宽松。 超高落地床头：从头到腰的整体支撑。大板直拼舒畅木纹。 全床静音系统：安静安心。德国榉木双龙骨，10点支撑。 | I80: 北美进口FAS级黑胡桃木 | J80: 床铺板：德国进口AA级榉木/新西兰松木 | K80: 宽度：1250mm；长度：2100mm；高度950 | L80: 床头高度可任意定制；床长度支持1800mm-2500mm定制；床宽度支持1000mm-2200mm定制；超出范围转人工 | M80: . | N80: ✅ 可导入 | O80: ✓
A81: PPS26330150118 | B81: 卧室-床 | C81: 畔色黑胡桃木悬浮双人床 |黑胡桃木标准床 | D81: https://img.alicdn.com/imgextra/i4/2215699812811/O1CN015fCgsq1WdUTgF91sN_!!2215699812811.jpg | E81: 黑胡桃木悬浮床-1.35米-松木铺板 | F81: PPS2633015011816 | G81: 在售 | H81: 暂无北美进口FAS级黑胡桃木：大板直拼流畅木纹。悬浮空气设计，云端睡卧感。 悬浮透光背板：点亮温馨夜晚。无线开关，无极亮暗调节。 床头预设电力插座：舒适不断线。床头背板可置物，兼具储物功能。 加厚圆墩象腿：强力稳固支撑。建筑式块状承托，沉稳厚重。 悬浮内收床腿：不磕碰。悬浮视感，放大卧室空间。 薄床头设计：卧室空间节省10%。窄体设计，床尾走道宽松。 超高落地床头：从头到腰的整体支撑。大板直拼舒畅木纹。 全床静音系统：安静安心。德国榉木双龙骨，10点支撑。 | I81: 北美进口FAS级黑胡桃木 | J81: 床铺板：德国进口AA级榉木/新西兰松木 | K81: 宽度：1400mm；长度：2100mm；高度950 | L81: 床头高度可任意定制；床长度支持1800mm-2500mm定制；床宽度支持1000mm-2200mm定制；超出范围转人工 | M81: . | N81: ✅ 可导入 | O81: ✓
A82: PPS26330150118 | B82: 卧室-床 | C82: 畔色黑胡桃木悬浮双人床 |黑胡桃木标准床 | D82: https://img.alicdn.com/imgextra/i4/2215699812811/O1CN015fCgsq1WdUTgF91sN_!!2215699812811.jpg | E82: 黑胡桃木悬浮床-1.5米-松木铺板 | F82: PPS2633015011817 | G82: 在售 | H82: 暂无北美进口FAS级黑胡桃木：大板直拼流畅木纹。悬浮空气设计，云端睡卧感。 悬浮透光背板：点亮温馨夜晚。无线开关，无极亮暗调节。 床头预设电力插座：舒适不断线。床头背板可置物，兼具储物功能。 加厚圆墩象腿：强力稳固支撑。建筑式块状承托，沉稳厚重。 悬浮内收床腿：不磕碰。悬浮视感，放大卧室空间。 薄床头设计：卧室空间节省10%。窄体设计，床尾走道宽松。 超高落地床头：从头到腰的整体支撑。大板直拼舒畅木纹。 全床静音系统：安静安心。德国榉木双龙骨，10点支撑。 | I82: 北美进口FAS级黑胡桃木 | J82: 床铺板：德国进口AA级榉木/新西兰松木 | K82: 宽度：1550mm；长度：2100mm；高度950 | L82: 床头高度可任意定制；床长度支持1800mm-2500mm定制；床宽度支持1000mm-2200mm定制；超出范围转人工 | M82: . | N82: ✅ 可导入 | O82: ✓
A83: PPS26330150118 | B83: 卧室-床 | C83: 畔色黑胡桃木悬浮双人床 |黑胡桃木标准床 | D83: https://img.alicdn.com/imgextra/i4/2215699812811/O1CN015fCgsq1WdUTgF91sN_!!2215699812811.jpg | E83: 黑胡桃木悬浮床-1.8米-松木铺板 | F83: PPS2633015011818 | G83: 在售 | H83: 暂无北美进口FAS级黑胡桃木：大板直拼流畅木纹。悬浮空气设计，云端睡卧感。 悬浮透光背板：点亮温馨夜晚。无线开关，无极亮暗调节。 床头预设电力插座：舒适不断线。床头背板可置物，兼具储物功能。 加厚圆墩象腿：强力稳固支撑。建筑式块状承托，沉稳厚重。 悬浮内收床腿：不磕碰。悬浮视感，放大卧室空间。 薄床头设计：卧室空间节省10%。窄体设计，床尾走道宽松。 超高落地床头：从头到腰的整体支撑。大板直拼舒畅木纹。 全床静音系统：安静安心。德国榉木双龙骨，10点支撑。 | I83: 北美进口FAS级黑胡桃木 | J83: 床铺板：德国进口AA级榉木/新西兰松木 | K83: 宽度：1850mm；长度：2100mm；高度950 | L83: 床头高度可任意定制；床长度支持1800mm-2500mm定制；床宽度支持1000mm-2200mm定制；超出范围转人工 | M83: . | N83: ✅ 可导入 | O83: ✓
A84: PPS26380040225 | B84: 卧室-床头柜 | C84: 畔色榉木床头柜 |榉木铁板床头柜 | D84: https://img.alicdn.com/imgextra/i1/2215699812811/O1CN01v4u1KN1WdUTcaGHb9_!!2215699812811.jpg | E84: 榉木床头柜-标准 | F84: PPS2638004022511 | G84: 在售 | H84: 德国进口AA级榉木：清新木色纹路。整柜原木拒绝贴皮，安心呼吸整夜安睡。 细腻美耐板台面：耐高温防指纹。脏污好清理，划痕可修复随心用。 宽窄双尺寸可选：灵活搭配各种空间。窄体设计留出卧室空间，衣柜开门顺畅。 边缘立耳设计：防止物件掉落。超宽置物台面，手机书籍安稳放置。 开放式收纳层：一目了然清爽抽板。不抽开也能拿，日用小物伸手可得。 大容量下抽：超大体积囤货无忧。书籍耳机纸巾面膜，分类收纳井井有条。 按压式抽屉面板：不弯腰也好开。随心开合方便自在，自吸静音底轨。 背板内收设计：轻松理线。后部走线孔，排插放置位预留。 柜体全落地：轻松免打扫。全柜圆润倒角，舒适亲肤磕碰无忧。 预留踢脚线位：方便贴墙。严丝合缝不藏垢，美观实用。 | I84: 德国进口AA级榉木 | K84: 长度：450mm 深度：400mm 高度：420mm | L84: 长度可任意定制；高度不可定制；深度不可定制 | M84: . | N84: ✅ 可导入 | O84: ✓
A85: PPS26380040225 | B85: 卧室-床头柜 | C85: 畔色榉木床头柜 |榉木铁板床头柜 | D85: https://img.alicdn.com/imgextra/i1/2215699812811/O1CN01v4u1KN1WdUTcaGHb9_!!2215699812811.jpg | E85: 榉木床头柜-窄款 | F85: PPS2638004022512 | G85: 在售 | H85: 德国进口AA级榉木：清新木色纹路。整柜原木拒绝贴皮，安心呼吸整夜安睡。 细腻美耐板台面：耐高温防指纹。脏污好清理，划痕可修复随心用。 宽窄双尺寸可选：灵活搭配各种空间。窄体设计留出卧室空间，衣柜开门顺畅。 边缘立耳设计：防止物件掉落。超宽置物台面，手机书籍安稳放置。 开放式收纳层：一目了然清爽抽板。不抽开也能拿，日用小物伸手可得。 大容量下抽：超大体积囤货无忧。书籍耳机纸巾面膜，分类收纳井井有条。 按压式抽屉面板：不弯腰也好开。随心开合方便自在，自吸静音底轨。 背板内收设计：轻松理线。后部走线孔，排插放置位预留。 柜体全落地：轻松免打扫。全柜圆润倒角，舒适亲肤磕碰无忧。 预留踢脚线位：方便贴墙。严丝合缝不藏垢，美观实用。 | I85: 德国进口AA级榉木 | K85: 长度：450mm 深度：400mm 高度：420mm | L85: 长度可任意定制；高度不可定制；深度不可定制 | M85: . | N85: ✅ 可导入 | O85: ✓
A86: PPS26380050301 | B86: 卧室-床头柜 | C86: 畔色樱桃木轻盈边柜 |樱桃木玻璃床头柜 |黑色玻璃床头柜 |樱桃木玻璃边柜 | D86: https://img.alicdn.com/imgextra/i4/2215699812811/O1CN01aV7b7w1WdUTd0Dctr_!!2215699812811.jpg | E86: 轻盈边柜-榉木黑-木底座 | F86: PPS2638005030111 | G86: 在售 | H86: 北美进口FAS级樱桃木：温润木色流畅纹路。整柜原木纹理细腻，自然和煦。 12mm超厚钢化玻璃台面：安全无虞。防冲击耐高温，晶莹透亮让光线自由呼吸。 长虹玻璃侧板：光影交织美学设计。空气感线条，光与影的浪漫在时刻中隽永驻留。 双层式置物设计：开放取物不拘束。躺着也好拿，日用小物伸手可得。 条块镂空底板：光线潺潺倾泻而下。分层收纳条理分明，插线板可隐藏轻松理线。 迷人夜灯：亮度无极可调。一键点亮光影艺术，潺潺微光静谧美梦相伴。 一体式钢化台面：清爽利落方便置物。台面玻璃倒圆，无惧磕碰亲肤好用。 侧边预留走线间隙：桌面更清爽。充电更便捷，告别杂乱线材。 背后预留踢脚线位：方便贴墙。高度刚刚好，随手放置很方便。 | I86: 德国进口AA级榉木 | J86: 侧板：玻璃 | K86: 长度：430mm 深度：510mm 高度：460mm | L86: 长度可任意定制；深度可任意定制；高度可任意定制； | M86: . | N86: ✅ 可导入 | O86: ✓
A87: PPS26380050301 | B87: 卧室-床头柜 | C87: 畔色樱桃木轻盈边柜 |樱桃木玻璃床头柜 |黑色玻璃床头柜 |樱桃木玻璃边柜 | D87: https://img.alicdn.com/imgextra/i4/2215699812811/O1CN01aV7b7w1WdUTd0Dctr_!!2215699812811.jpg | E87: 轻盈边柜-樱桃木-木底座 | F87: PPS2638005030112 | G87: 在售 | H87: 北美进口FAS级樱桃木：温润木色流畅纹路。整柜原木纹理细腻，自然和煦。 12mm超厚钢化玻璃台面：安全无虞。防冲击耐高温，晶莹透亮让光线自由呼吸。 长虹玻璃侧板：光影交织美学设计。空气感线条，光与影的浪漫在时刻中隽永驻留。 双层式置物设计：开放取物不拘束。躺着也好拿，日用小物伸手可得。 条块镂空底板：光线潺潺倾泻而下。分层收纳条理分明，插线板可隐藏轻松理线。 迷人夜灯：亮度无极可调。一键点亮光影艺术，潺潺微光静谧美梦相伴。 一体式钢化台面：清爽利落方便置物。台面玻璃倒圆，无惧磕碰亲肤好用。 侧边预留走线间隙：桌面更清爽。充电更便捷，告别杂乱线材。 背后预留踢脚线位：方便贴墙。高度刚刚好，随手放置很方便。 | I87: 北美进口FAS级樱桃木 | J87: 侧板：玻璃 | K87: 长度：430mm 深度：510mm 高度：460mm | L87: 长度可任意定制；深度可任意定制；高度可任意定制； | M87: . | N87: ✅ 可导入 | O87: ✓
A88: PPS26380050301 | B88: 卧室-床头柜 | C88: 畔色樱桃木轻盈边柜 |樱桃木玻璃床头柜 |黑色玻璃床头柜 |樱桃木玻璃边柜 | D88: https://img.alicdn.com/imgextra/i4/2215699812811/O1CN01aV7b7w1WdUTd0Dctr_!!2215699812811.jpg | E88: 轻盈边柜-黑胡桃木-木底座 | F88: PPS2638005030113 | G88: 在售 | H88: 北美进口FAS级樱桃木：温润木色流畅纹路。整柜原木纹理细腻，自然和煦。 12mm超厚钢化玻璃台面：安全无虞。防冲击耐高温，晶莹透亮让光线自由呼吸。 长虹玻璃侧板：光影交织美学设计。空气感线条，光与影的浪漫在时刻中隽永驻留。 双层式置物设计：开放取物不拘束。躺着也好拿，日用小物伸手可得。 条块镂空底板：光线潺潺倾泻而下。分层收纳条理分明，插线板可隐藏轻松理线。 迷人夜灯：亮度无极可调。一键点亮光影艺术，潺潺微光静谧美梦相伴。 一体式钢化台面：清爽利落方便置物。台面玻璃倒圆，无惧磕碰亲肤好用。 侧边预留走线间隙：桌面更清爽。充电更便捷，告别杂乱线材。 背后预留踢脚线位：方便贴墙。高度刚刚好，随手放置很方便。 | I88: 北美进口FAS级黑胡桃木 | J88: 侧板：玻璃 | K88: 长度：430mm 深度：510mm 高度：460mm | L88: 长度可任意定制；深度可任意定制；高度可任意定制； | M88: . | N88: ✅ 可导入 | O88: ✓
A89: PPS26380050301 | B89: 卧室-床头柜 | C89: 畔色樱桃木轻盈边柜 |樱桃木玻璃床头柜 |黑色玻璃床头柜 |樱桃木玻璃边柜 | D89: https://img.alicdn.com/imgextra/i4/2215699812811/O1CN01aV7b7w1WdUTd0Dctr_!!2215699812811.jpg | E89: 轻盈边柜-榉木黑-玻璃底座 | F89: PPS2638005030114 | G89: 在售 | H89: 北美进口FAS级樱桃木：温润木色流畅纹路。整柜原木纹理细腻，自然和煦。 12mm超厚钢化玻璃台面：安全无虞。防冲击耐高温，晶莹透亮让光线自由呼吸。 长虹玻璃侧板：光影交织美学设计。空气感线条，光与影的浪漫在时刻中隽永驻留。 双层式置物设计：开放取物不拘束。躺着也好拿，日用小物伸手可得。 条块镂空底板：光线潺潺倾泻而下。分层收纳条理分明，插线板可隐藏轻松理线。 迷人夜灯：亮度无极可调。一键点亮光影艺术，潺潺微光静谧美梦相伴。 一体式钢化台面：清爽利落方便置物。台面玻璃倒圆，无惧磕碰亲肤好用。 侧边预留走线间隙：桌面更清爽。充电更便捷，告别杂乱线材。 背后预留踢脚线位：方便贴墙。高度刚刚好，随手放置很方便。 | I89: 德国进口AA级榉木 | J89: 侧板：玻璃 | K89: 长度：430mm 深度：510mm 高度：460mm | L89: 长度可任意定制；深度可任意定制；高度可任意定制； | M89: . | N89: ✅ 可导入 | O89: ✓
A90: PPS26380050301 | B90: 卧室-床头柜 | C90: 畔色樱桃木轻盈边柜 |樱桃木玻璃床头柜 |黑色玻璃床头柜 |樱桃木玻璃边柜 | D90: https://img.alicdn.com/imgextra/i4/2215699812811/O1CN01aV7b7w1WdUTd0Dctr_!!2215699812811.jpg | E90: 轻盈边柜-樱桃木-玻璃底座 | F90: PPS2638005030115 | G90: 在售 | H90: 北美进口FAS级樱桃木：温润木色流畅纹路。整柜原木纹理细腻，自然和煦。 12mm超厚钢化玻璃台面：安全无虞。防冲击耐高温，晶莹透亮让光线自由呼吸。 长虹玻璃侧板：光影交织美学设计。空气感线条，光与影的浪漫在时刻中隽永驻留。 双层式置物设计：开放取物不拘束。躺着也好拿，日用小物伸手可得。 条块镂空底板：光线潺潺倾泻而下。分层收纳条理分明，插线板可隐藏轻松理线。 迷人夜灯：亮度无极可调。一键点亮光影艺术，潺潺微光静谧美梦相伴。 一体式钢化台面：清爽利落方便置物。台面玻璃倒圆，无惧磕碰亲肤好用。 侧边预留走线间隙：桌面更清爽。充电更便捷，告别杂乱线材。 背后预留踢脚线位：方便贴墙。高度刚刚好，随手放置很方便。 | I90: 北美进口FAS级樱桃木 | J90: 侧板：玻璃 | K90: 长度：430mm 深度：510mm 高度：460mm | L90: 长度可任意定制；深度可任意定制；高度可任意定制； | M90: . | N90: ✅ 可导入 | O90: ✓
A91: PPS26380050301 | B91: 卧室-床头柜 | C91: 畔色樱桃木轻盈边柜 |樱桃木玻璃床头柜 |黑色玻璃床头柜 |樱桃木玻璃边柜 | D91: https://img.alicdn.com/imgextra/i4/2215699812811/O1CN01aV7b7w1WdUTd0Dctr_!!2215699812811.jpg | E91: 轻盈边柜-黑胡桃木-玻璃底座 | F91: PPS2638005030116 | G91: 在售 | H91: 北美进口FAS级樱桃木：温润木色流畅纹路。整柜原木纹理细腻，自然和煦。 12mm超厚钢化玻璃台面：安全无虞。防冲击耐高温，晶莹透亮让光线自由呼吸。 长虹玻璃侧板：光影交织美学设计。空气感线条，光与影的浪漫在时刻中隽永驻留。 双层式置物设计：开放取物不拘束。躺着也好拿，日用小物伸手可得。 条块镂空底板：光线潺潺倾泻而下。分层收纳条理分明，插线板可隐藏轻松理线。 迷人夜灯：亮度无极可调。一键点亮光影艺术，潺潺微光静谧美梦相伴。 一体式钢化台面：清爽利落方便置物。台面玻璃倒圆，无惧磕碰亲肤好用。 侧边预留走线间隙：桌面更清爽。充电更便捷，告别杂乱线材。 背后预留踢脚线位：方便贴墙。高度刚刚好，随手放置很方便。 | I91: 北美进口FAS级黑胡桃木 | J91: 侧板：玻璃 | K91: 长度：430mm 深度：510mm 高度：460mm | L91: 长度可任意定制；深度可任意定制；高度可任意定制； | M91: . | N91: ✅ 可导入 | O91: ✓
A92: PPS26390070315 | B92: 卧室-床头柜 | C92: 畔色樱桃木床头窄柜 | 樱桃木窄床头柜 | D92: https://img.alicdn.com/imgextra/i3/2215699812811/O1CN01Iuil5d1WdUTXCr2Tl_!!2215699812811.jpg | E92: 樱桃木床头窄柜-标准宽度 | F92: PPS2639007031511 | G92: 在售 | H92: 北美进口FAS级樱桃木：温润木色流畅纹路。整柜原木天然纹理，温润细腻。 超窄设计：留出床边大空间。窄身床头柜小空间专属，台面大深度置物无忧。 双抽分区收纳：上层日常小物轻松取放。下抽囤货随心储放，收纳井井有条。 一体式实木台面：清爽利落方便置物。摒弃繁杂线条，台面浑然一体。 定制拉手：丝滑省力。轻巧设计，舒适握感。 随取随用：合适高度的台面。美的恰好，温雅床头气质。 背板内收设计：轻松理线。后部走线孔，背板内收避让插座。 排插放置位预留：线材有序台面清爽。预留走线槽，告别杂乱。 底部高空间：扫地机清扫无忧。清洁无死角，方便打理。 全柜圆润倒角：舒适亲肤磕碰无忧。边缘温润，安心使用。 预留踢脚线位：方便贴墙。畔色柜30cm，衣柜开门顺畅抽屉可用。 | I92: 北美进口FAS级樱桃木 | J92: 把手：不锈钢 | K92: 长度：340mm 深度：400mm 高度：480mm | L92: 长度可任意定制；深度可任意定制；高度可任意定制； | M92: . | N92: ✅ 可导入 | O92: ✓
A93: PPS26380060320 | B93: 卧室-床头柜 | C93: 畔色黑胡桃木床头柜 |黑胡桃木岩板床头柜 | D93: https://img.alicdn.com/imgextra/i2/2215699812811/O1CN01m01PAA1WdUTaTRZji_!!2215699812811.jpg | E93: 黑胡桃木床头柜-岩板台面 | F93: PPS2638006032011 | G93: 在售 | H93: 北美进口FAS级黑胡桃木：雅致纹理。在时光隽永中印刻，天然纹理温润细腻。 细腻岩板台面：耐用随心用。防刮擦易清理，耐高温热水壶也好放。 雕刻柜门：细腻抚触感。精致工艺，雅致美学设计。 磁吸拉门：精致镜面拉手。一体式开门设计，单手操作轻松取放。 内设隔板：小物分区收纳。一体收纳系统，分类储物井井有条。 边缘围栏设计：防止物件掉落。台面大深度置物无忧，物品安稳放置。 悬浮底座：预留踢脚线位。底部高空间，扫地机友好。 背板内收设计：轻松理线。后部走线孔，排插放置位预留。 预留走线槽：线材有序台面清爽。告别杂乱，美观实用。 全柜圆润倒角：舒适亲肤磕碰无忧。一体式台面清爽利落方便置物。 定制镜面把手：省力好用。质感出众，细节贴心。 | I93: 北美进口FAS级黑胡桃木 | J93: 把手：不锈钢 | K93: 长度：450mm 深度：400mm 高度：450mm | L93: 长度可任意定制；深度可任意定制；高度可任意定制； | M93: . | N93: ✅ 可导入 | O93: ✓
A94: PPS26380060320 | B94: 卧室-床头柜 | C94: 畔色黑胡桃木床头柜 |黑胡桃木岩板床头柜 | D94: https://img.alicdn.com/imgextra/i2/2215699812811/O1CN01m01PAA1WdUTaTRZji_!!2215699812811.jpg | E94: 黑胡桃木床头柜-木台面 | F94: PPS2638006032012 | G94: 在售 | H94: 北美进口FAS级黑胡桃木：雅致纹理。在时光隽永中印刻，天然纹理温润细腻。 细腻岩板台面：耐用随心用。防刮擦易清理，耐高温热水壶也好放。 雕刻柜门：细腻抚触感。精致工艺，雅致美学设计。 磁吸拉门：精致镜面拉手。一体式开门设计，单手操作轻松取放。 内设隔板：小物分区收纳。一体收纳系统，分类储物井井有条。 边缘围栏设计：防止物件掉落。台面大深度置物无忧，物品安稳放置。 悬浮底座：预留踢脚线位。底部高空间，扫地机友好。 背板内收设计：轻松理线。后部走线孔，排插放置位预留。 预留走线槽：线材有序台面清爽。告别杂乱，美观实用。 全柜圆润倒角：舒适亲肤磕碰无忧。一体式台面清爽利落方便置物。 定制镜面把手：省力好用。质感出众，细节贴心。 | I94: 北美进口FAS级黑胡桃木 | J94: 把手：不锈钢 | K94: 长度：450mm 深度：400mm 高度：450mm | L94: 长度可任意定制；深度可任意定制；高度可任意定制； | M94: . | N94: ✅ 可导入 | O94: ✓
A95: PPS25250090401 | B95: 餐厅-柜 | C95: 樱桃木基础餐边柜 |樱桃木AA柱餐边柜下柜 | D95: https://img.alicdn.com/imgextra/i4/2215699812811/O1CN01f4ih2H1WdUTjPeRt9_!!2215699812811.jpg | E95: 基础柜-下柜-2.1米-无轨道 | F95: PPS2525009040111 | G95: 下架 | H95: 北美进口FAS级樱桃木：精选进口全实木。温润细腻，氧化后更具复古韵味。 12mm防水岩板台面：质感出众耐高温。清爽利落，通长设计无接缝。 IP54级防水电力轨道：安全检测认证。插座左右位移，独立断电无忧使用。 88cm黄金台面高度：不弯腰操作。轻松直立，舒适烹饪体验。 超大收纳容量：容量升级45%。分类抽屉+移门柜，储物空间满满。 预留踢脚线位：方便贴墙。电线方便穿出，严丝合缝不藏垢。 清爽柜底设计：扫地机进出自如。无尘才安心，日常轻松打理。 | I95: 北美进口FAS级樱桃木 | J95: 抽屉围板：实木多层板 台面：12mm岩板 内部赠送层板：实木多层板 电力轨道：xpower 内嵌电力轨道 | K95: 整体长度：2100mm 整体深度：480mm 整体高度：880mm | L95: 长度可任意定制；深度可任意定制；高度支持920mm内定制 | M95: . | N95: ✅ 可导入 | O95: ✓
A96: PPS25250090401 | B96: 餐厅-柜 | C96: 樱桃木基础餐边柜 |樱桃木AA柱餐边柜下柜 | D96: https://img.alicdn.com/imgextra/i4/2215699812811/O1CN01f4ih2H1WdUTjPeRt9_!!2215699812811.jpg | E96: 基础柜-下柜-1.8米-无轨道 | F96: PPS2525009040112 | G96: 下架 | H96: 北美进口FAS级樱桃木：精选进口全实木。温润细腻，氧化后更具复古韵味。 12mm防水岩板台面：质感出众耐高温。清爽利落，通长设计无接缝。 IP54级防水电力轨道：安全检测认证。插座左右位移，独立断电无忧使用。 88cm黄金台面高度：不弯腰操作。轻松直立，舒适烹饪体验。 超大收纳容量：容量升级45%。分类抽屉+移门柜，储物空间满满。 预留踢脚线位：方便贴墙。电线方便穿出，严丝合缝不藏垢。 清爽柜底设计：扫地机进出自如。无尘才安心，日常轻松打理。 | I96: 北美进口FAS级樱桃木 | J96: 抽屉围板：实木多层板 台面：12mm岩板 内部赠送层板：实木多层板 电力轨道：xpower 内嵌电力轨道 | K96: 整体长度：1800mm 整体深度：480mm 整体高度：880mm | L96: 长度可任意定制；深度可任意定制；高度支持920mm内定制 | M96: . | N96: ✅ 可导入 | O96: ✓
A97: PPS25250090401 | B97: 餐厅-柜 | C97: 樱桃木基础餐边柜 |樱桃木AA柱餐边柜下柜 | D97: https://img.alicdn.com/imgextra/i4/2215699812811/O1CN01f4ih2H1WdUTjPeRt9_!!2215699812811.jpg | E97: 基础柜-下柜-1.5米-无轨道 | F97: PPS2525009040113 | G97: 下架 | H97: 北美进口FAS级樱桃木：精选进口全实木。温润细腻，氧化后更具复古韵味。 12mm防水岩板台面：质感出众耐高温。清爽利落，通长设计无接缝。 IP54级防水电力轨道：安全检测认证。插座左右位移，独立断电无忧使用。 88cm黄金台面高度：不弯腰操作。轻松直立，舒适烹饪体验。 超大收纳容量：容量升级46%。分类抽屉+移门柜，储物空间满满。 预留踢脚线位：方便贴墙。电线方便穿出，严丝合缝不藏垢。 清爽柜底设计：扫地机进出自如。无尘才安心，日常轻松打理。 | I97: 北美进口FAS级樱桃木 | J97: 抽屉围板：实木多层板 台面：12mm岩板 内部赠送层板：实木多层板 电力轨道：xpower 内嵌电力轨道 | K97: 整体长度：1500mm 整体深度：480mm 整体高度：880mm | L97: 长度可任意定制；深度可任意定制；高度支持920mm内定制 | M97: . | N97: ✅ 可导入 | O97: ✓
A98: PPS25250090401 | B98: 餐厅-柜 | C98: 樱桃木基础餐边柜 |樱桃木AA柱餐边柜下柜 | D98: https://img.alicdn.com/imgextra/i4/2215699812811/O1CN01f4ih2H1WdUTjPeRt9_!!2215699812811.jpg | E98: 基础柜-下柜-1.2米-无轨道 | F98: PPS2525009040114 | G98: 下架 | H98: 北美进口FAS级樱桃木：精选进口全实木。温润细腻，氧化后更具复古韵味。 12mm防水岩板台面：质感出众耐高温。清爽利落，通长设计无接缝。 IP54级防水电力轨道：安全检测认证。插座左右位移，独立断电无忧使用。 88cm黄金台面高度：不弯腰操作。轻松直立，舒适烹饪体验。 超大收纳容量：容量升级47%。分类抽屉+移门柜，储物空间满满。 预留踢脚线位：方便贴墙。电线方便穿出，严丝合缝不藏垢。 清爽柜底设计：扫地机进出自如。无尘才安心，日常轻松打理。 | I98: 北美进口FAS级樱桃木 | J98: 抽屉围板：实木多层板 台面：12mm岩板 内部赠送层板：实木多层板 电力轨道：xpower 内嵌电力轨道 | K98: 整体长度：1200mm 整体深度：480mm 整体高度：880mm | L98: 长度可任意定制；深度可任意定制；高度支持920mm内定制 | M98: . | N98: ✅ 可导入 | O98: ✓
A99: PPS25250090401 | B99: 餐厅-柜 | C99: 樱桃木基础餐边柜 |樱桃木AA柱餐边柜下柜 | D99: https://img.alicdn.com/imgextra/i4/2215699812811/O1CN01f4ih2H1WdUTjPeRt9_!!2215699812811.jpg | E99: 基础柜-下柜-2.1米-带电力轨道 | F99: PPS2525009040115 | G99: 下架 | H99: 北美进口FAS级樱桃木：精选进口全实木。温润细腻，氧化后更具复古韵味。 12mm防水岩板台面：质感出众耐高温。清爽利落，通长设计无接缝。 IP54级防水电力轨道：安全检测认证。插座左右位移，独立断电无忧使用。 88cm黄金台面高度：不弯腰操作。轻松直立，舒适烹饪体验。 超大收纳容量：容量升级48%。分类抽屉+移门柜，储物空间满满。 预留踢脚线位：方便贴墙。电线方便穿出，严丝合缝不藏垢。 清爽柜底设计：扫地机进出自如。无尘才安心，日常轻松打理。 | I99: 北美进口FAS级樱桃木 | J99: 抽屉围板：实木多层板 台面：12mm岩板 内部赠送层板：实木多层板 电力轨道：xpower 内嵌电力轨道 | K99: 整体长度：2100mm 整体深度：480mm 整体高度：880mm | L99: 长度可任意定制；深度可任意定制；高度支持920mm内定制 | N99: ✅ 可导入 | O99: ✓
A100: PPS25250090401 | B100: 餐厅-柜 | C100: 樱桃木基础餐边柜 |樱桃木AA柱餐边柜下柜 | D100: https://img.alicdn.com/imgextra/i4/2215699812811/O1CN01f4ih2H1WdUTjPeRt9_!!2215699812811.jpg | E100: 基础柜-下柜-1.8米-带电力轨道 | F100: PPS2525009040116 | G100: 下架 | H100: 北美进口FAS级樱桃木：精选进口全实木。温润细腻，氧化后更具复古韵味。 12mm防水岩板台面：质感出众耐高温。清爽利落，通长设计无接缝。 IP54级防水电力轨道：安全检测认证。插座左右位移，独立断电无忧使用。 88cm黄金台面高度：不弯腰操作。轻松直立，舒适烹饪体验。 超大收纳容量：容量升级49%。分类抽屉+移门柜，储物空间满满。 预留踢脚线位：方便贴墙。电线方便穿出，严丝合缝不藏垢。 清爽柜底设计：扫地机进出自如。无尘才安心，日常轻松打理。 | I100: 北美进口FAS级樱桃木 | J100: 抽屉围板：实木多层板 台面：12mm岩板 内部赠送层板：实木多层板 电力轨道：xpower 内嵌电力轨道 | K100: 整体长度：1800mm 整体深度：480mm 整体高度：880mm | L100: 长度可任意定制；深度可任意定制；高度支持920mm内定制 | N100: ✅ 可导入 | O100: ✓
A101: PPS25250090401 | B101: 餐厅-柜 | C101: 樱桃木基础餐边柜 |樱桃木AA柱餐边柜下柜 | D101: https://img.alicdn.com/imgextra/i4/2215699812811/O1CN01f4ih2H1WdUTjPeRt9_!!2215699812811.jpg | E101: 基础柜-下柜-1.5米-带电力轨道 | F101: PPS2525009040117 | G101: 下架 | H101: 北美进口FAS级樱桃木：精选进口全实木。温润细腻，氧化后更具复古韵味。 12mm防水岩板台面：质感出众耐高温。清爽利落，通长设计无接缝。 IP54级防水电力轨道：安全检测认证。插座左右位移，独立断电无忧使用。 88cm黄金台面高度：不弯腰操作。轻松直立，舒适烹饪体验。 超大收纳容量：容量升级50%。分类抽屉+移门柜，储物空间满满。 预留踢脚线位：方便贴墙。电线方便穿出，严丝合缝不藏垢。 清爽柜底设计：扫地机进出自如。无尘才安心，日常轻松打理。 | I101: 北美进口FAS级樱桃木 | J101: 抽屉围板：实木多层板 台面：12mm岩板 内部赠送层板：实木多层板 电力轨道：xpower 内嵌电力轨道 | K101: 整体长度：1500mm 整体深度：480mm 整体高度：880mm | L101: 长度可任意定制；深度可任意定制；高度支持920mm内定制 | N101: ✅ 可导入 | O101: ✓
A102: PPS25250090401 | B102: 餐厅-柜 | C102: 樱桃木基础餐边柜 |樱桃木AA柱餐边柜下柜 | D102: https://img.alicdn.com/imgextra/i4/2215699812811/O1CN01f4ih2H1WdUTjPeRt9_!!2215699812811.jpg | E102: 基础柜-下柜-1.2米-带电力轨道 | F102: PPS2525009040118 | G102: 下架 | H102: 北美进口FAS级樱桃木：精选进口全实木。温润细腻，氧化后更具复古韵味。 12mm防水岩板台面：质感出众耐高温。清爽利落，通长设计无接缝。 IP54级防水电力轨道：安全检测认证。插座左右位移，独立断电无忧使用。 88cm黄金台面高度：不弯腰操作。轻松直立，舒适烹饪体验。 超大收纳容量：容量升级51%。分类抽屉+移门柜，储物空间满满。 预留踢脚线位：方便贴墙。电线方便穿出，严丝合缝不藏垢。 清爽柜底设计：扫地机进出自如。无尘才安心，日常轻松打理。 | I102: 北美进口FAS级樱桃木 | J102: 抽屉围板：实木多层板 台面：12mm岩板 内部赠送层板：实木多层板 电力轨道：xpower 内嵌电力轨道 | K102: 整体长度：1200mm 整体深度：480mm 整体高度：880mm | L102: 长度可任意定制；深度可任意定制；高度支持920mm内定制 | N102: ✅ 可导入 | O102: ✓
A103: PPS25250090403 | B103: 餐厅-柜 | C103: 樱桃木基础餐边柜 |樱桃木AA柱餐边柜 | D103: https://img.alicdn.com/imgextra/i2/2215699812811/O1CN01JuK2F31WdUOrID1Wc_!!2215699812811.jpg | E103: 基础柜-整柜AA柱背板-2.1米 | F103: PPS2525009040111 | G103: 在售 | H103: 北美FAS级樱桃木：精选进口大板直拼。色泽温润，随时间氧化愈发优雅。 AA柱模块化背板：自由移动式收纳。配件左右滑动随心DIY，适配不同场景。 右上角实木卷帘门柜：上下滑动极具特色。不占空间且防尘，开合更优雅灵动。 耐高温砂白洞石台面：自带天然艺术呼吸感。防刮耐磨易打理，打造居家咖啡吧。 科学阶梯式分区布局：涵盖卷帘柜、台面、抽屉与柜体。杯盏家电各归其位。 全圆润打磨倒角：纯手工细腻处理。触感丝滑不硌手，全方位守护家人安全。 | I103: 北美进口FAS级樱桃木 | J103: 抽屉围板：实木多层板 台面：12mm岩板 背板：实木多层板（AA柱）/亚克力洞洞板 内部赠送层板：实木多层板 电力轨道：xpower 内嵌电力轨道 顶柜玻璃：灰玻 | K103: 整体长度：2100mm 整体深度：480mm 整体高度：1980mm 顶柜长度：2100mm 顶柜深度：300mm 顶柜高度：490mm 立体收纳长度：2100mm 立体收纳深度：300mm 立体收纳高度：610mm 下柜长度：2100mm 下柜深度：480mm 下柜高度：880mm | L103: 长度可任意定制；深度可任意定制；高度可任意定制； | M103: . | N103: ✅ 可导入 | O103: ✓
A104: PPS25250090403 | B104: 餐厅-柜 | C104: 樱桃木基础餐边柜 |樱桃木AA柱餐边柜 | D104: https://img.alicdn.com/imgextra/i2/2215699812811/O1CN01JuK2F31WdUOrID1Wc_!!2215699812811.jpg | E104: 基础柜-整柜AA柱背板-1.8米 | F104: PPS2525009040112 | G104: 在售 | H104: 北美FAS级樱桃木：精选进口大板直拼。色泽温润，随时间氧化愈发优雅。 AA柱模块化背板：自由移动式收纳。配件左右滑动随心DIY，适配不同场景。 右上角实木卷帘门柜：上下滑动极具特色。不占空间且防尘，开合更优雅灵动。 耐高温砂白洞石台面：自带天然艺术呼吸感。防刮耐磨易打理，打造居家咖啡吧。 科学阶梯式分区布局：涵盖卷帘柜、台面、抽屉与柜体。杯盏家电各归其位。 全圆润打磨倒角：纯手工细腻处理。触感丝滑不硌手，全方位守护家人安全。 | I104: 北美进口FAS级樱桃木 | J104: 抽屉围板：实木多层板 台面：12mm岩板 背板：实木多层板（AA柱）/亚克力洞洞板 内部赠送层板：实木多层板 电力轨道：xpower 内嵌电力轨道 顶柜玻璃：灰玻 | K104: 整体长度：1800mm 整体深度：480mm 整体高度：1980mm 顶柜长度：1800mm 顶柜深度：300mm 顶柜高度：490mm 立体收纳长度：1800mm 立体收纳深度：300mm 立体收纳高度：610mm 下柜长度：1800mm 下柜深度：480mm 下柜高度：880mm | L104: 长度可任意定制；深度可任意定制；高度可任意定制； | M104: . | N104: ✅ 可导入 | O104: ✓
A105: PPS25250090403 | B105: 餐厅-柜 | C105: 樱桃木基础餐边柜 |樱桃木AA柱餐边柜 | D105: https://img.alicdn.com/imgextra/i2/2215699812811/O1CN01JuK2F31WdUOrID1Wc_!!2215699812811.jpg | E105: 基础柜-整柜AA柱背板-1.5米 | F105: PPS2525009040113 | G105: 在售 | H105: 北美FAS级樱桃木：精选进口大板直拼。色泽温润，随时间氧化愈发优雅。 AA柱模块化背板：自由移动式收纳。配件左右滑动随心DIY，适配不同场景。 右上角实木卷帘门柜：上下滑动极具特色。不占空间且防尘，开合更优雅灵动。 耐高温砂白洞石台面：自带天然艺术呼吸感。防刮耐磨易打理，打造居家咖啡吧。 科学阶梯式分区布局：涵盖卷帘柜、台面、抽屉与柜体。杯盏家电各归其位。 全圆润打磨倒角：纯手工细腻处理。触感丝滑不硌手，全方位守护家人安全。 | I105: 北美进口FAS级樱桃木 | J105: 抽屉围板：实木多层板 台面：12mm岩板 背板：实木多层板（AA柱）/亚克力洞洞板 内部赠送层板：实木多层板 电力轨道：xpower 内嵌电力轨道 顶柜玻璃：灰玻 | K105: 整体长度：1500mm 整体深度：480mm 整体高度：1980mm 顶柜长度：1500mm 顶柜深度：300mm 顶柜高度：490mm 立体收纳长度：1500mm 立体收纳深度：300mm 立体收纳高度：610mm 下柜长度：1500mm 下柜深度：480mm 下柜高度：880mm | L105: 长度可任意定制；深度可任意定制；高度可任意定制； | M105: . | N105: ✅ 可导入 | O105: ✓
A106: PPS25250090403 | B106: 餐厅-柜 | C106: 樱桃木基础餐边柜 |樱桃木AA柱餐边柜 | D106: https://img.alicdn.com/imgextra/i2/2215699812811/O1CN01JuK2F31WdUOrID1Wc_!!2215699812811.jpg | E106: 基础柜-整柜AA柱背板-1.2米 | F106: PPS2525009040114 | G106: 在售 | H106: 北美FAS级樱桃木：精选进口大板直拼。色泽温润，随时间氧化愈发优雅。 AA柱模块化背板：自由移动式收纳。配件左右滑动随心DIY，适配不同场景。 右上角实木卷帘门柜：上下滑动极具特色。不占空间且防尘，开合更优雅灵动。 耐高温砂白洞石台面：自带天然艺术呼吸感。防刮耐磨易打理，打造居家咖啡吧。 科学阶梯式分区布局：涵盖卷帘柜、台面、抽屉与柜体。杯盏家电各归其位。 全圆润打磨倒角：纯手工细腻处理。触感丝滑不硌手，全方位守护家人安全。 | I106: 北美进口FAS级樱桃木 | J106: 抽屉围板：实木多层板 台面：12mm岩板 背板：实木多层板（AA柱）/亚克力洞洞板 内部赠送层板：实木多层板 电力轨道：xpower 内嵌电力轨道 顶柜玻璃：灰玻 | K106: 整体长度：1200mm 整体深度：480mm 整体高度：1980mm 顶柜长度：1200mm 顶柜深度：300mm 顶柜高度：490mm 立体收纳长度：1200mm 立体收纳深度：300mm 立体收纳高度：610mm 下柜长度：1200mm 下柜深度：480mm 下柜高度：880mm | L106: 长度可任意定制；深度可任意定制；高度可任意定制； | M106: . | N106: ✅ 可导入 | O106: ✓
A107: PPS25250090403 | B107: 餐厅-柜 | C107: 樱桃木基础餐边柜 |樱桃木AA柱餐边柜 | D107: https://img.alicdn.com/imgextra/i2/2215699812811/O1CN01JuK2F31WdUOrID1Wc_!!2215699812811.jpg | E107: 基础柜-整柜洞洞板背板-2.1米 | F107: PPS2525009040115 | G107: 在售 | H107: 北美FAS级樱桃木：精选进口大板直拼。色泽温润，随时间氧化愈发优雅。 AA柱模块化背板：自由移动式收纳。配件左右滑动随心DIY，适配不同场景。 右上角实木卷帘门柜：上下滑动极具特色。不占空间且防尘，开合更优雅灵动。 耐高温砂白洞石台面：自带天然艺术呼吸感。防刮耐磨易打理，打造居家咖啡吧。 科学阶梯式分区布局：涵盖卷帘柜、台面、抽屉与柜体。杯盏家电各归其位。 全圆润打磨倒角：纯手工细腻处理。触感丝滑不硌手，全方位守护家人安全。 | I107: 北美进口FAS级樱桃木 | J107: 抽屉围板：实木多层板 台面：12mm岩板 背板：实木多层板（AA柱）/亚克力洞洞板 内部赠送层板：实木多层板 电力轨道：xpower 内嵌电力轨道 顶柜玻璃：灰玻 | K107: 整体长度：2100mm 整体深度：480mm 整体高度：1980mm 顶柜长度：2100mm 顶柜深度：300mm 顶柜高度：490mm 立体收纳长度：2100mm 立体收纳深度：300mm 立体收纳高度：610mm 下柜长度：2100mm 下柜深度：480mm 下柜高度：880mm | L107: 长度可任意定制；深度可任意定制；高度可任意定制； | M107: . | N107: ✅ 可导入 | O107: ✓
A108: PPS25250090403 | B108: 餐厅-柜 | C108: 樱桃木基础餐边柜 |樱桃木AA柱餐边柜 | D108: https://img.alicdn.com/imgextra/i2/2215699812811/O1CN01JuK2F31WdUOrID1Wc_!!2215699812811.jpg | E108: 基础柜-整柜洞洞板背板-1.8米 | F108: PPS2525009040116 | G108: 在售 | H108: 北美FAS级樱桃木：精选进口大板直拼。色泽温润，随时间氧化愈发优雅。 AA柱模块化背板：自由移动式收纳。配件左右滑动随心DIY，适配不同场景。 右上角实木卷帘门柜：上下滑动极具特色。不占空间且防尘，开合更优雅灵动。 耐高温砂白洞石台面：自带天然艺术呼吸感。防刮耐磨易打理，打造居家咖啡吧。 科学阶梯式分区布局：涵盖卷帘柜、台面、抽屉与柜体。杯盏家电各归其位。 全圆润打磨倒角：纯手工细腻处理。触感丝滑不硌手，全方位守护家人安全。 | I108: 北美进口FAS级樱桃木 | J108: 抽屉围板：实木多层板 台面：12mm岩板 背板：实木多层板（AA柱）/亚克力洞洞板 内部赠送层板：实木多层板 电力轨道：xpower 内嵌电力轨道 顶柜玻璃：灰玻 | K108: 整体长度：1800mm 整体深度：480mm 整体高度：1980mm 顶柜长度：1800mm 顶柜深度：300mm 顶柜高度：490mm 立体收纳长度：1800mm 立体收纳深度：300mm 立体收纳高度：610mm 下柜长度：1800mm 下柜深度：480mm 下柜高度：880mm | L108: 长度可任意定制；深度可任意定制；高度可任意定制； | M108: . | N108: ✅ 可导入 | O108: ✓
A109: PPS25250090403 | B109: 餐厅-柜 | C109: 樱桃木基础餐边柜 |樱桃木AA柱餐边柜 | D109: https://img.alicdn.com/imgextra/i2/2215699812811/O1CN01JuK2F31WdUOrID1Wc_!!2215699812811.jpg | E109: 基础柜-整柜洞洞板背板-1.5米 | F109: PPS2525009040117 | G109: 在售 | H109: 北美FAS级樱桃木：精选进口大板直拼。色泽温润，随时间氧化愈发优雅。 AA柱模块化背板：自由移动式收纳。配件左右滑动随心DIY，适配不同场景。 右上角实木卷帘门柜：上下滑动极具特色。不占空间且防尘，开合更优雅灵动。 耐高温砂白洞石台面：自带天然艺术呼吸感。防刮耐磨易打理，打造居家咖啡吧。 科学阶梯式分区布局：涵盖卷帘柜、台面、抽屉与柜体。杯盏家电各归其位。 全圆润打磨倒角：纯手工细腻处理。触感丝滑不硌手，全方位守护家人安全。 | I109: 北美进口FAS级樱桃木 | J109: 抽屉围板：实木多层板 台面：12mm岩板 背板：实木多层板（AA柱）/亚克力洞洞板 内部赠送层板：实木多层板 电力轨道：xpower 内嵌电力轨道 顶柜玻璃：灰玻 | K109: 整体长度：1500mm 整体深度：480mm 整体高度：1980mm 顶柜长度：1500mm 顶柜深度：300mm 顶柜高度：490mm 立体收纳长度：1500mm 立体收纳深度：300mm 立体收纳高度：610mm 下柜长度：1500mm 下柜深度：480mm 下柜高度：880mm | L109: 长度可任意定制；深度可任意定制；高度可任意定制； | M109: . | N109: ✅ 可导入 | O109: ✓
A110: PPS25250090403 | B110: 餐厅-柜 | C110: 樱桃木基础餐边柜 |樱桃木AA柱餐边柜 | D110: https://img.alicdn.com/imgextra/i2/2215699812811/O1CN01JuK2F31WdUOrID1Wc_!!2215699812811.jpg | E110: 基础柜-整柜洞洞板背板-1.2米 | F110: PPS2525009040118 | G110: 在售 | H110: 北美FAS级樱桃木：精选进口大板直拼。色泽温润，随时间氧化愈发优雅。 AA柱模块化背板：自由移动式收纳。配件左右滑动随心DIY，适配不同场景。 右上角实木卷帘门柜：上下滑动极具特色。不占空间且防尘，开合更优雅灵动。 耐高温砂白洞石台面：自带天然艺术呼吸感。防刮耐磨易打理，打造居家咖啡吧。 科学阶梯式分区布局：涵盖卷帘柜、台面、抽屉与柜体。杯盏家电各归其位。 全圆润打磨倒角：纯手工细腻处理。触感丝滑不硌手，全方位守护家人安全。 | I110: 北美进口FAS级樱桃木 | J110: 抽屉围板：实木多层板 台面：12mm岩板 背板：实木多层板（AA柱）/亚克力洞洞板 内部赠送层板：实木多层板 电力轨道：xpower 内嵌电力轨道 顶柜玻璃：灰玻 | K110: 整体长度：1200mm 整体深度：480mm 整体高度：1980mm 顶柜长度：1200mm 顶柜深度：300mm 顶柜高度：490mm 立体收纳长度：1200mm 立体收纳深度：300mm 立体收纳高度：610mm 下柜长度：1200mm 下柜深度：480mm 下柜高度：880mm | L110: 长度可任意定制；深度可任意定制；高度可任意定制； | M110: . | N110: ✅ 可导入 | O110: ✓
A111: PPS25250100405 | B111: 餐厅-柜 | C111: 樱桃木窄柜 |樱桃木1米餐边柜 | D111: https://img.alicdn.com/imgextra/i2/2215699812811/O1CN015zkqb51WdUOfdHLdz_!!2215699812811.jpg | E111: 窄柜-整柜洞石背板-1.2米 | F111: PPS2525010040511 | G111: 在售 | H111: 北美FAS级樱桃木：进口全实木，质感细腻顺滑，自然美感。 极致面宽缝隙大师：40cm面宽，完美嵌入墙缝转角，榨干空间。 上展下储科学分区：开放格配大抽屉，海量收纳，杂物隐形。 隐藏斜切拉手：极简无拉手，防磕碰更美观，有娃家庭首选。 典雅木腿设计：紧贴墙面避开踢脚线，稳固承重，无卫生死角。 | I111: 北美进口FAS级樱桃木 | J111: 抽屉围板：新西兰松木 台面：洞石岩板 背板：洞石纹理背板 电力轨道：xpower 内嵌电力轨道 顶柜玻璃：超透玻璃 | K111: 整体长度：1200mm 整体深度：450mm 整体高度：1900mm 顶柜长度：1200mm 顶柜深度：400mm 顶柜高度：325mm 立体收纳长度：1200mm 立体收纳深度：400mm 立体收纳高度：655mm 下柜长度：1200mm 下柜深度：450mm 下柜高度：910mm | L111: 长度可任意定制；深度可任意定制；高度可任意定制； | M111: . | N111: ✅ 可导入 | O111: ✓
A112: PPS25250100405 | B112: 餐厅-柜 | C112: 樱桃木窄柜 |樱桃木1米餐边柜 | D112: https://img.alicdn.com/imgextra/i2/2215699812811/O1CN015zkqb51WdUOfdHLdz_!!2215699812811.jpg | E112: 窄柜-整柜洞石背板-1.0米 | F112: PPS2525010040512 | G112: 在售 | H112: 北美FAS级樱桃木：进口全实木，质感细腻顺滑，自然美感。 极致面宽缝隙大师：40cm面宽，完美嵌入墙缝转角，榨干空间。 上展下储科学分区：开放格配大抽屉，海量收纳，杂物隐形。 隐藏斜切拉手：极简无拉手，防磕碰更美观，有娃家庭首选。 典雅木腿设计：紧贴墙面避开踢脚线，稳固承重，无卫生死角。 | I112: 北美进口FAS级樱桃木 | J112: 抽屉围板：新西兰松木 台面：洞石岩板 背板：洞石纹理背板 电力轨道：xpower 内嵌电力轨道 顶柜玻璃：超透玻璃 | K112: 整体长度：1000mm 整体深度：450mm 整体高度：1900mm 顶柜长度：1000mm 顶柜深度：400mm 顶柜高度：325mm 立体收纳长度：1000mm 立体收纳深度：400mm 立体收纳高度：655mm 下柜长度：1000mm 下柜深度：450mm 下柜高度：910mm | L112: 长度可任意定制；深度可任意定制；高度可任意定制； | M112: . | N112: ✅ 可导入 | O112: ✓
A113: PPS25250100405 | B113: 餐厅-柜 | C113: 樱桃木窄柜 |樱桃木1米餐边柜 | D113: https://img.alicdn.com/imgextra/i2/2215699812811/O1CN015zkqb51WdUOfdHLdz_!!2215699812811.jpg | E113: 窄柜-整柜洞石背板-0.8米 | F113: PPS2525010040513 | G113: 在售 | H113: 北美FAS级樱桃木：进口全实木，质感细腻顺滑，自然美感。 极致面宽缝隙大师：40cm面宽，完美嵌入墙缝转角，榨干空间。 上展下储科学分区：开放格配大抽屉，海量收纳，杂物隐形。 隐藏斜切拉手：极简无拉手，防磕碰更美观，有娃家庭首选。 典雅木腿设计：紧贴墙面避开踢脚线，稳固承重，无卫生死角。 | I113: 北美进口FAS级樱桃木 | J113: 抽屉围板：新西兰松木 台面：洞石岩板 背板：洞石纹理背板 电力轨道：xpower 内嵌电力轨道 顶柜玻璃：超透玻璃 | K113: 整体长度：800mm 整体深度：450mm 整体高度：1900mm 顶柜长度：800mm 顶柜深度：400mm 顶柜高度：325mm 立体收纳长度：800mm 立体收纳深度：400mm 立体收纳高度：655mm 下柜长度：800mm 下柜深度：450mm 下柜高度：910mm | L113: 长度可任意定制；深度可任意定制；高度可任意定制； | M113: . | N113: ✅ 可导入 | O113: ✓
A114: PPS25250100405 | B114: 餐厅-柜 | C114: 樱桃木窄柜 |樱桃木1米餐边柜 | D114: https://img.alicdn.com/imgextra/i2/2215699812811/O1CN015zkqb51WdUOfdHLdz_!!2215699812811.jpg | E114: 窄柜-整柜洞洞板背板-1.2米 | F114: PPS2525010040514 | G114: 在售 | H114: 北美FAS级樱桃木：进口全实木，质感细腻顺滑，自然美感。 极致面宽缝隙大师：40cm面宽，完美嵌入墙缝转角，榨干空间。 上展下储科学分区：开放格配大抽屉，海量收纳，杂物隐形。 隐藏斜切拉手：极简无拉手，防磕碰更美观，有娃家庭首选。 典雅木腿设计：紧贴墙面避开踢脚线，稳固承重，无卫生死角。 | I114: 北美进口FAS级樱桃木 | J114: 抽屉围板：新西兰松木 台面：洞石岩板 背板：洞石纹理背板 电力轨道：xpower 内嵌电力轨道 顶柜玻璃：超透玻璃 | K114: 整体长度：1200mm 整体深度：450mm 整体高度：1900mm 顶柜长度：1200mm 顶柜深度：400mm 顶柜高度：325mm 立体收纳长度：1200mm 立体收纳深度：400mm 立体收纳高度：655mm 下柜长度：1200mm 下柜深度：450mm 下柜高度：910mm | L114: 长度可任意定制；深度可任意定制；高度可任意定制； | M114: . | N114: ✅ 可导入 | O114: ✓
... A256: PPS24410040513 | B256: 书房-桌 | C256: 升降桌（基础款） |樱桃木2024款新升降桌 | D256: https://img.alicdn.com/imgextra/i4/2215699812811/O1CN01y0Uow81WdULVKW60U_!!2215699812811.jpg | E256: 升降桌-190*75cm 基础版，无高台，无置物架，无木腿 | F256: PPS2441004051318 | G256: 在售 | H256: 北美FAS级樱桃木：精选进口全实木。温润细腻，氧化后更具韵味。 双电机高效升降：静音平稳不晃动。升降快速，无惧繁重摆件。 20mm厚实桌板：用料考究稳固。边缘斜切处理，视觉轻薄灵动。 全圆润打磨倒角：纯手工细腻处理。触感丝滑，守护家人孩童安全。 底部清爽高留空：入座自在局促。扫地机穿行无阻，清洁无死角。 母婴级环保标准：天然植物木蜡油。零甲醛无异味，健康安心即买即用。 | I256: 北美进口FAS级樱桃木 | J256: 抽屉围板：实木多层板 升降支架：重机械级冷轧钢 桌腿包围：北美进口FAS级樱桃木 增高架：北美进口FAS级樱桃木 | K256: 升降桌1.9米基础版-长度：1900mm 升降桌1.9米基础版-深度：750mm 升降桌1.9米基础版-高度：1260mm | L256: 长度支持2000mm内定制；深度可任意定制；高度最高1260mm； | M256: . | N256: ✅ 可导入 | O256: ✓
A257: PPS24410040513 | B257: 书房-桌 | C257: 升降桌（基础款） |樱桃木2024款新升降桌 | D257: https://img.alicdn.com/imgextra/i4/2215699812811/O1CN01y0Uow81WdULVKW60U_!!2215699812811.jpg | E257: 升降桌-单独桌腿木料 | F257: PPS2441004051319 | G257: 在售 | H257: 北美FAS级樱桃木：精选进口全实木。温润细腻，氧化后更具韵味。 双电机高效升降：静音平稳不晃动。升降快速，无惧繁重摆件。 20mm厚实桌板：用料考究稳固。边缘斜切处理，视觉轻薄灵动。 全圆润打磨倒角：纯手工细腻处理。触感丝滑，守护家人孩童安全。 底部清爽高留空：入座自在局促。扫地机穿行无阻，清洁无死角。 母婴级环保标准：天然植物木蜡油。零甲醛无异味，健康安心即买即用。 | I257: 北美进口FAS级樱桃木 | J257: 抽屉围板：实木多层板 升降支架：重机械级冷轧钢 桌腿包围：北美进口FAS级樱桃木 增高架：北美进口FAS级樱桃木 | K257: / | M257: . | N257: ✅ 可导入 | O257: ✓
A258: PPS23140010915 | B258: 客厅-茶几 | C258: 榉木茶几 | D258: 暂无 | E258: 榉木茶几-0.8米 | F258: PPS2314001091511 | G258: 在售 | H258: 暂无 | I258: 暂无 | J258: 暂无 | K258: 暂无 | M258: . | N258: ✅ 可导入 | O258: ✓
A259: PPS23140010915 | B259: 客厅-茶几 | C259: 榉木茶几 | D259: 暂无 | E259: 榉木茶几-1米 | F259: PPS2314001091512 | G259: 在售 | H259: 暂无 | I259: 暂无 | J259: 暂无 | K259: 暂无 | M259: . | N259: ✅ 可导入 | O259: ✓
A260: PPS24350011005 | B260: 卧室-柜 | C260: 衣柜 | D260: 暂无 | E260: 衣柜-实木门款-1.5米 | F260: PPS2435001100511 | G260: 在售 | H260: 暂无 | I260: 暂无 | J260: 暂无 | K260: 暂无 | M260: . | N260: ✅ 可导入 | O260: ✓
A261: PPS24350011005 | B261: 卧室-柜 | C261: 衣柜 | D261: 暂无 | E261: 衣柜-实木门款-1米 | F261: PPS2435001100512 | G261: 在售 | H261: 暂无 | I261: 暂无 | J261: 暂无 | K261: 暂无 | M261: . | N261: ✅ 可导入 | O261: ✓
A262: PPS24350011005 | B262: 卧室-柜 | C262: 衣柜 | D262: 暂无 | E262: 衣柜-实木门款-0.75米 | F262: PPS2435001100513 | G262: 在售 | H262: 暂无 | I262: 暂无 | J262: 暂无 | K262: 暂无 | M262: . | N262: ✅ 可导入 | O262: ✓
A263: PPS24350011005 | B263: 卧室-柜 | C263: 衣柜 | D263: 暂无 | E263: 衣柜-玻璃门款-1.5米 | F263: PPS2435001100514 | G263: 在售 | H263: 暂无 | I263: 暂无 | J263: 暂无 | K263: 暂无 | M263: . | N263: ✅ 可导入 | O263: ✓
A264: PPS24350011005 | B264: 卧室-柜 | C264: 衣柜 | D264: 暂无 | E264: 衣柜-玻璃门款-1米 | F264: PPS2435001100515 | G264: 在售 | H264: 暂无 | I264: 暂无 | J264: 暂无 | K264: 暂无 | M264: . | N264: ✅ 可导入 | O264: ✓
A265: PPS24350011005 | B265: 卧室-柜 | C265: 衣柜 | D265: 暂无 | E265: 衣柜-玻璃门款-0.75米 | F265: PPS2435001100516 | G265: 在售 | H265: 暂无 | I265: 暂无 | J265: 暂无 | K265: 暂无 | M265: . | N265: ✅ 可导入 | O265: ✓
A266: PPS24350011005 | B266: 卧室-柜 | C266: 衣柜 | D266: 暂无 | E266: 衣柜-配件-隔板 | F266: PPS2435001100517 | G266: 在售 | H266: 暂无 | I266: 暂无 | J266: 暂无 | K266: 暂无 | M266: . | N266: ✅ 可导入 | O266: ✓
A267: PPS24350011005 | B267: 卧室-柜 | C267: 衣柜 | D267: 暂无 | E267: 衣柜-配件-宜家篮筐 | F267: PPS2435001100518 | G267: 在售 | H267: 暂无 | I267: 暂无 | J267: 暂无 | K267: 暂无 | M267: . | N267: ✅ 可导入 | O267: ✓
A268: PPS24210040513 | B268: 餐厅-桌 | C268: 畔色实木餐桌 3cm桌面 |樱桃木老款实木餐桌 |樱桃木轻盈餐桌air | D268: https://img.alicdn.com/imgextra/i2/2215699812811/O1CN01jncdaQ1WdUIn9Wtal_!!2215699812811.jpg | E268: 实木餐桌-120cm | F268: PPS2421004051311 | G268: 在售 | H268: 空气悬浮感设计：视觉轻盈灵动。打破笨重感，适配多种家装风格。 北美FAS级全实木：精选进口樱桃木。质感温润细腻，随时间更具韵味。 20mm厚实桌板：用料考究。边缘自然斜切，轻薄而不失稳固。 全圆润打磨倒角：纯手工细腻处理。触感丝滑，守护家人孩童安全。 内收式桌腿布局：增加腿部活动空间。入座自在，扫地机穿行无阻。 母婴级环保标准：天然植物木蜡油。零甲醛无异味，健康安心即买即用。 | I268: 北美进口FAS级樱桃木 | J268: 无辅材 | K268: 长度：1200mm 宽度：850mm 高度：750mm | L268: 长度支持2300mm内定制；深度可任意定制；高度支持850mm内定制 | M268: . | N268: ✅ 可导入 | O268: ✓
A269: PPS24210040513 | B269: 餐厅-桌 | C269: 畔色实木餐桌 3cm桌面 |樱桃木老款实木餐桌 |樱桃木轻盈餐桌air | D269: https://img.alicdn.com/imgextra/i2/2215699812811/O1CN01jncdaQ1WdUIn9Wtal_!!2215699812811.jpg | E269: 实木餐桌-140cm | F269: PPS2421004051312 | G269: 在售 | H269: 空气悬浮感设计：视觉轻盈灵动。打破笨重感，适配多种家装风格。 北美FAS级全实木：精选进口樱桃木。质感温润细腻，随时间更具韵味。 20mm厚实桌板：用料考究。边缘自然斜切，轻薄而不失稳固。 全圆润打磨倒角：纯手工细腻处理。触感丝滑，守护家人孩童安全。 内收式桌腿布局：增加腿部活动空间。入座自在，扫地机穿行无阻。 母婴级环保标准：天然植物木蜡油。零甲醛无异味，健康安心即买即用。 | I269: 北美进口FAS级樱桃木 | J269: 无辅材 | K269: 长度：1400mm 宽度：850mm 高度：750mm | L269: 长度支持2300mm内定制；深度可任意定制；高度支持850mm内定制 | M269: . | N269: ✅ 可导入 | O269: ✓
A270: PPS24210040513 | B270: 餐厅-桌 | C270: 畔色实木餐桌 3cm桌面 |樱桃木老款实木餐桌 |樱桃木轻盈餐桌air | D270: https://img.alicdn.com/imgextra/i2/2215699812811/O1CN01jncdaQ1WdUIn9Wtal_!!2215699812811.jpg | E270: 实木餐桌-160cm | F270: PPS2421004051313 | G270: 在售 | H270: 空气悬浮感设计：视觉轻盈灵动。打破笨重感，适配多种家装风格。 北美FAS级全实木：精选进口樱桃木。质感温润细腻，随时间更具韵味。 20mm厚实桌板：用料考究。边缘自然斜切，轻薄而不失稳固。 全圆润打磨倒角：纯手工细腻处理。触感丝滑，守护家人孩童安全。 内收式桌腿布局：增加腿部活动空间。入座自在，扫地机穿行无阻。 母婴级环保标准：天然植物木蜡油。零甲醛无异味，健康安心即买即用。 | I270: 北美进口FAS级樱桃木 | J270: 无辅材 | K270: 长度：1600mm 宽度：850mm 高度：750mm | L270: 长度支持2300mm内定制；深度可任意定制；高度支持850mm内定制 | M270: . | N270: ✅ 可导入 | O270: ✓
A271: PPS24210040513 | B271: 餐厅-桌 | C271: 畔色实木餐桌 3cm桌面 |樱桃木老款实木餐桌 |樱桃木轻盈餐桌air | D271: https://img.alicdn.com/imgextra/i2/2215699812811/O1CN01jncdaQ1WdUIn9Wtal_!!2215699812811.jpg | E271: 实木餐桌-180*80cm | F271: PPS2421004051314 | G271: 在售 | H271: 空气悬浮感设计：视觉轻盈灵动。打破笨重感，适配多种家装风格。 北美FAS级全实木：精选进口樱桃木。质感温润细腻，随时间更具韵味。 20mm厚实桌板：用料考究。边缘自然斜切，轻薄而不失稳固。 全圆润打磨倒角：纯手工细腻处理。触感丝滑，守护家人孩童安全。 内收式桌腿布局：增加腿部活动空间。入座自在，扫地机穿行无阻。 母婴级环保标准：天然植物木蜡油。零甲醛无异味，健康安心即买即用。 | I271: 北美进口FAS级樱桃木 | J271: 无辅材 | K271: 长度：1800mm 宽度：850mm 高度：750mm | L271: 长度支持2300mm内定制；深度可任意定制；高度支持850mm内定制 | M271: . | N271: ✅ 可导入 | O271: ✓
A272: PPS24210040513 | B272: 餐厅-桌 | C272: 畔色实木餐桌 3cm桌面 |樱桃木老款实木餐桌 |樱桃木轻盈餐桌air | D272: https://img.alicdn.com/imgextra/i2/2215699812811/O1CN01jncdaQ1WdUIn9Wtal_!!2215699812811.jpg | E272: 实木餐桌-200cm | F272: PPS2421004051315 | G272: 在售 | H272: 空气悬浮感设计：视觉轻盈灵动。打破笨重感，适配多种家装风格。 北美FAS级全实木：精选进口樱桃木。质感温润细腻，随时间更具韵味。 20mm厚实桌板：用料考究。边缘自然斜切，轻薄而不失稳固。 全圆润打磨倒角：纯手工细腻处理。触感丝滑，守护家人孩童安全。 内收式桌腿布局：增加腿部活动空间。入座自在，扫地机穿行无阻。 母婴级环保标准：天然植物木蜡油。零甲醛无异味，健康安心即买即用。 | I272: 北美进口FAS级樱桃木 | J272: 无辅材 | K272: 长度：2000mm 宽度：850mm 高度：750mm | L272: 长度支持2300mm内定制；深度可任意定制；高度支持850mm内定制 | M272: . | N272: ✅ 可导入 | O272: ✓
A273: PPS24210050510 | B273: 餐厅-桌 | C273: 畔色岩板餐桌 |樱桃木老款岩板餐桌 | D273: https://img.alicdn.com/imgextra/i3/2215699812811/O1CN019U1jnO1WdUIlbQCu2_!!2215699812811.jpg | E273: 岩板餐桌-120cm | F273: PPS2421005051011 | G273: 在售 | H273: 黑科技哑光岩板台面：耐刮耐温防渗透。支持桌面裸用，一抹即净。 精选FAS级樱桃木实木脚：进口全实木。纹理温润，随时间更具韵味，拒绝贴皮。 创新工字型稳固支架：升级受力结构。承重强，大力切剁稳如泰山，静音无异响。 开放式桌腿多人聚餐：侧边无横梁。入座自在，底部高留空，扫地机穿行无阻。 全圆润防磕碰打磨：深度圆润打磨。触感丝滑，全方位守护家人孩童安全。 母婴级木蜡油涂装：天然植物提炼。零甲醛无异味，保留原木呼吸感，环保安心。 | I273: 北美进口FAS级樱桃木 | J273: 台面：黑色岩板 | K273: 长度：1200mm 宽度：850mm 高度：750mm | L273: 长度支持2300mm内定制；深度可任意定制；高度支持850mm内定制 | M273: . | N273: ✅ 可导入 | O273: ✓
A274: PPS24210050510 | B274: 餐厅-桌 | C274: 畔色岩板餐桌 |樱桃木老款岩板餐桌 | D274: https://img.alicdn.com/imgextra/i3/2215699812811/O1CN019U1jnO1WdUIlbQCu2_!!2215699812811.jpg | E274: 岩板餐桌-140cm | F274: PPS2421005051012 | G274: 在售 | H274: 黑科技哑光岩板台面：耐刮耐温防渗透。支持桌面裸用，一抹即净。 精选FAS级樱桃木实木脚：进口全实木。纹理温润，随时间更具韵味，拒绝贴皮。 创新工字型稳固支架：升级受力结构。承重强，大力切剁稳如泰山，静音无异响。 开放式桌腿多人聚餐：侧边无横梁。入座自在，底部高留空，扫地机穿行无阻。 全圆润防磕碰打磨：深度圆润打磨。触感丝滑，全方位守护家人孩童安全。 母婴级木蜡油涂装：天然植物提炼。零甲醛无异味，保留原木呼吸感，环保安心。 | I274: 北美进口FAS级樱桃木 | J274: 台面：黑色岩板 | K274: 长度：1400mm 宽度：850mm 高度：750mm | L274: 长度支持2300mm内定制；深度可任意定制；高度支持850mm内定制 | M274: . | N274: ✅ 可导入 | O274: ✓
A275: PPS24210050510 | B275: 餐厅-桌 | C275: 畔色岩板餐桌 |樱桃木老款岩板餐桌 | D275: https://img.alicdn.com/imgextra/i3/2215699812811/O1CN019U1jnO1WdUIlbQCu2_!!2215699812811.jpg | E275: 岩板餐桌-160cm | F275: PPS2421005051013 | G275: 在售 | H275: 黑科技哑光岩板台面：耐刮耐温防渗透。支持桌面裸用，一抹即净。 精选FAS级樱桃木实木脚：进口全实木。纹理温润，随时间更具韵味，拒绝贴皮。 创新工字型稳固支架：升级受力结构。承重强，大力切剁稳如泰山，静音无异响。 开放式桌腿多人聚餐：侧边无横梁。入座自在，底部高留空，扫地机穿行无阻。 全圆润防磕碰打磨：深度圆润打磨。触感丝滑，全方位守护家人孩童安全。 母婴级木蜡油涂装：天然植物提炼。零甲醛无异味，保留原木呼吸感，环保安心。 | I275: 北美进口FAS级樱桃木 | J275: 台面：黑色岩板 | K275: 长度：1600mm 宽度：850mm 高度：750mm | L275: 长度支持2300mm内定制；深度可任意定制；高度支持850mm内定制 | M275: . | N275: ✅ 可导入 | O275: ✓
A276: PPS24210050510 | B276: 餐厅-桌 | C276: 畔色岩板餐桌 |樱桃木老款岩板餐桌 | D276: https://img.alicdn.com/imgextra/i3/2215699812811/O1CN019U1jnO1WdUIlbQCu2_!!2215699812811.jpg | E276: 岩板餐桌-180*80cm | F276: PPS2421005051014 | G276: 在售 | H276: 黑科技哑光岩板台面：耐刮耐温防渗透。支持桌面裸用，一抹即净。 精选FAS级樱桃木实木脚：进口全实木。纹理温润，随时间更具韵味，拒绝贴皮。 创新工字型稳固支架：升级受力结构。承重强，大力切剁稳如泰山，静音无异响。 开放式桌腿多人聚餐：侧边无横梁。入座自在，底部高留空，扫地机穿行无阻。 全圆润防磕碰打磨：深度圆润打磨。触感丝滑，全方位守护家人孩童安全。 母婴级木蜡油涂装：天然植物提炼。零甲醛无异味，保留原木呼吸感，环保安心。 | I276: 北美进口FAS级樱桃木 | J276: 台面：黑色岩板 | K276: 长度：1800mm 宽度：850mm 高度：750mm | L276: 长度支持2300mm内定制；深度可任意定制；高度支持850mm内定制 | M276: . | N276: ✅ 可导入 | O276: ✓
A277: PPS24210050510 | B277: 餐厅-桌 | C277: 畔色岩板餐桌 |樱桃木老款岩板餐桌 | D277: https://img.alicdn.com/imgextra/i3/2215699812811/O1CN019U1jnO1WdUIlbQCu2_!!2215699812811.jpg | E277: 岩板餐桌-200cm | F277: PPS2421005051015 | G277: 在售 | H277: 黑科技哑光岩板台面：耐刮耐温防渗透。支持桌面裸用，一抹即净。 精选FAS级樱桃木实木脚：进口全实木。纹理温润，随时间更具韵味，拒绝贴皮。 创新工字型稳固支架：升级受力结构。承重强，大力切剁稳如泰山，静音无异响。 开放式桌腿多人聚餐：侧边无横梁。入座自在，底部高留空，扫地机穿行无阻。 全圆润防磕碰打磨：深度圆润打磨。触感丝滑，全方位守护家人孩童安全。 母婴级木蜡油涂装：天然植物提炼。零甲醛无异味，保留原木呼吸感，环保安心。 | I277: 北美进口FAS级樱桃木 | J277: 台面：黑色岩板 | K277: 长度：2000mm 宽度：850mm 高度：750mm | L277: 长度支持2300mm内定制；深度可任意定制；高度支持850mm内定制 | M277: . | N277: ✅ 可导入 | O277: ✓
A278: PPS24210060501 | B278: 餐厅-桌 | C278: 畔色圆桌 |樱桃木老款圆桌 | D278: https://img.alicdn.com/imgextra/i2/2215699812811/O1CN01SzgoZi1WdUIjZWIh4_!!2215699812811.jpg | E278: 实木圆桌-95cm | F278: PPS2421006050111 | G278: 在售 | H278: 北美FAS级全实木：进口樱桃木，质感温润细腻，拒绝贴皮。 28mm加厚圆润桌板：用料扎实，打磨丝滑。视觉大气，全方位守护安全。 围合式温馨团圆：1.2m/1.3m大尺寸可选。营造温馨用餐氛围。 结构稳固承重MAX：科学三角支架配合加粗腿。大力剁切不晃动。 底部清爽高留空：入座自在局促。扫地机穿行无阻，清洁无死角。 母婴级环保标准：植物木蜡油涂装。零甲醛无异味，健康安心即买即用。 | I278: 北美进口FAS级樱桃木 | J278: 桌腿：黑胡桃木+金属 | K278: 长度：950mm 高度：750mm | L278: 长度支持1400mm内定制；高度支持850mm内定制 | M278: . | N278: ✅ 可导入 | O278: ✓
A279: PPS24210060501 | B279: 餐厅-桌 | C279: 畔色圆桌 |樱桃木老款圆桌 | D279: https://img.alicdn.com/imgextra/i2/2215699812811/O1CN01SzgoZi1WdUIjZWIh4_!!2215699812811.jpg | E279: 实木圆桌-110cm | F279: PPS2421006050112 | G279: 在售 | H279: 北美FAS级全实木：进口樱桃木，质感温润细腻，拒绝贴皮。 28mm加厚圆润桌板：用料扎实，打磨丝滑。视觉大气，全方位守护安全。 围合式温馨团圆：1.2m/1.3m大尺寸可选。营造温馨用餐氛围。 结构稳固承重MAX：科学三角支架配合加粗腿。大力剁切不晃动。 底部清爽高留空：入座自在局促。扫地机穿行无阻，清洁无死角。 母婴级环保标准：植物木蜡油涂装。零甲醛无异味，健康安心即买即用。 | I279: 北美进口FAS级樱桃木 | J279: 桌腿：黑胡桃木+金属 | K279: 长度：110mm 高度：750mm | L279: 长度支持1400mm内定制；高度支持850mm内定制 | M279: . | N279: ✅ 可导入 | O279: ✓
A280: PPS24210060501 | B280: 餐厅-桌 | C280: 畔色圆桌 |樱桃木老款圆桌 | D280: https://img.alicdn.com/imgextra/i2/2215699812811/O1CN01SzgoZi1WdUIjZWIh4_!!2215699812811.jpg | E280: 实木圆桌-120cm | F280: PPS2421006050113 | G280: 在售 | H280: 北美FAS级全实木：进口樱桃木，质感温润细腻，拒绝贴皮。 28mm加厚圆润桌板：用料扎实，打磨丝滑。视觉大气，全方位守护安全。 围合式温馨团圆：1.2m/1.3m大尺寸可选。营造温馨用餐氛围。 结构稳固承重MAX：科学三角支架配合加粗腿。大力剁切不晃动。 底部清爽高留空：入座自在局促。扫地机穿行无阻，清洁无死角。 母婴级环保标准：植物木蜡油涂装。零甲醛无异味，健康安心即买即用。 | I280: 北美进口FAS级樱桃木 | J280: 桌腿：黑胡桃木+金属 | K280: 长度：120mm 高度：750mm | L280: 长度支持1400mm内定制；高度支持850mm内定制 | M280: . | N280: ✅ 可导入 | O280: ✓
A281: PPS24330050510 | B281: 卧室-床 | C281: 畔色床-主卧款 |樱桃木老款主卧床 | D281: https://img.alicdn.com/imgextra/i3/2215699812811/O1CN01cd9TiU1WdUIk1p7pC_!!2215699812811.jpg | E281: 梯形床头实木床-120cm-榉木铺板 | F281: PPS2433005051011 | G281: 在售 | H281: 北美FAS级全实木：樱桃木自然温润，回归自然睡眠环境。 极致用料加厚屏背：厚板打造，打磨丝滑，倚靠扎实舒适。 悬浮内收床腿：防磕碰设计，视觉灵动，扫地机进出无阻。 强力承重排骨架：实木密拼，翻身无异响，稳托500kg。 母婴级木蜡油：植物提取，零醛无味，开箱即用更健康。 | I281: 北美进口FAS级樱桃木 | J281: 床铺板：德国进口AA级榉木/新西兰松木 | K281: 暂无 | M281: . | N281: ✅ 可导入 | O281: ✓
A282: PPS24330050510 | B282: 卧室-床 | C282: 畔色床-主卧款 |樱桃木老款主卧床 | D282: https://img.alicdn.com/imgextra/i3/2215699812811/O1CN01cd9TiU1WdUIk1p7pC_!!2215699812811.jpg | E282: 梯形床头实木床-150cm-榉木铺板 | F282: PPS2433005051012 | G282: 在售 | H282: 北美FAS级全实木：樱桃木自然温润，回归自然睡眠环境。 极致用料加厚屏背：厚板打造，打磨丝滑，倚靠扎实舒适。 悬浮内收床腿：防磕碰设计，视觉灵动，扫地机进出无阻。 强力承重排骨架：实木密拼，翻身无异响，稳托500kg。 母婴级木蜡油：植物提取，零醛无味，开箱即用更健康。 | I282: 北美进口FAS级樱桃木 | J282: 床铺板：德国进口AA级榉木/新西兰松木 | K282: 暂无 | M282: . | N282: ✅ 可导入 | O282: ✓
A283: PPS24330050510 | B283: 卧室-床 | C283: 畔色床-主卧款 |樱桃木老款主卧床 | D283: https://img.alicdn.com/imgextra/i3/2215699812811/O1CN01cd9TiU1WdUIk1p7pC_!!2215699812811.jpg | E283: 梯形床头实木床-180cm-榉木铺板 | F283: PPS2433005051013 | G283: 在售 | H283: 北美FAS级全实木：樱桃木自然温润，回归自然睡眠环境。 极致用料加厚屏背：厚板打造，打磨丝滑，倚靠扎实舒适。 悬浮内收床腿：防磕碰设计，视觉灵动，扫地机进出无阻。 强力承重排骨架：实木密拼，翻身无异响，稳托500kg。 母婴级木蜡油：植物提取，零醛无味，开箱即用更健康。 | I283: 北美进口FAS级樱桃木 | J283: 床铺板：德国进口AA级榉木/新西兰松木 | K283: 暂无 | M283: . | N283: ✅ 可导入 | O283: ✓
A284: PPS24330050510 | B284: 卧室-床 | C284: 畔色床-主卧款 |樱桃木老款主卧床 | D284: https://img.alicdn.com/imgextra/i3/2215699812811/O1CN01cd9TiU1WdUIk1p7pC_!!2215699812811.jpg | E284: 梯形床头实木床-120cm-松木铺板 | F284: PPS2433005051014 | G284: 在售 | H284: 北美FAS级全实木：樱桃木自然温润，回归自然睡眠环境。 极致用料加厚屏背：厚板打造，打磨丝滑，倚靠扎实舒适。 悬浮内收床腿：防磕碰设计，视觉灵动，扫地机进出无阻。 强力承重排骨架：实木密拼，翻身无异响，稳托500kg。 母婴级木蜡油：植物提取，零醛无味，开箱即用更健康。 | I284: 北美进口FAS级樱桃木 | J284: 床铺板：德国进口AA级榉木/新西兰松木 | K284: 暂无 | M284: . | N284: ✅ 可导入 | O284: ✓
A285: PPS24330050510 | B285: 卧室-床 | C285: 畔色床-主卧款 |樱桃木老款主卧床 | D285: https://img.alicdn.com/imgextra/i3/2215699812811/O1CN01cd9TiU1WdUIk1p7pC_!!2215699812811.jpg | E285: 梯形床头实木床-150cm-松木铺板 | F285: PPS2433005051015 | G285: 在售 | H285: 北美FAS级全实木：樱桃木自然温润，回归自然睡眠环境。 极致用料加厚屏背：厚板打造，打磨丝滑，倚靠扎实舒适。 悬浮内收床腿：防磕碰设计，视觉灵动，扫地机进出无阻。 强力承重排骨架：实木密拼，翻身无异响，稳托500kg。 母婴级木蜡油：植物提取，零醛无味，开箱即用更健康。 | I285: 北美进口FAS级樱桃木 | J285: 床铺板：德国进口AA级榉木/新西兰松木 | K285: 暂无 | M285: . | N285: ✅ 可导入 | O285: ✓
A286: PPS24330050510 | B286: 卧室-床 | C286: 畔色床-主卧款 |樱桃木老款主卧床 | D286: https://img.alicdn.com/imgextra/i3/2215699812811/O1CN01cd9TiU1WdUIk1p7pC_!!2215699812811.jpg | E286: 梯形床头实木床-180cm-松木铺板 | F286: PPS2433005051016 | G286: 在售 | H286: 北美FAS级全实木：樱桃木自然温润，回归自然睡眠环境。 极致用料加厚屏背：厚板打造，打磨丝滑，倚靠扎实舒适。 悬浮内收床腿：防磕碰设计，视觉灵动，扫地机进出无阻。 强力承重排骨架：实木密拼，翻身无异响，稳托500kg。 母婴级木蜡油：植物提取，零醛无味，开箱即用更健康。 | I286: 北美进口FAS级樱桃木 | J286: 床铺板：德国进口AA级榉木/新西兰松木 | K286: 暂无 | M286: . | N286: ✅ 可导入 | O286: ✓
A287: PPS24380010513 | B287: 卧室-床头柜 | C287: 畔色床头柜-榫卯 |樱桃木榫卯开放床头柜 | D287: https://img.alicdn.com/imgextra/i2/2215699812811/O1CN01GnAtPh1WdUIrUTjr4_!!2215699812811.jpg | E287: 榫卯床头柜-宽款 | F287: PPS2438001051311 | G287: 在售 | H287: 精选FAS级实木：北美进口樱桃木/黑胡桃木。木质坚韧，纹理自然美观。 全榫卯结构工艺：传统燕尾榫连接。结构稳固，经久耐用不开裂。 科学分区收纳：开放格配大抽屉。储物灵活，手机书本随手取放。 全圆润防磕碰：深度圆滑打磨。触感细腻，全方位守护家人安全。 反弹抽设计：极简无拉手设计。视觉平整，有效防止意外磕碰。 母婴级环保标准：植物木蜡油涂装。零甲醛无异味，健康安全即装即用。 | I287: 北美进口FAS级樱桃木 | J287: 背板：实木多层板 抽屉围板：实木多层板 | K287: 长度：500mm 深度：450mm 整体高度：450mm 底座：30mm | L287: 长度可任意定制；深度可任意定制；高度可任意定制； | M287: . | N287: ✅ 可导入 | O287: ✓
A288: PPS24380010513 | B288: 卧室-床头柜 | C288: 畔色床头柜-榫卯 |樱桃木榫卯开放床头柜 | D288: https://img.alicdn.com/imgextra/i2/2215699812811/O1CN01GnAtPh1WdUIrUTjr4_!!2215699812811.jpg | E288: 榫卯床头柜-窄款 | F288: PPS2438001051312 | G288: 在售 | H288: 精选FAS级实木：北美进口樱桃木/黑胡桃木。木质坚韧，纹理自然美观。 全榫卯结构工艺：传统燕尾榫连接。结构稳固，经久耐用不开裂。 科学分区收纳：开放格配大抽屉。储物灵活，手机书本随手取放。 全圆润防磕碰：深度圆滑打磨。触感细腻，全方位守护家人安全。 反弹抽设计：极简无拉手设计。视觉平整，有效防止意外磕碰。 母婴级环保标准：植物木蜡油涂装。零甲醛无异味，健康安全即装即用。 | I288: 北美进口FAS级樱桃木 | J288: 背板：实木多层板 抽屉围板：实木多层板 | K288: 长度：310mm 深度：450mm 整体高度：450mm 底座：30mm | L288: 长度可任意定制；深度可任意定制；高度可任意定制； | M288: . | N288: ✅ 可导入 | O288: ✓
A289: PPS24380020510 | B289: 卧室-床头柜 | C289: 畔色床头柜-拉手 |樱桃木拉手床头柜 | D289: https://img.alicdn.com/imgextra/i4/2215699812811/O1CN01XpR7Rq1WdUIoIzPJE_!!2215699812811.jpg | E289: 拉手床头柜 | F289: PPS2438002051011 | G289: 在售 | H289: 北美FAS级樱桃木：精选原产地全实木。触感温润，随时间氧化愈发优雅。 精致实木圆润拉手：立体感十足的纯木质触感。推拉省力顺滑，视觉端庄大方。 双层分类储物空间：涵盖开放格与大容量抽屉。书籍杂物有序收纳，重塑床头秩序。 传统手工燕尾榫工艺：抽屉咬合紧密牢固。无需钉子胶水，结构稳固经久耐用。 全实木静音木质轨道：越用越顺滑。无金属冰冷感，保留纯粹的实木使用体验。 全圆润打磨防磕碰：纯手工深度细腻处理。触感丝滑，全方位守护睡眠区安全。 | I289: 北美进口FAS级樱桃木 | J289: 背板：实木多层板 抽屉围板：实木多层板 | K289: 长度：500mm 深度：450mm 整体高度：450mm 底座：30mm | L289: 长度可任意定制；深度可任意定制；高度可任意定制； | M289: . | N289: ✅ 可导入 | O289: ✓
A290: PPS24380030501 | B290: 卧室-床头柜 | C290: 畔色床头柜-洞洞板 |樱桃木洞洞板圆台面床头柜 | D290: https://img.alicdn.com/imgextra/i1/2215699812811/O1CN01r7KwCb1WdUIsnJWyE_!!2215699812811.jpg | E290: 洞洞板床头柜-无灯带 | F290: PPS2438003050111 | G290: 在售 | H290: 北美FAS级樱桃木：精选大板直拼。色泽温润，随岁月氧化更具琥珀质感。 实木洞洞板设计：自带生活美学。支持挂钩自由DIY，满足随身物件收纳。光影交织更具美感。 360°全圆润无棱角造型：视觉柔和饱满。告别磕碰隐患，为睡眠空间增加安全感。 二级科学分区储物：开放格配私密抽屉。随手取放与隐蔽收纳兼得，重塑床头秩序。 母婴级健康环保涂装：天然植物木蜡油。零甲醛无异味，健康安心即买即用。 | I290: 北美进口FAS级樱桃木 | J290: 无辅材 | K290: 长度：450mm 深度：450mm 高度：450mm | L290: 长度可任意定制；深度可任意定制；高度可任意定制； | M290: . | N290: ✅ 可导入 | O290: ✓
A291: PPS24380030501 | B291: 卧室-床头柜 | C291: 畔色床头柜-洞洞板-灯带款 | D291: https://img.alicdn.com/imgextra/i1/2215699812811/O1CN01r7KwCb1WdUIsnJWyE_!!2215699812811.jpg | E291: 洞洞板床头柜-带灯带 | F291: PPS2438003050112 | G291: 在售 | H291: 北美FAS级樱桃木：精选大板直拼。色泽温润，随岁月氧化更具琥珀质感。 实木洞洞板设计：自带生活美学。支持挂钩自由DIY，满足随身物件收纳。光影交织更具美感。 360°全圆润无棱角造型：视觉柔和饱满。告别磕碰隐患，为睡眠空间增加安全感。 二级科学分区储物：开放格配私密抽屉。随手取放与隐蔽收纳兼得，重塑床头秩序。 母婴级健康环保涂装：天然植物木蜡油。零甲醛无异味，健康安心即买即用。 | I291: 北美进口FAS级樱桃木 | J291: 无辅材 | K291: 长度：450mm 深度：450mm 高度：450mm | L291: 长度可任意定制；深度可任意定制；高度可任意定制； | M291: . | N291: ✅ 可导入 | O291: ✓
A292: PPS24350010410 | B292: 卧室-斗柜 | C292: 畔色斗柜-普通 |樱桃木标准款九斗柜 | D292: https://img.alicdn.com/imgextra/i3/2215699812811/O1CN01Ajp4Q81WdUIbOBAo8_!!2215699812811.jpg | E292: 斗柜-普通版-1.6米-岩板台面 | F292: PPS2435001041011 | G292: 在售 | H292: 岩板/实木双面板可选：百搭好看，适用不同家居环境 北美FAS级樱桃木：进口全实木。质感温润，氧化后色泽更显韵味。 科学九宫格分区：大小抽屉组合。分类收纳衣物杂物，告别翻找凌乱。 全实木静音木导轨：越用越顺滑。无金属生锈烦恼，经久耐用更环保。 传统燕尾榫工艺：抽屉连接紧密。结构稳固扎实，历经百年不开裂。 全圆润打磨倒角：深度细腻处理。视觉柔美，全方位守护家人安全。 母婴级环保涂装：天然植物木蜡油。零甲醛无异味，健康安心即装即用。 | I292: 北美进口FAS级樱桃木 | J292: 背板：实木多层板 抽屉围板：新西兰进口松木 台面：黑色岩板/樱桃木台面 | K292: 长度：1600mm 深度：400mm 整体高度：800mm 腿部：135mm | L292: 长度可任意定制；深度可任意定制；高度可任意定制； | M292: . | N292: ✅ 可导入 | O292: ✓
A293: PPS24350010410 | B293: 卧室-斗柜 | C293: 畔色斗柜-普通 |樱桃木标准款九斗柜 | D293: https://img.alicdn.com/imgextra/i3/2215699812811/O1CN01Ajp4Q81WdUIbOBAo8_!!2215699812811.jpg | E293: 斗柜-普通版-1.6米-实木台面 | F293: PPS2435001041012 | G293: 在售 | H293: 岩板/实木双面板可选：百搭好看，适用不同家居环境 北美FAS级樱桃木：进口全实木。质感温润，氧化后色泽更显韵味。 科学九宫格分区：大小抽屉组合。分类收纳衣物杂物，告别翻找凌乱。 全实木静音木导轨：越用越顺滑。无金属生锈烦恼，经久耐用更环保。 传统燕尾榫工艺：抽屉连接紧密。结构稳固扎实，历经百年不开裂。 全圆润打磨倒角：深度细腻处理。视觉柔美，全方位守护家人安全。 母婴级环保涂装：天然植物木蜡油。零甲醛无异味，健康安心即装即用。 | I293: 北美进口FAS级樱桃木 | J293: 背板：实木多层板 抽屉围板：新西兰进口松木 台面：黑色岩板/樱桃木台面 | K293: 长度：1600mm 深度：400mm 整体高度：800mm 腿部：135mm | L293: 长度可任意定制；深度可任意定制；高度可任意定制； | M293: . | N293: ✅ 可导入 | O293: ✓
...

Sheet 2-定价总表
A1: 2-定价总表 | CC1: 本表共 490 行数据，132 行存在问题。 主要问题: 数值含文本×111、公式错误×16、关键字段为空×5 导入将丢失的列(无系统字段映射): 图片链接、大促利润、即时毛利率、平台费率、税费、物流费用、安装费用、总出厂成本、木作成本、打包、外采配件成本、岩板、抽屉轨道、灯带、玻璃、电力轨道、打包纸片、铁销、连接片、铝合金轨道、塑料轨道、mini把手、免钉胶、雕刻、亚克力条、...
A2: 产品编码 | B2: 产品名称 | C2: SKU | D2: SKU编码 | E2: 图片链接 | F2: 产品大小类型 | G2: 标价计算 | H2: 日常价/单品宝 | I2: 小促价（超级立减） | J2: 中促价（88券活动） | K2: 大促到手价（双11） | L2: 大促利润 | M2: 即时毛利率 | N2: 会计总成本 | O2: 平台费率 | P2: 税费 | Q2: 物理总成本 | R2: 物流费用 | S2: 安装费用 | T2: 总出厂成本 | U2: 木作成本 | V2: 打包 | W2: 外采配件成本 | X2: 岩板 | Y2: 抽屉轨道 | Z2: 灯带 | AA2: 玻璃 | AB2: 电力轨道 | AC2: 打包纸片 | AD2: 铁销 | AE2: 连接片 | AF2: 铝合金轨道 | AG2: 塑料轨道 | AH2: mini把手 | AI2: 免钉胶 | AJ2: 雕刻 | AK2: 亚克力条 | AL2: 预埋套杆 | AM2: 理线架+插排 | AN2: 背板 | AO2: 装饰条（不锈钢） | AP2: 腿部 | AQ2: 软包 | AR2: 床铺板 | AS2: 其他 | AT2: 外配件说明 | AU2: 配件备注 | AV2: 小红书商品ID | AW2: 小红书SKU名 | AX2: 小红书SKU ID | AY2: RN 标价 | AZ2: RN单品宝报名价 | BA2: RN大促优惠比例 | BB2: RN大促价格 | BC2: 淘宝商品ID | BD2: 淘宝链接 | BE2: 淘宝SKU ID | BF2: 淘宝活动报名价 | BG2: 店内活动-店铺宝 | BH2: 店内活动-到手价 | BI2: 无国补中促-平台立减 12% | BJ2: 无国补中促-店铺宝 | BK2: 无国补中促-买家到手价（不含消费券） | BL2: 无国补中促-88VIP佣金 | BM2: 无国补中促-店铺实收价格 | BN2: 无国补中促-88vip买家最终到手价 | BO2: 无国补大促-平台立减 12% | BP2: 无国补大促-店铺宝设置 | BQ2: 无国补大促-买家到手价（不含消费券） | BR2: 无国补大促-88VIP佣金 | BS2: 无国补大促-店铺实收价格 | BT2: 无国补大促-买家最终到手价 | BU2: 备注 | CB2: 导入校验 | CC2: ⚠️问题标注
A3: PPS26330070320 | B3: 畔色榉木无边床 |榉木金属腿床 | C3: 榉木无边床-1.2米-榉木铺板 | D3: PPS2633007032011 | E3: https://img.alicdn.com/imgextra/i1/2215699812811/O1CN01weGhhJ1WdUTWXDll4_!!2215699812811.jpg | F3: 中型 | G3: =Q3/0.4 | H3: =G3*0.75 | I3: =Q3 / (0.855 - 0.02 - 0.006) | J3: =Q3 / (0.87 - 0.02 - 0.006) | K3: =Q3 / (0.9 - 0.02 - 0.006) | L3: =K3-N3 | M3: =L3/K3 | N3: =O3+P3+Q3 | O3: =K3*0.006 | P3: =K3*0.02 | Q3: =SUM(R3:T3) | R3: =IF(F3="大型",700,IF(F3="中型",300,IF(F3="小型",80,0))) | S3: =IF(F3="大型",150,IF(F3="中型",100,IF(F3="小型",0,0))) | T3: =SUM(U3:W3) | U3: 1360 | V3: 140 | W3: =SUM(X3:AS3) | X3: 0 | Y3: 0 | Z3: 0 | AA3: 0 | AB3: 0 | AC3: 0 | AD3: 0 | AE3: 0 | AF3: 0 | AG3: 0 | AH3: 0 | AI3: 0 | AJ3: 0 | AK3: 0 | AL3: 0 | AM3: 0 | AN3: 0 | AO3: 0 | AP3: 240 | AQ3: 0 | AR3: 590 | AS3: 0 | AV3: 69f6f21130d08600013a69ea | AW3: 榉木无边床-1.2米-榉木铺板 | AX3: 69f6f21130d08600013a69eb | AY3: =H3 | AZ3: =BB3/(1-BA3) | BA3: 0.15 | BB3: =K3*0.96 | BC3: 1038062316046 | BD3: 待定 | BF3: =H3 | BG3: =BH3/BF3 | BH3: =I3 | BI3: =1-12% | BJ3: =BK3/(BF3-BF3*(1-BI3)) | BK3: =BM3/(1-BL3) | BL3: 0.01 | BM3: =J3 | BN3: =IF(BK3>=1500,BK3-150,IF(BK3>=800,BK3-80,IF(BK3>=500,BK3-50,IF(BK3>=200,BK3-20,BK3)))) | BO3: =1-12% | BP3: =BQ3/(BF3-BF3*(1-BO3)) | BQ3: =BS3/(1-BR3) | BR3: 0 | BS3: =K3 | BT3: =IF(BQ3>=1500,BQ3-150,IF(BQ3>=800,BQ3-80,IF(BQ3>=500,BQ3-50,IF(BQ3>=200,BQ3-20,BQ3)))) | CB3: ✅ 可导入 | CC3: ✓
A4: PPS26330070320 | B4: 畔色榉木无边床 |榉木金属腿床 | C4: 榉木无边床-1.35米-榉木铺板 | D4: PPS2633007032012 | E4: https://img.alicdn.com/imgextra/i1/2215699812811/O1CN01weGhhJ1WdUTWXDll4_!!2215699812811.jpg | F4: 中型 | G4: =Q4/0.4 | H4: =G4*0.75 | I4: =Q4 / (0.855 - 0.02 - 0.006) | J4: =Q4 / (0.87 - 0.02 - 0.006) | K4: =Q4 / (0.9 - 0.02 - 0.006) | L4: =K4-N4 | M4: =L4/K4 | N4: =O4+P4+Q4 | O4: =K4*0.006 | P4: =K4*0.02 | Q4: =SUM(R4:T4) | R4: =IF(F4="大型",700,IF(F4="中型",300,IF(F4="小型",80,0))) | S4: =IF(F4="大型",150,IF(F4="中型",100,IF(F4="小型",0,0))) | T4: =SUM(U4:W4) | U4: 1390 | V4: 140 | W4: =SUM(X4:AS4) | X4: 0 | Y4: 0 | Z4: 0 | AA4: 0 | AB4: 0 | AC4: 0 | AD4: 0 | AE4: 0 | AF4: 0 | AG4: 0 | AH4: 0 | AI4: 0 | AJ4: 0 | AK4: 0 | AL4: 0 | AM4: 0 | AN4: 0 | AO4: 0 | AP4: 240 | AQ4: 0 | AR4: 610 | AS4: 0 | AV4: 69f6f21130d08600013a69ea | AW4: 榉木无边床-1.35米-榉木铺板 | AX4: 69f6f21130d08600013a69ee | AY4: =H4 | AZ4: =BB4/(1-BA4) | BA4: 0.15 | BB4: =K4*0.96 | BC4: 1038062316046 | BD4: 待定 | BF4: =H4 | BG4: =BH4/BF4 | BH4: =I4 | BI4: =1-12% | BJ4: =BK4/(BF4-BF4*(1-BI4)) | BK4: =BM4/(1-BL4) | BL4: 0.01 | BM4: =J4 | BN4: =IF(BK4>=1500,BK4-150,IF(BK4>=800,BK4-80,IF(BK4>=500,BK4-50,IF(BK4>=200,BK4-20,BK4)))) | BO4: =1-12% | BP4: =BQ4/(BF4-BF4*(1-BO4)) | BQ4: =BS4/(1-BR4) | BR4: 0 | BS4: =K4 | BT4: =IF(BQ4>=1500,BQ4-150,IF(BQ4>=800,BQ4-80,IF(BQ4>=500,BQ4-50,IF(BQ4>=200,BQ4-20,BQ4)))) | CB4: ✅ 可导入 | CC4: ✓
A5: PPS26330070320 | B5: 畔色榉木无边床 |榉木金属腿床 | C5: 榉木无边床-1.5米-榉木铺板 | D5: PPS2633007032013 | E5: https://img.alicdn.com/imgextra/i1/2215699812811/O1CN01weGhhJ1WdUTWXDll4_!!2215699812811.jpg | F5: 中型 | G5: =Q5/0.4 | H5: =G5*0.75 | I5: =Q5 / (0.855 - 0.02 - 0.006) | J5: =Q5 / (0.87 - 0.02 - 0.006) | K5: =Q5 / (0.9 - 0.02 - 0.006) | L5: =K5-N5 | M5: =L5/K5 | N5: =O5+P5+Q5 | O5: =K5*0.006 | P5: =K5*0.02 | Q5: =SUM(R5:T5) | R5: =IF(F5="大型",700,IF(F5="中型",300,IF(F5="小型",80,0))) | S5: =IF(F5="大型",150,IF(F5="中型",100,IF(F5="小型",0,0))) | T5: =SUM(U5:W5) | U5: 1420 | V5: 150 | W5: =SUM(X5:AS5) | X5: 0 | Y5: 0 | Z5: 0 | AA5: 0 | AB5: 0 | AC5: 0 | AD5: 0 | AE5: 0 | AF5: 0 | AG5: 0 | AH5: 0 | AI5: 0 | AJ5: 0 | AK5: 0 | AL5: 0 | AM5: 0 | AN5: 0 | AO5: 0 | AP5: 240 | AQ5: 0 | AR5: 630 | AS5: 0 | AV5: 69f6f21130d08600013a69ea | AW5: 榉木无边床-1.5米-榉木铺板 | AX5: 69f6f21130d08600013a69f1 | AY5: =H5 | AZ5: =BB5/(1-BA5) | BA5: 0.15 | BB5: =K5*0.96 | BC5: 1038062316046 | BD5: 待定 | BF5: =H5 | BG5: =BH5/BF5 | BH5: =I5 | BI5: =1-12% | BJ5: =BK5/(BF5-BF5*(1-BI5)) | BK5: =BM5/(1-BL5) | BL5: 0.01 | BM5: =J5 | BN5: =IF(BK5>=1500,BK5-150,IF(BK5>=800,BK5-80,IF(BK5>=500,BK5-50,IF(BK5>=200,BK5-20,BK5)))) | BO5: =1-12% | BP5: =BQ5/(BF5-BF5*(1-BO5)) | BQ5: =BS5/(1-BR5) | BR5: 0 | BS5: =K5 | BT5: =IF(BQ5>=1500,BQ5-150,IF(BQ5>=800,BQ5-80,IF(BQ5>=500,BQ5-50,IF(BQ5>=200,BQ5-20,BQ5)))) | CB5: ✅ 可导入 | CC5: ✓
A6: PPS26330070320 | B6: 畔色榉木无边床 |榉木金属腿床 | C6: 榉木无边床-1.8米-榉木铺板 | D6: PPS2633007032014 | E6: https://img.alicdn.com/imgextra/i1/2215699812811/O1CN01weGhhJ1WdUTWXDll4_!!2215699812811.jpg | F6: 中型 | G6: =Q6/0.4 | H6: =G6*0.75 | I6: =Q6 / (0.855 - 0.02 - 0.006) | J6: =Q6 / (0.87 - 0.02 - 0.006) | K6: =Q6 / (0.9 - 0.02 - 0.006) | L6: =K6-N6 | M6: =L6/K6 | N6: =O6+P6+Q6 | O6: =K6*0.006 | P6: =K6*0.02 | Q6: =SUM(R6:T6) | R6: =IF(F6="大型",700,IF(F6="中型",300,IF(F6="小型",80,0))) | S6: =IF(F6="大型",150,IF(F6="中型",100,IF(F6="小型",0,0))) | T6: =SUM(U6:W6) | U6: 1500 | V6: 150 | W6: =SUM(X6:AS6) | X6: 0 | Y6: 0 | Z6: 0 | AA6: 0 | AB6: 0 | AC6: 0 | AD6: 0 | AE6: 0 | AF6: 0 | AG6: 0 | AH6: 0 | AI6: 0 | AJ6: 0 | AK6: 0 | AL6: 0 | AM6: 0 | AN6: 0 | AO6: 0 | AP6: 240 | AQ6: 0 | AR6: 650 | AS6: 0 | AV6: 69f6f21130d08600013a69ea | AW6: 榉木无边床-1.8米-榉木铺板 | AX6: 69f6f21130d08600013a69f4 | AY6: =H6 | AZ6: =BB6/(1-BA6) | BA6: 0.15 | BB6: =K6*0.96 | BC6: 1038062316046 | BD6: 待定 | BF6: =H6 | BG6: =BH6/BF6 | BH6: =I6 | BI6: =1-12% | BJ6: =BK6/(BF6-BF6*(1-BI6)) | BK6: =BM6/(1-BL6) | BL6: 0.01 | BM6: =J6 | BN6: =IF(BK6>=1500,BK6-150,IF(BK6>=800,BK6-80,IF(BK6>=500,BK6-50,IF(BK6>=200,BK6-20,BK6)))) | BO6: =1-12% | BP6: =BQ6/(BF6-BF6*(1-BO6)) | BQ6: =BS6/(1-BR6) | BR6: 0 | BS6: =K6 | BT6: =IF(BQ6>=1500,BQ6-150,IF(BQ6>=800,BQ6-80,IF(BQ6>=500,BQ6-50,IF(BQ6>=200,BQ6-20,BQ6)))) | CB6: ✅ 可导入 | CC6: ✓
A7: PPS26330070320 | B7: 畔色榉木无边床 |榉木金属腿床 | C7: 榉木无边床-1.2米-松木铺板 | D7: PPS2633007032015 | E7: https://img.alicdn.com/imgextra/i1/2215699812811/O1CN01weGhhJ1WdUTWXDll4_!!2215699812811.jpg | F7: 中型 | G7: =Q7/0.4 | H7: =G7*0.75 | I7: =Q7 / (0.855 - 0.02 - 0.006) | J7: =Q7 / (0.87 - 0.02 - 0.006) | K7: =Q7 / (0.9 - 0.02 - 0.006) | L7: =K7-N7 | M7: =L7/K7 | N7: =O7+P7+Q7 | O7: =K7*0.006 | P7: =K7*0.02 | Q7: =SUM(R7:T7) | R7: =IF(F7="大型",700,IF(F7="中型",300,IF(F7="小型",80,0))) | S7: =IF(F7="大型",150,IF(F7="中型",100,IF(F7="小型",0,0))) | T7: =SUM(U7:W7) | U7: 1390 | V7: 140 | W7: =SUM(X7:AS7) | X7: 0 | Y7: 0 | Z7: 0 | AA7: 0 | AB7: 0 | AC7: 0 | AD7: 0 | AE7: 0 | AF7: 0 | AG7: 0 | AH7: 0 | AI7: 0 | AJ7: 0 | AK7: 0 | AL7: 0 | AM7: 0 | AN7: 0 | AO7: 0 | AP7: 240 | AQ7: 0 | AR7: 160 | AS7: 0 | AV7: 69f6f21130d08600013a69ea | AW7: 榉木无边床-1.2米-松木铺板 | AX7: 69f6f21130d08600013a69f7 | AY7: =H7 | AZ7: =BB7/(1-BA7) | BA7: 0.15 | BB7: =K7*0.96 | BC7: 1038062316046 | BD7: 待定 | BF7: =H7 | BG7: =BH7/BF7 | BH7: =I7 | BI7: =1-12% | BJ7: =BK7/(BF7-BF7*(1-BI7)) | BK7: =BM7/(1-BL7) | BL7: 0.01 | BM7: =J7 | BN7: =IF(BK7>=1500,BK7-150,IF(BK7>=800,BK7-80,IF(BK7>=500,BK7-50,IF(BK7>=200,BK7-20,BK7)))) | BO7: =1-12% | BP7: =BQ7/(BF7-BF7*(1-BO7)) | BQ7: =BS7/(1-BR7) | BR7: 0 | BS7: =K7 | BT7: =IF(BQ7>=1500,BQ7-150,IF(BQ7>=800,BQ7-80,IF(BQ7>=500,BQ7-50,IF(BQ7>=200,BQ7-20,BQ7)))) | CB7: ✅ 可导入 | CC7: ✓
A8: PPS26330070320 | B8: 畔色榉木无边床 |榉木金属腿床 | C8: 榉木无边床-1.35米-松木铺板 | D8: PPS2633007032016 | E8: https://img.alicdn.com/imgextra/i1/2215699812811/O1CN01weGhhJ1WdUTWXDll4_!!2215699812811.jpg | F8: 中型 | G8: =Q8/0.4 | H8: =G8*0.75 | I8: =Q8 / (0.855 - 0.02 - 0.006) | J8: =Q8 / (0.87 - 0.02 - 0.006) | K8: =Q8 / (0.9 - 0.02 - 0.006) | L8: =K8-N8 | M8: =L8/K8 | N8: =O8+P8+Q8 | O8: =K8*0.006 | P8: =K8*0.02 | Q8: =SUM(R8:T8) | R8: =IF(F8="大型",700,IF(F8="中型",300,IF(F8="小型",80,0))) | S8: =IF(F8="大型",150,IF(F8="中型",100,IF(F8="小型",0,0))) | T8: =SUM(U8:W8) | U8: 1420 | V8: 140 | W8: =SUM(X8:AS8) | X8: 0 | Y8: 0 | Z8: 0 | AA8: 0 | AB8: 0 | AC8: 0 | AD8: 0 | AE8: 0 | AF8: 0 | AG8: 0 | AH8: 0 | AI8: 0 | AJ8: 0 | AK8: 0 | AL8: 0 | AM8: 0 | AN8: 0 | AO8: 0 | AP8: 240 | AQ8: 0 | AR8: 180 | AS8: 0 | AV8: 69f6f21130d08600013a69ea | AW8: 榉木无边床-1.35米-松木铺板 | AX8: 69f6f21130d08600013a69fa | AY8: =H8 | AZ8: =BB8/(1-BA8) | BA8: 0.15 | BB8: =K8*0.96 | BC8: 1038062316046 | BD8: 待定 | BF8: =H8 | BG8: =BH8/BF8 | BH8: =I8 | BI8: =1-12% | BJ8: =BK8/(BF8-BF8*(1-BI8)) | BK8: =BM8/(1-BL8) | BL8: 0.01 | BM8: =J8 | BN8: =IF(BK8>=1500,BK8-150,IF(BK8>=800,BK8-80,IF(BK8>=500,BK8-50,IF(BK8>=200,BK8-20,BK8)))) | BO8: =1-12% | BP8: =BQ8/(BF8-BF8*(1-BO8)) | BQ8: =BS8/(1-BR8) | BR8: 0 | BS8: =K8 | BT8: =IF(BQ8>=1500,BQ8-150,IF(BQ8>=800,BQ8-80,IF(BQ8>=500,BQ8-50,IF(BQ8>=200,BQ8-20,BQ8)))) | CB8: ✅ 可导入 | CC8: ✓
A9: PPS26330070320 | B9: 畔色榉木无边床 |榉木金属腿床 | C9: 榉木无边床-1.5米-松木铺板 | D9: PPS2633007032017 | E9: https://img.alicdn.com/imgextra/i1/2215699812811/O1CN01weGhhJ1WdUTWXDll4_!!2215699812811.jpg | F9: 中型 | G9: =Q9/0.4 | H9: =G9*0.75 | I9: =Q9 / (0.855 - 0.02 - 0.006) | J9: =Q9 / (0.87 - 0.02 - 0.006) | K9: =Q9 / (0.9 - 0.02 - 0.006) | L9: =K9-N9 | M9: =L9/K9 | N9: =O9+P9+Q9 | O9: =K9*0.006 | P9: =K9*0.02 | Q9: =SUM(R9:T9) | R9: =IF(F9="大型",700,IF(F9="中型",300,IF(F9="小型",80,0))) | S9: =IF(F9="大型",150,IF(F9="中型",100,IF(F9="小型",0,0))) | T9: =SUM(U9:W9) | U9: 1470 | V9: 150 | W9: =SUM(X9:AS9) | X9: 0 | Y9: 0 | Z9: 0 | AA9: 0 | AB9: 0 | AC9: 0 | AD9: 0 | AE9: 0 | AF9: 0 | AG9: 0 | AH9: 0 | AI9: 0 | AJ9: 0 | AK9: 0 | AL9: 0 | AM9: 0 | AN9: 0 | AO9: 0 | AP9: 240 | AQ9: 0 | AR9: 180 | AS9: 0 | AV9: 69f6f21130d08600013a69ea | AW9: 榉木无边床-1.5米-松木铺板 | AX9: 69f6f21130d08600013a69fd | AY9: =H9 | AZ9: =BB9/(1-BA9) | BA9: 0.15 | BB9: =K9*0.96 | BC9: 1038062316046 | BD9: 待定 | BF9: =H9 | BG9: =BH9/BF9 | BH9: =I9 | BI9: =1-12% | BJ9: =BK9/(BF9-BF9*(1-BI9)) | BK9: =BM9/(1-BL9) | BL9: 0.01 | BM9: =J9 | BN9: =IF(BK9>=1500,BK9-150,IF(BK9>=800,BK9-80,IF(BK9>=500,BK9-50,IF(BK9>=200,BK9-20,BK9)))) | BO9: =1-12% | BP9: =BQ9/(BF9-BF9*(1-BO9)) | BQ9: =BS9/(1-BR9) | BR9: 0 | BS9: =K9 | BT9: =IF(BQ9>=1500,BQ9-150,IF(BQ9>=800,BQ9-80,IF(BQ9>=500,BQ9-50,IF(BQ9>=200,BQ9-20,BQ9)))) | CB9: ✅ 可导入 | CC9: ✓
A10: PPS26330070320 | B10: 畔色榉木无边床 |榉木金属腿床 | C10: 榉木无边床-1.8米-松木铺板 | D10: PPS2633007032018 | E10: https://img.alicdn.com/imgextra/i1/2215699812811/O1CN01weGhhJ1WdUTWXDll4_!!2215699812811.jpg | F10: 中型 | G10: =Q10/0.4 | H10: =G10*0.75 | I10: =Q10 / (0.855 - 0.02 - 0.006) | J10: =Q10 / (0.87 - 0.02 - 0.006) | K10: =Q10 / (0.9 - 0.02 - 0.006) | L10: =K10-N10 | M10: =L10/K10 | N10: =O10+P10+Q10 | O10: =K10*0.006 | P10: =K10*0.02 | Q10: =SUM(R10:T10) | R10: =IF(F10="大型",700,IF(F10="中型",300,IF(F10="小型",80,0))) | S10: =IF(F10="大型",150,IF(F10="中型",100,IF(F10="小型",0,0))) | T10: =SUM(U10:W10) | U10: 1500 | V10: 150 | W10: =SUM(X10:AS10) | X10: 0 | Y10: 0 | Z10: 0 | AA10: 0 | AB10: 0 | AC10: 0 | AD10: 0 | AE10: 0 | AF10: 0 | AG10: 0 | AH10: 0 | AI10: 0 | AJ10: 0 | AK10: 0 | AL10: 0 | AM10: 0 | AN10: 0 | AO10: 0 | AP10: 240 | AQ10: 0 | AR10: 200 | AS10: 0 | AV10: 69f6f21130d08600013a69ea | AW10: 榉木无边床-1.8米-松木铺板 | AX10: 69f6f21130d08600013a6a00 | AY10: =H10 | AZ10: =BB10/(1-BA10) | BA10: 0.15 | BB10: =K10*0.96 | BC10: 1038062316046 | BD10: 待定 | BF10: =H10 | BG10: =BH10/BF10 | BH10: =I10 | BI10: =1-12% | BJ10: =BK10/(BF10-BF10*(1-BI10)) | BK10: =BM10/(1-BL10) | BL10: 0.01 | BM10: =J10 | BN10: =IF(BK10>=1500,BK10-150,IF(BK10>=800,BK10-80,IF(BK10>=500,BK10-50,IF(BK10>=200,BK10-20,BK10)))) | BO10: =1-12% | BP10: =BQ10/(BF10-BF10*(1-BO10)) | BQ10: =BS10/(1-BR10) | BR10: 0 | BS10: =K10 | BT10: =IF(BQ10>=1500,BQ10-150,IF(BQ10>=800,BQ10-80,IF(BQ10>=500,BQ10-50,IF(BQ10>=200,BQ10-20,BQ10)))) | CB10: ✅ 可导入 | CC10: ✓
A11: PPS26330080322 | B11: 畔色榉木柔光双人床 |榉木小灯床 | C11: 榉木柔光床-1.2米-榉木铺板 | D11: PPS2633008032211 | E11: https://img.alicdn.com/imgextra/i3/2215699812811/O1CN011b8ljX1WdUTWEOKNH_!!2215699812811.jpg | F11: 中型 | G11: =Q11/0.4 | H11: =G11*0.75 | I11: =Q11 / (0.855 - 0.02 - 0.006) | J11: =Q11 / (0.87 - 0.02 - 0.006) | K11: =Q11 / (0.9 - 0.02 - 0.006) | L11: =K11-N11 | M11: =L11/K11 | N11: =O11+P11+Q11 | O11: =K11*0.006 | P11: =K11*0.02 | Q11: =SUM(R11:T11) | R11: =IF(F11="大型",700,IF(F11="中型",300,IF(F11="小型",80,0))) | S11: =IF(F11="大型",150,IF(F11="中型",100,IF(F11="小型",0,0))) | T11: =SUM(U11:W11) | U11: 2010 | V11: 140 | W11: =SUM(X11:AS11) | X11: 0 | Y11: 0 | Z11: 100 | AA11: 0 | AB11: 0 | AC11: 0 | AD11: 0 | AE11: 0 | AF11: 0 | AG11: 0 | AH11: 0 | AI11: 0 | AJ11: 0 | AK11: 0 | AL11: 0 | AM11: 0 | AN11: 0 | AO11: 0 | AP11: 0 | AQ11: 0 | AR11: 590 | AS11: 0 | AU11: 外面价格：1.8床铺板打孔+纸箱+整片=23*22+50=556 1.5规格是536，1.2规格是516 | AV11: 69f6f3de6eeaf7000137dca2 | AW11: 榉木柔光床-1.2米-榉木铺板 | AX11: 69f6f3de6eeaf7000137dca3 | AY11: =H11 | AZ11: =BB11/(1-BA11) | BA11: 0.15 | BB11: =K11*0.96 | BC11: 1036279566778 | BD11: 待定 | BF11: =H11 | BG11: =BH11/BF11 | BH11: =I11 | BI11: =1-12% | BJ11: =BK11/(BF11-BF11*(1-BI11)) | BK11: =BM11/(1-BL11) | BL11: 0.01 | BM11: =J11 | BN11: =IF(BK11>=1500,BK11-150,IF(BK11>=800,BK11-80,IF(BK11>=500,BK11-50,IF(BK11>=200,BK11-20,BK11)))) | BO11: =1-12% | BP11: =BQ11/(BF11-BF11*(1-BO11)) | BQ11: =BS11/(1-BR11) | BR11: 0 | BS11: =K11 | BT11: =IF(BQ11>=1500,BQ11-150,IF(BQ11>=800,BQ11-80,IF(BQ11>=500,BQ11-50,IF(BQ11>=200,BQ11-20,BQ11)))) | CB11: ✅ 可导入 | CC11: ✓
A12: PPS26330080322 | B12: 畔色榉木柔光双人床 |榉木小灯床 | C12: 榉木柔光床-1.35米-榉木铺板 | D12: PPS2633008032212 | E12: https://img.alicdn.com/imgextra/i3/2215699812811/O1CN011b8ljX1WdUTWEOKNH_!!2215699812811.jpg | F12: 中型 | G12: =Q12/0.4 | H12: =G12*0.75 | I12: =Q12 / (0.855 - 0.02 - 0.006) | J12: =Q12 / (0.87 - 0.02 - 0.006) | K12: =Q12 / (0.9 - 0.02 - 0.006) | L12: =K12-N12 | M12: =L12/K12 | N12: =O12+P12+Q12 | O12: =K12*0.006 | P12: =K12*0.02 | Q12: =SUM(R12:T12) | R12: =IF(F12="大型",700,IF(F12="中型",300,IF(F12="小型",80,0))) | S12: =IF(F12="大型",150,IF(F12="中型",100,IF(F12="小型",0,0))) | T12: =SUM(U12:W12) | U12: 2040 | V12: 140 | W12: =SUM(X12:AS12) | X12: 0 | Y12: 0 | Z12: 100 | AA12: 0 | AB12: 0 | AC12: 0 | AD12: 0 | AE12: 0 | AF12: 0 | AG12: 0 | AH12: 0 | AI12: 0 | AJ12: 0 | AK12: 0 | AL12: 0 | AM12: 0 | AN12: 0 | AO12: 0 | AP12: 0 | AQ12: 0 | AR12: 610 | AS12: 0 | AU12: 外面价格：1.8床铺板打孔+纸箱+整片=23*22+50=556 1.5规格是536，1.2规格是516 | AV12: 69f6f3de6eeaf7000137dca2 | AW12: 榉木柔光床-1.35米-榉木铺板 | AX12: 69f6f3de6eeaf7000137dca6 | AY12: =H12 | AZ12: =BB12/(1-BA12) | BA12: 0.15 | BB12: =K12*0.96 | BC12: 1036279566778 | BD12: 待定 | BF12: =H12 | BG12: =BH12/BF12 | BH12: =I12 | BI12: =1-12% | BJ12: =BK12/(BF12-BF12*(1-BI12)) | BK12: =BM12/(1-BL12) | BL12: 0.01 | BM12: =J12 | BN12: =IF(BK12>=1500,BK12-150,IF(BK12>=800,BK12-80,IF(BK12>=500,BK12-50,IF(BK12>=200,BK12-20,BK12)))) | BO12: =1-12% | BP12: =BQ12/(BF12-BF12*(1-BO12)) | BQ12: =BS12/(1-BR12) | BR12: 0 | BS12: =K12 | BT12: =IF(BQ12>=1500,BQ12-150,IF(BQ12>=800,BQ12-80,IF(BQ12>=500,BQ12-50,IF(BQ12>=200,BQ12-20,BQ12)))) | CB12: ✅ 可导入 | CC12: ✓
A13: PPS26330080322 | B13: 畔色榉木柔光双人床 |榉木小灯床 | C13: 榉木柔光床-1.5米-榉木铺板 | D13: PPS2633008032213 | E13: https://img.alicdn.com/imgextra/i3/2215699812811/O1CN011b8ljX1WdUTWEOKNH_!!2215699812811.jpg | F13: 中型 | G13: =Q13/0.4 | H13: =G13*0.75 | I13: =Q13 / (0.855 - 0.02 - 0.006) | J13: =Q13 / (0.87 - 0.02 - 0.006) | K13: =Q13 / (0.9 - 0.02 - 0.006) | L13: =K13-N13 | M13: =L13/K13 | N13: =O13+P13+Q13 | O13: =K13*0.006 | P13: =K13*0.02 | Q13: =SUM(R13:T13) | R13: =IF(F13="大型",700,IF(F13="中型",300,IF(F13="小型",80,0))) | S13: =IF(F13="大型",150,IF(F13="中型",100,IF(F13="小型",0,0))) | T13: =SUM(U13:W13) | U13: 2120 | V13: 150 | W13: =SUM(X13:AS13) | X13: 0 | Y13: 0 | Z13: 100 | AA13: 0 | AB13: 0 | AC13: 0 | AD13: 0 | AE13: 0 | AF13: 0 | AG13: 0 | AH13: 0 | AI13: 0 | AJ13: 0 | AK13: 0 | AL13: 0 | AM13: 0 | AN13: 0 | AO13: 0 | AP13: 0 | AQ13: 0 | AR13: 630 | AS13: 0 | AU13: 外面价格：1.8床铺板打孔+纸箱+整片=23*22+50=556 1.5规格是536，1.2规格是516 | AV13: 69f6f3de6eeaf7000137dca2 | AW13: 榉木柔光床-1.5米-榉木铺板 | AX13: 69f6f3de6eeaf7000137dca9 | AY13: =H13 | AZ13: =BB13/(1-BA13) | BA13: 0.15 | BB13: =K13*0.96 | BC13: 1036279566778 | BD13: 待定 | BF13: =H13 | BG13: =BH13/BF13 | BH13: =I13 | BI13: =1-12% | BJ13: =BK13/(BF13-BF13*(1-BI13)) | BK13: =BM13/(1-BL13) | BL13: 0.01 | BM13: =J13 | BN13: =IF(BK13>=1500,BK13-150,IF(BK13>=800,BK13-80,IF(BK13>=500,BK13-50,IF(BK13>=200,BK13-20,BK13)))) | BO13: =1-12% | BP13: =BQ13/(BF13-BF13*(1-BO13)) | BQ13: =BS13/(1-BR13) | BR13: 0 | BS13: =K13 | BT13: =IF(BQ13>=1500,BQ13-150,IF(BQ13>=800,BQ13-80,IF(BQ13>=500,BQ13-50,IF(BQ13>=200,BQ13-20,BQ13)))) | CB13: ✅ 可导入 | CC13: ✓
A14: PPS26330080322 | B14: 畔色榉木柔光双人床 |榉木小灯床 | C14: 榉木柔光床-1.8米-榉木铺板 | D14: PPS2633008032214 | E14: https://img.alicdn.com/imgextra/i3/2215699812811/O1CN011b8ljX1WdUTWEOKNH_!!2215699812811.jpg | F14: 中型 | G14: =Q14/0.4 | H14: =G14*0.75 | I14: =Q14 / (0.855 - 0.02 - 0.006) | J14: =Q14 / (0.87 - 0.02 - 0.006) | K14: =Q14 / (0.9 - 0.02 - 0.006) | L14: =K14-N14 | M14: =L14/K14 | N14: =O14+P14+Q14 | O14: =K14*0.006 | P14: =K14*0.02 | Q14: =SUM(R14:T14) | R14: =IF(F14="大型",700,IF(F14="中型",300,IF(F14="小型",80,0))) | S14: =IF(F14="大型",150,IF(F14="中型",100,IF(F14="小型",0,0))) | T14: =SUM(U14:W14) | U14: 2210 | V14: 150 | W14: =SUM(X14:AS14) | X14: 0 | Y14: 0 | Z14: 100 | AA14: 0 | AB14: 0 | AC14: 0 | AD14: 0 | AE14: 0 | AF14: 0 | AG14: 0 | AH14: 0 | AI14: 0 | AJ14: 0 | AK14: 0 | AL14: 0 | AM14: 0 | AN14: 0 | AO14: 0 | AP14: 0 | AQ14: 0 | AR14: 650 | AS14: 0 | AU14: 外面价格：1.8床铺板打孔+纸箱+整片=23*22+50=556 1.5规格是536，1.2规格是516 | AV14: 69f6f3de6eeaf7000137dca2 | AW14: 榉木柔光床-1.8米-榉木铺板 | AX14: 69f6f3de6eeaf7000137dcac | AY14: =H14 | AZ14: =BB14/(1-BA14) | BA14: 0.15 | BB14: =K14*0.96 | BC14: 1036279566778 | BD14: 待定 | BF14: =H14 | BG14: =BH14/BF14 | BH14: =I14 | BI14: =1-12% | BJ14: =BK14/(BF14-BF14*(1-BI14)) | BK14: =BM14/(1-BL14) | BL14: 0.01 | BM14: =J14 | BN14: =IF(BK14>=1500,BK14-150,IF(BK14>=800,BK14-80,IF(BK14>=500,BK14-50,IF(BK14>=200,BK14-20,BK14)))) | BO14: =1-12% | BP14: =BQ14/(BF14-BF14*(1-BO14)) | BQ14: =BS14/(1-BR14) | BR14: 0 | BS14: =K14 | BT14: =IF(BQ14>=1500,BQ14-150,IF(BQ14>=800,BQ14-80,IF(BQ14>=500,BQ14-50,IF(BQ14>=200,BQ14-20,BQ14)))) | CB14: ✅ 可导入 | CC14: ✓
A15: PPS26330080322 | B15: 畔色榉木柔光双人床 |榉木小灯床 | C15: 榉木柔光床-1.2米-松木铺板 | D15: PPS2633008032215 | E15: https://img.alicdn.com/imgextra/i3/2215699812811/O1CN011b8ljX1WdUTWEOKNH_!!2215699812811.jpg | F15: 中型 | G15: =Q15/0.4 | H15: =G15*0.75 | I15: =Q15 / (0.855 - 0.02 - 0.006) | J15: =Q15 / (0.87 - 0.02 - 0.006) | K15: =Q15 / (0.9 - 0.02 - 0.006) | L15: =K15-N15 | M15: =L15/K15 | N15: =O15+P15+Q15 | O15: =K15*0.006 | P15: =K15*0.02 | Q15: =SUM(R15:T15) | R15: =IF(F15="大型",700,IF(F15="中型",300,IF(F15="小型",80,0))) | S15: =IF(F15="大型",150,IF(F15="中型",100,IF(F15="小型",0,0))) | T15: =SUM(U15:W15) | U15: 1840 | V15: 140 | W15: =SUM(X15:AS15) | X15: 0 | Y15: 0 | Z15: 100 | AA15: 0 | AB15: 0 | AC15: 0 | AD15: 0 | AE15: 0 | AF15: 0 | AG15: 0 | AH15: 0 | AI15: 0 | AJ15: 0 | AK15: 0 | AL15: 0 | AM15: 0 | AN15: 0 | AO15: 0 | AP15: 0 | AQ15: 0 | AR15: 160 | AS15: 0 | AU15: 外面价格：1.8床铺板打孔+纸箱+整片=23*22+50=556 1.5规格是536，1.2规格是516 | AV15: 69f6f3de6eeaf7000137dca2 | AW15: 榉木柔光床-1.2米-松木铺板 | AX15: 69f6f3de6eeaf7000137dcaf | AY15: =H15 | AZ15: =BB15/(1-BA15) | BA15: 0.15 | BB15: =K15*0.96 | BC15: 1036279566778 | BD15: 待定 | BF15: =H15 | BG15: =BH15/BF15 | BH15: =I15 | BI15: =1-12% | BJ15: =BK15/(BF15-BF15*(1-BI15)) | BK15: =BM15/(1-BL15) | BL15: 0.01 | BM15: =J15 | BN15: =IF(BK15>=1500,BK15-150,IF(BK15>=800,BK15-80,IF(BK15>=500,BK15-50,IF(BK15>=200,BK15-20,BK15)))) | BO15: =1-12% | BP15: =BQ15/(BF15-BF15*(1-BO15)) | BQ15: =BS15/(1-BR15) | BR15: 0 | BS15: =K15 | BT15: =IF(BQ15>=1500,BQ15-150,IF(BQ15>=800,BQ15-80,IF(BQ15>=500,BQ15-50,IF(BQ15>=200,BQ15-20,BQ15)))) | CB15: ✅ 可导入 | CC15: ✓
A16: PPS26330080322 | B16: 畔色榉木柔光双人床 |榉木小灯床 | C16: 榉木柔光床-1.35米-松木铺板 | D16: PPS2633008032216 | E16: https://img.alicdn.com/imgextra/i3/2215699812811/O1CN011b8ljX1WdUTWEOKNH_!!2215699812811.jpg | F16: 中型 | G16: =Q16/0.4 | H16: =G16*0.75 | I16: =Q16 / (0.855 - 0.02 - 0.006) | J16: =Q16 / (0.87 - 0.02 - 0.006) | K16: =Q16 / (0.9 - 0.02 - 0.006) | L16: =K16-N16 | M16: =L16/K16 | N16: =O16+P16+Q16 | O16: =K16*0.006 | P16: =K16*0.02 | Q16: =SUM(R16:T16) | R16: =IF(F16="大型",700,IF(F16="中型",300,IF(F16="小型",80,0))) | S16: =IF(F16="大型",150,IF(F16="中型",100,IF(F16="小型",0,0))) | T16: =SUM(U16:W16) | U16: 1870 | V16: 140 | W16: =SUM(X16:AS16) | X16: 0 | Y16: 0 | Z16: 100 | AA16: 0 | AB16: 0 | AC16: 0 | AD16: 0 | AE16: 0 | AF16: 0 | AG16: 0 | AH16: 0 | AI16: 0 | AJ16: 0 | AK16: 0 | AL16: 0 | AM16: 0 | AN16: 0 | AO16: 0 | AP16: 0 | AQ16: 0 | AR16: 180 | AS16: 0 | AU16: 外面价格：1.8床铺板打孔+纸箱+整片=23*22+50=556 1.5规格是536，1.2规格是516 | AV16: 69f6f3de6eeaf7000137dca2 | AW16: 榉木柔光床-1.35米-松木铺板 | AX16: 69f6f3de6eeaf7000137dcb2 | AY16: =H16 | AZ16: =BB16/(1-BA16) | BA16: 0.15 | BB16: =K16*0.96 | BC16: 1036279566778 | BD16: 待定 | BF16: =H16 | BG16: =BH16/BF16 | BH16: =I16 | BI16: =1-12% | BJ16: =BK16/(BF16-BF16*(1-BI16)) | BK16: =BM16/(1-BL16) | BL16: 0.01 | BM16: =J16 | BN16: =IF(BK16>=1500,BK16-150,IF(BK16>=800,BK16-80,IF(BK16>=500,BK16-50,IF(BK16>=200,BK16-20,BK16)))) | BO16: =1-12% | BP16: =BQ16/(BF16-BF16*(1-BO16)) | BQ16: =BS16/(1-BR16) | BR16: 0 | BS16: =K16 | BT16: =IF(BQ16>=1500,BQ16-150,IF(BQ16>=800,BQ16-80,IF(BQ16>=500,BQ16-50,IF(BQ16>=200,BQ16-20,BQ16)))) | CB16: ✅ 可导入 | CC16: ✓
A17: PPS26330080322 | B17: 畔色榉木柔光双人床 |榉木小灯床 | C17: 榉木柔光床-1.5米-松木铺板 | D17: PPS2633008032217 | E17: https://img.alicdn.com/imgextra/i3/2215699812811/O1CN011b8ljX1WdUTWEOKNH_!!2215699812811.jpg | F17: 中型 | G17: =Q17/0.4 | H17: =G17*0.75 | I17: =Q17 / (0.855 - 0.02 - 0.006) | J17: =Q17 / (0.87 - 0.02 - 0.006) | K17: =Q17 / (0.9 - 0.02 - 0.006) | L17: =K17-N17 | M17: =L17/K17 | N17: =O17+P17+Q17 | O17: =K17*0.006 | P17: =K17*0.02 | Q17: =SUM(R17:T17) | R17: =IF(F17="大型",700,IF(F17="中型",300,IF(F17="小型",80,0))) | S17: =IF(F17="大型",150,IF(F17="中型",100,IF(F17="小型",0,0))) | T17: =SUM(U17:W17) | U17: 1920 | V17: 150 | W17: =SUM(X17:AS17) | X17: 0 | Y17: 0 | Z17: 100 | AA17: 0 | AB17: 0 | AC17: 0 | AD17: 0 | AE17: 0 | AF17: 0 | AG17: 0 | AH17: 0 | AI17: 0 | AJ17: 0 | AK17: 0 | AL17: 0 | AM17: 0 | AN17: 0 | AO17: 0 | AP17: 0 | AQ17: 0 | AR17: 180 | AS17: 0 | AU17: 外面价格：1.8床铺板打孔+纸箱+整片=23*22+50=556 1.5规格是536，1.2规格是516 | AV17: 69f6f3de6eeaf7000137dca2 | AW17: 榉木柔光床-1.5米-松木铺板 | AX17: 69f6f3de6eeaf7000137dcb5 | AY17: =H17 | AZ17: =BB17/(1-BA17) | BA17: 0.15 | BB17: =K17*0.96 | BC17: 1036279566778 | BD17: 待定 | BF17: =H17 | BG17: =BH17/BF17 | BH17: =I17 | BI17: =1-12% | BJ17: =BK17/(BF17-BF17*(1-BI17)) | BK17: =BM17/(1-BL17) | BL17: 0.01 | BM17: =J17 | BN17: =IF(BK17>=1500,BK17-150,IF(BK17>=800,BK17-80,IF(BK17>=500,BK17-50,IF(BK17>=200,BK17-20,BK17)))) | BO17: =1-12% | BP17: =BQ17/(BF17-BF17*(1-BO17)) | BQ17: =BS17/(1-BR17) | BR17: 0 | BS17: =K17 | BT17: =IF(BQ17>=1500,BQ17-150,IF(BQ17>=800,BQ17-80,IF(BQ17>=500,BQ17-50,IF(BQ17>=200,BQ17-20,BQ17)))) | CB17: ✅ 可导入 | CC17: ✓
A18: PPS26330080322 | B18: 畔色榉木柔光双人床 |榉木小灯床 | C18: 榉木柔光床-1.8米-松木铺板 | D18: PPS2633008032218 | E18: https://img.alicdn.com/imgextra/i3/2215699812811/O1CN011b8ljX1WdUTWEOKNH_!!2215699812811.jpg | F18: 中型 | G18: =Q18/0.4 | H18: =G18*0.75 | I18: =Q18 / (0.855 - 0.02 - 0.006) | J18: =Q18 / (0.87 - 0.02 - 0.006) | K18: =Q18 / (0.9 - 0.02 - 0.006) | L18: =K18-N18 | M18: =L18/K18 | N18: =O18+P18+Q18 | O18: =K18*0.006 | P18: =K18*0.02 | Q18: =SUM(R18:T18) | R18: =IF(F18="大型",700,IF(F18="中型",300,IF(F18="小型",80,0))) | S18: =IF(F18="大型",150,IF(F18="中型",100,IF(F18="小型",0,0))) | T18: =SUM(U18:W18) | U18: 2000 | V18: 150 | W18: =SUM(X18:AS18) | X18: 0 | Y18: 0 | Z18: 100 | AA18: 0 | AB18: 0 | AC18: 0 | AD18: 0 | AE18: 0 | AF18: 0 | AG18: 0 | AH18: 0 | AI18: 0 | AJ18: 0 | AK18: 0 | AL18: 0 | AM18: 0 | AN18: 0 | AO18: 0 | AP18: 0 | AQ18: 0 | AR18: 200 | AS18: 0 | AU18: 外面价格：1.8床铺板打孔+纸箱+整片=23*22+50=556 1.5规格是536，1.2规格是516 | AV18: 69f6f3de6eeaf7000137dca2 | AW18: 榉木柔光床-1.8米-松木铺板 | AX18: 69f6f3de6eeaf7000137dcb8 | AY18: =H18 | AZ18: =BB18/(1-BA18) | BA18: 0.15 | BB18: =K18*0.96 | BC18: 1036279566778 | BD18: 待定 | BF18: =H18 | BG18: =BH18/BF18 | BH18: =I18 | BI18: =1-12% | BJ18: =BK18/(BF18-BF18*(1-BI18)) | BK18: =BM18/(1-BL18) | BL18: 0.01 | BM18: =J18 | BN18: =IF(BK18>=1500,BK18-150,IF(BK18>=800,BK18-80,IF(BK18>=500,BK18-50,IF(BK18>=200,BK18-20,BK18)))) | BO18: =1-12% | BP18: =BQ18/(BF18-BF18*(1-BO18)) | BQ18: =BS18/(1-BR18) | BR18: 0 | BS18: =K18 | BT18: =IF(BQ18>=1500,BQ18-150,IF(BQ18>=800,BQ18-80,IF(BQ18>=500,BQ18-50,IF(BQ18>=200,BQ18-20,BQ18)))) | CB18: ✅ 可导入 | CC18: ✓
A19: PPS26330080322 | B19: 畔色榉木柔光双人床 |榉木小灯床 | C19: 榉木大靠背床（无灯）-1.2米-榉木铺板 | D19: PPS2633008032219 | E19: https://img.alicdn.com/imgextra/i3/2215699812811/O1CN011b8ljX1WdUTWEOKNH_!!2215699812811.jpg | F19: 中型 | G19: =Q19/0.4 | H19: =G19*0.75 | I19: =Q19 / (0.855 - 0.02 - 0.006) | J19: =Q19 / (0.87 - 0.02 - 0.006) | K19: =Q19 / (0.9 - 0.02 - 0.006) | L19: =K19-N19 | M19: =L19/K19 | N19: =O19+P19+Q19 | O19: =K19*0.006 | P19: =K19*0.02 | Q19: =SUM(R19:T19) | R19: =IF(F19="大型",700,IF(F19="中型",300,IF(F19="小型",80,0))) | S19: =IF(F19="大型",150,IF(F19="中型",100,IF(F19="小型",0,0))) | T19: =SUM(U19:W19) | U19: 2010 | V19: 140 | W19: =SUM(X19:AS19) | X19: 0 | Y19: 0 | Z19: 0 | AA19: 0 | AB19: 0 | AC19: 0 | AD19: 0 | AE19: 0 | AF19: 0 | AG19: 0 | AH19: 0 | AI19: 0 | AJ19: 0 | AK19: 0 | AL19: 0 | AM19: 0 | AN19: 0 | AO19: 0 | AP19: 0 | AQ19: 0 | AR19: 590 | AS19: 0 | AU19: 外面价格：1.8床铺板打孔+纸箱+整片=23*22+50=556 1.5规格是536，1.2规格是516 | AV19: 69f6f3de6eeaf7000137dca2 | AW19: 榉木大靠背床（无灯）-1.2米-榉木铺板 | AX19: 69f6f3de6eeaf7000137dcbb | AY19: =H19 | AZ19: =BB19/(1-BA19) | BA19: 0.15 | BB19: =K19*0.96 | BC19: 1036279566778 | BD19: 待定 | BF19: =H19 | BG19: =BH19/BF19 | BH19: =I19 | BI19: =1-12% | BJ19: =BK19/(BF19-BF19*(1-BI19)) | BK19: =BM19/(1-BL19) | BL19: 0.01 | BM19: =J19 | BN19: =IF(BK19>=1500,BK19-150,IF(BK19>=800,BK19-80,IF(BK19>=500,BK19-50,IF(BK19>=200,BK19-20,BK19)))) | BO19: =1-12% | BP19: =BQ19/(BF19-BF19*(1-BO19)) | BQ19: =BS19/(1-BR19) | BR19: 0 | BS19: =K19 | BT19: =IF(BQ19>=1500,BQ19-150,IF(BQ19>=800,BQ19-80,IF(BQ19>=500,BQ19-50,IF(BQ19>=200,BQ19-20,BQ19)))) | CB19: ✅ 可导入 | CC19: ✓
A20: PPS26330080322 | B20: 畔色榉木柔光双人床 |榉木小灯床 | C20: 榉木大靠背床（无灯）-1.35米-榉木铺板 | D20: PPS2633008032220 | E20: https://img.alicdn.com/imgextra/i3/2215699812811/O1CN011b8ljX1WdUTWEOKNH_!!2215699812811.jpg | F20: 中型 | G20: =Q20/0.4 | H20: =G20*0.75 | I20: =Q20 / (0.855 - 0.02 - 0.006) | J20: =Q20 / (0.87 - 0.02 - 0.006) | K20: =Q20 / (0.9 - 0.02 - 0.006) | L20: =K20-N20 | M20: =L20/K20 | N20: =O20+P20+Q20 | O20: =K20*0.006 | P20: =K20*0.02 | Q20: =SUM(R20:T20) | R20: =IF(F20="大型",700,IF(F20="中型",300,IF(F20="小型",80,0))) | S20: =IF(F20="大型",150,IF(F20="中型",100,IF(F20="小型",0,0))) | T20: =SUM(U20:W20) | U20: 2040 | V20: 140 | W20: =SUM(X20:AS20) | X20: 0 | Y20: 0 | Z20: 0 | AA20: 0 | AB20: 0 | AC20: 0 | AD20: 0 | AE20: 0 | AF20: 0 | AG20: 0 | AH20: 0 | AI20: 0 | AJ20: 0 | AK20: 0 | AL20: 0 | AM20: 0 | AN20: 0 | AO20: 0 | AP20: 0 | AQ20: 0 | AR20: 610 | AS20: 0 | AU20: 外面价格：1.8床铺板打孔+纸箱+整片=23*22+50=556 1.5规格是536，1.2规格是516 | AV20: 69f6f3de6eeaf7000137dca2 | AW20: 榉木大靠背床（无灯）-1.35米-榉木铺板 | AX20: 69f6f3de6eeaf7000137dcbe | AY20: =H20 | AZ20: =BB20/(1-BA20) | BA20: 0.15 | BB20: =K20*0.96 | BC20: 1036279566778 | BD20: 待定 | BF20: =H20 | BG20: =BH20/BF20 | BH20: =I20 | BI20: =1-12% | BJ20: =BK20/(BF20-BF20*(1-BI20)) | BK20: =BM20/(1-BL20) | BL20: 0.01 | BM20: =J20 | BN20: =IF(BK20>=1500,BK20-150,IF(BK20>=800,BK20-80,IF(BK20>=500,BK20-50,IF(BK20>=200,BK20-20,BK20)))) | BO20: =1-12% | BP20: =BQ20/(BF20-BF20*(1-BO20)) | BQ20: =BS20/(1-BR20) | BR20: 0 | BS20: =K20 | BT20: =IF(BQ20>=1500,BQ20-150,IF(BQ20>=800,BQ20-80,IF(BQ20>=500,BQ20-50,IF(BQ20>=200,BQ20-20,BQ20)))) | CB20: ✅ 可导入 | CC20: ✓
A21: PPS26330080322 | B21: 畔色榉木柔光双人床 |榉木小灯床 | C21: 榉木大靠背床（无灯）-1.5米-榉木铺板 | D21: PPS2633008032221 | E21: https://img.alicdn.com/imgextra/i3/2215699812811/O1CN011b8ljX1WdUTWEOKNH_!!2215699812811.jpg | F21: 中型 | G21: =Q21/0.4 | H21: =G21*0.75 | I21: =Q21 / (0.855 - 0.02 - 0.006) | J21: =Q21 / (0.87 - 0.02 - 0.006) | K21: =Q21 / (0.9 - 0.02 - 0.006) | L21: =K21-N21 | M21: =L21/K21 | N21: =O21+P21+Q21 | O21: =K21*0.006 | P21: =K21*0.02 | Q21: =SUM(R21:T21) | R21: =IF(F21="大型",700,IF(F21="中型",300,IF(F21="小型",80,0))) | S21: =IF(F21="大型",150,IF(F21="中型",100,IF(F21="小型",0,0))) | T21: =SUM(U21:W21) | U21: 2120 | V21: 150 | W21: =SUM(X21:AS21) | X21: 0 | Y21: 0 | Z21: 0 | AA21: 0 | AB21: 0 | AC21: 0 | AD21: 0 | AE21: 0 | AF21: 0 | AG21: 0 | AH21: 0 | AI21: 0 | AJ21: 0 | AK21: 0 | AL21: 0 | AM21: 0 | AN21: 0 | AO21: 0 | AP21: 0 | AQ21: 0 | AR21: 630 | AS21: 0 | AU21: 外面价格：1.8床铺板打孔+纸箱+整片=23*22+50=556 1.5规格是536，1.2规格是516 | AV21: 69f6f3de6eeaf7000137dca2 | AW21: 榉木大靠背床（无灯）-1.5米-榉木铺板 | AX21: 69f6f3de6eeaf7000137dcc1 | AY21: =H21 | AZ21: =BB21/(1-BA21) | BA21: 0.15 | BB21: =K21*0.96 | BC21: 1036279566778 | BD21: 待定 | BF21: =H21 | BG21: =BH21/BF21 | BH21: =I21 | BI21: =1-12% | BJ21: =BK21/(BF21-BF21*(1-BI21)) | BK21: =BM21/(1-BL21) | BL21: 0.01 | BM21: =J21 | BN21: =IF(BK21>=1500,BK21-150,IF(BK21>=800,BK21-80,IF(BK21>=500,BK21-50,IF(BK21>=200,BK21-20,BK21)))) | BO21: =1-12% | BP21: =BQ21/(BF21-BF21*(1-BO21)) | BQ21: =BS21/(1-BR21) | BR21: 0 | BS21: =K21 | BT21: =IF(BQ21>=1500,BQ21-150,IF(BQ21>=800,BQ21-80,IF(BQ21>=500,BQ21-50,IF(BQ21>=200,BQ21-20,BQ21)))) | CB21: ✅ 可导入 | CC21: ✓
A22: PPS26330080322 | B22: 畔色榉木柔光双人床 |榉木小灯床 | C22: 榉木大靠背床（无灯）-1.8米-榉木铺板 | D22: PPS2633008032222 | E22: https://img.alicdn.com/imgextra/i3/2215699812811/O1CN011b8ljX1WdUTWEOKNH_!!2215699812811.jpg | F22: 中型 | G22: =Q22/0.4 | H22: =G22*0.75 | I22: =Q22 / (0.855 - 0.02 - 0.006) | J22: =Q22 / (0.87 - 0.02 - 0.006) | K22: =Q22 / (0.9 - 0.02 - 0.006) | L22: =K22-N22 | M22: =L22/K22 | N22: =O22+P22+Q22 | O22: =K22*0.006 | P22: =K22*0.02 | Q22: =SUM(R22:T22) | R22: =IF(F22="大型",700,IF(F22="中型",300,IF(F22="小型",80,0))) | S22: =IF(F22="大型",150,IF(F22="中型",100,IF(F22="小型",0,0))) | T22: =SUM(U22:W22) | U22: 2210 | V22: 150 | W22: =SUM(X22:AS22) | X22: 0 | Y22: 0 | Z22: 0 | AA22: 0 | AB22: 0 | AC22: 0 | AD22: 0 | AE22: 0 | AF22: 0 | AG22: 0 | AH22: 0 | AI22: 0 | AJ22: 0 | AK22: 0 | AL22: 0 | AM22: 0 | AN22: 0 | AO22: 0 | AP22: 0 | AQ22: 0 | AR22: 650 | AS22: 0 | AU22: 外面价格：1.8床铺板打孔+纸箱+整片=23*22+50=556 1.5规格是536，1.2规格是516 | AV22: 69f6f3de6eeaf7000137dca2 | AW22: 榉木大靠背床（无灯）-1.8米-榉木铺板 | AX22: 69f6f3de6eeaf7000137dcc4 | AY22: =H22 | AZ22: =BB22/(1-BA22) | BA22: 0.15 | BB22: =K22*0.96 | BC22: 1036279566778 | BD22: 待定 | BF22: =H22 | BG22: =BH22/BF22 | BH22: =I22 | BI22: =1-12% | BJ22: =BK22/(BF22-BF22*(1-BI22)) | BK22: =BM22/(1-BL22) | BL22: 0.01 | BM22: =J22 | BN22: =IF(BK22>=1500,BK22-150,IF(BK22>=800,BK22-80,IF(BK22>=500,BK22-50,IF(BK22>=200,BK22-20,BK22)))) | BO22: =1-12% | BP22: =BQ22/(BF22-BF22*(1-BO22)) | BQ22: =BS22/(1-BR22) | BR22: 0 | BS22: =K22 | BT22: =IF(BQ22>=1500,BQ22-150,IF(BQ22>=800,BQ22-80,IF(BQ22>=500,BQ22-50,IF(BQ22>=200,BQ22-20,BQ22)))) | CB22: ✅ 可导入 | CC22: ✓
A23: PPS26330090325 | B23: 畔色榉木编织双人床 |榉木藤编床 | C23: 榉木编织床-1.2米-榉木铺板 | D23: PPS2633009032511 | E23: 暂无 | F23: 中型 | G23: =Q23/0.4 | H23: =G23*0.75 | I23: =Q23 / (0.855 - 0.02 - 0.006) | J23: =Q23 / (0.87 - 0.02 - 0.006) | K23: =Q23 / (0.9 - 0.02 - 0.006) | L23: =K23-N23 | M23: =L23/K23 | N23: =O23+P23+Q23 | O23: =K23*0.006 | P23: =K23*0.02 | Q23: =SUM(R23:T23) | R23: =IF(F23="大型",700,IF(F23="中型",300,IF(F23="小型",80,0))) | S23: =IF(F23="大型",150,IF(F23="中型",100,IF(F23="小型",0,0))) | T23: =SUM(U23:W23) | U23: 0 | V23: 140 | W23: =SUM(X23:AS23) | X23: 0 | Y23: 0 | Z23: 0 | AA23: 0 | AB23: 0 | AC23: 0 | AD23: 0 | AE23: 0 | AF23: 0 | AG23: 0 | AH23: 0 | AI23: 0 | AJ23: 0 | AK23: 0 | AL23: 0 | AM23: 0 | AN23: 0 | AO23: 0 | AP23: 0 | AQ23: 0 | AR23: 590 | AS23: 0 | AV23: / | AW23: / | AX23: / | AY23: =H23 | AZ23: =BB23/(1-BA23) | BA23: 0.15 | BB23: =K23*0.96 | BC23: 暂无 | BD23: 待定 | BF23: =H23 | BG23: =BH23/BF23 | BH23: =I23 | BI23: =1-12% | BJ23: =BK23/(BF23-BF23*(1-BI23)) | BK23: =BM23/(1-BL23) | BL23: 0.01 | BM23: =J23 | BN23: =IF(BK23>=1500,BK23-150,IF(BK23>=800,BK23-80,IF(BK23>=500,BK23-50,IF(BK23>=200,BK23-20,BK23)))) | BO23: =1-12% | BP23: =BQ23/(BF23-BF23*(1-BO23)) | BQ23: =BS23/(1-BR23) | BR23: 0 | BS23: =K23 | BT23: =IF(BQ23>=1500,BQ23-150,IF(BQ23>=800,BQ23-80,IF(BQ23>=500,BQ23-50,IF(BQ23>=200,BQ23-20,BQ23)))) | CB23: ✅ 可导入 | CC23: 木作成本原为文字，已置0待补
A24: PPS26330090325 | B24: 畔色榉木编织双人床 |榉木藤编床 | C24: 榉木编织床-1.35米-榉木铺板 | D24: PPS2633009032512 | E24: 暂无 | F24: 中型 | G24: =Q24/0.4 | H24: =G24*0.75 | I24: =Q24 / (0.855 - 0.02 - 0.006) | J24: =Q24 / (0.87 - 0.02 - 0.006) | K24: =Q24 / (0.9 - 0.02 - 0.006) | L24: =K24-N24 | M24: =L24/K24 | N24: =O24+P24+Q24 | O24: =K24*0.006 | P24: =K24*0.02 | Q24: =SUM(R24:T24) | R24: =IF(F24="大型",700,IF(F24="中型",300,IF(F24="小型",80,0))) | S24: =IF(F24="大型",150,IF(F24="中型",100,IF(F24="小型",0,0))) | T24: =SUM(U24:W24) | U24: 0 | V24: 140 | W24: =SUM(X24:AS24) | X24: 0 | Y24: 0 | Z24: 0 | AA24: 0 | AB24: 0 | AC24: 0 | AD24: 0 | AE24: 0 | AF24: 0 | AG24: 0 | AH24: 0 | AI24: 0 | AJ24: 0 | AK24: 0 | AL24: 0 | AM24: 0 | AN24: 0 | AO24: 0 | AP24: 0 | AQ24: 0 | AR24: 610 | AS24: 0 | AV24: / | AW24: / | AX24: / | AY24: =H24 | AZ24: =BB24/(1-BA24) | BA24: 0.15 | BB24: =K24*0.96 | BC24: 暂无 | BD24: 待定 | BF24: =H24 | BG24: =BH24/BF24 | BH24: =I24 | BI24: =1-12% | BJ24: =BK24/(BF24-BF24*(1-BI24)) | BK24: =BM24/(1-BL24) | BL24: 0.01 | BM24: =J24 | BN24: =IF(BK24>=1500,BK24-150,IF(BK24>=800,BK24-80,IF(BK24>=500,BK24-50,IF(BK24>=200,BK24-20,BK24)))) | BO24: =1-12% | BP24: =BQ24/(BF24-BF24*(1-BO24)) | BQ24: =BS24/(1-BR24) | BR24: 0 | BS24: =K24 | BT24: =IF(BQ24>=1500,BQ24-150,IF(BQ24>=800,BQ24-80,IF(BQ24>=500,BQ24-50,IF(BQ24>=200,BQ24-20,BQ24)))) | CB24: ✅ 可导入 | CC24: 木作成本原为文字，已置0待补
A25: PPS26330090325 | B25: 畔色榉木编织双人床 |榉木藤编床 | C25: 榉木编织床-1.5米-榉木铺板 | D25: PPS2633009032513 | E25: 暂无 | F25: 中型 | G25: =Q25/0.4 | H25: =G25*0.75 | I25: =Q25 / (0.855 - 0.02 - 0.006) | J25: =Q25 / (0.87 - 0.02 - 0.006) | K25: =Q25 / (0.9 - 0.02 - 0.006) | L25: =K25-N25 | M25: =L25/K25 | N25: =O25+P25+Q25 | O25: =K25*0.006 | P25: =K25*0.02 | Q25: =SUM(R25:T25) | R25: =IF(F25="大型",700,IF(F25="中型",300,IF(F25="小型",80,0))) | S25: =IF(F25="大型",150,IF(F25="中型",100,IF(F25="小型",0,0))) | T25: =SUM(U25:W25) | U25: 0 | V25: 150 | W25: =SUM(X25:AS25) | X25: 0 | Y25: 0 | Z25: 0 | AA25: 0 | AB25: 0 | AC25: 0 | AD25: 0 | AE25: 0 | AF25: 0 | AG25: 0 | AH25: 0 | AI25: 0 | AJ25: 0 | AK25: 0 | AL25: 0 | AM25: 0 | AN25: 0 | AO25: 0 | AP25: 0 | AQ25: 0 | AR25: 630 | AS25: 0 | AV25: / | AW25: / | AX25: / | AY25: =H25 | AZ25: =BB25/(1-BA25) | BA25: 0.15 | BB25: =K25*0.96 | BC25: 暂无 | BD25: 待定 | BF25: =H25 | BG25: =BH25/BF25 | BH25: =I25 | BI25: =1-12% | BJ25: =BK25/(BF25-BF25*(1-BI25)) | BK25: =BM25/(1-BL25) | BL25: 0.01 | BM25: =J25 | BN25: =IF(BK25>=1500,BK25-150,IF(BK25>=800,BK25-80,IF(BK25>=500,BK25-50,IF(BK25>=200,BK25-20,BK25)))) | BO25: =1-12% | BP25: =BQ25/(BF25-BF25*(1-BO25)) | BQ25: =BS25/(1-BR25) | BR25: 0 | BS25: =K25 | BT25: =IF(BQ25>=1500,BQ25-150,IF(BQ25>=800,BQ25-80,IF(BQ25>=500,BQ25-50,IF(BQ25>=200,BQ25-20,BQ25)))) | CB25: ✅ 可导入 | CC25: 木作成本原为文字，已置0待补
A26: PPS26330090325 | B26: 畔色榉木编织双人床 |榉木藤编床 | C26: 榉木编织床-1.8米-榉木铺板 | D26: PPS2633009032514 | E26: 暂无 | F26: 中型 | G26: =Q26/0.4 | H26: =G26*0.75 | I26: =Q26 / (0.855 - 0.02 - 0.006) | J26: =Q26 / (0.87 - 0.02 - 0.006) | K26: =Q26 / (0.9 - 0.02 - 0.006) | L26: =K26-N26 | M26: =L26/K26 | N26: =O26+P26+Q26 | O26: =K26*0.006 | P26: =K26*0.02 | Q26: =SUM(R26:T26) | R26: =IF(F26="大型",700,IF(F26="中型",300,IF(F26="小型",80,0))) | S26: =IF(F26="大型",150,IF(F26="中型",100,IF(F26="小型",0,0))) | T26: =SUM(U26:W26) | U26: 0 | V26: 150 | W26: =SUM(X26:AS26) | X26: 0 | Y26: 0 | Z26: 0 | AA26: 0 | AB26: 0 | AC26: 0 | AD26: 0 | AE26: 0 | AF26: 0 | AG26: 0 | AH26: 0 | AI26: 0 | AJ26: 0 | AK26: 0 | AL26: 0 | AM26: 0 | AN26: 0 | AO26: 0 | AP26: 0 | AQ26: 0 | AR26: 650 | AS26: 0 | AV26: / | AW26: / | AX26: / | AY26: =H26 | AZ26: =BB26/(1-BA26) | BA26: 0.15 | BB26: =K26*0.96 | BC26: 暂无 | BD26: 待定 | BF26: =H26 | BG26: =BH26/BF26 | BH26: =I26 | BI26: =1-12% | BJ26: =BK26/(BF26-BF26*(1-BI26)) | BK26: =BM26/(1-BL26) | BL26: 0.01 | BM26: =J26 | BN26: =IF(BK26>=1500,BK26-150,IF(BK26>=800,BK26-80,IF(BK26>=500,BK26-50,IF(BK26>=200,BK26-20,BK26)))) | BO26: =1-12% | BP26: =BQ26/(BF26-BF26*(1-BO26)) | BQ26: =BS26/(1-BR26) | BR26: 0 | BS26: =K26 | BT26: =IF(BQ26>=1500,BQ26-150,IF(BQ26>=800,BQ26-80,IF(BQ26>=500,BQ26-50,IF(BQ26>=200,BQ26-20,BQ26)))) | CB26: ✅ 可导入 | CC26: 木作成本原为文字，已置0待补
A27: PPS26330090325 | B27: 畔色榉木编织双人床 |榉木藤编床 | C27: 榉木编织床-1.2米-松木铺板 | D27: PPS2633009032515 | E27: 暂无 | F27: 中型 | G27: =Q27/0.4 | H27: =G27*0.75 | I27: =Q27 / (0.855 - 0.02 - 0.006) | J27: =Q27 / (0.87 - 0.02 - 0.006) | K27: =Q27 / (0.9 - 0.02 - 0.006) | L27: =K27-N27 | M27: =L27/K27 | N27: =O27+P27+Q27 | O27: =K27*0.006 | P27: =K27*0.02 | Q27: =SUM(R27:T27) | R27: =IF(F27="大型",700,IF(F27="中型",300,IF(F27="小型",80,0))) | S27: =IF(F27="大型",150,IF(F27="中型",100,IF(F27="小型",0,0))) | T27: =SUM(U27:W27) | U27: 0 | V27: 140 | W27: =SUM(X27:AS27) | X27: 0 | Y27: 0 | Z27: 0 | AA27: 0 | AB27: 0 | AC27: 0 | AD27: 0 | AE27: 0 | AF27: 0 | AG27: 0 | AH27: 0 | AI27: 0 | AJ27: 0 | AK27: 0 | AL27: 0 | AM27: 0 | AN27: 0 | AO27: 0 | AP27: 0 | AQ27: 0 | AR27: 160 | AS27: 0 | AV27: / | AW27: / | AX27: / | AY27: =H27 | AZ27: =BB27/(1-BA27) | BA27: 0.15 | BB27: =K27*0.96 | BC27: 暂无 | BD27: 待定 | BF27: =H27 | BG27: =BH27/BF27 | BH27: =I27 | BI27: =1-12% | BJ27: =BK27/(BF27-BF27*(1-BI27)) | BK27: =BM27/(1-BL27) | BL27: 0.01 | BM27: =J27 | BN27: =IF(BK27>=1500,BK27-150,IF(BK27>=800,BK27-80,IF(BK27>=500,BK27-50,IF(BK27>=200,BK27-20,BK27)))) | BO27: =1-12% | BP27: =BQ27/(BF27-BF27*(1-BO27)) | BQ27: =BS27/(1-BR27) | BR27: 0 | BS27: =K27 | BT27: =IF(BQ27>=1500,BQ27-150,IF(BQ27>=800,BQ27-80,IF(BQ27>=500,BQ27-50,IF(BQ27>=200,BQ27-20,BQ27)))) | CB27: ✅ 可导入 | CC27: 木作成本原为文字，已置0待补
A28: PPS26330090325 | B28: 畔色榉木编织双人床 |榉木藤编床 | C28: 榉木编织床-1.35米-松木铺板 | D28: PPS2633009032516 | E28: 暂无 | F28: 中型 | G28: =Q28/0.4 | H28: =G28*0.75 | I28: =Q28 / (0.855 - 0.02 - 0.006) | J28: =Q28 / (0.87 - 0.02 - 0.006) | K28: =Q28 / (0.9 - 0.02 - 0.006) | L28: =K28-N28 | M28: =L28/K28 | N28: =O28+P28+Q28 | O28: =K28*0.006 | P28: =K28*0.02 | Q28: =SUM(R28:T28) | R28: =IF(F28="大型",700,IF(F28="中型",300,IF(F28="小型",80,0))) | S28: =IF(F28="大型",150,IF(F28="中型",100,IF(F28="小型",0,0))) | T28: =SUM(U28:W28) | U28: 0 | V28: 140 | W28: =SUM(X28:AS28) | X28: 0 | Y28: 0 | Z28: 0 | AA28: 0 | AB28: 0 | AC28: 0 | AD28: 0 | AE28: 0 | AF28: 0 | AG28: 0 | AH28: 0 | AI28: 0 | AJ28: 0 | AK28: 0 | AL28: 0 | AM28: 0 | AN28: 0 | AO28: 0 | AP28: 0 | AQ28: 0 | AR28: 180 | AS28: 0 | AV28: / | AW28: / | AX28: / | AY28: =H28 | AZ28: =BB28/(1-BA28) | BA28: 0.15 | BB28: =K28*0.96 | BC28: 暂无 | BD28: 待定 | BF28: =H28 | BG28: =BH28/BF28 | BH28: =I28 | BI28: =1-12% | BJ28: =BK28/(BF28-BF28*(1-BI28)) | BK28: =BM28/(1-BL28) | BL28: 0.01 | BM28: =J28 | BN28: =IF(BK28>=1500,BK28-150,IF(BK28>=800,BK28-80,IF(BK28>=500,BK28-50,IF(BK28>=200,BK28-20,BK28)))) | BO28: =1-12% | BP28: =BQ28/(BF28-BF28*(1-BO28)) | BQ28: =BS28/(1-BR28) | BR28: 0 | BS28: =K28 | BT28: =IF(BQ28>=1500,BQ28-150,IF(BQ28>=800,BQ28-80,IF(BQ28>=500,BQ28-50,IF(BQ28>=200,BQ28-20,BQ28)))) | CB28: ✅ 可导入 | CC28: 木作成本原为文字，已置0待补
A29: PPS26330090325 | B29: 畔色榉木编织双人床 |榉木藤编床 | C29: 榉木编织床-1.5米-松木铺板 | D29: PPS2633009032517 | E29: 暂无 | F29: 中型 | G29: =Q29/0.4 | H29: =G29*0.75 | I29: =Q29 / (0.855 - 0.02 - 0.006) | J29: =Q29 / (0.87 - 0.02 - 0.006) | K29: =Q29 / (0.9 - 0.02 - 0.006) | L29: =K29-N29 | M29: =L29/K29 | N29: =O29+P29+Q29 | O29: =K29*0.006 | P29: =K29*0.02 | Q29: =SUM(R29:T29) | R29: =IF(F29="大型",700,IF(F29="中型",300,IF(F29="小型",80,0))) | S29: =IF(F29="大型",150,IF(F29="中型",100,IF(F29="小型",0,0))) | T29: =SUM(U29:W29) | U29: 0 | V29: 150 | W29: =SUM(X29:AS29) | X29: 0 | Y29: 0 | Z29: 0 | AA29: 0 | AB29: 0 | AC29: 0 | AD29: 0 | AE29: 0 | AF29: 0 | AG29: 0 | AH29: 0 | AI29: 0 | AJ29: 0 | AK29: 0 | AL29: 0 | AM29: 0 | AN29: 0 | AO29: 0 | AP29: 0 | AQ29: 0 | AR29: 180 | AS29: 0 | AV29: / | AW29: / | AX29: / | AY29: =H29 | AZ29: =BB29/(1-BA29) | BA29: 0.15 | BB29: =K29*0.96 | BC29: 暂无 | BD29: 待定 | BF29: =H29 | BG29: =BH29/BF29 | BH29: =I29 | BI29: =1-12% | BJ29: =BK29/(BF29-BF29*(1-BI29)) | BK29: =BM29/(1-BL29) | BL29: 0.01 | BM29: =J29 | BN29: =IF(BK29>=1500,BK29-150,IF(BK29>=800,BK29-80,IF(BK29>=500,BK29-50,IF(BK29>=200,BK29-20,BK29)))) | BO29: =1-12% | BP29: =BQ29/(BF29-BF29*(1-BO29)) | BQ29: =BS29/(1-BR29) | BR29: 0 | BS29: =K29 | BT29: =IF(BQ29>=1500,BQ29-150,IF(BQ29>=800,BQ29-80,IF(BQ29>=500,BQ29-50,IF(BQ29>=200,BQ29-20,BQ29)))) | CB29: ✅ 可导入 | CC29: 木作成本原为文字，已置0待补
A30: PPS26330090325 | B30: 畔色榉木编织双人床 |榉木藤编床 | C30: 榉木编织床-1.8米-松木铺板 | D30: PPS2633009032518 | E30: 暂无 | F30: 中型 | G30: =Q30/0.4 | H30: =G30*0.75 | I30: =Q30 / (0.855 - 0.02 - 0.006) | J30: =Q30 / (0.87 - 0.02 - 0.006) | K30: =Q30 / (0.9 - 0.02 - 0.006) | L30: =K30-N30 | M30: =L30/K30 | N30: =O30+P30+Q30 | O30: =K30*0.006 | P30: =K30*0.02 | Q30: =SUM(R30:T30) | R30: =IF(F30="大型",700,IF(F30="中型",300,IF(F30="小型",80,0))) | S30: =IF(F30="大型",150,IF(F30="中型",100,IF(F30="小型",0,0))) | T30: =SUM(U30:W30) | U30: 0 | V30: 150 | W30: =SUM(X30:AS30) | X30: 0 | Y30: 0 | Z30: 0 | AA30: 0 | AB30: 0 | AC30: 0 | AD30: 0 | AE30: 0 | AF30: 0 | AG30: 0 | AH30: 0 | AI30: 0 | AJ30: 0 | AK30: 0 | AL30: 0 | AM30: 0 | AN30: 0 | AO30: 0 | AP30: 0 | AQ30: 0 | AR30: 200 | AS30: 0 | AV30: / | AW30: / | AX30: / | AY30: =H30 | AZ30: =BB30/(1-BA30) | BA30: 0.15 | BB30: =K30*0.96 | BC30: 暂无 | BD30: 待定 | BF30: =H30 | BG30: =BH30/BF30 | BH30: =I30 | BI30: =1-12% | BJ30: =BK30/(BF30-BF30*(1-BI30)) | BK30: =BM30/(1-BL30) | BL30: 0.01 | BM30: =J30 | BN30: =IF(BK30>=1500,BK30-150,IF(BK30>=800,BK30-80,IF(BK30>=500,BK30-50,IF(BK30>=200,BK30-20,BK30)))) | BO30: =1-12% | BP30: =BQ30/(BF30-BF30*(1-BO30)) | BQ30: =BS30/(1-BR30) | BR30: 0 | BS30: =K30 | BT30: =IF(BQ30>=1500,BQ30-150,IF(BQ30>=800,BQ30-80,IF(BQ30>=500,BQ30-50,IF(BQ30>=200,BQ30-20,BQ30)))) | CB30: ✅ 可导入 | CC30: 木作成本原为文字，已置0待补
A31: PPS26330100225 | B31: 畔色樱桃木齐边双人床 |樱桃木方腿床 | C31: 樱桃木齐边床-1.2米-榉木铺板 | D31: PPS2633010022511 | E31: https://img.alicdn.com/imgextra/i1/2215699812811/O1CN01MO8BI01WdUTZAVi4D_!!2215699812811.jpg | F31: 中型 | G31: =Q31/0.4 | H31: =G31*0.75 | I31: =Q31 / (0.855 - 0.02 - 0.006) | J31: =Q31 / (0.87 - 0.02 - 0.006) | K31: =Q31 / (0.9 - 0.02 - 0.006) | L31: =K31-N31 | M31: =L31/K31 | N31: =O31+P31+Q31 | O31: =K31*0.006 | P31: =K31*0.02 | Q31: =SUM(R31:T31) | R31: =IF(F31="大型",700,IF(F31="中型",300,IF(F31="小型",80,0))) | S31: =IF(F31="大型",150,IF(F31="中型",100,IF(F31="小型",0,0))) | T31: =SUM(U31:W31) | U31: 1610 | V31: 140 | W31: =SUM(X31:AS31) | X31: 0 | Y31: 0 | Z31: 0 | AA31: 0 | AB31: 0 | AC31: 0 | AD31: 0 | AE31: 0 | AF31: 0 | AG31: 0 | AH31: 0 | AI31: 0 | AJ31: 0 | AK31: 0 | AL31: 0 | AM31: 0 | AN31: 0 | AO31: 210 | AP31: 0 | AQ31: 0 | AR31: 590 | AS31: 0 | AT31: 装饰片；30*3*660mm；单价45；床腿内嵌条20*15*230mm；单价30 | AV31: 69f6d01f0511b500017699cb | AW31: 樱桃木齐边床-1.2米-榉木铺板 | AX31: 69f6d01f0511b500017699cc | AY31: =H31 | AZ31: =BB31/(1-BA31) | BA31: 0.15 | BB31: =K31*0.96 | BC31: 1038064128030 | BD31: 待定 | BF31: =H31 | BG31: =BH31/BF31 | BH31: =I31 | BI31: =1-12% | BJ31: =BK31/(BF31-BF31*(1-BI31)) | BK31: =BM31/(1-BL31) | BL31: 0.01 | BM31: =J31 | BN31: =IF(BK31>=1500,BK31-150,IF(BK31>=800,BK31-80,IF(BK31>=500,BK31-50,IF(BK31>=200,BK31-20,BK31)))) | BO31: =1-12% | BP31: =BQ31/(BF31-BF31*(1-BO31)) | BQ31: =BS31/(1-BR31) | BR31: 0 | BS31: =K31 | BT31: =IF(BQ31>=1500,BQ31-150,IF(BQ31>=800,BQ31-80,IF(BQ31>=500,BQ31-50,IF(BQ31>=200,BQ31-20,BQ31)))) | CB31: ✅ 可导入 | CC31: ✓
A32: PPS26330100225 | B32: 畔色樱桃木齐边双人床 |樱桃木方腿床 | C32: 樱桃木齐边床-1.35米-榉木铺板 | D32: PPS2633010022512 | E32: https://img.alicdn.com/imgextra/i1/2215699812811/O1CN01MO8BI01WdUTZAVi4D_!!2215699812811.jpg | F32: 中型 | G32: =Q32/0.4 | H32: =G32*0.75 | I32: =Q32 / (0.855 - 0.02 - 0.006) | J32: =Q32 / (0.87 - 0.02 - 0.006) | K32: =Q32 / (0.9 - 0.02 - 0.006) | L32: =K32-N32 | M32: =L32/K32 | N32: =O32+P32+Q32 | O32: =K32*0.006 | P32: =K32*0.02 | Q32: =SUM(R32:T32) | R32: =IF(F32="大型",700,IF(F32="中型",300,IF(F32="小型",80,0))) | S32: =IF(F32="大型",150,IF(F32="中型",100,IF(F32="小型",0,0))) | T32: =SUM(U32:W32) | U32: 1640 | V32: 140 | W32: =SUM(X32:AS32) | X32: 0 | Y32: 0 | Z32: 0 | AA32: 0 | AB32: 0 | AC32: 0 | AD32: 0 | AE32: 0 | AF32: 0 | AG32: 0 | AH32: 0 | AI32: 0 | AJ32: 0 | AK32: 0 | AL32: 0 | AM32: 0 | AN32: 0 | AO32: 210 | AP32: 0 | AQ32: 0 | AR32: 610 | AS32: 0 | AV32: 69f6d01f0511b500017699cb | AW32: 樱桃木齐边床-1.35米-榉木铺板 | AX32: 69f6d01f0511b500017699cf | AY32: =H32 | AZ32: =BB32/(1-BA32) | BA32: 0.15 | BB32: =K32*0.96 | BC32: 1038064128030 | BD32: 待定 | BF32: =H32 | BG32: =BH32/BF32 | BH32: =I32 | BI32: =1-12% | BJ32: =BK32/(BF32-BF32*(1-BI32)) | BK32: =BM32/(1-BL32) | BL32: 0.01 | BM32: =J32 | BN32: =IF(BK32>=1500,BK32-150,IF(BK32>=800,BK32-80,IF(BK32>=500,BK32-50,IF(BK32>=200,BK32-20,BK32)))) | BO32: =1-12% | BP32: =BQ32/(BF32-BF32*(1-BO32)) | BQ32: =BS32/(1-BR32) | BR32: 0 | BS32: =K32 | BT32: =IF(BQ32>=1500,BQ32-150,IF(BQ32>=800,BQ32-80,IF(BQ32>=500,BQ32-50,IF(BQ32>=200,BQ32-20,BQ32)))) | CB32: ✅ 可导入 | CC32: ✓
A33: PPS26330100225 | B33: 畔色樱桃木齐边双人床 |樱桃木方腿床 | C33: 樱桃木齐边床-1.5米-榉木铺板 | D33: PPS2633010022513 | E33: https://img.alicdn.com/imgextra/i1/2215699812811/O1CN01MO8BI01WdUTZAVi4D_!!2215699812811.jpg | F33: 中型 | G33: =Q33/0.4 | H33: =G33*0.75 | I33: =Q33 / (0.855 - 0.02 - 0.006) | J33: =Q33 / (0.87 - 0.02 - 0.006) | K33: =Q33 / (0.9 - 0.02 - 0.006) | L33: =K33-N33 | M33: =L33/K33 | N33: =O33+P33+Q33 | O33: =K33*0.006 | P33: =K33*0.02 | Q33: =SUM(R33:T33) | R33: =IF(F33="大型",700,IF(F33="中型",300,IF(F33="小型",80,0))) | S33: =IF(F33="大型",150,IF(F33="中型",100,IF(F33="小型",0,0))) | T33: =SUM(U33:W33) | U33: 1670 | V33: 150 | W33: =SUM(X33:AS33) | X33: 0 | Y33: 0 | Z33: 0 | AA33: 0 | AB33: 0 | AC33: 0 | AD33: 0 | AE33: 0 | AF33: 0 | AG33: 0 | AH33: 0 | AI33: 0 | AJ33: 0 | AK33: 0 | AL33: 0 | AM33: 0 | AN33: 0 | AO33: 210 | AP33: 0 | AQ33: 0 | AR33: 630 | AS33: 0 | AV33: 69f6d01f0511b500017699cb | AW33: 樱桃木齐边床-1.5米-榉木铺板 | AX33: 69f6d01f0511b500017699d2 | AY33: =H33 | AZ33: =BB33/(1-BA33) | BA33: 0.15 | BB33: =K33*0.96 | BC33: 1038064128030 | BD33: 待定 | BF33: =H33 | BG33: =BH33/BF33 | BH33: =I33 | BI33: =1-12% | BJ33: =BK33/(BF33-BF33*(1-BI33)) | BK33: =BM33/(1-BL33) | BL33: 0.01 | BM33: =J33 | BN33: =IF(BK33>=1500,BK33-150,IF(BK33>=800,BK33-80,IF(BK33>=500,BK33-50,IF(BK33>=200,BK33-20,BK33)))) | BO33: =1-12% | BP33: =BQ33/(BF33-BF33*(1-BO33)) | BQ33: =BS33/(1-BR33) | BR33: 0 | BS33: =K33 | BT33: =IF(BQ33>=1500,BQ33-150,IF(BQ33>=800,BQ33-80,IF(BQ33>=500,BQ33-50,IF(BQ33>=200,BQ33-20,BQ33)))) | CB33: ✅ 可导入 | CC33: ✓
A34: PPS26330100225 | B34: 畔色樱桃木齐边双人床 |樱桃木方腿床 | C34: 樱桃木齐边床-1.8米-榉木铺板 | D34: PPS2633010022514 | E34: https://img.alicdn.com/imgextra/i1/2215699812811/O1CN01MO8BI01WdUTZAVi4D_!!2215699812811.jpg | F34: 中型 | G34: =Q34/0.4 | H34: =G34*0.75 | I34: =Q34 / (0.855 - 0.02 - 0.006) | J34: =Q34 / (0.87 - 0.02 - 0.006) | K34: =Q34 / (0.9 - 0.02 - 0.006) | L34: =K34-N34 | M34: =L34/K34 | N34: =O34+P34+Q34 | O34: =K34*0.006 | P34: =K34*0.02 | Q34: =SUM(R34:T34) | R34: =IF(F34="大型",700,IF(F34="中型",300,IF(F34="小型",80,0))) | S34: =IF(F34="大型",150,IF(F34="中型",100,IF(F34="小型",0,0))) | T34: =SUM(U34:W34) | U34: 1750 | V34: 150 | W34: =SUM(X34:AS34) | X34: 0 | Y34: 0 | Z34: 0 | AA34: 0 | AB34: 0 | AC34: 0 | AD34: 0 | AE34: 0 | AF34: 0 | AG34: 0 | AH34: 0 | AI34: 0 | AJ34: 0 | AK34: 0 | AL34: 0 | AM34: 0 | AN34: 0 | AO34: 210 | AP34: 0 | AQ34: 0 | AR34: 650 | AS34: 0 | AV34: 69f6d01f0511b500017699cb | AW34: 樱桃木齐边床-1.8米-榉木铺板 | AX34: 69f6d01f0511b500017699d5 | AY34: =H34 | AZ34: =BB34/(1-BA34) | BA34: 0.15 | BB34: =K34*0.96 | BC34: 1038064128030 | BD34: 待定 | BF34: =H34 | BG34: =BH34/BF34 | BH34: =I34 | BI34: =1-12% | BJ34: =BK34/(BF34-BF34*(1-BI34)) | BK34: =BM34/(1-BL34) | BL34: 0.01 | BM34: =J34 | BN34: =IF(BK34>=1500,BK34-150,IF(BK34>=800,BK34-80,IF(BK34>=500,BK34-50,IF(BK34>=200,BK34-20,BK34)))) | BO34: =1-12% | BP34: =BQ34/(BF34-BF34*(1-BO34)) | BQ34: =BS34/(1-BR34) | BR34: 0 | BS34: =K34 | BT34: =IF(BQ34>=1500,BQ34-150,IF(BQ34>=800,BQ34-80,IF(BQ34>=500,BQ34-50,IF(BQ34>=200,BQ34-20,BQ34)))) | CB34: ✅ 可导入 | CC34: ✓
A35: PPS26330100225 | B35: 畔色樱桃木齐边双人床 |樱桃木方腿床 | C35: 樱桃木齐边床-1.2米-松木铺板 | D35: PPS2633010022515 | E35: https://img.alicdn.com/imgextra/i1/2215699812811/O1CN01MO8BI01WdUTZAVi4D_!!2215699812811.jpg | F35: 中型 | G35: =Q35/0.4 | H35: =G35*0.75 | I35: =Q35 / (0.855 - 0.02 - 0.006) | J35: =Q35 / (0.87 - 0.02 - 0.006) | K35: =Q35 / (0.9 - 0.02 - 0.006) | L35: =K35-N35 | M35: =L35/K35 | N35: =O35+P35+Q35 | O35: =K35*0.006 | P35: =K35*0.02 | Q35: =SUM(R35:T35) | R35: =IF(F35="大型",700,IF(F35="中型",300,IF(F35="小型",80,0))) | S35: =IF(F35="大型",150,IF(F35="中型",100,IF(F35="小型",0,0))) | T35: =SUM(U35:W35) | U35: 1640 | V35: 140 | W35: =SUM(X35:AS35) | X35: 0 | Y35: 0 | Z35: 0 | AA35: 0 | AB35: 0 | AC35: 0 | AD35: 0 | AE35: 0 | AF35: 0 | AG35: 0 | AH35: 0 | AI35: 0 | AJ35: 0 | AK35: 0 | AL35: 0 | AM35: 0 | AN35: 0 | AO35: 210 | AP35: 0 | AQ35: 0 | AR35: 160 | AS35: 0 | AV35: 69f6d01f0511b500017699cb | AW35: 樱桃木齐边床-1.2米-松木铺板 | AX35: 69f6d01f0511b500017699d8 | AY35: =H35 | AZ35: =BB35/(1-BA35) | BA35: 0.15 | BB35: =K35*0.96 | BC35: 1038064128030 | BD35: 待定 | BF35: =H35 | BG35: =BH35/BF35 | BH35: =I35 | BI35: =1-12% | BJ35: =BK35/(BF35-BF35*(1-BI35)) | BK35: =BM35/(1-BL35) | BL35: 0.01 | BM35: =J35 | BN35: =IF(BK35>=1500,BK35-150,IF(BK35>=800,BK35-80,IF(BK35>=500,BK35-50,IF(BK35>=200,BK35-20,BK35)))) | BO35: =1-12% | BP35: =BQ35/(BF35-BF35*(1-BO35)) | BQ35: =BS35/(1-BR35) | BR35: 0 | BS35: =K35 | BT35: =IF(BQ35>=1500,BQ35-150,IF(BQ35>=800,BQ35-80,IF(BQ35>=500,BQ35-50,IF(BQ35>=200,BQ35-20,BQ35)))) | CB35: ✅ 可导入 | CC35: ✓
A36: PPS26330100225 | B36: 畔色樱桃木齐边双人床 |樱桃木方腿床 | C36: 樱桃木齐边床-1.35米-松木铺板 | D36: PPS2633010022516 | E36: https://img.alicdn.com/imgextra/i1/2215699812811/O1CN01MO8BI01WdUTZAVi4D_!!2215699812811.jpg | F36: 中型 | G36: =Q36/0.4 | H36: =G36*0.75 | I36: =Q36 / (0.855 - 0.02 - 0.006) | J36: =Q36 / (0.87 - 0.02 - 0.006) | K36: =Q36 / (0.9 - 0.02 - 0.006) | L36: =K36-N36 | M36: =L36/K36 | N36: =O36+P36+Q36 | O36: =K36*0.006 | P36: =K36*0.02 | Q36: =SUM(R36:T36) | R36: =IF(F36="大型",700,IF(F36="中型",300,IF(F36="小型",80,0))) | S36: =IF(F36="大型",150,IF(F36="中型",100,IF(F36="小型",0,0))) | T36: =SUM(U36:W36) | U36: 1690 | V36: 140 | W36: =SUM(X36:AS36) | X36: 0 | Y36: 0 | Z36: 0 | AA36: 0 | AB36: 0 | AC36: 0 | AD36: 0 | AE36: 0 | AF36: 0 | AG36: 0 | AH36: 0 | AI36: 0 | AJ36: 0 | AK36: 0 | AL36: 0 | AM36: 0 | AN36: 0 | AO36: 210 | AP36: 0 | AQ36: 0 | AR36: 180 | AS36: 0 | AV36: 69f6d01f0511b500017699cb | AW36: 樱桃木齐边床-1.35米-松木铺板 | AX36: 69f6d01f0511b500017699db | AY36: =H36 | AZ36: =BB36/(1-BA36) | BA36: 0.15 | BB36: =K36*0.96 | BC36: 1038064128030 | BD36: 待定 | BF36: =H36 | BG36: =BH36/BF36 | BH36: =I36 | BI36: =1-12% | BJ36: =BK36/(BF36-BF36*(1-BI36)) | BK36: =BM36/(1-BL36) | BL36: 0.01 | BM36: =J36 | BN36: =IF(BK36>=1500,BK36-150,IF(BK36>=800,BK36-80,IF(BK36>=500,BK36-50,IF(BK36>=200,BK36-20,BK36)))) | BO36: =1-12% | BP36: =BQ36/(BF36-BF36*(1-BO36)) | BQ36: =BS36/(1-BR36) | BR36: 0 | BS36: =K36 | BT36: =IF(BQ36>=1500,BQ36-150,IF(BQ36>=800,BQ36-80,IF(BQ36>=500,BQ36-50,IF(BQ36>=200,BQ36-20,BQ36)))) | CB36: ✅ 可导入 | CC36: ✓
A37: PPS26330100225 | B37: 畔色樱桃木齐边双人床 |樱桃木方腿床 | C37: 樱桃木齐边床-1.5米-松木铺板 | D37: PPS2633010022517 | E37: https://img.alicdn.com/imgextra/i1/2215699812811/O1CN01MO8BI01WdUTZAVi4D_!!2215699812811.jpg | F37: 中型 | G37: =Q37/0.4 | H37: =G37*0.75 | I37: =Q37 / (0.855 - 0.02 - 0.006) | J37: =Q37 / (0.87 - 0.02 - 0.006) | K37: =Q37 / (0.9 - 0.02 - 0.006) | L37: =K37-N37 | M37: =L37/K37 | N37: =O37+P37+Q37 | O37: =K37*0.006 | P37: =K37*0.02 | Q37: =SUM(R37:T37) | R37: =IF(F37="大型",700,IF(F37="中型",300,IF(F37="小型",80,0))) | S37: =IF(F37="大型",150,IF(F37="中型",100,IF(F37="小型",0,0))) | T37: =SUM(U37:W37) | U37: 1720 | V37: 150 | W37: =SUM(X37:AS37) | X37: 0 | Y37: 0 | Z37: 0 | AA37: 0 | AB37: 0 | AC37: 0 | AD37: 0 | AE37: 0 | AF37: 0 | AG37: 0 | AH37: 0 | AI37: 0 | AJ37: 0 | AK37: 0 | AL37: 0 | AM37: 0 | AN37: 0 | AO37: 210 | AP37: 0 | AQ37: 0 | AR37: 180 | AS37: 0 | AV37: 69f6d01f0511b500017699cb | AW37: 樱桃木齐边床-1.5米-松木铺板 | AX37: 69f6d01f0511b500017699de | AY37: =H37 | AZ37: =BB37/(1-BA37) | BA37: 0.15 | BB37: =K37*0.96 | BC37: 1038064128030 | BD37: 待定 | BF37: =H37 | BG37: =BH37/BF37 | BH37: =I37 | BI37: =1-12% | BJ37: =BK37/(BF37-BF37*(1-BI37)) | BK37: =BM37/(1-BL37) | BL37: 0.01 | BM37: =J37 | BN37: =IF(BK37>=1500,BK37-150,IF(BK37>=800,BK37-80,IF(BK37>=500,BK37-50,IF(BK37>=200,BK37-20,BK37)))) | BO37: =1-12% | BP37: =BQ37/(BF37-BF37*(1-BO37)) | BQ37: =BS37/(1-BR37) | BR37: 0 | BS37: =K37 | BT37: =IF(BQ37>=1500,BQ37-150,IF(BQ37>=800,BQ37-80,IF(BQ37>=500,BQ37-50,IF(BQ37>=200,BQ37-20,BQ37)))) | CB37: ✅ 可导入 | CC37: ✓
A38: PPS26330100225 | B38: 畔色樱桃木齐边双人床 |樱桃木方腿床 | C38: 樱桃木齐边床-1.8米-松木铺板 | D38: PPS2633010022518 | E38: https://img.alicdn.com/imgextra/i1/2215699812811/O1CN01MO8BI01WdUTZAVi4D_!!2215699812811.jpg | F38: 中型 | G38: =Q38/0.4 | H38: =G38*0.75 | I38: =Q38 / (0.855 - 0.02 - 0.006) | J38: =Q38 / (0.87 - 0.02 - 0.006) | K38: =Q38 / (0.9 - 0.02 - 0.006) | L38: =K38-N38 | M38: =L38/K38 | N38: =O38+P38+Q38 | O38: =K38*0.006 | P38: =K38*0.02 | Q38: =SUM(R38:T38) | R38: =IF(F38="大型",700,IF(F38="中型",300,IF(F38="小型",80,0))) | S38: =IF(F38="大型",150,IF(F38="中型",100,IF(F38="小型",0,0))) | T38: =SUM(U38:W38) | U38: 1800 | V38: 150 | W38: =SUM(X38:AS38) | X38: 0 | Y38: 0 | Z38: 0 | AA38: 0 | AB38: 0 | AC38: 0 | AD38: 0 | AE38: 0 | AF38: 0 | AG38: 0 | AH38: 0 | AI38: 0 | AJ38: 0 | AK38: 0 | AL38: 0 | AM38: 0 | AN38: 0 | AO38: 210 | AP38: 0 | AQ38: 0 | AR38: 200 | AS38: 0 | AV38: 69f6d01f0511b500017699cb | AW38: 樱桃木齐边床-1.8米-松木铺板 | AX38: 69f6d01f0511b500017699e1 | AY38: =H38 | AZ38: =BB38/(1-BA38) | BA38: 0.15 | BB38: =K38*0.96 | BC38: 1038064128030 | BD38: 待定 | BF38: =H38 | BG38: =BH38/BF38 | BH38: =I38 | BI38: =1-12% | BJ38: =BK38/(BF38-BF38*(1-BI38)) | BK38: =BM38/(1-BL38) | BL38: 0.01 | BM38: =J38 | BN38: =IF(BK38>=1500,BK38-150,IF(BK38>=800,BK38-80,IF(BK38>=500,BK38-50,IF(BK38>=200,BK38-20,BK38)))) | BO38: =1-12% | BP38: =BQ38/(BF38-BF38*(1-BO38)) | BQ38: =BS38/(1-BR38) | BR38: 0 | BS38: =K38 | BT38: =IF(BQ38>=1500,BQ38-150,IF(BQ38>=800,BQ38-80,IF(BQ38>=500,BQ38-50,IF(BQ38>=200,BQ38-20,BQ38)))) | CB38: ✅ 可导入 | CC38: ✓
A39: PPS26330100225 | B39: 畔色樱桃木齐边双人床 |樱桃木方腿床 | C39: 樱桃木齐边床（软包款）-1.2米-榉木铺板 | D39: PPS2633010022519 | E39: https://img.alicdn.com/imgextra/i1/2215699812811/O1CN01MO8BI01WdUTZAVi4D_!!2215699812811.jpg | F39: 中型 | G39: =Q39/0.4 | H39: =G39*0.75 | I39: =Q39 / (0.855 - 0.02 - 0.006) | J39: =Q39 / (0.87 - 0.02 - 0.006) | K39: =Q39 / (0.9 - 0.02 - 0.006) | L39: =K39-N39 | M39: =L39/K39 | N39: =O39+P39+Q39 | O39: =K39*0.006 | P39: =K39*0.02 | Q39: =SUM(R39:T39) | R39: =IF(F39="大型",700,IF(F39="中型",300,IF(F39="小型",80,0))) | S39: =IF(F39="大型",150,IF(F39="中型",100,IF(F39="小型",0,0))) | T39: =SUM(U39:W39) | U39: 1610 | V39: 140 | W39: =SUM(X39:AS39) | X39: 0 | Y39: 0 | Z39: 0 | AA39: 0 | AB39: 0 | AC39: 0 | AD39: 0 | AE39: 0 | AF39: 0 | AG39: 0 | AH39: 0 | AI39: 0 | AJ39: 0 | AK39: 0 | AL39: 0 | AM39: 0 | AN39: 0 | AO39: 0 | AP39: 0 | AQ39: 440 | AR39: 590 | AS39: 0 | AT39: 黑色软包：240元；超纤皮加冲孔200元； | AV39: 69f6d01f0511b500017699cb | AW39: 樱桃木齐边床（软包款）-1.2米-榉木铺板 | AX39: 69f6d01f0511b500017699e4 | AY39: =H39 | AZ39: =BB39/(1-BA39) | BA39: 0.15 | BB39: =K39*0.96 | BC39: 1038064128030 | BD39: 待定 | BF39: =H39 | BG39: =BH39/BF39 | BH39: =I39 | BI39: =1-12% | BJ39: =BK39/(BF39-BF39*(1-BI39)) | BK39: =BM39/(1-BL39) | BL39: 0.01 | BM39: =J39 | BN39: =IF(BK39>=1500,BK39-150,IF(BK39>=800,BK39-80,IF(BK39>=500,BK39-50,IF(BK39>=200,BK39-20,BK39)))) | BO39: =1-12% | BP39: =BQ39/(BF39-BF39*(1-BO39)) | BQ39: =BS39/(1-BR39) | BR39: 0 | BS39: =K39 | BT39: =IF(BQ39>=1500,BQ39-150,IF(BQ39>=800,BQ39-80,IF(BQ39>=500,BQ39-50,IF(BQ39>=200,BQ39-20,BQ39)))) | CB39: ✅ 可导入 | CC39: ✓
A40: PPS26330100225 | B40: 畔色樱桃木齐边双人床 |樱桃木方腿床 | C40: 樱桃木齐边床（软包款）-1.35米-榉木铺板 | D40: PPS2633010022520 | E40: https://img.alicdn.com/imgextra/i1/2215699812811/O1CN01MO8BI01WdUTZAVi4D_!!2215699812811.jpg | F40: 中型 | G40: =Q40/0.4 | H40: =G40*0.75 | I40: =Q40 / (0.855 - 0.02 - 0.006) | J40: =Q40 / (0.87 - 0.02 - 0.006) | K40: =Q40 / (0.9 - 0.02 - 0.006) | L40: =K40-N40 | M40: =L40/K40 | N40: =O40+P40+Q40 | O40: =K40*0.006 | P40: =K40*0.02 | Q40: =SUM(R40:T40) | R40: =IF(F40="大型",700,IF(F40="中型",300,IF(F40="小型",80,0))) | S40: =IF(F40="大型",150,IF(F40="中型",100,IF(F40="小型",0,0))) | T40: =SUM(U40:W40) | U40: 1640 | V40: 140 | W40: =SUM(X40:AS40) | X40: 0 | Y40: 0 | Z40: 0 | AA40: 0 | AB40: 0 | AC40: 0 | AD40: 0 | AE40: 0 | AF40: 0 | AG40: 0 | AH40: 0 | AI40: 0 | AJ40: 0 | AK40: 0 | AL40: 0 | AM40: 0 | AN40: 0 | AO40: 0 | AP40: 0 | AQ40: 470 | AR40: 610 | AS40: 0 | AT40: 黑色软包：260元；超纤皮加冲孔210元； | AV40: 69f6d01f0511b500017699cb | AW40: 樱桃木齐边床（软包款）-1.35米-榉木铺板 | AX40: 69f6d01f0511b500017699e7 | AY40: =H40 | AZ40: =BB40/(1-BA40) | BA40: 0.15 | BB40: =K40*0.96 | BC40: 1038064128030 | BD40: 待定 | BF40: =H40 | BG40: =BH40/BF40 | BH40: =I40 | BI40: =1-12% | BJ40: =BK40/(BF40-BF40*(1-BI40)) | BK40: =BM40/(1-BL40) | BL40: 0.01 | BM40: =J40 | BN40: =IF(BK40>=1500,BK40-150,IF(BK40>=800,BK40-80,IF(BK40>=500,BK40-50,IF(BK40>=200,BK40-20,BK40)))) | BO40: =1-12% | BP40: =BQ40/(BF40-BF40*(1-BO40)) | BQ40: =BS40/(1-BR40) | BR40: 0 | BS40: =K40 | BT40: =IF(BQ40>=1500,BQ40-150,IF(BQ40>=800,BQ40-80,IF(BQ40>=500,BQ40-50,IF(BQ40>=200,BQ40-20,BQ40)))) | CB40: ✅ 可导入 | CC40: ✓
A41: PPS26330100225 | B41: 畔色樱桃木齐边双人床 |樱桃木方腿床 | C41: 樱桃木齐边床（软包款）-1.5米-榉木铺板 | D41: PPS2633010022521 | E41: https://img.alicdn.com/imgextra/i1/2215699812811/O1CN01MO8BI01WdUTZAVi4D_!!2215699812811.jpg | F41: 中型 | G41: =Q41/0.4 | H41: =G41*0.75 | I41: =Q41 / (0.855 - 0.02 - 0.006) | J41: =Q41 / (0.87 - 0.02 - 0.006) | K41: =Q41 / (0.9 - 0.02 - 0.006) | L41: =K41-N41 | M41: =L41/K41 | N41: =O41+P41+Q41 | O41: =K41*0.006 | P41: =K41*0.02 | Q41: =SUM(R41:T41) | R41: =IF(F41="大型",700,IF(F41="中型",300,IF(F41="小型",80,0))) | S41: =IF(F41="大型",150,IF(F41="中型",100,IF(F41="小型",0,0))) | T41: =SUM(U41:W41) | U41: 1670 | V41: 150 | W41: =SUM(X41:AS41) | X41: 0 | Y41: 0 | Z41: 0 | AA41: 0 | AB41: 0 | AC41: 0 | AD41: 0 | AE41: 0 | AF41: 0 | AG41: 0 | AH41: 0 | AI41: 0 | AJ41: 0 | AK41: 0 | AL41: 0 | AM41: 0 | AN41: 0 | AO41: 0 | AP41: 0 | AQ41: 500 | AR41: 630 | AS41: 0 | AT41: 黑色软包：280元；超纤皮加冲孔220元； | AV41: 69f6d01f0511b500017699cb | AW41: 樱桃木齐边床（软包款）-1.5米-榉木铺板 | AX41: 69f6d01f0511b500017699ea | AY41: =H41 | AZ41: =BB41/(1-BA41) | BA41: 0.15 | BB41: =K41*0.96 | BC41: 1038064128030 | BD41: 待定 | BF41: =H41 | BG41: =BH41/BF41 | BH41: =I41 | BI41: =1-12% | BJ41: =BK41/(BF41-BF41*(1-BI41)) | BK41: =BM41/(1-BL41) | BL41: 0.01 | BM41: =J41 | BN41: =IF(BK41>=1500,BK41-150,IF(BK41>=800,BK41-80,IF(BK41>=500,BK41-50,IF(BK41>=200,BK41-20,BK41)))) | BO41: =1-12% | BP41: =BQ41/(BF41-BF41*(1-BO41)) | BQ41: =BS41/(1-BR41) | BR41: 0 | BS41: =K41 | BT41: =IF(BQ41>=1500,BQ41-150,IF(BQ41>=800,BQ41-80,IF(BQ41>=500,BQ41-50,IF(BQ41>=200,BQ41-20,BQ41)))) | CB41: ✅ 可导入 | CC41: ✓
A42: PPS26330100225 | B42: 畔色樱桃木齐边双人床 |樱桃木方腿床 | C42: 樱桃木齐边床（软包款）-1.8米-榉木铺板 | D42: PPS2633010022522 | E42: https://img.alicdn.com/imgextra/i1/2215699812811/O1CN01MO8BI01WdUTZAVi4D_!!2215699812811.jpg | F42: 中型 | G42: =Q42/0.4 | H42: =G42*0.75 | I42: =Q42 / (0.855 - 0.02 - 0.006) | J42: =Q42 / (0.87 - 0.02 - 0.006) | K42: =Q42 / (0.9 - 0.02 - 0.006) | L42: =K42-N42 | M42: =L42/K42 | N42: =O42+P42+Q42 | O42: =K42*0.006 | P42: =K42*0.02 | Q42: =SUM(R42:T42) | R42: =IF(F42="大型",700,IF(F42="中型",300,IF(F42="小型",80,0))) | S42: =IF(F42="大型",150,IF(F42="中型",100,IF(F42="小型",0,0))) | T42: =SUM(U42:W42) | U42: 1750 | V42: 150 | W42: =SUM(X42:AS42) | X42: 0 | Y42: 0 | Z42: 0 | AA42: 0 | AB42: 0 | AC42: 0 | AD42: 0 | AE42: 0 | AF42: 0 | AG42: 0 | AH42: 0 | AI42: 0 | AJ42: 0 | AK42: 0 | AL42: 0 | AM42: 0 | AN42: 0 | AO42: 0 | AP42: 0 | AQ42: 531 | AR42: 650 | AS42: 0 | AT42: 黑色软包：300元；超纤皮加冲孔230元； | AV42: 69f6d01f0511b500017699cb | AW42: 樱桃木齐边床（软包款）-1.8米-榉木铺板 | AX42: 69f6d01f0511b500017699ed | AY42: =H42 | AZ42: =BB42/(1-BA42) | BA42: 0.15 | BB42: =K42*0.96 | BC42: 1038064128030 | BD42: 待定 | BF42: =H42 | BG42: =BH42/BF42 | BH42: =I42 | BI42: =1-12% | BJ42: =BK42/(BF42-BF42*(1-BI42)) | BK42: =BM42/(1-BL42) | BL42: 0.01 | BM42: =J42 | BN42: =IF(BK42>=1500,BK42-150,IF(BK42>=800,BK42-80,IF(BK42>=500,BK42-50,IF(BK42>=200,BK42-20,BK42)))) | BO42: =1-12% | BP42: =BQ42/(BF42-BF42*(1-BO42)) | BQ42: =BS42/(1-BR42) | BR42: 0 | BS42: =K42 | BT42: =IF(BQ42>=1500,BQ42-150,IF(BQ42>=800,BQ42-80,IF(BQ42>=500,BQ42-50,IF(BQ42>=200,BQ42-20,BQ42)))) | CB42: ✅ 可导入 | CC42: ✓
A43: PPS26330110226 | B43: 畔色樱桃木静音双人床 |樱桃木小金属腿床 | C43: 樱桃木静音床-1.2米-榉木铺板 | D43: PPS2633011022611 | E43: https://img.alicdn.com/imgextra/i1/2215699812811/O1CN01J8FGAH1WdUTYbCp0i_!!2215699812811.jpg | F43: 中型 | G43: =Q43/0.4 | H43: =G43*0.75 | I43: =Q43 / (0.855 - 0.02 - 0.006) | J43: =Q43 / (0.87 - 0.02 - 0.006) | K43: =Q43 / (0.9 - 0.02 - 0.006) | L43: =K43-N43 | M43: =L43/K43 | N43: =O43+P43+Q43 | O43: =K43*0.006 | P43: =K43*0.02 | Q43: =SUM(R43:T43) | R43: =IF(F43="大型",700,IF(F43="中型",300,IF(F43="小型",80,0))) | S43: =IF(F43="大型",150,IF(F43="中型",100,IF(F43="小型",0,0))) | T43: =SUM(U43:W43) | U43: 1660 | V43: 140 | W43: =SUM(X43:AS43) | X43: 0 | Y43: 0 | Z43: 0 | AA43: 0 | AB43: 0 | AC43: 0 | AD43: 0 | AE43: 0 | AF43: 0 | AG43: 0 | AH43: 0 | AI43: 0 | AJ43: 0 | AK43: 0 | AL43: 0 | AM43: 0 | AN43: 0 | AO43: 0 | AP43: 320 | AQ43: 0 | AR43: 590 | AS43: 0 | AV43: 69f6eaf230d08600013976ea | AW43: 樱桃木静音床-1.2米-榉木铺板 | AX43: 69f6eaf230d08600013976eb | AY43: =H43 | AZ43: =BB43/(1-BA43) | BA43: 0.15 | BB43: =K43*0.96 | BC43: 1036273574687 | BD43: 待定 | BF43: =H43 | BG43: =BH43/BF43 | BH43: =I43 | BI43: =1-12% | BJ43: =BK43/(BF43-BF43*(1-BI43)) | BK43: =BM43/(1-BL43) | BL43: 0.01 | BM43: =J43 | BN43: =IF(BK43>=1500,BK43-150,IF(BK43>=800,BK43-80,IF(BK43>=500,BK43-50,IF(BK43>=200,BK43-20,BK43)))) | BO43: =1-12% | BP43: =BQ43/(BF43-BF43*(1-BO43)) | BQ43: =BS43/(1-BR43) | BR43: 0 | BS43: =K43 | BT43: =IF(BQ43>=1500,BQ43-150,IF(BQ43>=800,BQ43-80,IF(BQ43>=500,BQ43-50,IF(BQ43>=200,BQ43-20,BQ43)))) | CB43: ✅ 可导入 | CC43: ✓
A44: PPS26330110226 | B44: 畔色樱桃木静音双人床 |樱桃木小金属腿床 | C44: 樱桃木静音床-1.35米-榉木铺板 | D44: PPS2633011022612 | E44: https://img.alicdn.com/imgextra/i1/2215699812811/O1CN01J8FGAH1WdUTYbCp0i_!!2215699812811.jpg | F44: 中型 | G44: =Q44/0.4 | H44: =G44*0.75 | I44: =Q44 / (0.855 - 0.02 - 0.006) | J44: =Q44 / (0.87 - 0.02 - 0.006) | K44: =Q44 / (0.9 - 0.02 - 0.006) | L44: =K44-N44 | M44: =L44/K44 | N44: =O44+P44+Q44 | O44: =K44*0.006 | P44: =K44*0.02 | Q44: =SUM(R44:T44) | R44: =IF(F44="大型",700,IF(F44="中型",300,IF(F44="小型",80,0))) | S44: =IF(F44="大型",150,IF(F44="中型",100,IF(F44="小型",0,0))) | T44: =SUM(U44:W44) | U44: 1690 | V44: 140 | W44: =SUM(X44:AS44) | X44: 0 | Y44: 0 | Z44: 0 | AA44: 0 | AB44: 0 | AC44: 0 | AD44: 0 | AE44: 0 | AF44: 0 | AG44: 0 | AH44: 0 | AI44: 0 | AJ44: 0 | AK44: 0 | AL44: 0 | AM44: 0 | AN44: 0 | AO44: 0 | AP44: 320 | AQ44: 0 | AR44: 610 | AS44: 0 | AV44: 69f6eaf230d08600013976ea | AW44: 樱桃木静音床-1.35米-榉木铺板 | AX44: 69f6eaf230d08600013976ee | AY44: =H44 | AZ44: =BB44/(1-BA44) | BA44: 0.15 | BB44: =K44*0.96 | BC44: 1036273574687 | BD44: 待定 | BF44: =H44 | BG44: =BH44/BF44 | BH44: =I44 | BI44: =1-12% | BJ44: =BK44/(BF44-BF44*(1-BI44)) | BK44: =BM44/(1-BL44) | BL44: 0.01 | BM44: =J44 | BN44: =IF(BK44>=1500,BK44-150,IF(BK44>=800,BK44-80,IF(BK44>=500,BK44-50,IF(BK44>=200,BK44-20,BK44)))) | BO44: =1-12% | BP44: =BQ44/(BF44-BF44*(1-BO44)) | BQ44: =BS44/(1-BR44) | BR44: 0 | BS44: =K44 | BT44: =IF(BQ44>=1500,BQ44-150,IF(BQ44>=800,BQ44-80,IF(BQ44>=500,BQ44-50,IF(BQ44>=200,BQ44-20,BQ44)))) | CB44: ✅ 可导入 | CC44: ✓
A45: PPS26330110226 | B45: 畔色樱桃木静音双人床 |樱桃木小金属腿床 | C45: 樱桃木静音床-1.5米-榉木铺板 | D45: PPS2633011022613 | E45: https://img.alicdn.com/imgextra/i1/2215699812811/O1CN01J8FGAH1WdUTYbCp0i_!!2215699812811.jpg | F45: 中型 | G45: =Q45/0.4 | H45: =G45*0.75 | I45: =Q45 / (0.855 - 0.02 - 0.006) | J45: =Q45 / (0.87 - 0.02 - 0.006) | K45: =Q45 / (0.9 - 0.02 - 0.006) | L45: =K45-N45 | M45: =L45/K45 | N45: =O45+P45+Q45 | O45: =K45*0.006 | P45: =K45*0.02 | Q45: =SUM(R45:T45) | R45: =IF(F45="大型",700,IF(F45="中型",300,IF(F45="小型",80,0))) | S45: =IF(F45="大型",150,IF(F45="中型",100,IF(F45="小型",0,0))) | T45: =SUM(U45:W45) | U45: 1770 | V45: 150 | W45: =SUM(X45:AS45) | X45: 0 | Y45: 0 | Z45: 0 | AA45: 0 | AB45: 0 | AC45: 0 | AD45: 0 | AE45: 0 | AF45: 0 | AG45: 0 | AH45: 0 | AI45: 0 | AJ45: 0 | AK45: 0 | AL45: 0 | AM45: 0 | AN45: 0 | AO45: 0 | AP45: 320 | AQ45: 0 | AR45: 630 | AS45: 0 | AV45: 69f6eaf230d08600013976ea | AW45: 樱桃木静音床-1.5米-榉木铺板 | AX45: 69f6eaf230d08600013976f1 | AY45: =H45 | AZ45: =BB45/(1-BA45) | BA45: 0.15 | BB45: =K45*0.96 | BC45: 1036273574687 | BD45: 待定 | BF45: =H45 | BG45: =BH45/BF45 | BH45: =I45 | BI45: =1-12% | BJ45: =BK45/(BF45-BF45*(1-BI45)) | BK45: =BM45/(1-BL45) | BL45: 0.01 | BM45: =J45 | BN45: =IF(BK45>=1500,BK45-150,IF(BK45>=800,BK45-80,IF(BK45>=500,BK45-50,IF(BK45>=200,BK45-20,BK45)))) | BO45: =1-12% | BP45: =BQ45/(BF45-BF45*(1-BO45)) | BQ45: =BS45/(1-BR45) | BR45: 0 | BS45: =K45 | BT45: =IF(BQ45>=1500,BQ45-150,IF(BQ45>=800,BQ45-80,IF(BQ45>=500,BQ45-50,IF(BQ45>=200,BQ45-20,BQ45)))) | CB45: ✅ 可导入 | CC45: ✓
A46: PPS26330110226 | B46: 畔色樱桃木静音双人床 |樱桃木小金属腿床 | C46: 樱桃木静音床-1.8米-榉木铺板 | D46: PPS2633011022614 | E46: https://img.alicdn.com/imgextra/i1/2215699812811/O1CN01J8FGAH1WdUTYbCp0i_!!2215699812811.jpg | F46: 中型 | G46: =Q46/0.4 | H46: =G46*0.75 | I46: =Q46 / (0.855 - 0.02 - 0.006) | J46: =Q46 / (0.87 - 0.02 - 0.006) | K46: =Q46 / (0.9 - 0.02 - 0.006) | L46: =K46-N46 | M46: =L46/K46 | N46: =O46+P46+Q46 | O46: =K46*0.006 | P46: =K46*0.02 | Q46: =SUM(R46:T46) | R46: =IF(F46="大型",700,IF(F46="中型",300,IF(F46="小型",80,0))) | S46: =IF(F46="大型",150,IF(F46="中型",100,IF(F46="小型",0,0))) | T46: =SUM(U46:W46) | U46: 1890 | V46: 150 | W46: =SUM(X46:AS46) | X46: 0 | Y46: 0 | Z46: 0 | AA46: 0 | AB46: 0 | AC46: 0 | AD46: 0 | AE46: 0 | AF46: 0 | AG46: 0 | AH46: 0 | AI46: 0 | AJ46: 0 | AK46: 0 | AL46: 0 | AM46: 0 | AN46: 0 | AO46: 0 | AP46: 320 | AQ46: 0 | AR46: 650 | AS46: 0 | AV46: 69f6eaf230d08600013976ea | AW46: 樱桃木静音床-1.8米-榉木铺板 | AX46: 69f6eaf230d08600013976f4 | AY46: =H46 | AZ46: =BB46/(1-BA46) | BA46: 0.15 | BB46: =K46*0.96 | BC46: 1036273574687 | BD46: 待定 | BF46: =H46 | BG46: =BH46/BF46 | BH46: =I46 | BI46: =1-12% | BJ46: =BK46/(BF46-BF46*(1-BI46)) | BK46: =BM46/(1-BL46) | BL46: 0.01 | BM46: =J46 | BN46: =IF(BK46>=1500,BK46-150,IF(BK46>=800,BK46-80,IF(BK46>=500,BK46-50,IF(BK46>=200,BK46-20,BK46)))) | BO46: =1-12% | BP46: =BQ46/(BF46-BF46*(1-BO46)) | BQ46: =BS46/(1-BR46) | BR46: 0 | BS46: =K46 | BT46: =IF(BQ46>=1500,BQ46-150,IF(BQ46>=800,BQ46-80,IF(BQ46>=500,BQ46-50,IF(BQ46>=200,BQ46-20,BQ46)))) | CB46: ✅ 可导入 | CC46: ✓
A47: PPS26330110226 | B47: 畔色樱桃木静音双人床 |樱桃木小金属腿床 | C47: 樱桃木静音床-1.2米-松木铺板 | D47: PPS2633011022615 | E47: https://img.alicdn.com/imgextra/i1/2215699812811/O1CN01J8FGAH1WdUTYbCp0i_!!2215699812811.jpg | F47: 中型 | G47: =Q47/0.4 | H47: =G47*0.75 | I47: =Q47 / (0.855 - 0.02 - 0.006) | J47: =Q47 / (0.87 - 0.02 - 0.006) | K47: =Q47 / (0.9 - 0.02 - 0.006) | L47: =K47-N47 | M47: =L47/K47 | N47: =O47+P47+Q47 | O47: =K47*0.006 | P47: =K47*0.02 | Q47: =SUM(R47:T47) | R47: =IF(F47="大型",700,IF(F47="中型",300,IF(F47="小型",80,0))) | S47: =IF(F47="大型",150,IF(F47="中型",100,IF(F47="小型",0,0))) | T47: =SUM(U47:W47) | U47: 1640 | V47: 140 | W47: =SUM(X47:AS47) | X47: 0 | Y47: 0 | Z47: 0 | AA47: 0 | AB47: 0 | AC47: 0 | AD47: 0 | AE47: 0 | AF47: 0 | AG47: 0 | AH47: 0 | AI47: 0 | AJ47: 0 | AK47: 0 | AL47: 0 | AM47: 0 | AN47: 0 | AO47: 0 | AP47: 320 | AQ47: 0 | AR47: 160 | AS47: 0 | AV47: 69f6eaf230d08600013976ea | AW47: 樱桃木静音床-1.2米-松木铺板 | AX47: 69f6eaf230d08600013976f7 | AY47: =H47 | AZ47: =BB47/(1-BA47) | BA47: 0.15 | BB47: =K47*0.96 | BC47: 1036273574687 | BD47: 待定 | BF47: =H47 | BG47: =BH47/BF47 | BH47: =I47 | BI47: =1-12% | BJ47: =BK47/(BF47-BF47*(1-BI47)) | BK47: =BM47/(1-BL47) | BL47: 0.01 | BM47: =J47 | BN47: =IF(BK47>=1500,BK47-150,IF(BK47>=800,BK47-80,IF(BK47>=500,BK47-50,IF(BK47>=200,BK47-20,BK47)))) | BO47: =1-12% | BP47: =BQ47/(BF47-BF47*(1-BO47)) | BQ47: =BS47/(1-BR47) | BR47: 0 | BS47: =K47 | BT47: =IF(BQ47>=1500,BQ47-150,IF(BQ47>=800,BQ47-80,IF(BQ47>=500,BQ47-50,IF(BQ47>=200,BQ47-20,BQ47)))) | CB47: ✅ 可导入 | CC47: ✓
A48: PPS26330110226 | B48: 畔色樱桃木静音双人床 |樱桃木小金属腿床 | C48: 樱桃木静音床-1.35米-松木铺板 | D48: PPS2633011022616 | E48: https://img.alicdn.com/imgextra/i1/2215699812811/O1CN01J8FGAH1WdUTYbCp0i_!!2215699812811.jpg | F48: 中型 | G48: =Q48/0.4 | H48: =G48*0.75 | I48: =Q48 / (0.855 - 0.02 - 0.006) | J48: =Q48 / (0.87 - 0.02 - 0.006) | K48: =Q48 / (0.9 - 0.02 - 0.006) | L48: =K48-N48 | M48: =L48/K48 | N48: =O48+P48+Q48 | O48: =K48*0.006 | P48: =K48*0.02 | Q48: =SUM(R48:T48) | R48: =IF(F48="大型",700,IF(F48="中型",300,IF(F48="小型",80,0))) | S48: =IF(F48="大型",150,IF(F48="中型",100,IF(F48="小型",0,0))) | T48: =SUM(U48:W48) | U48: 1670 | V48: 140 | W48: =SUM(X48:AS48) | X48: 0 | Y48: 0 | Z48: 0 | AA48: 0 | AB48: 0 | AC48: 0 | AD48: 0 | AE48: 0 | AF48: 0 | AG48: 0 | AH48: 0 | AI48: 0 | AJ48: 0 | AK48: 0 | AL48: 0 | AM48: 0 | AN48: 0 | AO48: 0 | AP48: 320 | AQ48: 0 | AR48: 180 | AS48: 0 | AV48: 69f6eaf230d08600013976ea | AW48: 樱桃木静音床-1.35米-松木铺板 | AX48: 69f6eaf230d08600013976fa | AY48: =H48 | AZ48: =BB48/(1-BA48) | BA48: 0.15 | BB48: =K48*0.96 | BC48: 1036273574687 | BD48: 待定 | BF48: =H48 | BG48: =BH48/BF48 | BH48: =I48 | BI48: =1-12% | BJ48: =BK48/(BF48-BF48*(1-BI48)) | BK48: =BM48/(1-BL48) | BL48: 0.01 | BM48: =J48 | BN48: =IF(BK48>=1500,BK48-150,IF(BK48>=800,BK48-80,IF(BK48>=500,BK48-50,IF(BK48>=200,BK48-20,BK48)))) | BO48: =1-12% | BP48: =BQ48/(BF48-BF48*(1-BO48)) | BQ48: =BS48/(1-BR48) | BR48: 0 | BS48: =K48 | BT48: =IF(BQ48>=1500,BQ48-150,IF(BQ48>=800,BQ48-80,IF(BQ48>=500,BQ48-50,IF(BQ48>=200,BQ48-20,BQ48)))) | CB48: ✅ 可导入 | CC48: ✓
A49: PPS26330110226 | B49: 畔色樱桃木静音双人床 |樱桃木小金属腿床 | C49: 樱桃木静音床-1.5米-松木铺板 | D49: PPS2633011022617 | E49: https://img.alicdn.com/imgextra/i1/2215699812811/O1CN01J8FGAH1WdUTYbCp0i_!!2215699812811.jpg | F49: 中型 | G49: =Q49/0.4 | H49: =G49*0.75 | I49: =Q49 / (0.855 - 0.02 - 0.006) | J49: =Q49 / (0.87 - 0.02 - 0.006) | K49: =Q49 / (0.9 - 0.02 - 0.006) | L49: =K49-N49 | M49: =L49/K49 | N49: =O49+P49+Q49 | O49: =K49*0.006 | P49: =K49*0.02 | Q49: =SUM(R49:T49) | R49: =IF(F49="大型",700,IF(F49="中型",300,IF(F49="小型",80,0))) | S49: =IF(F49="大型",150,IF(F49="中型",100,IF(F49="小型",0,0))) | T49: =SUM(U49:W49) | U49: 1720 | V49: 150 | W49: =SUM(X49:AS49) | X49: 0 | Y49: 0 | Z49: 0 | AA49: 0 | AB49: 0 | AC49: 0 | AD49: 0 | AE49: 0 | AF49: 0 | AG49: 0 | AH49: 0 | AI49: 0 | AJ49: 0 | AK49: 0 | AL49: 0 | AM49: 0 | AN49: 0 | AO49: 0 | AP49: 320 | AQ49: 0 | AR49: 180 | AS49: 0 | AV49: 69f6eaf230d08600013976ea | AW49: 樱桃木静音床-1.5米-松木铺板 | AX49: 69f6eaf230d08600013976fd | AY49: =H49 | AZ49: =BB49/(1-BA49) | BA49: 0.15 | BB49: =K49*0.96 | BC49: 1036273574687 | BD49: 待定 | BF49: =H49 | BG49: =BH49/BF49 | BH49: =I49 | BI49: =1-12% | BJ49: =BK49/(BF49-BF49*(1-BI49)) | BK49: =BM49/(1-BL49) | BL49: 0.01 | BM49: =J49 | BN49: =IF(BK49>=1500,BK49-150,IF(BK49>=800,BK49-80,IF(BK49>=500,BK49-50,IF(BK49>=200,BK49-20,BK49)))) | BO49: =1-12% | BP49: =BQ49/(BF49-BF49*(1-BO49)) | BQ49: =BS49/(1-BR49) | BR49: 0 | BS49: =K49 | BT49: =IF(BQ49>=1500,BQ49-150,IF(BQ49>=800,BQ49-80,IF(BQ49>=500,BQ49-50,IF(BQ49>=200,BQ49-20,BQ49)))) | CB49: ✅ 可导入 | CC49: ✓
A50: PPS26330110226 | B50: 畔色樱桃木静音双人床 |樱桃木小金属腿床 | C50: 樱桃木静音床-1.8米-松木铺板 | D50: PPS2633011022618 | E50: https://img.alicdn.com/imgextra/i1/2215699812811/O1CN01J8FGAH1WdUTYbCp0i_!!2215699812811.jpg | F50: 中型 | G50: =Q50/0.4 | H50: =G50*0.75 | I50: =Q50 / (0.855 - 0.02 - 0.006) | J50: =Q50 / (0.87 - 0.02 - 0.006) | K50: =Q50 / (0.9 - 0.02 - 0.006) | L50: =K50-N50 | M50: =L50/K50 | N50: =O50+P50+Q50 | O50: =K50*0.006 | P50: =K50*0.02 | Q50: =SUM(R50:T50) | R50: =IF(F50="大型",700,IF(F50="中型",300,IF(F50="小型",80,0))) | S50: =IF(F50="大型",150,IF(F50="中型",100,IF(F50="小型",0,0))) | T50: =SUM(U50:W50) | U50: 1800 | V50: 150 | W50: =SUM(X50:AS50) | X50: 0 | Y50: 0 | Z50: 0 | AA50: 0 | AB50: 0 | AC50: 0 | AD50: 0 | AE50: 0 | AF50: 0 | AG50: 0 | AH50: 0 | AI50: 0 | AJ50: 0 | AK50: 0 | AL50: 0 | AM50: 0 | AN50: 0 | AO50: 0 | AP50: 320 | AQ50: 0 | AR50: 200 | AS50: 0 | AV50: 69f6eaf230d08600013976ea | AW50: 樱桃木静音床-1.8米-松木铺板 | AX50: 69f6eaf230d0860001397700 | AY50: =H50 | AZ50: =BB50/(1-BA50) | BA50: 0.15 | BB50: =K50*0.96 | BC50: 1036273574687 | BD50: 待定 | BF50: =H50 | BG50: =BH50/BF50 | BH50: =I50 | BI50: =1-12% | BJ50: =BK50/(BF50-BF50*(1-BI50)) | BK50: =BM50/(1-BL50) | BL50: 0.01 | BM50: =J50 | BN50: =IF(BK50>=1500,BK50-150,IF(BK50>=800,BK50-80,IF(BK50>=500,BK50-50,IF(BK50>=200,BK50-20,BK50)))) | BO50: =1-12% | BP50: =BQ50/(BF50-BF50*(1-BO50)) | BQ50: =BS50/(1-BR50) | BR50: 0 | BS50: =K50 | BT50: =IF(BQ50>=1500,BQ50-150,IF(BQ50>=800,BQ50-80,IF(BQ50>=500,BQ50-50,IF(BQ50>=200,BQ50-20,BQ50)))) | CB50: ✅ 可导入 | CC50: ✓
A51: PPS26330110226 | B51: 畔色樱桃木静音双人床 |樱桃木小金属腿床 | C51: 樱桃木静音床-配件-mini床头柜 | D51: PPS2633011022619 | E51: https://img.alicdn.com/imgextra/i1/2215699812811/O1CN01J8FGAH1WdUTYbCp0i_!!2215699812811.jpg | F51: 中型 | G51: =Q51/0.4 | H51: =G51*0.75 | I51: =Q51 / (0.855 - 0.02 - 0.006) | J51: =Q51 / (0.87 - 0.02 - 0.006) | K51: =Q51 / (0.9 - 0.02 - 0.006) | L51: =K51-N51 | M51: =L51/K51 | N51: =O51+P51+Q51 | O51: =ZS21*0.006 | P51: =ZS21*0.02 | Q51: =SUM(R51:T51) | R51: =IF(F51="大型",700,IF(F51="中型",300,IF(F51="小型",80,0))) | S51: =IF(F51="大型",150,IF(F51="中型",100,IF(F51="小型",0,0))) | T51: =SUM(U51:W51) | U51: 40 | V51: 20 | W51: =SUM(X51:AS51) | X51: 0 | Y51: 0 | Z51: 0 | AA51: 0 | AB51: 0 | AC51: 0 | AD51: 0 | AE51: 0 | AF51: 0 | AG51: 0 | AH51: 0 | AI51: 0 | AJ51: 0 | AK51: 0 | AL51: 0 | AM51: 0 | AN51: 0 | AO51: 0 | AP51: 0 | AQ51: 0 | AR51: 0 | AS51: 0 | AV51: 69f6eaf230d08600013976ea | AW51: 樱桃木静音床-配件-mini床头柜 | AX51: 69f6eaf230d0860001397703 | AY51: =H51 | AZ51: =BB51/(1-BA51) | BA51: 0.15 | BB51: =K51*0.96 | BC51: 1036273574687 | BD51: 待定 | BF51: =H51 | BG51: =BH51/BF51 | BH51: =I51 | BI51: =1-12% | BJ51: =BK51/(BF51-BF51*(1-BI51)) | BK51: =BM51/(1-BL51) | BL51: 0.01 | BM51: =J51 | BN51: =IF(BK51>=1500,BK51-150,IF(BK51>=800,BK51-80,IF(BK51>=500,BK51-50,IF(BK51>=200,BK51-20,BK51)))) | BO51: =1-12% | BP51: =BQ51/(BF51-BF51*(1-BO51)) | BQ51: =BS51/(1-BR51) | BR51: 0 | BS51: =K51 | BT51: =IF(BQ51>=1500,BQ51-150,IF(BQ51>=800,BQ51-80,IF(BQ51>=500,BQ51-50,IF(BQ51>=200,BQ51-20,BQ51)))) | CB51: ✅ 可导入 | CC51: ✓
A52: PPS26330120327 | B52: 畔色樱桃木箱体床 |樱桃木软包箱体床 | C52: 樱桃木箱体床-软包床头-1.5米-榉木铺板 | D52: PPS2633012032711 | E52: https://img.alicdn.com/imgextra/i2/2215699812811/O1CN01oo0Q9I1WdUTX1875x_!!2215699812811.jpg | F52: 中型 | G52: =Q52/0.4 | H52: =G52*0.75 | I52: =Q52 / (0.855 - 0.02 - 0.006) | J52: =Q52 / (0.87 - 0.02 - 0.006) | K52: =Q52 / (0.9 - 0.02 - 0.006) | L52: =K52-N52 | M52: =L52/K52 | N52: =O52+P52+Q52 | O52: =ZS22*0.006 | P52: =ZS22*0.02 | Q52: =SUM(R52:T52) | R52: =IF(F52="大型",700,IF(F52="中型",300,IF(F52="小型",80,0))) | S52: =IF(F52="大型",150,IF(F52="中型",100,IF(F52="小型",0,0))) | T52: =SUM(U52:W52) | U52: 1770 | V52: 200 | W52: =SUM(X52:AS52) | X52: 0 | Y52: 0 | Z52: 0 | AA52: 0 | AB52: 0 | AC52: 0 | AD52: 0 | AE52: 0 | AF52: 0 | AG52: 0 | AH52: 0 | AI52: 0 | AJ52: 0 | AK52: 0 | AL52: 0 | AM52: 0 | AN52: 0 | AO52: 0 | AP52: 0 | AQ52: 1030 | AR52: 630 | AS52: 0 | AT52: 大象耳朵：420；超纤皮加冲孔210元；液压杆400元 | AV52: 69f6effa9dea2d0001b313db | AW52: 樱桃木箱体床-软包床头-1.5米-榉木铺板 | AX52: 69f6effa9dea2d0001b313dc | AY52: =H52 | AZ52: =BB52/(1-BA52) | BA52: 0.15 | BB52: =K52*0.96 | BC52: 1037224597517 | BD52: 待定 | BF52: =H52 | BG52: =BH52/BF52 | BH52: =I52 | BI52: =1-12% | BJ52: =BK52/(BF52-BF52*(1-BI52)) | BK52: =BM52/(1-BL52) | BL52: 0.01 | BM52: =J52 | BN52: =IF(BK52>=1500,BK52-150,IF(BK52>=800,BK52-80,IF(BK52>=500,BK52-50,IF(BK52>=200,BK52-20,BK52)))) | BO52: =1-12% | BP52: =BQ52/(BF52-BF52*(1-BO52)) | BQ52: =BS52/(1-BR52) | BR52: 0 | BS52: =K52 | BT52: =IF(BQ52>=1500,BQ52-150,IF(BQ52>=800,BQ52-80,IF(BQ52>=500,BQ52-50,IF(BQ52>=200,BQ52-20,BQ52)))) | CB52: ✅ 可导入 | CC52: ✓
A53: PPS26330120327 | B53: 畔色樱桃木箱体床 |樱桃木软包箱体床 | C53: 樱桃木箱体床-软包床头-1.8米-榉木铺板 | D53: PPS2633012032712 | E53: https://img.alicdn.com/imgextra/i2/2215699812811/O1CN01oo0Q9I1WdUTX1875x_!!2215699812811.jpg | F53: 中型 | G53: =Q53/0.4 | H53: =G53*0.75 | I53: =Q53 / (0.855 - 0.02 - 0.006) | J53: =Q53 / (0.87 - 0.02 - 0.006) | K53: =Q53 / (0.9 - 0.02 - 0.006) | L53: =K53-N53 | M53: =L53/K53 | N53: =O53+P53+Q53 | O53: =ZS23*0.006 | P53: =ZS23*0.02 | Q53: =SUM(R53:T53) | R53: =IF(F53="大型",700,IF(F53="中型",300,IF(F53="小型",80,0))) | S53: =IF(F53="大型",150,IF(F53="中型",100,IF(F53="小型",0,0))) | T53: =SUM(U53:W53) | U53: 1890 | V53: 230 | W53: =SUM(X53:AS53) | X53: 0 | Y53: 0 | Z53: 0 | AA53: 0 | AB53: 0 | AC53: 0 | AD53: 0 | AE53: 0 | AF53: 0 | AG53: 0 | AH53: 0 | AI53: 0 | AJ53: 0 | AK53: 0 | AL53: 0 | AM53: 0 | AN53: 0 | AO53: 0 | AP53: 0 | AQ53: 1081 | AR53: 650 | AS53: 0 | AT53: 大象耳朵：450；超纤皮加冲孔231元；液压杆400元 | AV53: 69f6effa9dea2d0001b313db | AW53: 樱桃木箱体床-软包床头-1.8米-榉木铺板 | AX53: 69f6effa9dea2d0001b313df | AY53: =H53 | AZ53: =BB53/(1-BA53) | BA53: 0.15 | BB53: =K53*0.96 | BC53: 1037224597517 | BD53: 待定 | BF53: =H53 | BG53: =BH53/BF53 | BH53: =I53 | BI53: =1-12% | BJ53: =BK53/(BF53-BF53*(1-BI53)) | BK53: =BM53/(1-BL53) | BL53: 0.01 | BM53: =J53 | BN53: =IF(BK53>=1500,BK53-150,IF(BK53>=800,BK53-80,IF(BK53>=500,BK53-50,IF(BK53>=200,BK53-20,BK53)))) | BO53: =1-12% | BP53: =BQ53/(BF53-BF53*(1-BO53)) | BQ53: =BS53/(1-BR53) | BR53: 0 | BS53: =K53 | BT53: =IF(BQ53>=1500,BQ53-150,IF(BQ53>=800,BQ53-80,IF(BQ53>=500,BQ53-50,IF(BQ53>=200,BQ53-20,BQ53)))) | CB53: ✅ 可导入 | CC53: ✓
A54: PPS26330120327 | B54: 畔色樱桃木箱体床 |樱桃木软包箱体床 | C54: 樱桃木箱体床-无床头-1.5米-榉木铺板 | D54: PPS2633012032713 | E54: https://img.alicdn.com/imgextra/i2/2215699812811/O1CN01oo0Q9I1WdUTX1875x_!!2215699812811.jpg | F54: 中型 | G54: =Q54/0.4 | H54: =G54*0.75 | I54: =Q54 / (0.855 - 0.02 - 0.006) | J54: =Q54 / (0.87 - 0.02 - 0.006) | K54: =Q54 / (0.9 - 0.02 - 0.006) | L54: =K54-N54 | M54: =L54/K54 | N54: =O54+P54+Q54 | O54: =ZS24*0.006 | P54: =ZS24*0.02 | Q54: =SUM(R54:T54) | R54: =IF(F54="大型",700,IF(F54="中型",300,IF(F54="小型",80,0))) | S54: =IF(F54="大型",150,IF(F54="中型",100,IF(F54="小型",0,0))) | T54: =SUM(U54:W54) | U54: 1470 | V54: 150 | W54: =SUM(X54:AS54) | X54: 0 | Y54: 0 | Z54: 0 | AA54: 0 | AB54: 0 | AC54: 0 | AD54: 0 | AE54: 0 | AF54: 0 | AG54: 0 | AH54: 0 | AI54: 0 | AJ54: 0 | AK54: 0 | AL54: 0 | AM54: 0 | AN54: 0 | AO54: 0 | AP54: 0 | AQ54: 400 | AR54: 630 | AS54: 0 | AT54: 液压杆400元 | AV54: 69f6effa9dea2d0001b313db | AW54: 樱桃木箱体床-无床头-1.5米-榉木铺板 | AX54: 69f6effa9dea2d0001b313e2 | AY54: =H54 | AZ54: =BB54/(1-BA54) | BA54: 0.15 | BB54: =K54*0.96 | BC54: 1037224597517 | BD54: 待定 | BF54: =H54 | BG54: =BH54/BF54 | BH54: =I54 | BI54: =1-12% | BJ54: =BK54/(BF54-BF54*(1-BI54)) | BK54: =BM54/(1-BL54) | BL54: 0.01 | BM54: =J54 | BN54: =IF(BK54>=1500,BK54-150,IF(BK54>=800,BK54-80,IF(BK54>=500,BK54-50,IF(BK54>=200,BK54-20,BK54)))) | BO54: =1-12% | BP54: =BQ54/(BF54-BF54*(1-BO54)) | BQ54: =BS54/(1-BR54) | BR54: 0 | BS54: =K54 | BT54: =IF(BQ54>=1500,BQ54-150,IF(BQ54>=800,BQ54-80,IF(BQ54>=500,BQ54-50,IF(BQ54>=200,BQ54-20,BQ54)))) | CB54: ✅ 可导入 | CC54: ✓
A55: PPS26330120327 | B55: 畔色樱桃木箱体床 |樱桃木软包箱体床 | C55: 樱桃木箱体床-无床头-1.8米-榉木铺板 | D55: PPS2633012032714 | E55: https://img.alicdn.com/imgextra/i2/2215699812811/O1CN01oo0Q9I1WdUTX1875x_!!2215699812811.jpg | F55: 中型 | G55: =Q55/0.4 | H55: =G55*0.75 | I55: =Q55 / (0.855 - 0.02 - 0.006) | J55: =Q55 / (0.87 - 0.02 - 0.006) | K55: =Q55 / (0.9 - 0.02 - 0.006) | L55: =K55-N55 | M55: =L55/K55 | N55: =O55+P55+Q55 | O55: =ZS25*0.006 | P55: =ZS25*0.02 | Q55: =SUM(R55:T55) | R55: =IF(F55="大型",700,IF(F55="中型",300,IF(F55="小型",80,0))) | S55: =IF(F55="大型",150,IF(F55="中型",100,IF(F55="小型",0,0))) | T55: =SUM(U55:W55) | U55: 1590 | V55: 180 | W55: =SUM(X55:AS55) | X55: 0 | Y55: 0 | Z55: 0 | AA55: 0 | AB55: 0 | AC55: 0 | AD55: 0 | AE55: 0 | AF55: 0 | AG55: 0 | AH55: 0 | AI55: 0 | AJ55: 0 | AK55: 0 | AL55: 0 | AM55: 0 | AN55: 0 | AO55: 0 | AP55: 0 | AQ55: 400 | AR55: 650 | AS55: 0 | AT55: 液压杆400元 | AV55: 69f6effa9dea2d0001b313db | AW55: 樱桃木箱体床-无床头-1.8米-榉木铺板 | AX55: 69f6effa9dea2d0001b313e5 | AY55: =H55 | AZ55: =BB55/(1-BA55) | BA55: 0.15 | BB55: =K55*0.96 | BC55: 1037224597517 | BD55: 待定 | BF55: =H55 | BG55: =BH55/BF55 | BH55: =I55 | BI55: =1-12% | BJ55: =BK55/(BF55-BF55*(1-BI55)) | BK55: =BM55/(1-BL55) | BL55: 0.01 | BM55: =J55 | BN55: =IF(BK55>=1500,BK55-150,IF(BK55>=800,BK55-80,IF(BK55>=500,BK55-50,IF(BK55>=200,BK55-20,BK55)))) | BO55: =1-12% | BP55: =BQ55/(BF55-BF55*(1-BO55)) | BQ55: =BS55/(1-BR55) | BR55: 0 | BS55: =K55 | BT55: =IF(BQ55>=1500,BQ55-150,IF(BQ55>=800,BQ55-80,IF(BQ55>=500,BQ55-50,IF(BQ55>=200,BQ55-20,BQ55)))) | CB55: ✅ 可导入 | CC55: ✓
A56: PPS26330130115 | B56: 畔色黑胡桃木梯形腿双人床 |黑胡桃木拱形腿床 | C56: 黑胡桃木梯形腿床-1.2米-榉木铺板 | D56: PPS2633013011511 | E56: https://img.alicdn.com/imgextra/i1/2215699812811/O1CN018XX4eC1WdUTgNWN85_!!2215699812811.jpg | F56: 中型 | G56: =Q56/0.4 | H56: =G56*0.75 | I56: =Q56 / (0.79 - 0.02 - 0.006) | J56: =Q56 / (0.8 - 0.02 - 0.006) | K56: =Q56 / (0.82 - 0.02 - 0.006) | L56: =K56-N56 | M56: =L56/K56 | N56: =O56+P56+Q56 | O56: =ZS26*0.006 | P56: =ZS26*0.02 | Q56: =SUM(R56:T56) | R56: =IF(F56="大型",700,IF(F56="中型",300,IF(F56="小型",80,0))) | S56: =IF(F56="大型",150,IF(F56="中型",100,IF(F56="小型",0,0))) | T56: =SUM(U56:W56) | U56: 1810 | V56: 140 | W56: =SUM(X56:AS56) | X56: 0 | Y56: 0 | Z56: 0 | AA56: 0 | AB56: 0 | AC56: 0 | AD56: 0 | AE56: 0 | AF56: 0 | AG56: 0 | AH56: 0 | AI56: 0 | AJ56: 0 | AK56: 0 | AL56: 0 | AM56: 0 | AN56: 0 | AO56: 0 | AP56: 0 | AQ56: 320 | AR56: 590 | AS56: 0 | AT56: 拉点床软包：320 | AU56: 1.8床铺板打孔+纸箱+整片=23*22+50=556 1.5规格是536，1.2规格是520 | AV56: 69f6f7fa0283e20001b46bbb | AW56: 黑胡桃木梯形腿床-1.2米-榉木铺板 | AX56: 69f6f7fa0283e20001b46bbc | AY56: =H56 | AZ56: =BB56/(1-BA56) | BA56: 0.15 | BB56: =K56*0.96 | BC56: 1038071596128 | BD56: 待定 | BF56: =H56 | BG56: =BH56/BF56 | BH56: =I56 | BI56: =1-12% | BJ56: =BK56/(BF56-BF56*(1-BI56)) | BK56: =BM56/(1-BL56) | BL56: 0.01 | BM56: =J56 | BN56: =IF(BK56>=1500,BK56-150,IF(BK56>=800,BK56-80,IF(BK56>=500,BK56-50,IF(BK56>=200,BK56-20,BK56)))) | BO56: =1-12% | BP56: =BQ56/(BF56-BF56*(1-BO56)) | BQ56: =BS56/(1-BR56) | BR56: 0 | BS56: =K56 | BT56: =IF(BQ56>=1500,BQ56-150,IF(BQ56>=800,BQ56-80,IF(BQ56>=500,BQ56-50,IF(BQ56>=200,BQ56-20,BQ56)))) | CB56: ✅ 可导入 | CC56: ✓
A57: PPS26330130115 | B57: 畔色黑胡桃木梯形腿双人床 |黑胡桃木拱形腿床 | C57: 黑胡桃木梯形腿床-1.35米-榉木铺板 | D57: PPS2633013011512 | E57: https://img.alicdn.com/imgextra/i1/2215699812811/O1CN018XX4eC1WdUTgNWN85_!!2215699812811.jpg | F57: 中型 | G57: =Q57/0.4 | H57: =G57*0.75 | I57: =Q57 / (0.79 - 0.02 - 0.006) | J57: =Q57 / (0.8 - 0.02 - 0.006) | K57: =Q57 / (0.82 - 0.02 - 0.006) | L57: =K57-N57 | M57: =L57/K57 | N57: =O57+P57+Q57 | O57: =ZS27*0.006 | P57: =ZS27*0.02 | Q57: =SUM(R57:T57) | R57: =IF(F57="大型",700,IF(F57="中型",300,IF(F57="小型",80,0))) | S57: =IF(F57="大型",150,IF(F57="中型",100,IF(F57="小型",0,0))) | T57: =SUM(U57:W57) | U57: 1840 | V57: 140 | W57: =SUM(X57:AS57) | X57: 0 | Y57: 0 | Z57: 0 | AA57: 0 | AB57: 0 | AC57: 0 | AD57: 0 | AE57: 0 | AF57: 0 | AG57: 0 | AH57: 0 | AI57: 0 | AJ57: 0 | AK57: 0 | AL57: 0 | AM57: 0 | AN57: 0 | AO57: 0 | AP57: 0 | AQ57: 330 | AR57: 610 | AS57: 0 | AT57: 拉点床软包：330 | AU57: 1.8床铺板打孔+纸箱+整片=23*22+50=556 1.5规格是536，1.2规格是521 | AV57: 69f6f7fa0283e20001b46bbb | AW57: 黑胡桃木梯形腿床-1.35米-榉木铺板 | AX57: 69f6f7fa0283e20001b46bbf | AY57: =H57 | AZ57: =BB57/(1-BA57) | BA57: 0.15 | BB57: =K57*0.96 | BC57: 1038071596128 | BD57: 待定 | BF57: =H57 | BG57: =BH57/BF57 | BH57: =I57 | BI57: =1-12% | BJ57: =BK57/(BF57-BF57*(1-BI57)) | BK57: =BM57/(1-BL57) | BL57: 0.01 | BM57: =J57 | BN57: =IF(BK57>=1500,BK57-150,IF(BK57>=800,BK57-80,IF(BK57>=500,BK57-50,IF(BK57>=200,BK57-20,BK57)))) | BO57: =1-12% | BP57: =BQ57/(BF57-BF57*(1-BO57)) | BQ57: =BS57/(1-BR57) | BR57: 0 | BS57: =K57 | BT57: =IF(BQ57>=1500,BQ57-150,IF(BQ57>=800,BQ57-80,IF(BQ57>=500,BQ57-50,IF(BQ57>=200,BQ57-20,BQ57)))) | CB57: ✅ 可导入 | CC57: ✓
A58: PPS26330130115 | B58: 畔色黑胡桃木梯形腿双人床 |黑胡桃木拱形腿床 | C58: 黑胡桃木梯形腿床-1.5米-榉木铺板 | D58: PPS2633013011513 | E58: https://img.alicdn.com/imgextra/i1/2215699812811/O1CN018XX4eC1WdUTgNWN85_!!2215699812811.jpg | F58: 中型 | G58: =Q58/0.4 | H58: =G58*0.75 | I58: =Q58 / (0.79 - 0.02 - 0.006) | J58: =Q58 / (0.8 - 0.02 - 0.006) | K58: =Q58 / (0.82 - 0.02 - 0.006) | L58: =K58-N58 | M58: =L58/K58 | N58: =O58+P58+Q58 | O58: =ZS28*0.006 | P58: =ZS28*0.02 | Q58: =SUM(R58:T58) | R58: =IF(F58="大型",700,IF(F58="中型",300,IF(F58="小型",80,0))) | S58: =IF(F58="大型",150,IF(F58="中型",100,IF(F58="小型",0,0))) | T58: =SUM(U58:W58) | U58: 1920 | V58: 150 | W58: =SUM(X58:AS58) | X58: 0 | Y58: 0 | Z58: 0 | AA58: 0 | AB58: 0 | AC58: 0 | AD58: 0 | AE58: 0 | AF58: 0 | AG58: 0 | AH58: 0 | AI58: 0 | AJ58: 0 | AK58: 0 | AL58: 0 | AM58: 0 | AN58: 0 | AO58: 0 | AP58: 0 | AQ58: 340 | AR58: 630 | AS58: 0 | AT58: 拉点床软包：340 | AU58: 1.8床铺板打孔+纸箱+整片=23*22+50=556 1.5规格是536，1.2规格是522 | AV58: 69f6f7fa0283e20001b46bbb | AW58: 黑胡桃木梯形腿床-1.5米-榉木铺板 | AX58: 69f6f7fa0283e20001b46bc2 | AY58: =H58 | AZ58: =BB58/(1-BA58) | BA58: 0.15 | BB58: =K58*0.96 | BC58: 1038071596128 | BD58: 待定 | BF58: =H58 | BG58: =BH58/BF58 | BH58: =I58 | BI58: =1-12% | BJ58: =BK58/(BF58-BF58*(1-BI58)) | BK58: =BM58/(1-BL58) | BL58: 0.01 | BM58: =J58 | BN58: =IF(BK58>=1500,BK58-150,IF(BK58>=800,BK58-80,IF(BK58>=500,BK58-50,IF(BK58>=200,BK58-20,BK58)))) | BO58: =1-12% | BP58: =BQ58/(BF58-BF58*(1-BO58)) | BQ58: =BS58/(1-BR58) | BR58: 0 | BS58: =K58 | BT58: =IF(BQ58>=1500,BQ58-150,IF(BQ58>=800,BQ58-80,IF(BQ58>=500,BQ58-50,IF(BQ58>=200,BQ58-20,BQ58)))) | CB58: ✅ 可导入 | CC58: ✓
A59: PPS26330130115 | B59: 畔色黑胡桃木梯形腿双人床 |黑胡桃木拱形腿床 | C59: 黑胡桃木梯形腿床-1.8米-榉木铺板 | D59: PPS2633013011514 | E59: https://img.alicdn.com/imgextra/i1/2215699812811/O1CN018XX4eC1WdUTgNWN85_!!2215699812811.jpg | F59: 中型 | G59: =Q59/0.4 | H59: =G59*0.75 | I59: =Q59 / (0.79 - 0.02 - 0.006) | J59: =Q59 / (0.8 - 0.02 - 0.006) | K59: =Q59 / (0.82 - 0.02 - 0.006) | L59: =K59-N59 | M59: =L59/K59 | N59: =O59+P59+Q59 | O59: =ZS29*0.006 | P59: =ZS29*0.02 | Q59: =SUM(R59:T59) | R59: =IF(F59="大型",700,IF(F59="中型",300,IF(F59="小型",80,0))) | S59: =IF(F59="大型",150,IF(F59="中型",100,IF(F59="小型",0,0))) | T59: =SUM(U59:W59) | U59: 2050 | V59: 150 | W59: =SUM(X59:AS59) | X59: 0 | Y59: 0 | Z59: 0 | AA59: 0 | AB59: 0 | AC59: 0 | AD59: 0 | AE59: 0 | AF59: 0 | AG59: 0 | AH59: 0 | AI59: 0 | AJ59: 0 | AK59: 0 | AL59: 0 | AM59: 0 | AN59: 0 | AO59: 0 | AP59: 0 | AQ59: 350 | AR59: 650 | AS59: 0 | AT59: 拉点床软包：350 | AU59: 1.8床铺板打孔+纸箱+整片=23*22+50=556 1.5规格是536，1.2规格是523 | AV59: 69f6f7fa0283e20001b46bbb | AW59: 黑胡桃木梯形腿床-1.8米-榉木铺板 | AX59: 69f6f7fa0283e20001b46bc5 | AY59: =H59 | AZ59: =BB59/(1-BA59) | BA59: 0.15 | BB59: =K59*0.96 | BC59: 1038071596128 | BD59: 待定 | BF59: =H59 | BG59: =BH59/BF59 | BH59: =I59 | BI59: =1-12% | BJ59: =BK59/(BF59-BF59*(1-BI59)) | BK59: =BM59/(1-BL59) | BL59: 0.01 | BM59: =J59 | BN59: =IF(BK59>=1500,BK59-150,IF(BK59>=800,BK59-80,IF(BK59>=500,BK59-50,IF(BK59>=200,BK59-20,BK59)))) | BO59: =1-12% | BP59: =BQ59/(BF59-BF59*(1-BO59)) | BQ59: =BS59/(1-BR59) | BR59: 0 | BS59: =K59 | BT59: =IF(BQ59>=1500,BQ59-150,IF(BQ59>=800,BQ59-80,IF(BQ59>=500,BQ59-50,IF(BQ59>=200,BQ59-20,BQ59)))) | CB59: ✅ 可导入 | CC59: ✓
A60: PPS26330130115 | B60: 畔色黑胡桃木梯形腿双人床 |黑胡桃木拱形腿床 | C60: 黑胡桃木梯形腿床-1.2米-松木铺板 | D60: PPS2633013011515 | E60: https://img.alicdn.com/imgextra/i1/2215699812811/O1CN018XX4eC1WdUTgNWN85_!!2215699812811.jpg | F60: 中型 | G60: =Q60/0.4 | H60: =G60*0.75 | I60: =Q60 / (0.79 - 0.02 - 0.006) | J60: =Q60 / (0.8 - 0.02 - 0.006) | K60: =Q60 / (0.82 - 0.02 - 0.006) | L60: =K60-N60 | M60: =L60/K60 | N60: =O60+P60+Q60 | O60: =ZS30*0.006 | P60: =ZS30*0.02 | Q60: =SUM(R60:T60) | R60: =IF(F60="大型",700,IF(F60="中型",300,IF(F60="小型",80,0))) | S60: =IF(F60="大型",150,IF(F60="中型",100,IF(F60="小型",0,0))) | T60: =SUM(U60:W60) | U60: 1740 | V60: 140 | W60: =SUM(X60:AS60) | X60: 0 | Y60: 0 | Z60: 0 | AA60: 0 | AB60: 0 | AC60: 0 | AD60: 0 | AE60: 0 | AF60: 0 | AG60: 0 | AH60: 0 | AI60: 0 | AJ60: 0 | AK60: 0 | AL60: 0 | AM60: 0 | AN60: 0 | AO60: 0 | AP60: 0 | AQ60: 320 | AR60: 160 | AS60: 0 | AT60: 拉点床软包：320 | AU60: 1.8床铺板打孔+纸箱+整片=23*22+50=556 1.5规格是536，1.2规格是524 | AV60: 69f6f7fa0283e20001b46bbb | AW60: 黑胡桃木梯形腿床-1.2米-松木铺板 | AX60: 69f6f7fa0283e20001b46bc8 | AY60: =H60 | AZ60: =BB60/(1-BA60) | BA60: 0.15 | BB60: =K60*0.96 | BC60: 1038071596128 | BD60: 待定 | BF60: =H60 | BG60: =BH60/BF60 | BH60: =I60 | BI60: =1-12% | BJ60: =BK60/(BF60-BF60*(1-BI60)) | BK60: =BM60/(1-BL60) | BL60: 0.01 | BM60: =J60 | BN60: =IF(BK60>=1500,BK60-150,IF(BK60>=800,BK60-80,IF(BK60>=500,BK60-50,IF(BK60>=200,BK60-20,BK60)))) | BO60: =1-12% | BP60: =BQ60/(BF60-BF60*(1-BO60)) | BQ60: =BS60/(1-BR60) | BR60: 0 | BS60: =K60 | BT60: =IF(BQ60>=1500,BQ60-150,IF(BQ60>=800,BQ60-80,IF(BQ60>=500,BQ60-50,IF(BQ60>=200,BQ60-20,BQ60)))) | CB60: ✅ 可导入 | CC60: ✓
A61: PPS26330130115 | B61: 畔色黑胡桃木梯形腿双人床 |黑胡桃木拱形腿床 | C61: 黑胡桃木梯形腿床-1.35米-松木铺板 | D61: PPS2633013011516 | E61: https://img.alicdn.com/imgextra/i1/2215699812811/O1CN018XX4eC1WdUTgNWN85_!!2215699812811.jpg | F61: 中型 | G61: =Q61/0.4 | H61: =G61*0.75 | I61: =Q61 / (0.79 - 0.02 - 0.006) | J61: =Q61 / (0.8 - 0.02 - 0.006) | K61: =Q61 / (0.82 - 0.02 - 0.006) | L61: =K61-N61 | M61: =L61/K61 | N61: =O61+P61+Q61 | O61: =K61*0.006 | P61: =K61*0.02 | Q61: =SUM(R61:T61) | R61: =IF(F61="大型",700,IF(F61="中型",300,IF(F61="小型",80,0))) | S61: =IF(F61="大型",150,IF(F61="中型",100,IF(F61="小型",0,0))) | T61: =SUM(U61:W61) | U61: 1770 | V61: 140 | W61: =SUM(X61:AS61) | X61: 0 | Y61: 0 | Z61: 0 | AA61: 0 | AB61: 0 | AC61: 0 | AD61: 0 | AE61: 0 | AF61: 0 | AG61: 0 | AH61: 0 | AI61: 0 | AJ61: 0 | AK61: 0 | AL61: 0 | AM61: 0 | AN61: 0 | AO61: 0 | AP61: 0 | AQ61: 330 | AR61: 180 | AS61: 0 | AT61: 拉点床软包：330 | AU61: 1.8床铺板打孔+纸箱+整片=23*22+50=556 1.5规格是536，1.2规格是525 | AV61: 69f6f7fa0283e20001b46bbb | AW61: 黑胡桃木梯形腿床-1.35米-松木铺板 | AX61: 69f6f7fa0283e20001b46bcb | AY61: =H61 | AZ61: =BB61/(1-BA61) | BA61: 0.15 | BB61: =K61*0.96 | BC61: 1038071596128 | BD61: 待定 | BF61: =H61 | BG61: =BH61/BF61 | BH61: =I61 | BI61: =1-12% | BJ61: =BK61/(BF61-BF61*(1-BI61)) | BK61: =BM61/(1-BL61) | BL61: 0.01 | BM61: =J61 | BN61: =IF(BK61>=1500,BK61-150,IF(BK61>=800,BK61-80,IF(BK61>=500,BK61-50,IF(BK61>=200,BK61-20,BK61)))) | BO61: =1-12% | BP61: =BQ61/(BF61-BF61*(1-BO61)) | BQ61: =BS61/(1-BR61) | BR61: 0 | BS61: =K61 | BT61: =IF(BQ61>=1500,BQ61-150,IF(BQ61>=800,BQ61-80,IF(BQ61>=500,BQ61-50,IF(BQ61>=200,BQ61-20,BQ61)))) | CB61: ✅ 可导入 | CC61: ✓
A62: PPS26330130115 | B62: 畔色黑胡桃木梯形腿双人床 |黑胡桃木拱形腿床 | C62: 黑胡桃木梯形腿床-1.5米-松木铺板 | D62: PPS2633013011517 | E62: https://img.alicdn.com/imgextra/i1/2215699812811/O1CN018XX4eC1WdUTgNWN85_!!2215699812811.jpg | F62: 中型 | G62: =Q62/0.4 | H62: =G62*0.75 | I62: =Q62 / (0.79 - 0.02 - 0.006) | J62: =Q62 / (0.8 - 0.02 - 0.006) | K62: =Q62 / (0.82 - 0.02 - 0.006) | L62: =K62-N62 | M62: =L62/K62 | N62: =O62+P62+Q62 | O62: =K62*0.006 | P62: =K62*0.02 | Q62: =SUM(R62:T62) | R62: =IF(F62="大型",700,IF(F62="中型",300,IF(F62="小型",80,0))) | S62: =IF(F62="大型",150,IF(F62="中型",100,IF(F62="小型",0,0))) | T62: =SUM(U62:W62) | U62: 1820 | V62: 150 | W62: =SUM(X62:AS62) | X62: 0 | Y62: 0 | Z62: 0 | AA62: 0 | AB62: 0 | AC62: 0 | AD62: 0 | AE62: 0 | AF62: 0 | AG62: 0 | AH62: 0 | AI62: 0 | AJ62: 0 | AK62: 0 | AL62: 0 | AM62: 0 | AN62: 0 | AO62: 0 | AP62: 0 | AQ62: 340 | AR62: 180 | AS62: 0 | AT62: 拉点床软包：340 | AU62: 1.8床铺板打孔+纸箱+整片=23*22+50=556 1.5规格是536，1.2规格是526 | AV62: 69f6f7fa0283e20001b46bbb | AW62: 黑胡桃木梯形腿床-1.5米-松木铺板 | AX62: 69f6f7fa0283e20001b46bce | AY62: =H62 | AZ62: =BB62/(1-BA62) | BA62: 0.15 | BB62: =K62*0.96 | BC62: 1038071596128 | BD62: 待定 | BF62: =H62 | BG62: =BH62/BF62 | BH62: =I62 | BI62: =1-12% | BJ62: =BK62/(BF62-BF62*(1-BI62)) | BK62: =BM62/(1-BL62) | BL62: 0.01 | BM62: =J62 | BN62: =IF(BK62>=1500,BK62-150,IF(BK62>=800,BK62-80,IF(BK62>=500,BK62-50,IF(BK62>=200,BK62-20,BK62)))) | BO62: =1-12% | BP62: =BQ62/(BF62-BF62*(1-BO62)) | BQ62: =BS62/(1-BR62) | BR62: 0 | BS62: =K62 | BT62: =IF(BQ62>=1500,BQ62-150,IF(BQ62>=800,BQ62-80,IF(BQ62>=500,BQ62-50,IF(BQ62>=200,BQ62-20,BQ62)))) | CB62: ✅ 可导入 | CC62: ✓
A63: PPS26330130115 | B63: 畔色黑胡桃木梯形腿双人床 |黑胡桃木拱形腿床 | C63: 黑胡桃木梯形腿床-1.8米-松木铺板 | D63: PPS2633013011518 | E63: https://img.alicdn.com/imgextra/i1/2215699812811/O1CN018XX4eC1WdUTgNWN85_!!2215699812811.jpg | F63: 中型 | G63: =Q63/0.4 | H63: =G63*0.75 | I63: =Q63 / (0.79 - 0.02 - 0.006) | J63: =Q63 / (0.8 - 0.02 - 0.006) | K63: =Q63 / (0.82 - 0.02 - 0.006) | L63: =K63-N63 | M63: =L63/K63 | N63: =O63+P63+Q63 | O63: =K63*0.006 | P63: =K63*0.02 | Q63: =SUM(R63:T63) | R63: =IF(F63="大型",700,IF(F63="中型",300,IF(F63="小型",80,0))) | S63: =IF(F63="大型",150,IF(F63="中型",100,IF(F63="小型",0,0))) | T63: =SUM(U63:W63) | U63: 1900 | V63: 150 | W63: =SUM(X63:AS63) | X63: 0 | Y63: 0 | Z63: 0 | AA63: 0 | AB63: 0 | AC63: 0 | AD63: 0 | AE63: 0 | AF63: 0 | AG63: 0 | AH63: 0 | AI63: 0 | AJ63: 0 | AK63: 0 | AL63: 0 | AM63: 0 | AN63: 0 | AO63: 0 | AP63: 0 | AQ63: 350 | AR63: 200 | AS63: 0 | AT63: 拉点床软包：350 | AU63: 1.8床铺板打孔+纸箱+整片=23*22+50=556 1.5规格是536，1.2规格是527 | AV63: 69f6f7fa0283e20001b46bbb | AW63: 黑胡桃木梯形腿床-1.8米-松木铺板 | AX63: 69f6f7fa0283e20001b46bd1 | AY63: =H63 | AZ63: =BB63/(1-BA63) | BA63: 0.15 | BB63: =K63*0.96 | BC63: 1038071596128 | BD63: 待定 | BF63: =H63 | BG63: =BH63/BF63 | BH63: =I63 | BI63: =1-12% | BJ63: =BK63/(BF63-BF63*(1-BI63)) | BK63: =BM63/(1-BL63) | BL63: 0.01 | BM63: =J63 | BN63: =IF(BK63>=1500,BK63-150,IF(BK63>=800,BK63-80,IF(BK63>=500,BK63-50,IF(BK63>=200,BK63-20,BK63)))) | BO63: =1-12% | BP63: =BQ63/(BF63-BF63*(1-BO63)) | BQ63: =BS63/(1-BR63) | BR63: 0 | BS63: =K63 | BT63: =IF(BQ63>=1500,BQ63-150,IF(BQ63>=800,BQ63-80,IF(BQ63>=500,BQ63-50,IF(BQ63>=200,BQ63-20,BQ63)))) | CB63: ✅ 可导入 | CC63: ✓
A64: PPS26330140117 | B64: 畔色黑胡桃木软包双人床 |黑胡桃木落地大软包床 | C64: 黑胡桃木软包床-1.2米-榉木铺板 | D64: PPS2633014011711 | E64: https://img.alicdn.com/imgextra/i4/2215699812811/O1CN01eDD7Xt1WdUTbnanUa_!!2215699812811.jpg | F64: 中型 | G64: =Q64/0.4 | H64: =G64*0.75 | I64: =Q64 / (0.79 - 0.02 - 0.006) | J64: =Q64 / (0.8 - 0.02 - 0.006) | K64: =Q64 / (0.82 - 0.02 - 0.006) | L64: =K64-N64 | M64: =L64/K64 | N64: =O64+P64+Q64 | O64: =K64*0.006 | P64: =K64*0.02 | Q64: =SUM(R64:T64) | R64: =IF(F64="大型",700,IF(F64="中型",300,IF(F64="小型",80,0))) | S64: =IF(F64="大型",150,IF(F64="中型",100,IF(F64="小型",0,0))) | T64: =SUM(U64:W64) | U64: 2260 | V64: 140 | W64: =SUM(X64:AS64) | X64: 0 | Y64: 0 | Z64: 0 | AA64: 0 | AB64: 0 | AC64: 0 | AD64: 0 | AE64: 0 | AF64: 0 | AG64: 0 | AH64: 0 | AI64: 0 | AJ64: 0 | AK64: 0 | AL64: 0 | AM64: 0 | AN64: 0 | AO64: 0 | AP64: 0 | AQ64: 400 | AR64: 590 | AS64: 0 | AT64: 灯芯绒软包320元（含加工费150元）；灯芯绒80元 | AU64: 1.8床铺板打孔+纸箱+整片=23*22+50=556 1.5规格是536，1.2规格是520 | AV64: 69f6f672273c7d000171f0cf | AW64: 黑胡桃木软包床-1.2米-榉木铺板 | AX64: 69f6f672273c7d000171f0d0 | AY64: =H64 | AZ64: =BB64/(1-BA64) | BA64: 0.15 | BB64: =K64*0.96 | BC64: 1035582527998 | BD64: 待定 | BF64: =H64 | BG64: =BH64/BF64 | BH64: =I64 | BI64: =1-12% | BJ64: =BK64/(BF64-BF64*(1-BI64)) | BK64: =BM64/(1-BL64) | BL64: 0.01 | BM64: =J64 | BN64: =IF(BK64>=1500,BK64-150,IF(BK64>=800,BK64-80,IF(BK64>=500,BK64-50,IF(BK64>=200,BK64-20,BK64)))) | BO64: =1-12% | BP64: =BQ64/(BF64-BF64*(1-BO64)) | BQ64: =BS64/(1-BR64) | BR64: 0 | BS64: =K64 | BT64: =IF(BQ64>=1500,BQ64-150,IF(BQ64>=800,BQ64-80,IF(BQ64>=500,BQ64-50,IF(BQ64>=200,BQ64-20,BQ64)))) | CB64: ✅ 可导入 | CC64: ✓
A65: PPS26330140117 | B65: 畔色黑胡桃木软包双人床 |黑胡桃木落地大软包床 | C65: 黑胡桃木软包床-1.35米-榉木铺板 | D65: PPS2633014011712 | E65: https://img.alicdn.com/imgextra/i4/2215699812811/O1CN01eDD7Xt1WdUTbnanUa_!!2215699812811.jpg | F65: 中型 | G65: =Q65/0.4 | H65: =G65*0.75 | I65: =Q65 / (0.79 - 0.02 - 0.006) | J65: =Q65 / (0.8 - 0.02 - 0.006) | K65: =Q65 / (0.82 - 0.02 - 0.006) | L65: =K65-N65 | M65: =L65/K65 | N65: =O65+P65+Q65 | O65: =K65*0.006 | P65: =K65*0.02 | Q65: =SUM(R65:T65) | R65: =IF(F65="大型",700,IF(F65="中型",300,IF(F65="小型",80,0))) | S65: =IF(F65="大型",150,IF(F65="中型",100,IF(F65="小型",0,0))) | T65: =SUM(U65:W65) | U65: 2290 | V65: 140 | W65: =SUM(X65:AS65) | X65: 0 | Y65: 0 | Z65: 0 | AA65: 0 | AB65: 0 | AC65: 0 | AD65: 0 | AE65: 0 | AF65: 0 | AG65: 0 | AH65: 0 | AI65: 0 | AJ65: 0 | AK65: 0 | AL65: 0 | AM65: 0 | AN65: 0 | AO65: 0 | AP65: 0 | AQ65: 420 | AR65: 610 | AS65: 0 | AT65: 灯芯绒软包330元（含加工费150元）；灯芯绒90元 | AU65: 1.8床铺板打孔+纸箱+整片=23*22+50=556 1.5规格是536，1.2规格是521 | AV65: 69f6f672273c7d000171f0cf | AW65: 黑胡桃木软包床-1.35米-榉木铺板 | AX65: 69f6f672273c7d000171f0d3 | AY65: =H65 | AZ65: =BB65/(1-BA65) | BA65: 0.15 | BB65: =K65*0.96 | BC65: 1035582527998 | BD65: 待定 | BF65: =H65 | BG65: =BH65/BF65 | BH65: =I65 | BI65: =1-12% | BJ65: =BK65/(BF65-BF65*(1-BI65)) | BK65: =BM65/(1-BL65) | BL65: 0.01 | BM65: =J65 | BN65: =IF(BK65>=1500,BK65-150,IF(BK65>=800,BK65-80,IF(BK65>=500,BK65-50,IF(BK65>=200,BK65-20,BK65)))) | BO65: =1-12% | BP65: =BQ65/(BF65-BF65*(1-BO65)) | BQ65: =BS65/(1-BR65) | BR65: 0 | BS65: =K65 | BT65: =IF(BQ65>=1500,BQ65-150,IF(BQ65>=800,BQ65-80,IF(BQ65>=500,BQ65-50,IF(BQ65>=200,BQ65-20,BQ65)))) | CB65: ✅ 可导入 | CC65: ✓
A66: PPS26330140117 | B66: 畔色黑胡桃木软包双人床 |黑胡桃木落地大软包床 | C66: 黑胡桃木软包床-1.5米-榉木铺板 | D66: PPS2633014011713 | E66: https://img.alicdn.com/imgextra/i4/2215699812811/O1CN01eDD7Xt1WdUTbnanUa_!!2215699812811.jpg | F66: 中型 | G66: =Q66/0.4 | H66: =G66*0.75 | I66: =Q66 / (0.79 - 0.02 - 0.006) | J66: =Q66 / (0.8 - 0.02 - 0.006) | K66: =Q66 / (0.82 - 0.02 - 0.006) | L66: =K66-N66 | M66: =L66/K66 | N66: =O66+P66+Q66 | O66: =K66*0.006 | P66: =K66*0.02 | Q66: =SUM(R66:T66) | R66: =IF(F66="大型",700,IF(F66="中型",300,IF(F66="小型",80,0))) | S66: =IF(F66="大型",150,IF(F66="中型",100,IF(F66="小型",0,0))) | T66: =SUM(U66:W66) | U66: 2370 | V66: 150 | W66: =SUM(X66:AS66) | X66: 0 | Y66: 0 | Z66: 0 | AA66: 0 | AB66: 0 | AC66: 0 | AD66: 0 | AE66: 0 | AF66: 0 | AG66: 0 | AH66: 0 | AI66: 0 | AJ66: 0 | AK66: 0 | AL66: 0 | AM66: 0 | AN66: 0 | AO66: 0 | AP66: 0 | AQ66: 440 | AR66: 630 | AS66: 0 | AT66: 灯芯绒软包340元（含加工费150元）；灯芯绒100元 | AU66: 1.8床铺板打孔+纸箱+整片=23*22+50=556 1.5规格是536，1.2规格是522 | AV66: 69f6f672273c7d000171f0cf | AW66: 黑胡桃木软包床-1.5米-榉木铺板 | AX66: 69f6f672273c7d000171f0d6 | AY66: =H66 | AZ66: =BB66/(1-BA66) | BA66: 0.15 | BB66: =K66*0.96 | BC66: 1035582527998 | BD66: 待定 | BF66: =H66 | BG66: =BH66/BF66 | BH66: =I66 | BI66: =1-12% | BJ66: =BK66/(BF66-BF66*(1-BI66)) | BK66: =BM66/(1-BL66) | BL66: 0.01 | BM66: =J66 | BN66: =IF(BK66>=1500,BK66-150,IF(BK66>=800,BK66-80,IF(BK66>=500,BK66-50,IF(BK66>=200,BK66-20,BK66)))) | BO66: =1-12% | BP66: =BQ66/(BF66-BF66*(1-BO66)) | BQ66: =BS66/(1-BR66) | BR66: 0 | BS66: =K66 | BT66: =IF(BQ66>=1500,BQ66-150,IF(BQ66>=800,BQ66-80,IF(BQ66>=500,BQ66-50,IF(BQ66>=200,BQ66-20,BQ66)))) | CB66: ✅ 可导入 | CC66: ✓
A67: PPS26330140117 | B67: 畔色黑胡桃木软包双人床 |黑胡桃木落地大软包床 | C67: 黑胡桃木软包床-1.8米-榉木铺板 | D67: PPS2633014011714 | E67: https://img.alicdn.com/imgextra/i4/2215699812811/O1CN01eDD7Xt1WdUTbnanUa_!!2215699812811.jpg | F67: 中型 | G67: =Q67/0.4 | H67: =G67*0.75 | I67: =Q67 / (0.79 - 0.02 - 0.006) | J67: =Q67 / (0.8 - 0.02 - 0.006) | K67: =Q67 / (0.82 - 0.02 - 0.006) | L67: =K67-N67 | M67: =L67/K67 | N67: =O67+P67+Q67 | O67: =K67*0.006 | P67: =K67*0.02 | Q67: =SUM(R67:T67) | R67: =IF(F67="大型",700,IF(F67="中型",300,IF(F67="小型",80,0))) | S67: =IF(F67="大型",150,IF(F67="中型",100,IF(F67="小型",0,0))) | T67: =SUM(U67:W67) | U67: 2500 | V67: 150 | W67: =SUM(X67:AS67) | X67: 0 | Y67: 0 | Z67: 0 | AA67: 0 | AB67: 0 | AC67: 0 | AD67: 0 | AE67: 0 | AF67: 0 | AG67: 0 | AH67: 0 | AI67: 0 | AJ67: 0 | AK67: 0 | AL67: 0 | AM67: 0 | AN67: 0 | AO67: 0 | AP67: 0 | AQ67: 470 | AR67: 650 | AS67: 0 | AT67: 灯芯绒软包350元（含加工费150元）；灯芯绒120元 | AU67: 1.8床铺板打孔+纸箱+整片=23*22+50=556 1.5规格是536，1.2规格是523 | AV67: 69f6f672273c7d000171f0cf | AW67: 黑胡桃木软包床-1.8米-榉木铺板 | AX67: 69f6f672273c7d000171f0d9 | AY67: =H67 | AZ67: =BB67/(1-BA67) | BA67: 0.15 | BB67: =K67*0.96 | BC67: 1035582527998 | BD67: 待定 | BF67: =H67 | BG67: =BH67/BF67 | BH67: =I67 | BI67: =1-12% | BJ67: =BK67/(BF67-BF67*(1-BI67)) | BK67: =BM67/(1-BL67) | BL67: 0.01 | BM67: =J67 | BN67: =IF(BK67>=1500,BK67-150,IF(BK67>=800,BK67-80,IF(BK67>=500,BK67-50,IF(BK67>=200,BK67-20,BK67)))) | BO67: =1-12% | BP67: =BQ67/(BF67-BF67*(1-BO67)) | BQ67: =BS67/(1-BR67) | BR67: 0 | BS67: =K67 | BT67: =IF(BQ67>=1500,BQ67-150,IF(BQ67>=800,BQ67-80,IF(BQ67>=500,BQ67-50,IF(BQ67>=200,BQ67-20,BQ67)))) | CB67: ✅ 可导入 | CC67: ✓
A68: PPS26330140117 | B68: 畔色黑胡桃木软包双人床 |黑胡桃木落地大软包床 | C68: 黑胡桃木软包床-1.2米-松木铺板 | D68: PPS2633014011715 | E68: https://img.alicdn.com/imgextra/i4/2215699812811/O1CN01eDD7Xt1WdUTbnanUa_!!2215699812811.jpg | F68: 中型 | G68: =Q68/0.4 | H68: =G68*0.75 | I68: =Q68 / (0.79 - 0.02 - 0.006) | J68: =Q68 / (0.8 - 0.02 - 0.006) | K68: =Q68 / (0.82 - 0.02 - 0.006) | L68: =K68-N68 | M68: =L68/K68 | N68: =O68+P68+Q68 | O68: =K68*0.006 | P68: =K68*0.02 | Q68: =SUM(R68:T68) | R68: =IF(F68="大型",700,IF(F68="中型",300,IF(F68="小型",80,0))) | S68: =IF(F68="大型",150,IF(F68="中型",100,IF(F68="小型",0,0))) | T68: =SUM(U68:W68) | U68: 2090 | V68: 140 | W68: =SUM(X68:AS68) | X68: 0 | Y68: 0 | Z68: 0 | AA68: 0 | AB68: 0 | AC68: 0 | AD68: 0 | AE68: 0 | AF68: 0 | AG68: 0 | AH68: 0 | AI68: 0 | AJ68: 0 | AK68: 0 | AL68: 0 | AM68: 0 | AN68: 0 | AO68: 0 | AP68: 0 | AQ68: 400 | AR68: 160 | AS68: 0 | AT68: 灯芯绒软包320元（含加工费150元）；灯芯绒80元 | AU68: 1.8床铺板打孔+纸箱+整片=23*22+50=556 1.5规格是536，1.2规格是524 | AV68: 69f6f672273c7d000171f0cf | AW68: 黑胡桃木软包床-1.2米-松木铺板 | AX68: 69f6f672273c7d000171f0dc | AY68: =H68 | AZ68: =BB68/(1-BA68) | BA68: 0.15 | BB68: =K68*0.96 | BC68: 1035582527998 | BD68: 待定 | BF68: =H68 | BG68: =BH68/BF68 | BH68: =I68 | BI68: =1-12% | BJ68: =BK68/(BF68-BF68*(1-BI68)) | BK68: =BM68/(1-BL68) | BL68: 0.01 | BM68: =J68 | BN68: =IF(BK68>=1500,BK68-150,IF(BK68>=800,BK68-80,IF(BK68>=500,BK68-50,IF(BK68>=200,BK68-20,BK68)))) | BO68: =1-12% | BP68: =BQ68/(BF68-BF68*(1-BO68)) | BQ68: =BS68/(1-BR68) | BR68: 0 | BS68: =K68 | BT68: =IF(BQ68>=1500,BQ68-150,IF(BQ68>=800,BQ68-80,IF(BQ68>=500,BQ68-50,IF(BQ68>=200,BQ68-20,BQ68)))) | CB68: ✅ 可导入 | CC68: ✓
A69: PPS26330140117 | B69: 畔色黑胡桃木软包双人床 |黑胡桃木落地大软包床 | C69: 黑胡桃木软包床-1.35米-松木铺板 | D69: PPS2633014011716 | E69: https://img.alicdn.com/imgextra/i4/2215699812811/O1CN01eDD7Xt1WdUTbnanUa_!!2215699812811.jpg | F69: 中型 | G69: =Q69/0.4 | H69: =G69*0.75 | I69: =Q69 / (0.79 - 0.02 - 0.006) | J69: =Q69 / (0.8 - 0.02 - 0.006) | K69: =Q69 / (0.82 - 0.02 - 0.006) | L69: =K69-N69 | M69: =L69/K69 | N69: =O69+P69+Q69 | O69: =K69*0.006 | P69: =K69*0.02 | Q69: =SUM(R69:T69) | R69: =IF(F69="大型",700,IF(F69="中型",300,IF(F69="小型",80,0))) | S69: =IF(F69="大型",150,IF(F69="中型",100,IF(F69="小型",0,0))) | T69: =SUM(U69:W69) | U69: 2120 | V69: 140 | W69: =SUM(X69:AS69) | X69: 0 | Y69: 0 | Z69: 0 | AA69: 0 | AB69: 0 | AC69: 0 | AD69: 0 | AE69: 0 | AF69: 0 | AG69: 0 | AH69: 0 | AI69: 0 | AJ69: 0 | AK69: 0 | AL69: 0 | AM69: 0 | AN69: 0 | AO69: 0 | AP69: 0 | AQ69: 420 | AR69: 180 | AS69: 0 | AT69: 灯芯绒软包330元（含加工费150元）；灯芯绒90元 | AU69: 1.8床铺板打孔+纸箱+整片=23*22+50=556 1.5规格是536，1.2规格是525 | AV69: 69f6f672273c7d000171f0cf | AW69: 黑胡桃木软包床-1.35米-松木铺板 | AX69: 69f6f672273c7d000171f0df | AY69: =H69 | AZ69: =BB69/(1-BA69) | BA69: 0.15 | BB69: =K69*0.96 | BC69: 1035582527998 | BD69: 待定 | BF69: =H69 | BG69: =BH69/BF69 | BH69: =I69 | BI69: =1-12% | BJ69: =BK69/(BF69-BF69*(1-BI69)) | BK69: =BM69/(1-BL69) | BL69: 0.01 | BM69: =J69 | BN69: =IF(BK69>=1500,BK69-150,IF(BK69>=800,BK69-80,IF(BK69>=500,BK69-50,IF(BK69>=200,BK69-20,BK69)))) | BO69: =1-12% | BP69: =BQ69/(BF69-BF69*(1-BO69)) | BQ69: =BS69/(1-BR69) | BR69: 0 | BS69: =K69 | BT69: =IF(BQ69>=1500,BQ69-150,IF(BQ69>=800,BQ69-80,IF(BQ69>=500,BQ69-50,IF(BQ69>=200,BQ69-20,BQ69)))) | CB69: ✅ 可导入 | CC69: ✓
A70: PPS26330140117 | B70: 畔色黑胡桃木软包双人床 |黑胡桃木落地大软包床 | C70: 黑胡桃木软包床-1.5米-松木铺板 | D70: PPS2633014011717 | E70: https://img.alicdn.com/imgextra/i4/2215699812811/O1CN01eDD7Xt1WdUTbnanUa_!!2215699812811.jpg | F70: 中型 | G70: =Q70/0.4 | H70: =G70*0.75 | I70: =Q70 / (0.79 - 0.02 - 0.006) | J70: =Q70 / (0.8 - 0.02 - 0.006) | K70: =Q70 / (0.82 - 0.02 - 0.006) | L70: =K70-N70 | M70: =L70/K70 | N70: =O70+P70+Q70 | O70: =K70*0.006 | P70: =K70*0.02 | Q70: =SUM(R70:T70) | R70: =IF(F70="大型",700,IF(F70="中型",300,IF(F70="小型",80,0))) | S70: =IF(F70="大型",150,IF(F70="中型",100,IF(F70="小型",0,0))) | T70: =SUM(U70:W70) | U70: 2220 | V70: 150 | W70: =SUM(X70:AS70) | X70: 0 | Y70: 0 | Z70: 0 | AA70: 0 | AB70: 0 | AC70: 0 | AD70: 0 | AE70: 0 | AF70: 0 | AG70: 0 | AH70: 0 | AI70: 0 | AJ70: 0 | AK70: 0 | AL70: 0 | AM70: 0 | AN70: 0 | AO70: 0 | AP70: 0 | AQ70: 440 | AR70: 180 | AS70: 0 | AT70: 灯芯绒软包340元（含加工费150元）；灯芯绒100元 | AU70: 1.8床铺板打孔+纸箱+整片=23*22+50=556 1.5规格是536，1.2规格是526 | AV70: 69f6f672273c7d000171f0cf | AW70: 黑胡桃木软包床-1.5米-松木铺板 | AX70: 69f6f672273c7d000171f0e2 | AY70: =H70 | AZ70: =BB70/(1-BA70) | BA70: 0.15 | BB70: =K70*0.96 | BC70: 1035582527998 | BD70: 待定 | BF70: =H70 | BG70: =BH70/BF70 | BH70: =I70 | BI70: =1-12% | BJ70: =BK70/(BF70-BF70*(1-BI70)) | BK70: =BM70/(1-BL70) | BL70: 0.01 | BM70: =J70 | BN70: =IF(BK70>=1500,BK70-150,IF(BK70>=800,BK70-80,IF(BK70>=500,BK70-50,IF(BK70>=200,BK70-20,BK70)))) | BO70: =1-12% | BP70: =BQ70/(BF70-BF70*(1-BO70)) | BQ70: =BS70/(1-BR70) | BR70: 0 | BS70: =K70 | BT70: =IF(BQ70>=1500,BQ70-150,IF(BQ70>=800,BQ70-80,IF(BQ70>=500,BQ70-50,IF(BQ70>=200,BQ70-20,BQ70)))) | CB70: ✅ 可导入 | CC70: ✓
A71: PPS26330140117 | B71: 畔色黑胡桃木软包双人床 |黑胡桃木落地大软包床 | C71: 黑胡桃木软包床-1.8米-松木铺板 | D71: PPS2633014011718 | E71: https://img.alicdn.com/imgextra/i4/2215699812811/O1CN01eDD7Xt1WdUTbnanUa_!!2215699812811.jpg | F71: 中型 | G71: =Q71/0.4 | H71: =G71*0.75 | I71: =Q71 / (0.79 - 0.02 - 0.006) | J71: =Q71 / (0.8 - 0.02 - 0.006) | K71: =Q71 / (0.82 - 0.02 - 0.006) | L71: =K71-N71 | M71: =L71/K71 | N71: =O71+P71+Q71 | O71: =K71*0.006 | P71: =K71*0.02 | Q71: =SUM(R71:T71) | R71: =IF(F71="大型",700,IF(F71="中型",300,IF(F71="小型",80,0))) | S71: =IF(F71="大型",150,IF(F71="中型",100,IF(F71="小型",0,0))) | T71: =SUM(U71:W71) | U71: 2350 | V71: 150 | W71: =SUM(X71:AS71) | X71: 0 | Y71: 0 | Z71: 0 | AA71: 0 | AB71: 0 | AC71: 0 | AD71: 0 | AE71: 0 | AF71: 0 | AG71: 0 | AH71: 0 | AI71: 0 | AJ71: 0 | AK71: 0 | AL71: 0 | AM71: 0 | AN71: 0 | AO71: 0 | AP71: 0 | AQ71: 470 | AR71: 200 | AS71: 0 | AT71: 灯芯绒软包350元（含加工费150元）；灯芯绒120元 | AU71: 1.8床铺板打孔+纸箱+整片=23*22+50=556 1.5规格是536，1.2规格是527 | AV71: 69f6f672273c7d000171f0cf | AW71: 黑胡桃木软包床-1.8米-松木铺板 | AX71: 69f6f672273c7d000171f0e5 | AY71: =H71 | AZ71: =BB71/(1-BA71) | BA71: 0.15 | BB71: =K71*0.96 | BC71: 1035582527998 | BD71: 待定 | BF71: =H71 | BG71: =BH71/BF71 | BH71: =I71 | BI71: =1-12% | BJ71: =BK71/(BF71-BF71*(1-BI71)) | BK71: =BM71/(1-BL71) | BL71: 0.01 | BM71: =J71 | BN71: =IF(BK71>=1500,BK71-150,IF(BK71>=800,BK71-80,IF(BK71>=500,BK71-50,IF(BK71>=200,BK71-20,BK71)))) | BO71: =1-12% | BP71: =BQ71/(BF71-BF71*(1-BO71)) | BQ71: =BS71/(1-BR71) | BR71: 0 | BS71: =K71 | BT71: =IF(BQ71>=1500,BQ71-150,IF(BQ71>=800,BQ71-80,IF(BQ71>=500,BQ71-50,IF(BQ71>=200,BQ71-20,BQ71)))) | CB71: ✅ 可导入 | CC71: ✓
A72: PPS26330140117 | B72: 畔色黑胡桃木软包双人床 |黑胡桃木落地大软包床 | C72: 黑胡桃木榻榻米（无床头）-1.2米-榉木铺板 | D72: PPS2633014011719 | E72: https://img.alicdn.com/imgextra/i4/2215699812811/O1CN01eDD7Xt1WdUTbnanUa_!!2215699812811.jpg | F72: 中型 | G72: =Q72/0.4 | H72: =G72*0.75 | I72: =Q72 / (0.79 - 0.02 - 0.006) | J72: =Q72 / (0.8 - 0.02 - 0.006) | K72: =Q72 / (0.82 - 0.02 - 0.006) | L72: =K72-N72 | M72: =L72/K72 | N72: =O72+P72+Q72 | O72: =K72*0.006 | P72: =K72*0.02 | Q72: =SUM(R72:T72) | R72: =IF(F72="大型",700,IF(F72="中型",300,IF(F72="小型",80,0))) | S72: =IF(F72="大型",150,IF(F72="中型",100,IF(F72="小型",0,0))) | T72: =SUM(U72:W72) | U72: 2260 | V72: 140 | W72: =SUM(X72:AS72) | X72: 0 | Y72: 0 | Z72: 0 | AA72: 0 | AB72: 0 | AC72: 0 | AD72: 0 | AE72: 0 | AF72: 0 | AG72: 0 | AH72: 0 | AI72: 0 | AJ72: 0 | AK72: 0 | AL72: 0 | AM72: 0 | AN72: 0 | AO72: 0 | AP72: 0 | AQ72: 0 | AR72: 590 | AS72: 0 | AU72: 1.8床铺板打孔+纸箱+整片=23*22+50=556 1.5规格是536，1.2规格是528 | AV72: 69f6f672273c7d000171f0cf | AW72: 黑胡桃木榻榻米（无床头）-1.2米-榉木铺板 | AX72: 69f6f672273c7d000171f0e8 | AY72: =H72 | AZ72: =BB72/(1-BA72) | BA72: 0.15 | BB72: =K72*0.96 | BC72: 1035582527998 | BD72: 待定 | BF72: =H72 | BG72: =BH72/BF72 | BH72: =I72 | BI72: =1-12% | BJ72: =BK72/(BF72-BF72*(1-BI72)) | BK72: =BM72/(1-BL72) | BL72: 0.01 | BM72: =J72 | BN72: =IF(BK72>=1500,BK72-150,IF(BK72>=800,BK72-80,IF(BK72>=500,BK72-50,IF(BK72>=200,BK72-20,BK72)))) | BO72: =1-12% | BP72: =BQ72/(BF72-BF72*(1-BO72)) | BQ72: =BS72/(1-BR72) | BR72: 0 | BS72: =K72 | BT72: =IF(BQ72>=1500,BQ72-150,IF(BQ72>=800,BQ72-80,IF(BQ72>=500,BQ72-50,IF(BQ72>=200,BQ72-20,BQ72)))) | CB72: ✅ 可导入 | CC72: ✓
A73: PPS26330140117 | B73: 畔色黑胡桃木软包双人床 |黑胡桃木落地大软包床 | C73: 黑胡桃木榻榻米（无床头）-1.35米-榉木铺板 | D73: PPS2633014011720 | E73: https://img.alicdn.com/imgextra/i4/2215699812811/O1CN01eDD7Xt1WdUTbnanUa_!!2215699812811.jpg | F73: 中型 | G73: =Q73/0.4 | H73: =G73*0.75 | I73: =Q73 / (0.79 - 0.02 - 0.006) | J73: =Q73 / (0.8 - 0.02 - 0.006) | K73: =Q73 / (0.82 - 0.02 - 0.006) | L73: =K73-N73 | M73: =L73/K73 | N73: =O73+P73+Q73 | O73: =K73*0.006 | P73: =K73*0.02 | Q73: =SUM(R73:T73) | R73: =IF(F73="大型",700,IF(F73="中型",300,IF(F73="小型",80,0))) | S73: =IF(F73="大型",150,IF(F73="中型",100,IF(F73="小型",0,0))) | T73: =SUM(U73:W73) | U73: 2290 | V73: 140 | W73: =SUM(X73:AS73) | X73: 0 | Y73: 0 | Z73: 0 | AA73: 0 | AB73: 0 | AC73: 0 | AD73: 0 | AE73: 0 | AF73: 0 | AG73: 0 | AH73: 0 | AI73: 0 | AJ73: 0 | AK73: 0 | AL73: 0 | AM73: 0 | AN73: 0 | AO73: 0 | AP73: 0 | AQ73: 0 | AR73: 610 | AS73: 0 | AU73: 1.8床铺板打孔+纸箱+整片=23*22+50=556 1.5规格是536，1.2规格是529 | AV73: 69f6f672273c7d000171f0cf | AW73: 黑胡桃木榻榻米（无床头）-1.35米-榉木铺板 | AX73: 69f6f672273c7d000171f0eb | AY73: =H73 | AZ73: =BB73/(1-BA73) | BA73: 0.15 | BB73: =K73*0.96 | BC73: 1035582527998 | BD73: 待定 | BF73: =H73 | BG73: =BH73/BF73 | BH73: =I73 | BI73: =1-12% | BJ73: =BK73/(BF73-BF73*(1-BI73)) | BK73: =BM73/(1-BL73) | BL73: 0.01 | BM73: =J73 | BN73: =IF(BK73>=1500,BK73-150,IF(BK73>=800,BK73-80,IF(BK73>=500,BK73-50,IF(BK73>=200,BK73-20,BK73)))) | BO73: =1-12% | BP73: =BQ73/(BF73-BF73*(1-BO73)) | BQ73: =BS73/(1-BR73) | BR73: 0 | BS73: =K73 | BT73: =IF(BQ73>=1500,BQ73-150,IF(BQ73>=800,BQ73-80,IF(BQ73>=500,BQ73-50,IF(BQ73>=200,BQ73-20,BQ73)))) | CB73: ✅ 可导入 | CC73: ✓
A74: PPS26330140117 | B74: 畔色黑胡桃木软包双人床 |黑胡桃木落地大软包床 | C74: 黑胡桃木榻榻米（无床头）-1.5米-榉木铺板 | D74: PPS2633014011721 | E74: https://img.alicdn.com/imgextra/i4/2215699812811/O1CN01eDD7Xt1WdUTbnanUa_!!2215699812811.jpg | F74: 中型 | G74: =Q74/0.4 | H74: =G74*0.75 | I74: =Q74 / (0.79 - 0.02 - 0.006) | J74: =Q74 / (0.8 - 0.02 - 0.006) | K74: =Q74 / (0.82 - 0.02 - 0.006) | L74: =K74-N74 | M74: =L74/K74 | N74: =O74+P74+Q74 | O74: =K74*0.006 | P74: =K74*0.02 | Q74: =SUM(R74:T74) | R74: =IF(F74="大型",700,IF(F74="中型",300,IF(F74="小型",80,0))) | S74: =IF(F74="大型",150,IF(F74="中型",100,IF(F74="小型",0,0))) | T74: =SUM(U74:W74) | U74: 2370 | V74: 150 | W74: =SUM(X74:AS74) | X74: 0 | Y74: 0 | Z74: 0 | AA74: 0 | AB74: 0 | AC74: 0 | AD74: 0 | AE74: 0 | AF74: 0 | AG74: 0 | AH74: 0 | AI74: 0 | AJ74: 0 | AK74: 0 | AL74: 0 | AM74: 0 | AN74: 0 | AO74: 0 | AP74: 0 | AQ74: 0 | AR74: 630 | AS74: 0 | AU74: 1.8床铺板打孔+纸箱+整片=23*22+50=556 1.5规格是536，1.2规格是530 | AV74: 69f6f672273c7d000171f0cf | AW74: 黑胡桃木榻榻米（无床头）-1.5米-榉木铺板 | AX74: 69f6f672273c7d000171f0ee | AY74: =H74 | AZ74: =BB74/(1-BA74) | BA74: 0.15 | BB74: =K74*0.96 | BC74: 1035582527998 | BD74: 待定 | BF74: =H74 | BG74: =BH74/BF74 | BH74: =I74 | BI74: =1-12% | BJ74: =BK74/(BF74-BF74*(1-BI74)) | BK74: =BM74/(1-BL74) | BL74: 0.01 | BM74: =J74 | BN74: =IF(BK74>=1500,BK74-150,IF(BK74>=800,BK74-80,IF(BK74>=500,BK74-50,IF(BK74>=200,BK74-20,BK74)))) | BO74: =1-12% | BP74: =BQ74/(BF74-BF74*(1-BO74)) | BQ74: =BS74/(1-BR74) | BR74: 0 | BS74: =K74 | BT74: =IF(BQ74>=1500,BQ74-150,IF(BQ74>=800,BQ74-80,IF(BQ74>=500,BQ74-50,IF(BQ74>=200,BQ74-20,BQ74)))) | CB74: ✅ 可导入 | CC74: ✓
A75: PPS26330140117 | B75: 畔色黑胡桃木软包双人床 |黑胡桃木落地大软包床 | C75: 黑胡桃木榻榻米（无床头）-1.8米-榉木铺板 | D75: PPS2633014011722 | E75: https://img.alicdn.com/imgextra/i4/2215699812811/O1CN01eDD7Xt1WdUTbnanUa_!!2215699812811.jpg | F75: 中型 | G75: =Q75/0.4 | H75: =G75*0.75 | I75: =Q75 / (0.79 - 0.02 - 0.006) | J75: =Q75 / (0.8 - 0.02 - 0.006) | K75: =Q75 / (0.82 - 0.02 - 0.006) | L75: =K75-N75 | M75: =L75/K75 | N75: =O75+P75+Q75 | O75: =K75*0.006 | P75: =K75*0.02 | Q75: =SUM(R75:T75) | R75: =IF(F75="大型",700,IF(F75="中型",300,IF(F75="小型",80,0))) | S75: =IF(F75="大型",150,IF(F75="中型",100,IF(F75="小型",0,0))) | T75: =SUM(U75:W75) | U75: 2500 | V75: 150 | W75: =SUM(X75:AS75) | X75: 0 | Y75: 0 | Z75: 0 | AA75: 0 | AB75: 0 | AC75: 0 | AD75: 0 | AE75: 0 | AF75: 0 | AG75: 0 | AH75: 0 | AI75: 0 | AJ75: 0 | AK75: 0 | AL75: 0 | AM75: 0 | AN75: 0 | AO75: 0 | AP75: 0 | AQ75: 0 | AR75: 650 | AS75: 0 | AU75: 1.8床铺板打孔+纸箱+整片=23*22+50=556 1.5规格是536，1.2规格是531 | AV75: 69f6f672273c7d000171f0cf | AW75: 黑胡桃木榻榻米（无床头）-1.8米-榉木铺板 | AX75: 69f6f672273c7d000171f0f1 | AY75: =H75 | AZ75: =BB75/(1-BA75) | BA75: 0.15 | BB75: =K75*0.96 | BC75: 1035582527998 | BD75: 待定 | BF75: =H75 | BG75: =BH75/BF75 | BH75: =I75 | BI75: =1-12% | BJ75: =BK75/(BF75-BF75*(1-BI75)) | BK75: =BM75/(1-BL75) | BL75: 0.01 | BM75: =J75 | BN75: =IF(BK75>=1500,BK75-150,IF(BK75>=800,BK75-80,IF(BK75>=500,BK75-50,IF(BK75>=200,BK75-20,BK75)))) | BO75: =1-12% | BP75: =BQ75/(BF75-BF75*(1-BO75)) | BQ75: =BS75/(1-BR75) | BR75: 0 | BS75: =K75 | BT75: =IF(BQ75>=1500,BQ75-150,IF(BQ75>=800,BQ75-80,IF(BQ75>=500,BQ75-50,IF(BQ75>=200,BQ75-20,BQ75)))) | CB75: ✅ 可导入 | CC75: ✓
A76: PPS26330150118 | B76: 畔色黑胡桃木悬浮双人床 |黑胡桃木标准床 | C76: 黑胡桃木悬浮床-1.2米-榉木铺板 | D76: PPS2633015011811 | E76: https://img.alicdn.com/imgextra/i4/2215699812811/O1CN015fCgsq1WdUTgF91sN_!!2215699812811.jpg | F76: 中型 | G76: =Q76/0.4 | H76: =G76*0.75 | I76: =Q76 / (0.79 - 0.02 - 0.006) | J76: =Q76 / (0.8 - 0.02 - 0.006) | K76: =Q76 / (0.82 - 0.02 - 0.006) | L76: =K76-N76 | M76: =L76/K76 | N76: =O76+P76+Q76 | O76: =K76*0.006 | P76: =K76*0.02 | Q76: =SUM(R76:T76) | R76: =IF(F76="大型",700,IF(F76="中型",300,IF(F76="小型",80,0))) | S76: =IF(F76="大型",150,IF(F76="中型",100,IF(F76="小型",0,0))) | T76: =SUM(U76:W76) | U76: 2710 | V76: 140 | W76: =SUM(X76:AS76) | X76: 0 | Y76: 0 | Z76: 73 | AA76: 0 | AB76: 0 | AC76: 0 | AD76: 0 | AE76: 0 | AF76: 0 | AG76: 0 | AH76: 0 | AI76: 0 | AJ76: 0 | AK76: 0 | AL76: 0 | AM76: 0 | AN76: 0 | AO76: 0 | AP76: 0 | AQ76: 0 | AR76: 590 | AS76: 0 | AU76: 1.8床铺板打孔+纸箱+整片=23*22+50=556 1.5规格是536，1.2规格是520 | AV76: 69f6f4f6f888bb0001debee9 | AW76: 黑胡桃木悬浮床-1.2米-榉木铺板 | AX76: 69f6f4f6f888bb0001debeea | AY76: =H76 | AZ76: =BB76/(1-BA76) | BA76: 0.15 | BB76: =K76*0.96 | BC76: 1037237545657 | BD76: 待定 | BF76: =H76 | BG76: =BH76/BF76 | BH76: =I76 | BI76: =1-12% | BJ76: =BK76/(BF76-BF76*(1-BI76)) | BK76: =BM76/(1-BL76) | BL76: 0.01 | BM76: =J76 | BN76: =IF(BK76>=1500,BK76-150,IF(BK76>=800,BK76-80,IF(BK76>=500,BK76-50,IF(BK76>=200,BK76-20,BK76)))) | BO76: =1-12% | BP76: =BQ76/(BF76-BF76*(1-BO76)) | BQ76: =BS76/(1-BR76) | BR76: 0 | BS76: =K76 | BT76: =IF(BQ76>=1500,BQ76-150,IF(BQ76>=800,BQ76-80,IF(BQ76>=500,BQ76-50,IF(BQ76>=200,BQ76-20,BQ76)))) | CB76: ✅ 可导入 | CC76: ✓
A77: PPS26330150118 | B77: 畔色黑胡桃木悬浮双人床 |黑胡桃木标准床 | C77: 黑胡桃木悬浮床-1.35米-榉木铺板 | D77: PPS2633015011812 | E77: https://img.alicdn.com/imgextra/i4/2215699812811/O1CN015fCgsq1WdUTgF91sN_!!2215699812811.jpg | F77: 中型 | G77: =Q77/0.4 | H77: =G77*0.75 | I77: =Q77 / (0.79 - 0.02 - 0.006) | J77: =Q77 / (0.8 - 0.02 - 0.006) | K77: =Q77 / (0.82 - 0.02 - 0.006) | L77: =K77-N77 | M77: =L77/K77 | N77: =O77+P77+Q77 | O77: =K77*0.006 | P77: =K77*0.02 | Q77: =SUM(R77:T77) | R77: =IF(F77="大型",700,IF(F77="中型",300,IF(F77="小型",80,0))) | S77: =IF(F77="大型",150,IF(F77="中型",100,IF(F77="小型",0,0))) | T77: =SUM(U77:W77) | U77: 2740 | V77: 140 | W77: =SUM(X77:AS77) | X77: 0 | Y77: 0 | Z77: 73 | AB77: 0 | AC77: 0 | AD77: 0 | AE77: 0 | AF77: 0 | AG77: 0 | AH77: 0 | AI77: 0 | AJ77: 0 | AK77: 0 | AL77: 0 | AM77: 0 | AN77: 0 | AO77: 0 | AP77: 0 | AQ77: 0 | AR77: 610 | AS77: 0 | AU77: 1.8床铺板打孔+纸箱+整片=23*22+50=556 1.5规格是536，1.2规格是521 | AV77: 69f6f4f6f888bb0001debee9 | AW77: 黑胡桃木悬浮床-1.35米-榉木铺板 | AX77: 69f6f4f6f888bb0001debeed | AY77: =H77 | AZ77: =BB77/(1-BA77) | BA77: 0.15 | BB77: =K77*0.96 | BC77: 1037237545657 | BD77: 待定 | BF77: =H77 | BG77: =BH77/BF77 | BH77: =I77 | BI77: =1-12% | BJ77: =BK77/(BF77-BF77*(1-BI77)) | BK77: =BM77/(1-BL77) | BL77: 0.01 | BM77: =J77 | BN77: =IF(BK77>=1500,BK77-150,IF(BK77>=800,BK77-80,IF(BK77>=500,BK77-50,IF(BK77>=200,BK77-20,BK77)))) | BO77: =1-12% | BP77: =BQ77/(BF77-BF77*(1-BO77)) | BQ77: =BS77/(1-BR77) | BR77: 0 | BS77: =K77 | BT77: =IF(BQ77>=1500,BQ77-150,IF(BQ77>=800,BQ77-80,IF(BQ77>=500,BQ77-50,IF(BQ77>=200,BQ77-20,BQ77)))) | CB77: ✅ 可导入 | CC77: ✓
A78: PPS26330150118 | B78: 畔色黑胡桃木悬浮双人床 |黑胡桃木标准床 | C78: 黑胡桃木悬浮床-1.5米-榉木铺板 | D78: PPS2633015011813 | E78: https://img.alicdn.com/imgextra/i4/2215699812811/O1CN015fCgsq1WdUTgF91sN_!!2215699812811.jpg | F78: 中型 | G78: =Q78/0.4 | H78: =G78*0.75 | I78: =Q78 / (0.79 - 0.02 - 0.006) | J78: =Q78 / (0.8 - 0.02 - 0.006) | K78: =Q78 / (0.82 - 0.02 - 0.006) | L78: =K78-N78 | M78: =L78/K78 | N78: =O78+P78+Q78 | O78: =K78*0.006 | P78: =K78*0.02 | Q78: =SUM(R78:T78) | R78: =IF(F78="大型",700,IF(F78="中型",300,IF(F78="小型",80,0))) | S78: =IF(F78="大型",150,IF(F78="中型",100,IF(F78="小型",0,0))) | T78: =SUM(U78:W78) | U78: 2820 | V78: 150 | W78: =SUM(X78:AS78) | X78: 0 | Y78: 0 | Z78: 73 | AA78: 0 | AB78: 0 | AC78: 0 | AD78: 0 | AE78: 0 | AF78: 0 | AG78: 0 | AH78: 0 | AI78: 0 | AJ78: 0 | AK78: 0 | AL78: 0 | AM78: 0 | AN78: 0 | AO78: 0 | AP78: 0 | AQ78: 0 | AR78: 630 | AS78: 0 | AU78: 1.8床铺板打孔+纸箱+整片=23*22+50=556 1.5规格是536，1.2规格是522 | AV78: 69f6f4f6f888bb0001debee9 | AW78: 黑胡桃木悬浮床-1.5米-榉木铺板 | AX78: 69f6f4f6f888bb0001debef0 | AY78: =H78 | AZ78: =BB78/(1-BA78) | BA78: 0.15 | BB78: =K78*0.96 | BC78: 1037237545657 | BD78: 待定 | BF78: =H78 | BG78: =BH78/BF78 | BH78: =I78 | BI78: =1-12% | BJ78: =BK78/(BF78-BF78*(1-BI78)) | BK78: =BM78/(1-BL78) | BL78: 0.01 | BM78: =J78 | BN78: =IF(BK78>=1500,BK78-150,IF(BK78>=800,BK78-80,IF(BK78>=500,BK78-50,IF(BK78>=200,BK78-20,BK78)))) | BO78: =1-12% | BP78: =BQ78/(BF78-BF78*(1-BO78)) | BQ78: =BS78/(1-BR78) | BR78: 0 | BS78: =K78 | BT78: =IF(BQ78>=1500,BQ78-150,IF(BQ78>=800,BQ78-80,IF(BQ78>=500,BQ78-50,IF(BQ78>=200,BQ78-20,BQ78)))) | CB78: ✅ 可导入 | CC78: ✓
A79: PPS26330150118 | B79: 畔色黑胡桃木悬浮双人床 |黑胡桃木标准床 | C79: 黑胡桃木悬浮床-1.8米-榉木铺板 | D79: PPS2633015011814 | E79: https://img.alicdn.com/imgextra/i4/2215699812811/O1CN015fCgsq1WdUTgF91sN_!!2215699812811.jpg | F79: 中型 | G79: =Q79/0.4 | H79: =G79*0.75 | I79: =Q79 / (0.79 - 0.02 - 0.006) | J79: =Q79 / (0.8 - 0.02 - 0.006) | K79: =Q79 / (0.82 - 0.02 - 0.006) | L79: =K79-N79 | M79: =L79/K79 | N79: =O79+P79+Q79 | O79: =K79*0.006 | P79: =K79*0.02 | Q79: =SUM(R79:T79) | R79: =IF(F79="大型",700,IF(F79="中型",300,IF(F79="小型",80,0))) | S79: =IF(F79="大型",150,IF(F79="中型",100,IF(F79="小型",0,0))) | T79: =SUM(U79:W79) | U79: 2950 | V79: 150 | W79: =SUM(X79:AS79) | X79: 0 | Y79: 0 | Z79: 73 | AA79: 0 | AB79: 0 | AC79: 0 | AD79: 0 | AE79: 0 | AF79: 0 | AG79: 0 | AH79: 0 | AI79: 0 | AJ79: 0 | AK79: 0 | AL79: 0 | AM79: 0 | AN79: 0 | AO79: 0 | AP79: 0 | AQ79: 0 | AR79: 650 | AS79: 0 | AU79: 1.8床铺板打孔+纸箱+整片=23*22+50=556 1.5规格是536，1.2规格是523 | AV79: 69f6f4f6f888bb0001debee9 | AW79: 黑胡桃木悬浮床-1.8米-榉木铺板 | AX79: 69f6f4f6f888bb0001debef3 | AY79: =H79 | AZ79: =BB79/(1-BA79) | BA79: 0.15 | BB79: =K79*0.96 | BC79: 1037237545657 | BD79: 待定 | BF79: =H79 | BG79: =BH79/BF79 | BH79: =I79 | BI79: =1-12% | BJ79: =BK79/(BF79-BF79*(1-BI79)) | BK79: =BM79/(1-BL79) | BL79: 0.01 | BM79: =J79 | BN79: =IF(BK79>=1500,BK79-150,IF(BK79>=800,BK79-80,IF(BK79>=500,BK79-50,IF(BK79>=200,BK79-20,BK79)))) | BO79: =1-12% | BP79: =BQ79/(BF79-BF79*(1-BO79)) | BQ79: =BS79/(1-BR79) | BR79: 0 | BS79: =K79 | BT79: =IF(BQ79>=1500,BQ79-150,IF(BQ79>=800,BQ79-80,IF(BQ79>=500,BQ79-50,IF(BQ79>=200,BQ79-20,BQ79)))) | CB79: ✅ 可导入 | CC79: ✓
A80: PPS26330150118 | B80: 畔色黑胡桃木悬浮双人床 |黑胡桃木标准床 | C80: 黑胡桃木悬浮床-1.2米-松木铺板 | D80: PPS2633015011815 | E80: https://img.alicdn.com/imgextra/i4/2215699812811/O1CN015fCgsq1WdUTgF91sN_!!2215699812811.jpg | F80: 中型 | G80: =Q80/0.4 | H80: =G80*0.75 | I80: =Q80 / (0.79 - 0.02 - 0.006) | J80: =Q80 / (0.8 - 0.02 - 0.006) | K80: =Q80 / (0.82 - 0.02 - 0.006) | L80: =K80-N80 | M80: =L80/K80 | N80: =O80+P80+Q80 | O80: =K80*0.006 | P80: =K80*0.02 | Q80: =SUM(R80:T80) | R80: =IF(F80="大型",700,IF(F80="中型",300,IF(F80="小型",80,0))) | S80: =IF(F80="大型",150,IF(F80="中型",100,IF(F80="小型",0,0))) | T80: =SUM(U80:W80) | U80: 2490 | V80: 140 | W80: =SUM(X80:AS80) | X80: 0 | Y80: 0 | Z80: 73 | AA80: 0 | AB80: 0 | AC80: 0 | AD80: 0 | AE80: 0 | AF80: 0 | AG80: 0 | AH80: 0 | AI80: 0 | AJ80: 0 | AK80: 0 | AL80: 0 | AM80: 0 | AN80: 0 | AO80: 0 | AP80: 0 | AQ80: 0 | AR80: 160 | AS80: 0 | AU80: 1.8床铺板打孔+纸箱+整片=23*22+50=556 1.5规格是536，1.2规格是524 | AV80: 69f6f4f6f888bb0001debee9 | AW80: 黑胡桃木悬浮床-1.2米-松木铺板 | AX80: 69f6f4f6f888bb0001debef6 | AY80: =H80 | AZ80: =BB80/(1-BA80) | BA80: 0.15 | BB80: =K80*0.96 | BC80: 1037237545657 | BD80: 待定 | BF80: =H80 | BG80: =BH80/BF80 | BH80: =I80 | BI80: =1-12% | BJ80: =BK80/(BF80-BF80*(1-BI80)) | BK80: =BM80/(1-BL80) | BL80: 0.01 | BM80: =J80 | BN80: =IF(BK80>=1500,BK80-150,IF(BK80>=800,BK80-80,IF(BK80>=500,BK80-50,IF(BK80>=200,BK80-20,BK80)))) | BO80: =1-12% | BP80: =BQ80/(BF80-BF80*(1-BO80)) | BQ80: =BS80/(1-BR80) | BR80: 0 | BS80: =K80 | BT80: =IF(BQ80>=1500,BQ80-150,IF(BQ80>=800,BQ80-80,IF(BQ80>=500,BQ80-50,IF(BQ80>=200,BQ80-20,BQ80)))) | CB80: ✅ 可导入 | CC80: ✓
A81: PPS26330150118 | B81: 畔色黑胡桃木悬浮双人床 |黑胡桃木标准床 | C81: 黑胡桃木悬浮床-1.35米-松木铺板 | D81: PPS2633015011816 | E81: https://img.alicdn.com/imgextra/i4/2215699812811/O1CN015fCgsq1WdUTgF91sN_!!2215699812811.jpg | F81: 中型 | G81: =Q81/0.4 | H81: =G81*0.75 | I81: =Q81 / (0.79 - 0.02 - 0.006) | J81: =Q81 / (0.8 - 0.02 - 0.006) | K81: =Q81 / (0.82 - 0.02 - 0.006) | L81: =K81-N81 | M81: =L81/K81 | N81: =O81+P81+Q81 | O81: =K81*0.006 | P81: =K81*0.02 | Q81: =SUM(R81:T81) | R81: =IF(F81="大型",700,IF(F81="中型",300,IF(F81="小型",80,0))) | S81: =IF(F81="大型",150,IF(F81="中型",100,IF(F81="小型",0,0))) | T81: =SUM(U81:W81) | U81: 2520 | V81: 140 | W81: =SUM(X81:AS81) | X81: 0 | Y81: 0 | Z81: 73 | AA81: 0 | AB81: 0 | AC81: 0 | AD81: 0 | AE81: 0 | AF81: 0 | AG81: 0 | AH81: 0 | AI81: 0 | AJ81: 0 | AK81: 0 | AL81: 0 | AM81: 0 | AN81: 0 | AO81: 0 | AP81: 0 | AQ81: 0 | AR81: 180 | AS81: 0 | AU81: 1.8床铺板打孔+纸箱+整片=23*22+50=556 1.5规格是536，1.2规格是525 | AV81: 69f6f4f6f888bb0001debee9 | AW81: 黑胡桃木悬浮床-1.35米-松木铺板 | AX81: 69f6f4f6f888bb0001debef9 | AY81: =H81 | AZ81: =BB81/(1-BA81) | BA81: 0.15 | BB81: =K81*0.96 | BC81: 1037237545657 | BD81: 待定 | BF81: =H81 | BG81: =BH81/BF81 | BH81: =I81 | BI81: =1-12% | BJ81: =BK81/(BF81-BF81*(1-BI81)) | BK81: =BM81/(1-BL81) | BL81: 0.01 | BM81: =J81 | BN81: =IF(BK81>=1500,BK81-150,IF(BK81>=800,BK81-80,IF(BK81>=500,BK81-50,IF(BK81>=200,BK81-20,BK81)))) | BO81: =1-12% | BP81: =BQ81/(BF81-BF81*(1-BO81)) | BQ81: =BS81/(1-BR81) | BR81: 0 | BS81: =K81 | BT81: =IF(BQ81>=1500,BQ81-150,IF(BQ81>=800,BQ81-80,IF(BQ81>=500,BQ81-50,IF(BQ81>=200,BQ81-20,BQ81)))) | CB81: ✅ 可导入 | CC81: ✓
A82: PPS26330150118 | B82: 畔色黑胡桃木悬浮双人床 |黑胡桃木标准床 | C82: 黑胡桃木悬浮床-1.5米-松木铺板 | D82: PPS2633015011817 | E82: https://img.alicdn.com/imgextra/i4/2215699812811/O1CN015fCgsq1WdUTgF91sN_!!2215699812811.jpg | F82: 中型 | G82: =Q82/0.4 | H82: =G82*0.75 | I82: =Q82 / (0.79 - 0.02 - 0.006) | J82: =Q82 / (0.8 - 0.02 - 0.006) | K82: =Q82 / (0.82 - 0.02 - 0.006) | L82: =K82-N82 | M82: =L82/K82 | N82: =O82+P82+Q82 | O82: =K82*0.006 | P82: =K82*0.02 | Q82: =SUM(R82:T82) | R82: =IF(F82="大型",700,IF(F82="中型",300,IF(F82="小型",80,0))) | S82: =IF(F82="大型",150,IF(F82="中型",100,IF(F82="小型",0,0))) | T82: =SUM(U82:W82) | U82: 2670 | V82: 150 | W82: =SUM(X82:AS82) | X82: 0 | Y82: 0 | Z82: 73 | AA82: 0 | AB82: 0 | AC82: 0 | AD82: 0 | AE82: 0 | AF82: 0 | AG82: 0 | AH82: 0 | AI82: 0 | AJ82: 0 | AK82: 0 | AL82: 0 | AM82: 0 | AN82: 0 | AO82: 0 | AP82: 0 | AQ82: 0 | AR82: 180 | AS82: 0 | AU82: 1.8床铺板打孔+纸箱+整片=23*22+50=556 1.5规格是536，1.2规格是526 | AV82: 69f6f4f6f888bb0001debee9 | AW82: 黑胡桃木悬浮床-1.5米-松木铺板 | AX82: 69f6f4f6f888bb0001debefc | AY82: =H82 | AZ82: =BB82/(1-BA82) | BA82: 0.15 | BB82: =K82*0.96 | BC82: 1037237545657 | BD82: 待定 | BF82: =H82 | BG82: =BH82/BF82 | BH82: =I82 | BI82: =1-12% | BJ82: =BK82/(BF82-BF82*(1-BI82)) | BK82: =BM82/(1-BL82) | BL82: 0.01 | BM82: =J82 | BN82: =IF(BK82>=1500,BK82-150,IF(BK82>=800,BK82-80,IF(BK82>=500,BK82-50,IF(BK82>=200,BK82-20,BK82)))) | BO82: =1-12% | BP82: =BQ82/(BF82-BF82*(1-BO82)) | BQ82: =BS82/(1-BR82) | BR82: 0 | BS82: =K82 | BT82: =IF(BQ82>=1500,BQ82-150,IF(BQ82>=800,BQ82-80,IF(BQ82>=500,BQ82-50,IF(BQ82>=200,BQ82-20,BQ82)))) | CB82: ✅ 可导入 | CC82: ✓
A83: PPS26330150118 | B83: 畔色黑胡桃木悬浮双人床 |黑胡桃木标准床 | C83: 黑胡桃木悬浮床-1.8米-松木铺板 | D83: PPS2633015011818 | E83: https://img.alicdn.com/imgextra/i4/2215699812811/O1CN015fCgsq1WdUTgF91sN_!!2215699812811.jpg | F83: 中型 | G83: =Q83/0.4 | H83: =G83*0.75 | I83: =Q83 / (0.79 - 0.02 - 0.006) | J83: =Q83 / (0.8 - 0.02 - 0.006) | K83: =Q83 / (0.82 - 0.02 - 0.006) | L83: =K83-N83 | M83: =L83/K83 | N83: =O83+P83+Q83 | O83: =K83*0.006 | P83: =K83*0.02 | Q83: =SUM(R83:T83) | R83: =IF(F83="大型",700,IF(F83="中型",300,IF(F83="小型",80,0))) | S83: =IF(F83="大型",150,IF(F83="中型",100,IF(F83="小型",0,0))) | T83: =SUM(U83:W83) | U83: 2800 | V83: 150 | W83: =SUM(X83:AS83) | X83: 0 | Y83: 0 | Z83: 73 | AA83: 0 | AB83: 0 | AC83: 0 | AD83: 0 | AE83: 0 | AF83: 0 | AG83: 0 | AH83: 0 | AI83: 0 | AJ83: 0 | AK83: 0 | AL83: 0 | AM83: 0 | AN83: 0 | AO83: 0 | AP83: 0 | AQ83: 0 | AR83: 200 | AS83: 0 | AU83: 1.8床铺板打孔+纸箱+整片=23*22+50=556 1.5规格是536，1.2规格是527 | AV83: 69f6f4f6f888bb0001debee9 | AW83: 黑胡桃木悬浮床-1.8米-松木铺板 | AX83: 69f6f4f6f888bb0001debeff | AY83: =H83 | AZ83: =BB83/(1-BA83) | BA83: 0.15 | BB83: =K83*0.96 | BC83: 1037237545657 | BD83: 待定 | BF83: =H83 | BG83: =BH83/BF83 | BH83: =I83 | BI83: =1-12% | BJ83: =BK83/(BF83-BF83*(1-BI83)) | BK83: =BM83/(1-BL83) | BL83: 0.01 | BM83: =J83 | BN83: =IF(BK83>=1500,BK83-150,IF(BK83>=800,BK83-80,IF(BK83>=500,BK83-50,IF(BK83>=200,BK83-20,BK83)))) | BO83: =1-12% | BP83: =BQ83/(BF83-BF83*(1-BO83)) | BQ83: =BS83/(1-BR83) | BR83: 0 | BS83: =K83 | BT83: =IF(BQ83>=1500,BQ83-150,IF(BQ83>=800,BQ83-80,IF(BQ83>=500,BQ83-50,IF(BQ83>=200,BQ83-20,BQ83)))) | CB83: ✅ 可导入 | CC83: ✓
A84: PPS26380040225 | B84: 畔色榉木床头柜 |榉木铁板床头柜 | C84: 榉木床头柜-标准 | D84: PPS2638004022511 | E84: https://img.alicdn.com/imgextra/i1/2215699812811/O1CN01v4u1KN1WdUTcaGHb9_!!2215699812811.jpg | F84: 小型 | G84: =Q84/0.4 | H84: =G84*0.75 | I84: =Q84 / (0.79 - 0.02 - 0.006) | J84: =Q84 / (0.8 - 0.02 - 0.006) | K84: =Q84 / (0.82 - 0.02 - 0.006) | L84: =K84-N84 | M84: =L84/K84 | N84: =O84+P84+Q84 | O84: =K84*0.006 | P84: =K84*0.02 | Q84: =SUM(R84:T84) | R84: =IF(F84="大型",700,IF(F84="中型",300,IF(F84="小型",80,0))) | S84: =IF(F84="大型",150,IF(F84="中型",100,IF(F84="小型",0,0))) | T84: =SUM(U84:W84) | U84: 450 | V84: 50 | W84: =SUM(X84:AS84) | X84: 0 | Y84: 0 | Z84: 0 | AA84: 0 | AB84: 0 | AC84: 0 | AD84: 0 | AE84: 0 | AF84: 0 | AG84: 0 | AH84: 0 | AI84: 0 | AJ84: 0 | AK84: 0 | AL84: 0 | AM84: 0 | AN84: 0 | AO84: 240 | AP84: 0 | AQ84: 0 | AR84: 0 | AS84: 0 | AT84: 碳素钢（铁板）:240元（包含2个侧板+1个横条） | AV84: 69f6f9f343360b0001b1eb1a | AW84: 榉木床头柜-标准 | AX84: 69f6f9f343360b0001b1eb1b | AY84: =H84 | AZ84: =BB84/(1-BA84) | BA84: 0.15 | BB84: =K84*0.96 | BC84: 1036312802226 | BD84: 待定 | BF84: =H84 | BG84: =BH84/BF84 | BH84: =I84 | BI84: =1-12% | BJ84: =BK84/(BF84-BF84*(1-BI84)) | BK84: =BM84/(1-BL84) | BL84: 0.01 | BM84: =J84 | BN84: =IF(BK84>=1500,BK84-150,IF(BK84>=800,BK84-80,IF(BK84>=500,BK84-50,IF(BK84>=200,BK84-20,BK84)))) | BO84: =1-12% | BP84: =BQ84/(BF84-BF84*(1-BO84)) | BQ84: =BS84/(1-BR84) | BR84: 0 | BS84: =K84 | BT84: =IF(BQ84>=1500,BQ84-150,IF(BQ84>=800,BQ84-80,IF(BQ84>=500,BQ84-50,IF(BQ84>=200,BQ84-20,BQ84)))) | CB84: ✅ 可导入 | CC84: ✓
A85: PPS26380040225 | B85: 畔色榉木床头柜 |榉木铁板床头柜 | C85: 榉木床头柜-窄款 | D85: PPS2638004022512 | E85: https://img.alicdn.com/imgextra/i1/2215699812811/O1CN01v4u1KN1WdUTcaGHb9_!!2215699812811.jpg | F85: 小型 | G85: =Q85/0.4 | H85: =G85*0.75 | I85: =Q85 / (0.79 - 0.02 - 0.006) | J85: =Q85 / (0.8 - 0.02 - 0.006) | K85: =Q85 / (0.82 - 0.02 - 0.006) | L85: =K85-N85 | M85: =L85/K85 | N85: =O85+P85+Q85 | O85: =K85*0.006 | P85: =K85*0.02 | Q85: =SUM(R85:T85) | R85: =IF(F85="大型",700,IF(F85="中型",300,IF(F85="小型",80,0))) | S85: =IF(F85="大型",150,IF(F85="中型",100,IF(F85="小型",0,0))) | T85: =SUM(U85:W85) | U85: 400 | V85: 50 | W85: =SUM(X85:AS85) | X85: 0 | Y85: 0 | Z85: 0 | AA85: 0 | AB85: 0 | AC85: 0 | AD85: 0 | AE85: 0 | AF85: 0 | AG85: 0 | AH85: 0 | AI85: 0 | AJ85: 0 | AK85: 0 | AL85: 0 | AM85: 0 | AN85: 0 | AO85: 240 | AP85: 0 | AQ85: 0 | AR85: 0 | AS85: 0 | AT85: 碳素钢（铁板）:240元（包含2个侧板+2个横条） | AV85: 69f6f9f343360b0001b1eb1a | AW85: 榉木床头柜-窄款 | AX85: 69f6f9f343360b0001b1eb1e | AY85: =H85 | AZ85: =BB85/(1-BA85) | BA85: 0.15 | BB85: =K85*0.96 | BC85: 1036312802226 | BD85: 待定 | BF85: =H85 | BG85: =BH85/BF85 | BH85: =I85 | BI85: =1-12% | BJ85: =BK85/(BF85-BF85*(1-BI85)) | BK85: =BM85/(1-BL85) | BL85: 0.01 | BM85: =J85 | BN85: =IF(BK85>=1500,BK85-150,IF(BK85>=800,BK85-80,IF(BK85>=500,BK85-50,IF(BK85>=200,BK85-20,BK85)))) | BO85: =1-12% | BP85: =BQ85/(BF85-BF85*(1-BO85)) | BQ85: =BS85/(1-BR85) | BR85: 0 | BS85: =K85 | BT85: =IF(BQ85>=1500,BQ85-150,IF(BQ85>=800,BQ85-80,IF(BQ85>=500,BQ85-50,IF(BQ85>=200,BQ85-20,BQ85)))) | CB85: ✅ 可导入 | CC85: ✓
A86: PPS26380050301 | B86: 畔色樱桃木轻盈边柜 |樱桃木玻璃床头柜 |黑色玻璃床头柜 |樱桃木玻璃边柜 | C86: 轻盈边柜-榉木黑-木底座 | D86: PPS2638005030111 | E86: https://img.alicdn.com/imgextra/i4/2215699812811/O1CN01aV7b7w1WdUTd0Dctr_!!2215699812811.jpg | F86: 小型 | G86: =Q86/0.4 | H86: =G86*0.75 | I86: =Q86 / (0.83 - 0.02 - 0.006) | J86: =Q86 / (0.85 - 0.02 - 0.006) | K86: =Q86 / (0.95 - 0.02 - 0.006) | L86: =K86-N86 | M86: =L86/K86 | N86: =O86+P86+Q86 | O86: =K86*0.006 | P86: =K86*0.02 | Q86: =SUM(R86:T86) | R86: 50 | S86: =IF(F86="大型",150,IF(F86="中型",100,IF(F86="小型",0,0))) | T86: =SUM(U86:W86) | U86: 200 | V86: 50 | W86: =SUM(X86:AS86) | X86: 0 | Y86: 0 | Z86: 0 | AA86: 150 | AB86: 0 | AC86: 0 | AD86: 0 | AE86: 0 | AF86: 0 | AG86: 0 | AH86: 0 | AI86: 0 | AJ86: 0 | AK86: 0 | AL86: 15 | AM86: 0 | AN86: 0 | AO86: 0 | AP86: 0 | AQ86: 0 | AR86: 0 | AS86: 0 | AV86: 69f425f515602900015c53bd | AW86: 轻盈边柜-榉木黑-原木底座 | AX86: 69f425f515602900015c53be | AY86: =H86 | AZ86: =BB86/(1-BA86) | BA86: 0.15 | BB86: =K86*0.96 | BC86: 1038087212258 | BD86: 待定 | BF86: =H86 | BG86: =BH86/BF86 | BH86: =I86 | BI86: =1-12% | BJ86: =BK86/(BF86-BF86*(1-BI86)) | BK86: =BM86/(1-BL86) | BL86: 0.01 | BM86: =J86 | BN86: =IF(BK86>=1500,BK86-150,IF(BK86>=800,BK86-80,IF(BK86>=500,BK86-50,IF(BK86>=200,BK86-20,BK86)))) | BO86: =1-12% | BP86: =BQ86/(BF86-BF86*(1-BO86)) | BQ86: =BS86/(1-BR86) | BR86: 0 | BS86: =K86 | BT86: =IF(BQ86>=1500,BQ86-150,IF(BQ86>=800,BQ86-80,IF(BQ86>=500,BQ86-50,IF(BQ86>=200,BQ86-20,BQ86)))) | CB86: ✅ 可导入 | CC86: ✓
A87: PPS26380050301 | B87: 畔色樱桃木轻盈边柜 |樱桃木玻璃床头柜 |黑色玻璃床头柜 |樱桃木玻璃边柜 | C87: 轻盈边柜-樱桃木-木底座 | D87: PPS2638005030112 | E87: https://img.alicdn.com/imgextra/i4/2215699812811/O1CN01aV7b7w1WdUTd0Dctr_!!2215699812811.jpg | F87: 小型 | G87: =Q87/0.4 | H87: =G87*0.75 | I87: =Q87 / (0.83 - 0.02 - 0.006) | J87: =Q87 / (0.85 - 0.02 - 0.006) | K87: =Q87 / (0.95 - 0.02 - 0.006) | L87: =K87-N87 | M87: =L87/K87 | N87: =O87+P87+Q87 | O87: =K87*0.006 | P87: =K87*0.02 | Q87: =SUM(R87:T87) | R87: 50 | S87: =IF(F87="大型",150,IF(F87="中型",100,IF(F87="小型",0,0))) | T87: =SUM(U87:W87) | U87: 220 | V87: 50 | W87: =SUM(X87:AS87) | X87: 0 | Y87: 0 | Z87: 0 | AA87: 150 | AB87: 0 | AC87: 0 | AD87: 0 | AE87: 0 | AF87: 0 | AG87: 0 | AH87: 0 | AI87: 0 | AJ87: 0 | AK87: 0 | AL87: 15 | AM87: 0 | AN87: 0 | AO87: 0 | AP87: 0 | AQ87: 0 | AR87: 0 | AS87: 0 | AV87: 69f425f515602900015c53bd | AW87: 轻盈边柜-樱桃木-原木底座 | AX87: 69f425f515602900015c53c1 | AY87: =H87 | AZ87: =BB87/(1-BA87) | BA87: 0.15 | BB87: =K87*0.96 | BC87: 1038087212258 | BD87: 待定 | BF87: =H87 | BG87: =BH87/BF87 | BH87: =I87 | BI87: =1-12% | BJ87: =BK87/(BF87-BF87*(1-BI87)) | BK87: =BM87/(1-BL87) | BL87: 0.01 | BM87: =J87 | BN87: =IF(BK87>=1500,BK87-150,IF(BK87>=800,BK87-80,IF(BK87>=500,BK87-50,IF(BK87>=200,BK87-20,BK87)))) | BO87: =1-12% | BP87: =BQ87/(BF87-BF87*(1-BO87)) | BQ87: =BS87/(1-BR87) | BR87: 0 | BS87: =K87 | BT87: =IF(BQ87>=1500,BQ87-150,IF(BQ87>=800,BQ87-80,IF(BQ87>=500,BQ87-50,IF(BQ87>=200,BQ87-20,BQ87)))) | CB87: ✅ 可导入 | CC87: ✓
A88: PPS26380050301 | B88: 畔色樱桃木轻盈边柜 |樱桃木玻璃床头柜 |黑色玻璃床头柜 |樱桃木玻璃边柜 | C88: 轻盈边柜-黑胡桃木-木底座 | D88: PPS2638005030113 | E88: https://img.alicdn.com/imgextra/i4/2215699812811/O1CN01aV7b7w1WdUTd0Dctr_!!2215699812811.jpg | F88: 小型 | G88: =Q88/0.4 | H88: =G88*0.75 | I88: =Q88 / (0.83 - 0.02 - 0.006) | J88: =Q88 / (0.85 - 0.02 - 0.006) | K88: =Q88 / (0.95 - 0.02 - 0.006) | L88: =K88-N88 | M88: =L88/K88 | N88: =O88+P88+Q88 | O88: =K88*0.006 | P88: =K88*0.02 | Q88: =SUM(R88:T88) | R88: 50 | S88: =IF(F88="大型",150,IF(F88="中型",100,IF(F88="小型",0,0))) | T88: =SUM(U88:W88) | U88: 280 | V88: 50 | W88: =SUM(X88:AS88) | X88: 0 | Y88: 0 | Z88: 0 | AA88: 150 | AB88: 0 | AC88: 0 | AD88: 0 | AE88: 0 | AF88: 0 | AG88: 0 | AH88: 0 | AI88: 0 | AJ88: 0 | AK88: 0 | AL88: 15 | AM88: 0 | AN88: 0 | AO88: 0 | AP88: 0 | AQ88: 0 | AR88: 0 | AS88: 0 | AV88: / | AW88: / | AX88: / | AY88: =H88 | AZ88: =BB88/(1-BA88) | BA88: 0.15 | BB88: =K88*0.96 | BC88: 1038087212258 | BD88: 待定 | BF88: =H88 | BG88: =BH88/BF88 | BH88: =I88 | BI88: =1-12% | BJ88: =BK88/(BF88-BF88*(1-BI88)) | BK88: =BM88/(1-BL88) | BL88: 0.01 | BM88: =J88 | BN88: =IF(BK88>=1500,BK88-150,IF(BK88>=800,BK88-80,IF(BK88>=500,BK88-50,IF(BK88>=200,BK88-20,BK88)))) | BO88: =1-12% | BP88: =BQ88/(BF88-BF88*(1-BO88)) | BQ88: =BS88/(1-BR88) | BR88: 0 | BS88: =K88 | BT88: =IF(BQ88>=1500,BQ88-150,IF(BQ88>=800,BQ88-80,IF(BQ88>=500,BQ88-50,IF(BQ88>=200,BQ88-20,BQ88)))) | CB88: ✅ 可导入 | CC88: ✓
A89: PPS26380050301 | B89: 畔色樱桃木轻盈边柜 |樱桃木玻璃床头柜 |黑色玻璃床头柜 |樱桃木玻璃边柜 | C89: 轻盈边柜-榉木黑-玻璃底座 | D89: PPS2638005030114 | E89: https://img.alicdn.com/imgextra/i4/2215699812811/O1CN01aV7b7w1WdUTd0Dctr_!!2215699812811.jpg | F89: 小型 | G89: =Q89/0.4 | H89: =G89*0.75 | I89: =Q89 / (0.83 - 0.02 - 0.006) | J89: =Q89 / (0.85 - 0.02 - 0.006) | K89: =Q89 / (0.95 - 0.02 - 0.006) | L89: =K89-N89 | M89: =L89/K89 | N89: =O89+P89+Q89 | O89: =K89*0.006 | P89: =K89*0.02 | Q89: =SUM(R89:T89) | R89: 50 | S89: =IF(F89="大型",150,IF(F89="中型",100,IF(F89="小型",0,0))) | T89: =SUM(U89:W89) | U89: 160 | V89: 50 | W89: =SUM(X89:AS89) | X89: 0 | Y89: 0 | Z89: 0 | AA89: 180 | AB89: 0 | AC89: 0 | AD89: 0 | AE89: 0 | AF89: 0 | AG89: 0 | AH89: 0 | AI89: 0 | AJ89: 0 | AK89: 0 | AL89: 15 | AM89: 0 | AN89: 0 | AO89: 0 | AP89: 0 | AQ89: 0 | AR89: 0 | AS89: 0 | AV89: 69f425f515602900015c53bd | AW89: 轻盈边柜-榉木黑-玻璃底座 | AX89: 69f425f515602900015c53c4 | AY89: =H89 | AZ89: =BB89/(1-BA89) | BA89: 0.15 | BB89: =K89*0.96 | BC89: 1038087212258 | BD89: 待定 | BF89: =H89 | BG89: =BH89/BF89 | BH89: =I89 | BI89: =1-12% | BJ89: =BK89/(BF89-BF89*(1-BI89)) | BK89: =BM89/(1-BL89) | BL89: 0.01 | BM89: =J89 | BN89: =IF(BK89>=1500,BK89-150,IF(BK89>=800,BK89-80,IF(BK89>=500,BK89-50,IF(BK89>=200,BK89-20,BK89)))) | BO89: =1-12% | BP89: =BQ89/(BF89-BF89*(1-BO89)) | BQ89: =BS89/(1-BR89) | BR89: 0 | BS89: =K89 | BT89: =IF(BQ89>=1500,BQ89-150,IF(BQ89>=800,BQ89-80,IF(BQ89>=500,BQ89-50,IF(BQ89>=200,BQ89-20,BQ89)))) | CB89: ✅ 可导入 | CC89: ✓
A90: PPS26380050301 | B90: 畔色樱桃木轻盈边柜 |樱桃木玻璃床头柜 |黑色玻璃床头柜 |樱桃木玻璃边柜 | C90: 轻盈边柜-樱桃木-玻璃底座 | D90: PPS2638005030115 | E90: https://img.alicdn.com/imgextra/i4/2215699812811/O1CN01aV7b7w1WdUTd0Dctr_!!2215699812811.jpg | F90: 小型 | G90: =Q90/0.4 | H90: =G90*0.75 | I90: =Q90 / (0.83 - 0.02 - 0.006) | J90: =Q90 / (0.85 - 0.02 - 0.006) | K90: =Q90 / (0.95 - 0.02 - 0.006) | L90: =K90-N90 | M90: =L90/K90 | N90: =O90+P90+Q90 | O90: =K90*0.006 | P90: =K90*0.02 | Q90: =SUM(R90:T90) | R90: 50 | S90: =IF(F90="大型",150,IF(F90="中型",100,IF(F90="小型",0,0))) | T90: =SUM(U90:W90) | U90: 170 | V90: 50 | W90: =SUM(X90:AS90) | X90: 0 | Y90: 0 | Z90: 0 | AA90: 180 | AB90: 0 | AC90: 0 | AD90: 0 | AE90: 0 | AF90: 0 | AG90: 0 | AH90: 0 | AI90: 0 | AJ90: 0 | AK90: 0 | AL90: 15 | AM90: 0 | AN90: 0 | AO90: 0 | AP90: 0 | AQ90: 0 | AR90: 0 | AS90: 0 | AV90: 69f425f515602900015c53bd | AW90: 轻盈边柜-樱桃木-玻璃底座 | AX90: 69f425f515602900015c53c7 | AY90: =H90 | AZ90: =BB90/(1-BA90) | BA90: 0.15 | BB90: =K90*0.96 | BC90: 1038087212258 | BD90: 待定 | BF90: =H90 | BG90: =BH90/BF90 | BH90: =I90 | BI90: =1-12% | BJ90: =BK90/(BF90-BF90*(1-BI90)) | BK90: =BM90/(1-BL90) | BL90: 0.01 | BM90: =J90 | BN90: =IF(BK90>=1500,BK90-150,IF(BK90>=800,BK90-80,IF(BK90>=500,BK90-50,IF(BK90>=200,BK90-20,BK90)))) | BO90: =1-12% | BP90: =BQ90/(BF90-BF90*(1-BO90)) | BQ90: =BS90/(1-BR90) | BR90: 0 | BS90: =K90 | BT90: =IF(BQ90>=1500,BQ90-150,IF(BQ90>=800,BQ90-80,IF(BQ90>=500,BQ90-50,IF(BQ90>=200,BQ90-20,BQ90)))) | CB90: ✅ 可导入 | CC90: ✓
A91: PPS26380050301 | B91: 畔色樱桃木轻盈边柜 |樱桃木玻璃床头柜 |黑色玻璃床头柜 |樱桃木玻璃边柜 | C91: 轻盈边柜-黑胡桃木-玻璃底座 | D91: PPS2638005030116 | E91: https://img.alicdn.com/imgextra/i4/2215699812811/O1CN01aV7b7w1WdUTd0Dctr_!!2215699812811.jpg | F91: 小型 | G91: =Q91/0.4 | H91: =G91*0.75 | I91: =Q91 / (0.83 - 0.02 - 0.006) | J91: =Q91 / (0.85 - 0.02 - 0.006) | K91: =Q91 / (0.95 - 0.02 - 0.006) | L91: =K91-N91 | M91: =L91/K91 | N91: =O91+P91+Q91 | O91: =K91*0.006 | P91: =K91*0.02 | Q91: =SUM(R91:T91) | R91: 50 | S91: =IF(F91="大型",150,IF(F91="中型",100,IF(F91="小型",0,0))) | T91: =SUM(U91:W91) | U91: 230 | V91: 50 | W91: =SUM(X91:AS91) | X91: 0 | Y91: 0 | Z91: 0 | AA91: 180 | AB91: 0 | AC91: 0 | AD91: 0 | AE91: 0 | AF91: 0 | AG91: 0 | AH91: 0 | AI91: 0 | AJ91: 0 | AK91: 0 | AL91: 15 | AM91: 0 | AN91: 0 | AO91: 0 | AP91: 0 | AQ91: 0 | AR91: 0 | AS91: 0 | AV91: / | AW91: / | AX91: / | AY91: =H91 | AZ91: =BB91/(1-BA91) | BA91: 0.15 | BB91: =K91*0.96 | BC91: 1038087212258 | BD91: 待定 | BF91: =H91 | BG91: =BH91/BF91 | BH91: =I91 | BI91: =1-12% | BJ91: =BK91/(BF91-BF91*(1-BI91)) | BK91: =BM91/(1-BL91) | BL91: 0.01 | BM91: =J91 | BN91: =IF(BK91>=1500,BK91-150,IF(BK91>=800,BK91-80,IF(BK91>=500,BK91-50,IF(BK91>=200,BK91-20,BK91)))) | BO91: =1-12% | BP91: =BQ91/(BF91-BF91*(1-BO91)) | BQ91: =BS91/(1-BR91) | BR91: 0 | BS91: =K91 | BT91: =IF(BQ91>=1500,BQ91-150,IF(BQ91>=800,BQ91-80,IF(BQ91>=500,BQ91-50,IF(BQ91>=200,BQ91-20,BQ91)))) | CB91: ✅ 可导入 | CC91: ✓
A92: PPS26390070315 | B92: 畔色樱桃木床头窄柜 | 樱桃木窄床头柜 | C92: 樱桃木床头窄柜-标准宽度 | D92: PPS2639007031511 | E92: https://img.alicdn.com/imgextra/i3/2215699812811/O1CN01Iuil5d1WdUTXCr2Tl_!!2215699812811.jpg | F92: 小型 | G92: =Q92/0.4 | H92: =G92*0.75 | I92: =Q92 / (0.79 - 0.02 - 0.006) | J92: =Q92 / (0.8 - 0.02 - 0.006) | K92: =Q92 / (0.9 - 0.02 - 0.006) | L92: =K92-N92 | M92: =L92/K92 | N92: =O92+P92+Q92 | O92: =K92*0.006 | P92: =K92*0.02 | Q92: =SUM(R92:T92) | R92: =IF(F92="大型",700,IF(F92="中型",300,IF(F92="小型",80,0))) | S92: =IF(F92="大型",150,IF(F92="中型",100,IF(F92="小型",0,0))) | T92: =SUM(U92:W92) | U92: 500 | V92: 50 | W92: =SUM(X92:AS92) | X92: 0 | Y92: 0 | Z92: 0 | AA92: 0 | AB92: 0 | AC92: 0 | AD92: 0 | AE92: 0 | AF92: 0 | AG92: 0 | AH92: 0 | AI92: 0 | AJ92: 0 | AK92: 0 | AL92: 0 | AM92: 0 | AN92: 0 | AO92: 0 | AP92: 100 | AQ92: 0 | AR92: 0 | AS92: 0 | AT92: 黑色金属腿：100元 | AV92: 69f6f8cb6bdc380001d3bbde | AW92: 0 | AX92: 69f6f8cb6bdc380001d3bbdf | AY92: =H92 | AZ92: =BB92/(1-BA92) | BA92: 0.15 | BB92: =K92*0.96 | BC92: 1037239277197 | BD92: 待定 | BF92: =H92 | BG92: =BH92/BF92 | BH92: =I92 | BI92: =1-12% | BJ92: =BK92/(BF92-BF92*(1-BI92)) | BK92: =BM92/(1-BL92) | BL92: 0.01 | BM92: =J92 | BN92: =IF(BK92>=1500,BK92-150,IF(BK92>=800,BK92-80,IF(BK92>=500,BK92-50,IF(BK92>=200,BK92-20,BK92)))) | BO92: =1-12% | BP92: =BQ92/(BF92-BF92*(1-BO92)) | BQ92: =BS92/(1-BR92) | BR92: 0 | BS92: =K92 | BT92: =IF(BQ92>=1500,BQ92-150,IF(BQ92>=800,BQ92-80,IF(BQ92>=500,BQ92-50,IF(BQ92>=200,BQ92-20,BQ92)))) | CB92: ✅ 可导入 | CC92: ✓
A93: PPS26380060320 | B93: 畔色黑胡桃木床头柜 |黑胡桃木岩板床头柜 | C93: 黑胡桃木床头柜-岩板台面 | D93: PPS2638006032011 | E93: https://img.alicdn.com/imgextra/i2/2215699812811/O1CN01m01PAA1WdUTaTRZji_!!2215699812811.jpg | F93: 小型 | G93: =Q93/0.4 | H93: =G93*0.75 | I93: =Q93 / (0.79 - 0.02 - 0.006) | J93: =Q93 / (0.8 - 0.02 - 0.006) | K93: =Q93 / (0.82 - 0.02 - 0.006) | L93: =K93-N93 | M93: =L93/K93 | N93: =O93+P93+Q93 | O93: =K93*0.006 | P93: =K93*0.02 | Q93: =SUM(R93:T93) | R93: =IF(F93="大型",700,IF(F93="中型",300,IF(F93="小型",80,0))) | S93: =IF(F93="大型",150,IF(F93="中型",100,IF(F93="小型",0,0))) | T93: =SUM(U93:W93) | U93: 900 | V93: 50 | W93: =SUM(X93:AS93) | X93: 100 | Y93: 0 | Z93: 0 | AA93: 0 | AB93: 0 | AC93: 0 | AD93: 0 | AE93: 0 | AF93: 0 | AG93: 0 | AH93: 24 | AI93: 0 | AJ93: 0 | AK93: 0 | AL93: 0 | AM93: 0 | AN93: 0 | AO93: 0 | AP93: 0 | AQ93: 0 | AR93: 0 | AS93: 0 | AV93: 69f6fab6e0e86e0001766018 | AW93: 黑胡桃木床头柜-岩板台面 | AX93: 69f6fab6e0e86e0001766019 | AY93: =H93 | AZ93: =BB93/(1-BA93) | BA93: 0.15 | BB93: =K93*0.96 | BC93: 1038088884522 | BD93: 待定 | BF93: =H93 | BG93: =BH93/BF93 | BH93: =I93 | BI93: =1-12% | BJ93: =BK93/(BF93-BF93*(1-BI93)) | BK93: =BM93/(1-BL93) | BL93: 0.01 | BM93: =J93 | BN93: =IF(BK93>=1500,BK93-150,IF(BK93>=800,BK93-80,IF(BK93>=500,BK93-50,IF(BK93>=200,BK93-20,BK93)))) | BO93: =1-12% | BP93: =BQ93/(BF93-BF93*(1-BO93)) | BQ93: =BS93/(1-BR93) | BR93: 0 | BS93: =K93 | BT93: =IF(BQ93>=1500,BQ93-150,IF(BQ93>=800,BQ93-80,IF(BQ93>=500,BQ93-50,IF(BQ93>=200,BQ93-20,BQ93)))) | CB93: ✅ 可导入 | CC93: ✓
A94: PPS26380060320 | B94: 畔色黑胡桃木床头柜 |黑胡桃木岩板床头柜 | C94: 黑胡桃木床头柜-木台面 | D94: PPS2638006032012 | E94: https://img.alicdn.com/imgextra/i2/2215699812811/O1CN01m01PAA1WdUTaTRZji_!!2215699812811.jpg | F94: 小型 | G94: =Q94/0.4 | H94: =G94*0.75 | I94: =Q94 / (0.79 - 0.02 - 0.006) | J94: =Q94 / (0.8 - 0.02 - 0.006) | K94: =Q94 / (0.82 - 0.02 - 0.006) | L94: =K94-N94 | M94: =L94/K94 | N94: =O94+P94+Q94 | O94: =K94*0.006 | P94: =K94*0.02 | Q94: =SUM(R94:T94) | R94: =IF(F94="大型",700,IF(F94="中型",300,IF(F94="小型",80,0))) | S94: =IF(F94="大型",150,IF(F94="中型",100,IF(F94="小型",0,0))) | T94: =SUM(U94:W94) | U94: 900 | V94: 50 | W94: =SUM(X94:AS94) | X94: 0 | Y94: 0 | Z94: 0 | AA94: 0 | AB94: 0 | AC94: 0 | AD94: 0 | AE94: 0 | AF94: 0 | AG94: 0 | AH94: 24 | AI94: 0 | AJ94: 0 | AK94: 0 | AL94: 0 | AM94: 0 | AN94: 0 | AO94: 0 | AP94: 0 | AQ94: 0 | AR94: 0 | AS94: 0 | AV94: 69f6fab6e0e86e0001766018 | AW94: 黑胡桃木床头柜-木台面 | AX94: 69f6fab6e0e86e000176601c | AY94: =H94 | AZ94: =BB94/(1-BA94) | BA94: 0.15 | BB94: =K94*0.96 | BC94: 1038088884522 | BD94: 待定 | BF94: =H94 | BG94: =BH94/BF94 | BH94: =I94 | BI94: =1-12% | BJ94: =BK94/(BF94-BF94*(1-BI94)) | BK94: =BM94/(1-BL94) | BL94: 0.01 | BM94: =J94 | BN94: =IF(BK94>=1500,BK94-150,IF(BK94>=800,BK94-80,IF(BK94>=500,BK94-50,IF(BK94>=200,BK94-20,BK94)))) | BO94: =1-12% | BP94: =BQ94/(BF94-BF94*(1-BO94)) | BQ94: =BS94/(1-BR94) | BR94: 0 | BS94: =K94 | BT94: =IF(BQ94>=1500,BQ94-150,IF(BQ94>=800,BQ94-80,IF(BQ94>=500,BQ94-50,IF(BQ94>=200,BQ94-20,BQ94)))) | CB94: ✅ 可导入 | CC94: ✓
