Workbook

Sheet ⚙️ 参数设置
A1: 畔色报价系统 — 参数设置 & 物料单价库 | G1: 系统参数（黄色格可修改）
A2: 成本分组 | B2: 材料/物料名称 | C2: 单位 | D2: 单价（¥） | E2: 备注 | G2: 参数名称 | H2: 当前值 | I2: 说明
A3: 木材成本 | B3: 黑胡桃木-2.2cm厚度 | C3: 平方米 | D3: 500 | G3: 工厂利润系数 | H3: 0.25 | I3: 木材+人工成本 × (1+系数) = 工厂报价给畔色
B4: 白橡木-2.2cm厚度 | C4: 平方米 | D4: 300 | G4: 畔色利润系数 | H4: 0.15 | I4: 高定模式：畔色总成本 ÷ (1-系数) = 最终报价
B5: 樱桃木-2.2cm厚度 | C5: 平方米 | D5: 300 | G5: 人工占出厂比例 | H5: 0.3 | I5: 轻定制追加部分人工费估算比例
B6: 白蜡木-2.2cm厚度 | C6: 平方米 | D6: 300
B7: 红橡木-2.2cm厚度 | C7: 平方米 | D7: 240 | G7: 打包费-小型 | H7: 100 | I7: 床头柜 / 组合柜 / 小推车 / 餐凳 / 衣帽架
B8: 榉木-2.2cm厚度 | C8: 平方米 | D8: 240 | G8: 打包费-中型 | H8: 200 | I8: 床 / 梳妆台 / 斗柜 / 镜子 / 电视柜 / 茶几 / 餐桌 / 升降桌
B9: 实木多层板1.8cm厚度 | C9: 平方米 | D9: 220 | G9: 打包费-大型 | H9: 400 | I9: 餐边柜 / 岛台 / 书柜 / 书桌 / 鞋柜
B10: 樱桃木-2.8cm厚度 | C10: 平方米 | D10: 520 | G10: 运费-小型 | H10: 80
A11: 配件材料成本 | B11: 12mm 普通岩板 | C11: 平方米 | D11: 200 | G11: 运费-中型 | H11: 100
B12: 12mm 洞石岩板 | C12: 平方米 | D12: 400 | G12: 运费-大型 | H12: 300
B13: 9mm 洞石下挂岩板 | C13: 平方米 | D13: 660 | E13: 不准确，2米以上的价格更贵；岩板按照具体尺寸计算 | G13: 安装费-小型 | H13: 50
B14: 亚克力洞洞板 | C14: 平方米 | D14: 300 | G14: 安装费-中型 | H14: 100
B15: 金属洞洞板 | C15: 平方米 | D15: 250 | G15: 安装费-大型 | H15: 150
B16: MDF纤维洞洞板 | C16: 平方米 | D16: 250
B17: 洞石背板 | C17: 平方米 | D17: 95 | G17: 榉木单价(参考) | H17: 240 | I17: 用于计算换材差价，如有变动请修改
B18: 软木板 | C18: 平方米 | D18: 86 | G18: 黑胡桃单价(参考) | H18: 500 | I18: 用于计算换材差价，如有变动请修改
B19: 电力轨道-带挂架 | C19: 米 | D19: 368 | E19: 挂架款1米均价；含2插座；标配3米长2.5平电线 | G19: 樱桃木单价(参考) | H19: 300 | I19: 用于计算换材差价，如有变动请修改
B20: 电力轨道-普通款 | C20: 米 | D20: 625 | E20: 普通款1米均价；含2插座；标配3米长2.5平电线
B21: 灯带 | C21: 米 | D21: 50 | E21: 按照100一根给客户算
B22: 层板灯 | C22: 米 | D22: 25 | E22: 不含感应按钮和变压器
B23: 超白玻璃 | C23: 平方米 | D23: 250 | E23: 1张顶柜玻璃40-50块左右
B24: 压花玻璃 | C24: 平方米 | D24: 250 | E24: 1张顶柜玻璃40-50块左右
B25: 钢化玻璃 | C25: 平方米 | D25: 250 | E25: 1张顶柜玻璃40-50块左右
B26: 瓷白玻璃 | C26: 平方米 | D26: 263 | E26: 实际是亚克力?
B27: 磁吸瓷白玻璃 | C27: 平方米 | D27: 309 | E27: 超自磁吸玻璃
B28: 美耐板 | C28: 平方米 | D28: 80 | E28: 1.22*2.44m 1mm厚度；买就是一整张135
B29: 铝合金轨道槽 | C29: 米 | D29: 25 | E29: 不含堵头，2米以上长度48一根，且超长需要加物流费
B30: 抽屉轨道 | C30: 付 | D30: 22 | E30: 16寸阻尼款（其他会不同）
B31: 桌下理线架 | C31: 个 | D31: 72
B32: 五金件 | C32: 组 | D32: 100
B33: 镜子 | C33: 平方米 | D33: 200
B34: 榉木床铺板 | C34: 张 | D34: 600
B35: 镜面金属板 | C35: 平方米 | D35: 200
B36: 旋转金属底座 | C36: 个 | D36: 400
B37: 亚克力条 | C37: 1米 | D37: 40
B38: 金属把手 | C38: 1个 | D38: 30
B39: 移动金属轮 | C39: 1个 | D39: 40
B40: 金属轨道 | C40: 1米 | D40: 25
B41: 金属杆 | C41: 1米 | D41: 30
B42: 黄铜挂钩 | C42: 1个 | D42: 10
... B54: 床铺板-松木 | C54: 副 | D54: 400
A55: 工厂人工费用 | B55: 床-人工费-小型 | C55: 1件 | D55: 600
B56: 床头柜-人工费-小型 | C56: 1件 | D56: 300
B57: 梳妆台-人工费-小型 | C57: 1件 | D57: 600
B58: 斗柜-人工费-小型 | C58: 1件 | D58: 600
B59: 镜子-人工费-小型 | C59: 1件 | D59: 400
B60: 电视柜-人工费-小型 | C60: 1件 | D60: 600
B61: 茶几-人工费-小型 | C61: 1件 | D61: 400
B62: 组合柜-人工费-小型 | C62: 1件 | D62: 300
B63: 小推车-人工费-小型 | C63: 1件 | D63: 400
B64: 餐边柜-人工费-小型 | C64: 1件 | D64: 840
B65: 餐桌-人工费-小型 | C65: 1件 | D65: 300
B66: 餐凳-人工费-小型 | C66: 1件 | D66: 300
B67: 岛台-人工费-小型 | C67: 1件 | D67: 600
... B108: 衣帽架-人工费-大型 | C108: 1件 | D108: 300
A109: 打包费用 | B109: 打包费用-小型家具 | C109: 1件 | D109: 100 | E109: 包含类目：床头柜；组合柜；小推车；餐凳；衣帽架；
B110: 打包费用-中型家具 | C110: 1件 | D110: 200 | E110: 包含类目：床；梳妆台；斗柜；镜子；电视柜；茶几；餐桌；升降桌；
B111: 打包费用-大型家具 | C111: 1件 | D111: 400 | E111: 包含类目：餐边柜；岛台；书柜；书桌；鞋柜；
A112: 运费 | B112: 运费-小型家具 | C112: 1件 | D112: 80
B113: 运费-中型家具 | C113: 1件 | D113: 100
B114: 运费-大型家具 | C114: 1件 | D114: 300
A115: 上门安装费 | B115: 上门安装费-小型家具 | C115: 1件 | D115: 50
B116: 上门安装费-中型家具 | C116: 1件 | D116: 100
B117: 上门安装费-大型家具 | C117: 1件 | D117: 150
A118: 工厂利润 | B118: 工厂利润系数 | C118: 系数 | D118: 0.25
A119: 畔色利润 | B119: 畔色利润系数 | C119: 系数 | D119: 0.15
A120: 一般人工费 | B120: 人工占出厂一般比例 | C120: 系数 | D120: 0.3

Sheet ① 轻定制报价
A1: 畔色 轻定制报价表 — 在标准款基础上调整尺寸/材质，自动计算售价
A2: 产品信息 | H2: 标准款成本（等工厂报价填H/I列） | L2: 四档利润率（黄色可改，每产品独立） | P2: 四档售价（自动计算） | T2: 四档实际毛利率（自动） | X2: 轻定制—尺寸调整单价（每±1cm 或 每㎡ 的加减金额） | AF2: 轻定制—换主材差价（手动填，正数=加价，负数=减价） | AH2: 备注
A3: 产品编码 | B3: 类目 | C3: 产品名称 | D3: SKU | E3: 主材 | F3: 辅材 | G3: 尺寸明细 | H3: 出厂价 (工厂报价) | I3: 木作成本 (纯材料) | J3: 木材占 木作比 | K3: 畔色 总成本 | L3: 日常价 利润率 | M3: 小促价 利润率 | N3: 中促价 利润率 | O3: 大促价 利润率 | P3: 日常价 (自动) | Q3: 小促价 (自动) | R3: 中促价 (自动) | S3: 大促价 (自动) | T3: 日常 毛利率 | U3: 小促 毛利率 | V3: 中促 毛利率 | W3: 大促 毛利率 | X3: 长度 每±1cm | Y3: 宽/深 每±1cm | Z3: 高度 每±1cm | AA3: 顶柜高 每±1cm | AB3: 立收高 每±1cm | AC3: 下柜深 每±1cm | AD3: 追加隔板 每㎡ | AE3: 包装物流 加10cm↑ | AF3: 改榉木 差价¥ | AG3: 改黑胡桃 差价¥ | AH3: 备注
A4: 2633007032099 | B4: 卧室-床 | C4: 畔色榉木无边床 |榉木金属腿床 | D4: 榉木无边床-1.2米-榉木铺板 | E4: 未知 | F4: 未知 | G4: 未知 | H4: 0 | I4: 0 | J4: 0.5 | K4: =IFERROR(H4,0) | L4: 0.4676 | M4: 0.2188 | N4: 0.2015 | O4: 0.1833 | P4: =IFERROR(IF(K4=0,"待填成本",ROUND(K4/(1-L4),0)),"" ) | Q4: =IFERROR(IF(K4=0,"待填成本",ROUND(K4/(1-M4),0)),"" ) | R4: =IFERROR(IF(K4=0,"待填成本",ROUND(K4/(1-N4),0)),"" ) | S4: =IFERROR(IF(K4=0,"待填成本",ROUND(K4/(1-O4),0)),"" ) | T4: =IFERROR(IF(K4=0,"",(P4-K4)/P4),"" ) | U4: =IFERROR(IF(K4=0,"",(Q4-K4)/Q4),"" ) | V4: =IFERROR(IF(K4=0,"",(R4-K4)/R4),"" ) | W4: =IFERROR(IF(K4=0,"",(S4-K4)/S4),"" )
A5: 2633007032099 | B5: 卧室-床 | C5: 畔色榉木无边床 |榉木金属腿床 | D5: 榉木无边床-1.35米-榉木铺板 | E5: 未知 | F5: 未知 | G5: 未知 | H5: 0 | I5: 0 | J5: 0.5 | K5: =IFERROR(H5,0) | L5: 0.4676 | M5: 0.2188 | N5: 0.2015 | O5: 0.1833 | P5: =IFERROR(IF(K5=0,"待填成本",ROUND(K5/(1-L5),0)),"" ) | Q5: =IFERROR(IF(K5=0,"待填成本",ROUND(K5/(1-M5),0)),"" ) | R5: =IFERROR(IF(K5=0,"待填成本",ROUND(K5/(1-N5),0)),"" ) | S5: =IFERROR(IF(K5=0,"待填成本",ROUND(K5/(1-O5),0)),"" ) | T5: =IFERROR(IF(K5=0,"",(P5-K5)/P5),"" ) | U5: =IFERROR(IF(K5=0,"",(Q5-K5)/Q5),"" ) | V5: =IFERROR(IF(K5=0,"",(R5-K5)/R5),"" ) | W5: =IFERROR(IF(K5=0,"",(S5-K5)/S5),"" )
A6: 2633007032099 | B6: 卧室-床 | C6: 畔色榉木无边床 |榉木金属腿床 | D6: 榉木无边床-1.5米-榉木铺板 | E6: 未知 | F6: 未知 | G6: 未知 | H6: 0 | I6: 0 | J6: 0.5 | K6: =IFERROR(H6,0) | L6: 0.4676 | M6: 0.2188 | N6: 0.2015 | O6: 0.1833 | P6: =IFERROR(IF(K6=0,"待填成本",ROUND(K6/(1-L6),0)),"" ) | Q6: =IFERROR(IF(K6=0,"待填成本",ROUND(K6/(1-M6),0)),"" ) | R6: =IFERROR(IF(K6=0,"待填成本",ROUND(K6/(1-N6),0)),"" ) | S6: =IFERROR(IF(K6=0,"待填成本",ROUND(K6/(1-O6),0)),"" ) | T6: =IFERROR(IF(K6=0,"",(P6-K6)/P6),"" ) | U6: =IFERROR(IF(K6=0,"",(Q6-K6)/Q6),"" ) | V6: =IFERROR(IF(K6=0,"",(R6-K6)/R6),"" ) | W6: =IFERROR(IF(K6=0,"",(S6-K6)/S6),"" )
A7: 2633007032099 | B7: 卧室-床 | C7: 畔色榉木无边床 |榉木金属腿床 | D7: 榉木无边床-1.8米-榉木铺板 | E7: 未知 | F7: 未知 | G7: 未知 | H7: 0 | I7: 0 | J7: 0.5 | K7: =IFERROR(H7,0) | L7: 0.4676 | M7: 0.2188 | N7: 0.2015 | O7: 0.1833 | P7: =IFERROR(IF(K7=0,"待填成本",ROUND(K7/(1-L7),0)),"" ) | Q7: =IFERROR(IF(K7=0,"待填成本",ROUND(K7/(1-M7),0)),"" ) | R7: =IFERROR(IF(K7=0,"待填成本",ROUND(K7/(1-N7),0)),"" ) | S7: =IFERROR(IF(K7=0,"待填成本",ROUND(K7/(1-O7),0)),"" ) | T7: =IFERROR(IF(K7=0,"",(P7-K7)/P7),"" ) | U7: =IFERROR(IF(K7=0,"",(Q7-K7)/Q7),"" ) | V7: =IFERROR(IF(K7=0,"",(R7-K7)/R7),"" ) | W7: =IFERROR(IF(K7=0,"",(S7-K7)/S7),"" )
A8: 2633007032099 | B8: 卧室-床 | C8: 畔色榉木无边床 |榉木金属腿床 | D8: 榉木无边床-1.2米-松木铺板 | E8: 未知 | F8: 未知 | G8: 未知 | H8: 0 | I8: 0 | J8: 0.5 | K8: =IFERROR(H8,0) | L8: 0.4676 | M8: 0.2188 | N8: 0.2015 | O8: 0.1833 | P8: =IFERROR(IF(K8=0,"待填成本",ROUND(K8/(1-L8),0)),"" ) | Q8: =IFERROR(IF(K8=0,"待填成本",ROUND(K8/(1-M8),0)),"" ) | R8: =IFERROR(IF(K8=0,"待填成本",ROUND(K8/(1-N8),0)),"" ) | S8: =IFERROR(IF(K8=0,"待填成本",ROUND(K8/(1-O8),0)),"" ) | T8: =IFERROR(IF(K8=0,"",(P8-K8)/P8),"" ) | U8: =IFERROR(IF(K8=0,"",(Q8-K8)/Q8),"" ) | V8: =IFERROR(IF(K8=0,"",(R8-K8)/R8),"" ) | W8: =IFERROR(IF(K8=0,"",(S8-K8)/S8),"" )
A9: 2633007032099 | B9: 卧室-床 | C9: 畔色榉木无边床 |榉木金属腿床 | D9: 榉木无边床-1.35米-松木铺板 | E9: 未知 | F9: 未知 | G9: 未知 | H9: 0 | I9: 0 | J9: 0.5 | K9: =IFERROR(H9,0) | L9: 0.4676 | M9: 0.2188 | N9: 0.2015 | O9: 0.1833 | P9: =IFERROR(IF(K9=0,"待填成本",ROUND(K9/(1-L9),0)),"" ) | Q9: =IFERROR(IF(K9=0,"待填成本",ROUND(K9/(1-M9),0)),"" ) | R9: =IFERROR(IF(K9=0,"待填成本",ROUND(K9/(1-N9),0)),"" ) | S9: =IFERROR(IF(K9=0,"待填成本",ROUND(K9/(1-O9),0)),"" ) | T9: =IFERROR(IF(K9=0,"",(P9-K9)/P9),"" ) | U9: =IFERROR(IF(K9=0,"",(Q9-K9)/Q9),"" ) | V9: =IFERROR(IF(K9=0,"",(R9-K9)/R9),"" ) | W9: =IFERROR(IF(K9=0,"",(S9-K9)/S9),"" )
A10: 2633007032099 | B10: 卧室-床 | C10: 畔色榉木无边床 |榉木金属腿床 | D10: 榉木无边床-1.5米-松木铺板 | E10: 未知 | F10: 未知 | G10: 未知 | H10: 0 | I10: 0 | J10: 0.5 | K10: =IFERROR(H10,0) | L10: 0.4676 | M10: 0.2188 | N10: 0.2015 | O10: 0.1833 | P10: =IFERROR(IF(K10=0,"待填成本",ROUND(K10/(1-L10),0)),"" ) | Q10: =IFERROR(IF(K10=0,"待填成本",ROUND(K10/(1-M10),0)),"" ) | R10: =IFERROR(IF(K10=0,"待填成本",ROUND(K10/(1-N10),0)),"" ) | S10: =IFERROR(IF(K10=0,"待填成本",ROUND(K10/(1-O10),0)),"" ) | T10: =IFERROR(IF(K10=0,"",(P10-K10)/P10),"" ) | U10: =IFERROR(IF(K10=0,"",(Q10-K10)/Q10),"" ) | V10: =IFERROR(IF(K10=0,"",(R10-K10)/R10),"" ) | W10: =IFERROR(IF(K10=0,"",(S10-K10)/S10),"" )
A11: 2633007032099 | B11: 卧室-床 | C11: 畔色榉木无边床 |榉木金属腿床 | D11: 榉木无边床-1.8米-松木铺板 | E11: 未知 | F11: 未知 | G11: 未知 | H11: 0 | I11: 0 | J11: 0.5 | K11: =IFERROR(H11,0) | L11: 0.4676 | M11: 0.2188 | N11: 0.2015 | O11: 0.1833 | P11: =IFERROR(IF(K11=0,"待填成本",ROUND(K11/(1-L11),0)),"" ) | Q11: =IFERROR(IF(K11=0,"待填成本",ROUND(K11/(1-M11),0)),"" ) | R11: =IFERROR(IF(K11=0,"待填成本",ROUND(K11/(1-N11),0)),"" ) | S11: =IFERROR(IF(K11=0,"待填成本",ROUND(K11/(1-O11),0)),"" ) | T11: =IFERROR(IF(K11=0,"",(P11-K11)/P11),"" ) | U11: =IFERROR(IF(K11=0,"",(Q11-K11)/Q11),"" ) | V11: =IFERROR(IF(K11=0,"",(R11-K11)/R11),"" ) | W11: =IFERROR(IF(K11=0,"",(S11-K11)/S11),"" )
A12: 2633008032299 | B12: 卧室-床 | C12: 畔色榉木柔光双人床 |榉木小灯床 | D12: 榉木柔光床-1.2米-榉木铺板 | E12: 未知 | F12: 未知 | G12: 未知 | H12: 0 | I12: 0 | J12: 0.5 | K12: =IFERROR(H12,0) | L12: 0.4676 | M12: 0.2188 | N12: 0.2015 | O12: 0.1833 | P12: =IFERROR(IF(K12=0,"待填成本",ROUND(K12/(1-L12),0)),"" ) | Q12: =IFERROR(IF(K12=0,"待填成本",ROUND(K12/(1-M12),0)),"" ) | R12: =IFERROR(IF(K12=0,"待填成本",ROUND(K12/(1-N12),0)),"" ) | S12: =IFERROR(IF(K12=0,"待填成本",ROUND(K12/(1-O12),0)),"" ) | T12: =IFERROR(IF(K12=0,"",(P12-K12)/P12),"" ) | U12: =IFERROR(IF(K12=0,"",(Q12-K12)/Q12),"" ) | V12: =IFERROR(IF(K12=0,"",(R12-K12)/R12),"" ) | W12: =IFERROR(IF(K12=0,"",(S12-K12)/S12),"" )
A13: 2633008032299 | B13: 卧室-床 | C13: 畔色榉木柔光双人床 |榉木小灯床 | D13: 榉木柔光床-1.35米-榉木铺板 | E13: 未知 | F13: 未知 | G13: 未知 | H13: 0 | I13: 0 | J13: 0.5 | K13: =IFERROR(H13,0) | L13: 0.4676 | M13: 0.2188 | N13: 0.2015 | O13: 0.1833 | P13: =IFERROR(IF(K13=0,"待填成本",ROUND(K13/(1-L13),0)),"" ) | Q13: =IFERROR(IF(K13=0,"待填成本",ROUND(K13/(1-M13),0)),"" ) | R13: =IFERROR(IF(K13=0,"待填成本",ROUND(K13/(1-N13),0)),"" ) | S13: =IFERROR(IF(K13=0,"待填成本",ROUND(K13/(1-O13),0)),"" ) | T13: =IFERROR(IF(K13=0,"",(P13-K13)/P13),"" ) | U13: =IFERROR(IF(K13=0,"",(Q13-K13)/Q13),"" ) | V13: =IFERROR(IF(K13=0,"",(R13-K13)/R13),"" ) | W13: =IFERROR(IF(K13=0,"",(S13-K13)/S13),"" )
A14: 2633008032299 | B14: 卧室-床 | C14: 畔色榉木柔光双人床 |榉木小灯床 | D14: 榉木柔光床-1.5米-榉木铺板 | E14: 未知 | F14: 未知 | G14: 未知 | H14: 0 | I14: 0 | J14: 0.5 | K14: =IFERROR(H14,0) | L14: 0.4676 | M14: 0.2188 | N14: 0.2015 | O14: 0.1833 | P14: =IFERROR(IF(K14=0,"待填成本",ROUND(K14/(1-L14),0)),"" ) | Q14: =IFERROR(IF(K14=0,"待填成本",ROUND(K14/(1-M14),0)),"" ) | R14: =IFERROR(IF(K14=0,"待填成本",ROUND(K14/(1-N14),0)),"" ) | S14: =IFERROR(IF(K14=0,"待填成本",ROUND(K14/(1-O14),0)),"" ) | T14: =IFERROR(IF(K14=0,"",(P14-K14)/P14),"" ) | U14: =IFERROR(IF(K14=0,"",(Q14-K14)/Q14),"" ) | V14: =IFERROR(IF(K14=0,"",(R14-K14)/R14),"" ) | W14: =IFERROR(IF(K14=0,"",(S14-K14)/S14),"" )
A15: 2633008032299 | B15: 卧室-床 | C15: 畔色榉木柔光双人床 |榉木小灯床 | D15: 榉木柔光床-1.8米-榉木铺板 | E15: 未知 | F15: 未知 | G15: 未知 | H15: 0 | I15: 0 | J15: 0.5 | K15: =IFERROR(H15,0) | L15: 0.4676 | M15: 0.2188 | N15: 0.2015 | O15: 0.1833 | P15: =IFERROR(IF(K15=0,"待填成本",ROUND(K15/(1-L15),0)),"" ) | Q15: =IFERROR(IF(K15=0,"待填成本",ROUND(K15/(1-M15),0)),"" ) | R15: =IFERROR(IF(K15=0,"待填成本",ROUND(K15/(1-N15),0)),"" ) | S15: =IFERROR(IF(K15=0,"待填成本",ROUND(K15/(1-O15),0)),"" ) | T15: =IFERROR(IF(K15=0,"",(P15-K15)/P15),"" ) | U15: =IFERROR(IF(K15=0,"",(Q15-K15)/Q15),"" ) | V15: =IFERROR(IF(K15=0,"",(R15-K15)/R15),"" ) | W15: =IFERROR(IF(K15=0,"",(S15-K15)/S15),"" )
... A73: 2638004022599 | B73: 卧室-床头柜 | C73: 畔色榉木床头柜 |榉木铁板床头柜 | D73: 榉木床头柜-标准 | E73: 未知 | F73: 未知 | G73: 未知 | H73: 0 | I73: 0 | J73: 0.55 | K73: =IFERROR(H73,0) | L73: 0.4785 | M73: 0.2533 | N73: 0.2533 | O73: 0.2533 | P73: =IFERROR(IF(K73=0,"待填成本",ROUND(K73/(1-L73),0)),"" ) | Q73: =IFERROR(IF(K73=0,"待填成本",ROUND(K73/(1-M73),0)),"" ) | R73: =IFERROR(IF(K73=0,"待填成本",ROUND(K73/(1-N73),0)),"" ) | S73: =IFERROR(IF(K73=0,"待填成本",ROUND(K73/(1-O73),0)),"" ) | T73: =IFERROR(IF(K73=0,"",(P73-K73)/P73),"" ) | U73: =IFERROR(IF(K73=0,"",(Q73-K73)/Q73),"" ) | V73: =IFERROR(IF(K73=0,"",(R73-K73)/R73),"" ) | W73: =IFERROR(IF(K73=0,"",(S73-K73)/S73),"" )
A74: 2638005030199 | B74: 卧室-床头柜 | C74: 畔色樱桃木轻盈边柜 |樱桃木玻璃床头柜 |黑色玻璃床头柜 |樱桃木玻璃边柜 | D74: 轻盈边柜-榉木黑-木底座 | E74: 未知 | F74: 未知 | G74: 未知 | H74: 0 | I74: 0 | J74: 0.55 | K74: =IFERROR(H74,0) | L74: 0.4785 | M74: 0.2533 | N74: 0.2533 | O74: 0.2533 | P74: =IFERROR(IF(K74=0,"待填成本",ROUND(K74/(1-L74),0)),"" ) | Q74: =IFERROR(IF(K74=0,"待填成本",ROUND(K74/(1-M74),0)),"" ) | R74: =IFERROR(IF(K74=0,"待填成本",ROUND(K74/(1-N74),0)),"" ) | S74: =IFERROR(IF(K74=0,"待填成本",ROUND(K74/(1-O74),0)),"" ) | T74: =IFERROR(IF(K74=0,"",(P74-K74)/P74),"" ) | U74: =IFERROR(IF(K74=0,"",(Q74-K74)/Q74),"" ) | V74: =IFERROR(IF(K74=0,"",(R74-K74)/R74),"" ) | W74: =IFERROR(IF(K74=0,"",(S74-K74)/S74),"" ) | X74: 20 | Y74: 20
A75: 2638005030199 | B75: 卧室-床头柜 | C75: 畔色樱桃木轻盈边柜 |樱桃木玻璃床头柜 |黑色玻璃床头柜 |樱桃木玻璃边柜 | D75: 轻盈边柜-樱桃木-木底座 | E75: 未知 | F75: 未知 | G75: 未知 | H75: 0 | I75: 0 | J75: 0.55 | K75: =IFERROR(H75,0) | L75: 0.4785 | M75: 0.2533 | N75: 0.2533 | O75: 0.2533 | P75: =IFERROR(IF(K75=0,"待填成本",ROUND(K75/(1-L75),0)),"" ) | Q75: =IFERROR(IF(K75=0,"待填成本",ROUND(K75/(1-M75),0)),"" ) | R75: =IFERROR(IF(K75=0,"待填成本",ROUND(K75/(1-N75),0)),"" ) | S75: =IFERROR(IF(K75=0,"待填成本",ROUND(K75/(1-O75),0)),"" ) | T75: =IFERROR(IF(K75=0,"",(P75-K75)/P75),"" ) | U75: =IFERROR(IF(K75=0,"",(Q75-K75)/Q75),"" ) | V75: =IFERROR(IF(K75=0,"",(R75-K75)/R75),"" ) | W75: =IFERROR(IF(K75=0,"",(S75-K75)/S75),"" ) | X75: 20 | Y75: 20
A76: 2638005030199 | B76: 卧室-床头柜 | C76: 畔色樱桃木轻盈边柜 |樱桃木玻璃床头柜 |黑色玻璃床头柜 |樱桃木玻璃边柜 | D76: 轻盈边柜-黑胡桃木-木底座 | E76: 未知 | F76: 未知 | G76: 未知 | H76: 0 | I76: 0 | J76: 0.55 | K76: =IFERROR(H76,0) | L76: 0.4785 | M76: 0.2533 | N76: 0.2533 | O76: 0.2533 | P76: =IFERROR(IF(K76=0,"待填成本",ROUND(K76/(1-L76),0)),"" ) | Q76: =IFERROR(IF(K76=0,"待填成本",ROUND(K76/(1-M76),0)),"" ) | R76: =IFERROR(IF(K76=0,"待填成本",ROUND(K76/(1-N76),0)),"" ) | S76: =IFERROR(IF(K76=0,"待填成本",ROUND(K76/(1-O76),0)),"" ) | T76: =IFERROR(IF(K76=0,"",(P76-K76)/P76),"" ) | U76: =IFERROR(IF(K76=0,"",(Q76-K76)/Q76),"" ) | V76: =IFERROR(IF(K76=0,"",(R76-K76)/R76),"" ) | W76: =IFERROR(IF(K76=0,"",(S76-K76)/S76),"" ) | X76: 20 | Y76: 20
A77: 2638005030199 | B77: 卧室-床头柜 | C77: 畔色樱桃木轻盈边柜 |樱桃木玻璃床头柜 |黑色玻璃床头柜 |樱桃木玻璃边柜 | D77: 轻盈边柜-榉木黑-玻璃底座 | E77: 未知 | F77: 未知 | G77: 未知 | H77: 0 | I77: 0 | J77: 0.55 | K77: =IFERROR(H77,0) | L77: 0.4785 | M77: 0.2533 | N77: 0.2533 | O77: 0.2533 | P77: =IFERROR(IF(K77=0,"待填成本",ROUND(K77/(1-L77),0)),"" ) | Q77: =IFERROR(IF(K77=0,"待填成本",ROUND(K77/(1-M77),0)),"" ) | R77: =IFERROR(IF(K77=0,"待填成本",ROUND(K77/(1-N77),0)),"" ) | S77: =IFERROR(IF(K77=0,"待填成本",ROUND(K77/(1-O77),0)),"" ) | T77: =IFERROR(IF(K77=0,"",(P77-K77)/P77),"" ) | U77: =IFERROR(IF(K77=0,"",(Q77-K77)/Q77),"" ) | V77: =IFERROR(IF(K77=0,"",(R77-K77)/R77),"" ) | W77: =IFERROR(IF(K77=0,"",(S77-K77)/S77),"" ) | X77: 20 | Y77: 20
A78: 2638005030199 | B78: 卧室-床头柜 | C78: 畔色樱桃木轻盈边柜 |樱桃木玻璃床头柜 |黑色玻璃床头柜 |樱桃木玻璃边柜 | D78: 轻盈边柜-樱桃木-玻璃底座 | E78: 未知 | F78: 未知 | G78: 未知 | H78: 0 | I78: 0 | J78: 0.55 | K78: =IFERROR(H78,0) | L78: 0.4785 | M78: 0.2533 | N78: 0.2533 | O78: 0.2533 | P78: =IFERROR(IF(K78=0,"待填成本",ROUND(K78/(1-L78),0)),"" ) | Q78: =IFERROR(IF(K78=0,"待填成本",ROUND(K78/(1-M78),0)),"" ) | R78: =IFERROR(IF(K78=0,"待填成本",ROUND(K78/(1-N78),0)),"" ) | S78: =IFERROR(IF(K78=0,"待填成本",ROUND(K78/(1-O78),0)),"" ) | T78: =IFERROR(IF(K78=0,"",(P78-K78)/P78),"" ) | U78: =IFERROR(IF(K78=0,"",(Q78-K78)/Q78),"" ) | V78: =IFERROR(IF(K78=0,"",(R78-K78)/R78),"" ) | W78: =IFERROR(IF(K78=0,"",(S78-K78)/S78),"" ) | X78: 20 | Y78: 20
A79: 2638005030199 | B79: 卧室-床头柜 | C79: 畔色樱桃木轻盈边柜 |樱桃木玻璃床头柜 |黑色玻璃床头柜 |樱桃木玻璃边柜 | D79: 轻盈边柜-黑胡桃木-玻璃底座 | E79: 未知 | F79: 未知 | G79: 未知 | H79: 0 | I79: 0 | J79: 0.55 | K79: =IFERROR(H79,0) | L79: 0.4785 | M79: 0.2533 | N79: 0.2533 | O79: 0.2533 | P79: =IFERROR(IF(K79=0,"待填成本",ROUND(K79/(1-L79),0)),"" ) | Q79: =IFERROR(IF(K79=0,"待填成本",ROUND(K79/(1-M79),0)),"" ) | R79: =IFERROR(IF(K79=0,"待填成本",ROUND(K79/(1-N79),0)),"" ) | S79: =IFERROR(IF(K79=0,"待填成本",ROUND(K79/(1-O79),0)),"" ) | T79: =IFERROR(IF(K79=0,"",(P79-K79)/P79),"" ) | U79: =IFERROR(IF(K79=0,"",(Q79-K79)/Q79),"" ) | V79: =IFERROR(IF(K79=0,"",(R79-K79)/R79),"" ) | W79: =IFERROR(IF(K79=0,"",(S79-K79)/S79),"" ) | X79: 20 | Y79: 20
A80: 2638006032099 | B80: 卧室-床头柜 | C80: 畔色黑胡桃木床头柜 |黑胡桃木岩板床头柜 | D80: 黑胡桃木床头柜-岩板台面 | E80: 未知 | F80: 未知 | G80: 未知 | H80: 0 | I80: 0 | J80: 0.55 | K80: =IFERROR(H80,0) | L80: 0.4785 | M80: 0.2533 | N80: 0.2533 | O80: 0.2533 | P80: =IFERROR(IF(K80=0,"待填成本",ROUND(K80/(1-L80),0)),"" ) | Q80: =IFERROR(IF(K80=0,"待填成本",ROUND(K80/(1-M80),0)),"" ) | R80: =IFERROR(IF(K80=0,"待填成本",ROUND(K80/(1-N80),0)),"" ) | S80: =IFERROR(IF(K80=0,"待填成本",ROUND(K80/(1-O80),0)),"" ) | T80: =IFERROR(IF(K80=0,"",(P80-K80)/P80),"" ) | U80: =IFERROR(IF(K80=0,"",(Q80-K80)/Q80),"" ) | V80: =IFERROR(IF(K80=0,"",(R80-K80)/R80),"" ) | W80: =IFERROR(IF(K80=0,"",(S80-K80)/S80),"" ) | X80: 25 | Y80: 25
A81: 2638006032099 | B81: 卧室-床头柜 | C81: 畔色黑胡桃木床头柜 |黑胡桃木岩板床头柜 | D81: 黑胡桃木床头柜-木台面 | E81: 未知 | F81: 未知 | G81: 未知 | H81: 0 | I81: 0 | J81: 0.55 | K81: =IFERROR(H81,0) | L81: 0.4785 | M81: 0.2533 | N81: 0.2533 | O81: 0.2533 | P81: =IFERROR(IF(K81=0,"待填成本",ROUND(K81/(1-L81),0)),"" ) | Q81: =IFERROR(IF(K81=0,"待填成本",ROUND(K81/(1-M81),0)),"" ) | R81: =IFERROR(IF(K81=0,"待填成本",ROUND(K81/(1-N81),0)),"" ) | S81: =IFERROR(IF(K81=0,"待填成本",ROUND(K81/(1-O81),0)),"" ) | T81: =IFERROR(IF(K81=0,"",(P81-K81)/P81),"" ) | U81: =IFERROR(IF(K81=0,"",(Q81-K81)/Q81),"" ) | V81: =IFERROR(IF(K81=0,"",(R81-K81)/R81),"" ) | W81: =IFERROR(IF(K81=0,"",(S81-K81)/S81),"" ) | X81: 20 | Y81: 20
A82: 2525009040199 | B82: 餐厅-柜 | C82: 樱桃木基础餐边柜 |樱桃木AA柱餐边柜 | D82: 基础柜-下柜-2.1米 | E82: 北美进口FAS级樱桃木 | F82: 抽屉围板：实木多层板 台面：12mm岩板 背板：实木多层板（AA柱）/亚克力洞洞板 内部赠送层板：实木多层板 电力轨道：xpower 内嵌电力轨道 顶柜玻璃：灰玻 | G82: 整体长度：2100mm/1800mm/1500mm 整体深度：480mm 整体高度：1980mm 顶柜长度：2100mm/1800mm/1500mm 顶柜深度：300mm 顶柜高度：490mm 立体收纳长度：2100mm/1800mm/1500mm 立体收纳深度：300mm 立体收纳高度：610mm 下柜长度：2100mm/1800mm/1500mm 下柜深度：480mm 下柜高度：880mm | H82: 4061 | I82: 3761 | J82: 0.48 | K82: =IFERROR(H82,0) | L82: 0.4669 | M82: 0.2109 | N82: 0.2009 | O82: 0.1801 | P82: =IFERROR(IF(K82=0,"待填成本",ROUND(K82/(1-L82),0)),"" ) | Q82: =IFERROR(IF(K82=0,"待填成本",ROUND(K82/(1-M82),0)),"" ) | R82: =IFERROR(IF(K82=0,"待填成本",ROUND(K82/(1-N82),0)),"" ) | S82: =IFERROR(IF(K82=0,"待填成本",ROUND(K82/(1-O82),0)),"" ) | T82: =IFERROR(IF(K82=0,"",(P82-K82)/P82),"" ) | U82: =IFERROR(IF(K82=0,"",(Q82-K82)/Q82),"" ) | V82: =IFERROR(IF(K82=0,"",(R82-K82)/R82),"" ) | W82: =IFERROR(IF(K82=0,"",(S82-K82)/S82),"" ) | AC82: 21.2175 | AD82: 300 | AE82: 150
A83: 2525009040199 | B83: 餐厅-柜 | C83: 樱桃木基础餐边柜 |樱桃木AA柱餐边柜 | D83: 基础柜-下柜-2.0米 | E83: 北美进口FAS级樱桃木 | F83: 抽屉围板：实木多层板 台面：12mm岩板 背板：实木多层板（AA柱）/亚克力洞洞板 内部赠送层板：实木多层板 电力轨道：xpower 内嵌电力轨道 顶柜玻璃：灰玻 | G83: 整体长度：2100mm/1800mm/1500mm 整体深度：480mm 整体高度：1980mm 顶柜长度：2100mm/1800mm/1500mm 顶柜深度：300mm 顶柜高度：490mm 立体收纳长度：2100mm/1800mm/1500mm 立体收纳深度：300mm 立体收纳高度：610mm 下柜长度：2100mm/1800mm/1500mm 下柜深度：480mm 下柜高度：880mm | H83: 3964.3333 | I83: 3677.6667 | J83: 0.48 | K83: =IFERROR(H83,0) | L83: 0.4669 | M83: 0.2108 | N83: 0.201 | O83: 0.1803 | P83: =IFERROR(IF(K83=0,"待填成本",ROUND(K83/(1-L83),0)),"" ) | Q83: =IFERROR(IF(K83=0,"待填成本",ROUND(K83/(1-M83),0)),"" ) | R83: =IFERROR(IF(K83=0,"待填成本",ROUND(K83/(1-N83),0)),"" ) | S83: =IFERROR(IF(K83=0,"待填成本",ROUND(K83/(1-O83),0)),"" ) | T83: =IFERROR(IF(K83=0,"",(P83-K83)/P83),"" ) | U83: =IFERROR(IF(K83=0,"",(Q83-K83)/Q83),"" ) | V83: =IFERROR(IF(K83=0,"",(R83-K83)/R83),"" ) | W83: =IFERROR(IF(K83=0,"",(S83-K83)/S83),"" ) | AC83: 20.93 | AD83: 300 | AE83: 150
A84: 2525009040199 | B84: 餐厅-柜 | C84: 樱桃木基础餐边柜 |樱桃木AA柱餐边柜 | D84: 基础柜-下柜-1.9米 | E84: 北美进口FAS级樱桃木 | F84: 抽屉围板：实木多层板 台面：12mm岩板 背板：实木多层板（AA柱）/亚克力洞洞板 内部赠送层板：实木多层板 电力轨道：xpower 内嵌电力轨道 顶柜玻璃：灰玻 | G84: 整体长度：2100mm/1800mm/1500mm 整体深度：480mm 整体高度：1980mm 顶柜长度：2100mm/1800mm/1500mm 顶柜深度：300mm 顶柜高度：490mm 立体收纳长度：2100mm/1800mm/1500mm 立体收纳深度：300mm 立体收纳高度：610mm 下柜长度：2100mm/1800mm/1500mm 下柜深度：480mm 下柜高度：880mm | H84: 3867.6667 | I84: 3594.3333 | J84: 0.48 | K84: =IFERROR(H84,0) | L84: 0.467 | M84: 0.2107 | N84: 0.2012 | O84: 0.1804 | P84: =IFERROR(IF(K84=0,"待填成本",ROUND(K84/(1-L84),0)),"" ) | Q84: =IFERROR(IF(K84=0,"待填成本",ROUND(K84/(1-M84),0)),"" ) | R84: =IFERROR(IF(K84=0,"待填成本",ROUND(K84/(1-N84),0)),"" ) | S84: =IFERROR(IF(K84=0,"待填成本",ROUND(K84/(1-O84),0)),"" ) | T84: =IFERROR(IF(K84=0,"",(P84-K84)/P84),"" ) | U84: =IFERROR(IF(K84=0,"",(Q84-K84)/Q84),"" ) | V84: =IFERROR(IF(K84=0,"",(R84-K84)/R84),"" ) | W84: =IFERROR(IF(K84=0,"",(S84-K84)/S84),"" ) | AC84: 20.6425 | AD84: 300 | AE84: 150
A85: 2525009040199 | B85: 餐厅-柜 | C85: 樱桃木基础餐边柜 |樱桃木AA柱餐边柜 | D85: 基础柜-下柜-1.8米 | E85: 北美进口FAS级樱桃木 | F85: 抽屉围板：实木多层板 台面：12mm岩板 背板：实木多层板（AA柱）/亚克力洞洞板 内部赠送层板：实木多层板 电力轨道：xpower 内嵌电力轨道 顶柜玻璃：灰玻 | G85: 整体长度：2100mm/1800mm/1500mm 整体深度：480mm 整体高度：1980mm 顶柜长度：2100mm/1800mm/1500mm 顶柜深度：300mm 顶柜高度：490mm 立体收纳长度：2100mm/1800mm/1500mm 立体收纳深度：300mm 立体收纳高度：610mm 下柜长度：2100mm/1800mm/1500mm 下柜深度：480mm 下柜高度：880mm | H85: 3771 | I85: 3511 | J85: 0.48 | K85: =IFERROR(H85,0) | L85: 0.4671 | M85: 0.2106 | N85: 0.2013 | O85: 0.1806 | P85: =IFERROR(IF(K85=0,"待填成本",ROUND(K85/(1-L85),0)),"" ) | Q85: =IFERROR(IF(K85=0,"待填成本",ROUND(K85/(1-M85),0)),"" ) | R85: =IFERROR(IF(K85=0,"待填成本",ROUND(K85/(1-N85),0)),"" ) | S85: =IFERROR(IF(K85=0,"待填成本",ROUND(K85/(1-O85),0)),"" ) | T85: =IFERROR(IF(K85=0,"",(P85-K85)/P85),"" ) | U85: =IFERROR(IF(K85=0,"",(Q85-K85)/Q85),"" ) | V85: =IFERROR(IF(K85=0,"",(R85-K85)/R85),"" ) | W85: =IFERROR(IF(K85=0,"",(S85-K85)/S85),"" ) | AC85: 20.355 | AD85: 300 | AE85: 150
A86: 2525009040199 | B86: 餐厅-柜 | C86: 樱桃木基础餐边柜 |樱桃木AA柱餐边柜 | D86: 基础柜-下柜-1.7米 | E86: 北美进口FAS级樱桃木 | F86: 抽屉围板：实木多层板 台面：12mm岩板 背板：实木多层板（AA柱）/亚克力洞洞板 内部赠送层板：实木多层板 电力轨道：xpower 内嵌电力轨道 顶柜玻璃：灰玻 | G86: 整体长度：2100mm/1800mm/1500mm 整体深度：480mm 整体高度：1980mm 顶柜长度：2100mm/1800mm/1500mm 顶柜深度：300mm 顶柜高度：490mm 立体收纳长度：2100mm/1800mm/1500mm 立体收纳深度：300mm 立体收纳高度：610mm 下柜长度：2100mm/1800mm/1500mm 下柜深度：480mm 下柜高度：880mm | H86: 3681 | I86: 3427.6667 | J86: 0.48 | K86: =IFERROR(H86,0) | L86: 0.467 | M86: 0.2106 | N86: 0.2012 | O86: 0.1805 | P86: =IFERROR(IF(K86=0,"待填成本",ROUND(K86/(1-L86),0)),"" ) | Q86: =IFERROR(IF(K86=0,"待填成本",ROUND(K86/(1-M86),0)),"" ) | R86: =IFERROR(IF(K86=0,"待填成本",ROUND(K86/(1-N86),0)),"" ) | S86: =IFERROR(IF(K86=0,"待填成本",ROUND(K86/(1-O86),0)),"" ) | T86: =IFERROR(IF(K86=0,"",(P86-K86)/P86),"" ) | U86: =IFERROR(IF(K86=0,"",(Q86-K86)/Q86),"" ) | V86: =IFERROR(IF(K86=0,"",(R86-K86)/R86),"" ) | W86: =IFERROR(IF(K86=0,"",(S86-K86)/S86),"" ) | AC86: 20.0675 | AD86: 300 | AE86: 150
A87: 2525009040199 | B87: 餐厅-柜 | C87: 樱桃木基础餐边柜 |樱桃木AA柱餐边柜 | D87: 基础柜-下柜-1.6米 | E87: 北美进口FAS级樱桃木 | F87: 抽屉围板：实木多层板 台面：12mm岩板 背板：实木多层板（AA柱）/亚克力洞洞板 内部赠送层板：实木多层板 电力轨道：xpower 内嵌电力轨道 顶柜玻璃：灰玻 | G87: 整体长度：2100mm/1800mm/1500mm 整体深度：480mm 整体高度：1980mm 顶柜长度：2100mm/1800mm/1500mm 顶柜深度：300mm 顶柜高度：490mm 立体收纳长度：2100mm/1800mm/1500mm 立体收纳深度：300mm 立体收纳高度：610mm 下柜长度：2100mm/1800mm/1500mm 下柜深度：480mm 下柜高度：880mm | H87: 3591 | I87: 3344.3333 | J87: 0.48 | K87: =IFERROR(H87,0) | L87: 0.4669 | M87: 0.2107 | N87: 0.201 | O87: 0.1804 | P87: =IFERROR(IF(K87=0,"待填成本",ROUND(K87/(1-L87),0)),"" ) | Q87: =IFERROR(IF(K87=0,"待填成本",ROUND(K87/(1-M87),0)),"" ) | R87: =IFERROR(IF(K87=0,"待填成本",ROUND(K87/(1-N87),0)),"" ) | S87: =IFERROR(IF(K87=0,"待填成本",ROUND(K87/(1-O87),0)),"" ) | T87: =IFERROR(IF(K87=0,"",(P87-K87)/P87),"" ) | U87: =IFERROR(IF(K87=0,"",(Q87-K87)/Q87),"" ) | V87: =IFERROR(IF(K87=0,"",(R87-K87)/R87),"" ) | W87: =IFERROR(IF(K87=0,"",(S87-K87)/S87),"" ) | AC87: 19.78 | AD87: 300 | AE87: 150
A88: 2525009040199 | B88: 餐厅-柜 | C88: 樱桃木基础餐边柜 |樱桃木AA柱餐边柜 | D88: 基础柜-下柜-1.5米 | E88: 北美进口FAS级樱桃木 | F88: 抽屉围板：实木多层板 台面：12mm岩板 背板：实木多层板（AA柱）/亚克力洞洞板 内部赠送层板：实木多层板 电力轨道：xpower 内嵌电力轨道 顶柜玻璃：灰玻 | G88: 整体长度：2100mm/1800mm/1500mm 整体深度：480mm 整体高度：1980mm 顶柜长度：2100mm/1800mm/1500mm 顶柜深度：300mm 顶柜高度：490mm 立体收纳长度：2100mm/1800mm/1500mm 立体收纳深度：300mm 立体收纳高度：610mm 下柜长度：2100mm/1800mm/1500mm 下柜深度：480mm 下柜高度：880mm | H88: 3501 | I88: 3261 | J88: 0.48 | K88: =IFERROR(H88,0) | L88: 0.4668 | M88: 0.2108 | N88: 0.2009 | O88: 0.1803 | P88: =IFERROR(IF(K88=0,"待填成本",ROUND(K88/(1-L88),0)),"" ) | Q88: =IFERROR(IF(K88=0,"待填成本",ROUND(K88/(1-M88),0)),"" ) | R88: =IFERROR(IF(K88=0,"待填成本",ROUND(K88/(1-N88),0)),"" ) | S88: =IFERROR(IF(K88=0,"待填成本",ROUND(K88/(1-O88),0)),"" ) | T88: =IFERROR(IF(K88=0,"",(P88-K88)/P88),"" ) | U88: =IFERROR(IF(K88=0,"",(Q88-K88)/Q88),"" ) | V88: =IFERROR(IF(K88=0,"",(R88-K88)/R88),"" ) | W88: =IFERROR(IF(K88=0,"",(S88-K88)/S88),"" ) | AC88: 19.4925 | AD88: 300 | AE88: 150
A89: 2525009040199 | B89: 餐厅-柜 | C89: 樱桃木基础餐边柜 |樱桃木AA柱餐边柜 | D89: 基础柜-下柜-1.4米 | E89: 北美进口FAS级樱桃木 | F89: 抽屉围板：实木多层板 台面：12mm岩板 背板：实木多层板（AA柱）/亚克力洞洞板 内部赠送层板：实木多层板 电力轨道：xpower 内嵌电力轨道 顶柜玻璃：灰玻 | G89: 整体长度：2100mm/1800mm/1500mm 整体深度：480mm 整体高度：1980mm 顶柜长度：2100mm/1800mm/1500mm 顶柜深度：300mm 顶柜高度：490mm 立体收纳长度：2100mm/1800mm/1500mm 立体收纳深度：300mm 立体收纳高度：610mm 下柜长度：2100mm/1800mm/1500mm 下柜深度：480mm 下柜高度：880mm | H89: 3404.3333 | I89: 3177.6667 | J89: 0.48 | K89: =IFERROR(H89,0) | L89: 0.4668 | M89: 0.2106 | N89: 0.201 | O89: 0.1805 | P89: =IFERROR(IF(K89=0,"待填成本",ROUND(K89/(1-L89),0)),"" ) | Q89: =IFERROR(IF(K89=0,"待填成本",ROUND(K89/(1-M89),0)),"" ) | R89: =IFERROR(IF(K89=0,"待填成本",ROUND(K89/(1-N89),0)),"" ) | S89: =IFERROR(IF(K89=0,"待填成本",ROUND(K89/(1-O89),0)),"" ) | T89: =IFERROR(IF(K89=0,"",(P89-K89)/P89),"" ) | U89: =IFERROR(IF(K89=0,"",(Q89-K89)/Q89),"" ) | V89: =IFERROR(IF(K89=0,"",(R89-K89)/R89),"" ) | W89: =IFERROR(IF(K89=0,"",(S89-K89)/S89),"" ) | AC89: 19.205 | AD89: 300 | AE89: 150
A90: 2525009040199 | B90: 餐厅-柜 | C90: 樱桃木基础餐边柜 |樱桃木AA柱餐边柜 | D90: 基础柜-下柜-1.3米 | E90: 北美进口FAS级樱桃木 | F90: 抽屉围板：实木多层板 台面：12mm岩板 背板：实木多层板（AA柱）/亚克力洞洞板 内部赠送层板：实木多层板 电力轨道：xpower 内嵌电力轨道 顶柜玻璃：灰玻 | G90: 整体长度：2100mm/1800mm/1500mm 整体深度：480mm 整体高度：1980mm 顶柜长度：2100mm/1800mm/1500mm 顶柜深度：300mm 顶柜高度：490mm 立体收纳长度：2100mm/1800mm/1500mm 立体收纳深度：300mm 立体收纳高度：610mm 下柜长度：2100mm/1800mm/1500mm 下柜深度：480mm 下柜高度：880mm | H90: 3307.6667 | I90: 3094.3333 | J90: 0.48 | K90: =IFERROR(H90,0) | L90: 0.4669 | M90: 0.2105 | N90: 0.2011 | O90: 0.1807 | P90: =IFERROR(IF(K90=0,"待填成本",ROUND(K90/(1-L90),0)),"" ) | Q90: =IFERROR(IF(K90=0,"待填成本",ROUND(K90/(1-M90),0)),"" ) | R90: =IFERROR(IF(K90=0,"待填成本",ROUND(K90/(1-N90),0)),"" ) | S90: =IFERROR(IF(K90=0,"待填成本",ROUND(K90/(1-O90),0)),"" ) | T90: =IFERROR(IF(K90=0,"",(P90-K90)/P90),"" ) | U90: =IFERROR(IF(K90=0,"",(Q90-K90)/Q90),"" ) | V90: =IFERROR(IF(K90=0,"",(R90-K90)/R90),"" ) | W90: =IFERROR(IF(K90=0,"",(S90-K90)/S90),"" ) | AC90: 18.9175 | AD90: 300 | AE90: 150
A91: 2525009040199 | B91: 餐厅-柜 | C91: 樱桃木基础餐边柜 |樱桃木AA柱餐边柜 | D91: 基础柜-下柜-1.2米 | E91: 北美进口FAS级樱桃木 | F91: 抽屉围板：实木多层板 台面：12mm岩板 背板：实木多层板（AA柱）/亚克力洞洞板 内部赠送层板：实木多层板 电力轨道：xpower 内嵌电力轨道 顶柜玻璃：灰玻 | G91: 整体长度：2100mm/1800mm/1500mm 整体深度：480mm 整体高度：1980mm 顶柜长度：2100mm/1800mm/1500mm 顶柜深度：300mm 顶柜高度：490mm 立体收纳长度：2100mm/1800mm/1500mm 立体收纳深度：300mm 立体收纳高度：610mm 下柜长度：2100mm/1800mm/1500mm 下柜深度：480mm 下柜高度：880mm | H91: 3211 | I91: 3011 | J91: 0.48 | K91: =IFERROR(H91,0) | L91: 0.467 | M91: 0.2103 | N91: 0.2013 | O91: 0.1809 | P91: =IFERROR(IF(K91=0,"待填成本",ROUND(K91/(1-L91),0)),"" ) | Q91: =IFERROR(IF(K91=0,"待填成本",ROUND(K91/(1-M91),0)),"" ) | R91: =IFERROR(IF(K91=0,"待填成本",ROUND(K91/(1-N91),0)),"" ) | S91: =IFERROR(IF(K91=0,"待填成本",ROUND(K91/(1-O91),0)),"" ) | T91: =IFERROR(IF(K91=0,"",(P91-K91)/P91),"" ) | U91: =IFERROR(IF(K91=0,"",(Q91-K91)/Q91),"" ) | V91: =IFERROR(IF(K91=0,"",(R91-K91)/R91),"" ) | W91: =IFERROR(IF(K91=0,"",(S91-K91)/S91),"" ) | AC91: 18.63 | AD91: 300 | AE91: 150
A92: 2525009040199 | B92: 餐厅-柜 | C92: 樱桃木基础餐边柜 |樱桃木AA柱餐边柜 | D92: 基础柜-下柜-1.1米 | E92: 北美进口FAS级樱桃木 | F92: 抽屉围板：实木多层板 台面：12mm岩板 背板：实木多层板（AA柱）/亚克力洞洞板 内部赠送层板：实木多层板 电力轨道：xpower 内嵌电力轨道 顶柜玻璃：灰玻 | G92: 整体长度：2100mm/1800mm/1500mm 整体深度：480mm 整体高度：1980mm 顶柜长度：2100mm/1800mm/1500mm 顶柜深度：300mm 顶柜高度：490mm 立体收纳长度：2100mm/1800mm/1500mm 立体收纳深度：300mm 立体收纳高度：610mm 下柜长度：2100mm/1800mm/1500mm 下柜深度：480mm 下柜高度：880mm | H92: 3114.3333 | I92: 2927.6667 | J92: 0.48 | K92: =IFERROR(H92,0) | L92: 0.4671 | M92: 0.2102 | N92: 0.2014 | O92: 0.1811 | P92: =IFERROR(IF(K92=0,"待填成本",ROUND(K92/(1-L92),0)),"" ) | Q92: =IFERROR(IF(K92=0,"待填成本",ROUND(K92/(1-M92),0)),"" ) | R92: =IFERROR(IF(K92=0,"待填成本",ROUND(K92/(1-N92),0)),"" ) | S92: =IFERROR(IF(K92=0,"待填成本",ROUND(K92/(1-O92),0)),"" ) | T92: =IFERROR(IF(K92=0,"",(P92-K92)/P92),"" ) | U92: =IFERROR(IF(K92=0,"",(Q92-K92)/Q92),"" ) | V92: =IFERROR(IF(K92=0,"",(R92-K92)/R92),"" ) | W92: =IFERROR(IF(K92=0,"",(S92-K92)/S92),"" ) | AC92: 18.3425 | AD92: 300 | AE92: 150
A93: 2525009040199 | B93: 餐厅-柜 | C93: 樱桃木基础餐边柜 |樱桃木AA柱餐边柜 | D93: 基础柜-下柜-1.0米 | E93: 北美进口FAS级樱桃木 | F93: 抽屉围板：实木多层板 台面：12mm岩板 背板：实木多层板（AA柱）/亚克力洞洞板 内部赠送层板：实木多层板 电力轨道：xpower 内嵌电力轨道 顶柜玻璃：灰玻 | G93: 整体长度：2100mm/1800mm/1500mm 整体深度：480mm 整体高度：1980mm 顶柜长度：2100mm/1800mm/1500mm 顶柜深度：300mm 顶柜高度：490mm 立体收纳长度：2100mm/1800mm/1500mm 立体收纳深度：300mm 立体收纳高度：610mm 下柜长度：2100mm/1800mm/1500mm 下柜深度：480mm 下柜高度：880mm | H93: 3017.6667 | I93: 2844.3333 | J93: 0.48 | K93: =IFERROR(H93,0) | L93: 0.4672 | M93: 0.21 | N93: 0.2016 | O93: 0.1813 | P93: =IFERROR(IF(K93=0,"待填成本",ROUND(K93/(1-L93),0)),"" ) | Q93: =IFERROR(IF(K93=0,"待填成本",ROUND(K93/(1-M93),0)),"" ) | R93: =IFERROR(IF(K93=0,"待填成本",ROUND(K93/(1-N93),0)),"" ) | S93: =IFERROR(IF(K93=0,"待填成本",ROUND(K93/(1-O93),0)),"" ) | T93: =IFERROR(IF(K93=0,"",(P93-K93)/P93),"" ) | U93: =IFERROR(IF(K93=0,"",(Q93-K93)/Q93),"" ) | V93: =IFERROR(IF(K93=0,"",(R93-K93)/R93),"" ) | W93: =IFERROR(IF(K93=0,"",(S93-K93)/S93),"" ) | AC93: 18.055 | AD93: 300 | AE93: 150
A94: 2525009040199 | B94: 餐厅-柜 | C94: 樱桃木基础餐边柜 |樱桃木AA柱餐边柜 | D94: 基础柜-整柜AA柱背板-2.1米 | E94: 北美进口FAS级樱桃木 | F94: 抽屉围板：实木多层板 台面：12mm岩板 背板：实木多层板（AA柱）/亚克力洞洞板 内部赠送层板：实木多层板 电力轨道：xpower 内嵌电力轨道 顶柜玻璃：灰玻 | G94: 整体长度：2100mm/1800mm/1500mm 整体深度：480mm 整体高度：1980mm 顶柜长度：2100mm/1800mm/1500mm 顶柜深度：300mm 顶柜高度：490mm 立体收纳长度：2100mm/1800mm/1500mm 立体收纳深度：300mm 立体收纳高度：610mm 下柜长度：2100mm/1800mm/1500mm 下柜深度：480mm 下柜高度：880mm | H94: 6422.04 | I94: 4700 | J94: 0.48 | K94: =IFERROR(H94,0) | L94: 0.4667 | M94: 0.21 | N94: 0.2 | O94: 0.1802 | P94: =IFERROR(IF(K94=0,"待填成本",ROUND(K94/(1-L94),0)),"" ) | Q94: =IFERROR(IF(K94=0,"待填成本",ROUND(K94/(1-M94),0)),"" ) | R94: =IFERROR(IF(K94=0,"待填成本",ROUND(K94/(1-N94),0)),"" ) | S94: =IFERROR(IF(K94=0,"待填成本",ROUND(K94/(1-O94),0)),"" ) | T94: =IFERROR(IF(K94=0,"",(P94-K94)/P94),"" ) | U94: =IFERROR(IF(K94=0,"",(Q94-K94)/Q94),"" ) | V94: =IFERROR(IF(K94=0,"",(R94-K94)/R94),"" ) | W94: =IFERROR(IF(K94=0,"",(S94-K94)/S94),"" ) | AA94: 19.86625 | AB94: 11.64375 | AC94: 21.2175 | AD94: 300 | AE94: 150
A95: 2525009040199 | B95: 餐厅-柜 | C95: 樱桃木基础餐边柜 |樱桃木AA柱餐边柜 | D95: 基础柜-整柜AA柱背板-2.0米 | E95: 北美进口FAS级樱桃木 | F95: 抽屉围板：实木多层板 台面：12mm岩板 背板：实木多层板（AA柱）/亚克力洞洞板 内部赠送层板：实木多层板 电力轨道：xpower 内嵌电力轨道 顶柜玻璃：灰玻 | G95: 整体长度：2100mm/1800mm/1500mm 整体深度：480mm 整体高度：1980mm 顶柜长度：2100mm/1800mm/1500mm 顶柜深度：300mm 顶柜高度：490mm 立体收纳长度：2100mm/1800mm/1500mm 立体收纳深度：300mm 立体收纳高度：610mm 下柜长度：2100mm/1800mm/1500mm 下柜深度：480mm 下柜高度：880mm | H95: 6271.7067 | I95: 4633.3333 | J95: 0.48 | K95: =IFERROR(H95,0) | L95: 0.4667 | M95: 0.2102 | N95: 0.2002 | O95: 0.1803 | P95: =IFERROR(IF(K95=0,"待填成本",ROUND(K95/(1-L95),0)),"" ) | Q95: =IFERROR(IF(K95=0,"待填成本",ROUND(K95/(1-M95),0)),"" ) | R95: =IFERROR(IF(K95=0,"待填成本",ROUND(K95/(1-N95),0)),"" ) | S95: =IFERROR(IF(K95=0,"待填成本",ROUND(K95/(1-O95),0)),"" ) | T95: =IFERROR(IF(K95=0,"",(P95-K95)/P95),"" ) | U95: =IFERROR(IF(K95=0,"",(Q95-K95)/Q95),"" ) | V95: =IFERROR(IF(K95=0,"",(R95-K95)/R95),"" ) | W95: =IFERROR(IF(K95=0,"",(S95-K95)/S95),"" ) | AA95: 19.166667 | AB95: 11.2125 | AC95: 20.93 | AD95: 300 | AE95: 150
A96: 2525009040199 | B96: 餐厅-柜 | C96: 樱桃木基础餐边柜 |樱桃木AA柱餐边柜 | D96: 基础柜-整柜AA柱背板-1.9米 | E96: 北美进口FAS级樱桃木 | F96: 抽屉围板：实木多层板 台面：12mm岩板 背板：实木多层板（AA柱）/亚克力洞洞板 内部赠送层板：实木多层板 电力轨道：xpower 内嵌电力轨道 顶柜玻璃：灰玻 | G96: 整体长度：2100mm/1800mm/1500mm 整体深度：480mm 整体高度：1980mm 顶柜长度：2100mm/1800mm/1500mm 顶柜深度：300mm 顶柜高度：490mm 立体收纳长度：2100mm/1800mm/1500mm 立体收纳深度：300mm 立体收纳高度：610mm 下柜长度：2100mm/1800mm/1500mm 下柜深度：480mm 下柜高度：880mm | H96: 6121.3733 | I96: 4566.6667 | J96: 0.48 | K96: =IFERROR(H96,0) | L96: 0.4668 | M96: 0.2103 | N96: 0.2005 | O96: 0.1803 | P96: =IFERROR(IF(K96=0,"待填成本",ROUND(K96/(1-L96),0)),"" ) | Q96: =IFERROR(IF(K96=0,"待填成本",ROUND(K96/(1-M96),0)),"" ) | R96: =IFERROR(IF(K96=0,"待填成本",ROUND(K96/(1-N96),0)),"" ) | S96: =IFERROR(IF(K96=0,"待填成本",ROUND(K96/(1-O96),0)),"" ) | T96: =IFERROR(IF(K96=0,"",(P96-K96)/P96),"" ) | U96: =IFERROR(IF(K96=0,"",(Q96-K96)/Q96),"" ) | V96: =IFERROR(IF(K96=0,"",(R96-K96)/R96),"" ) | W96: =IFERROR(IF(K96=0,"",(S96-K96)/S96),"" ) | AA96: 18.467083 | AB96: 10.78125 | AC96: 20.6425 | AD96: 300 | AE96: 150
A97: 2525009040199 | B97: 餐厅-柜 | C97: 樱桃木基础餐边柜 |樱桃木AA柱餐边柜 | D97: 基础柜-整柜AA柱背板-1.8米 | E97: 北美进口FAS级樱桃木 | F97: 抽屉围板：实木多层板 台面：12mm岩板 背板：实木多层板（AA柱）/亚克力洞洞板 内部赠送层板：实木多层板 电力轨道：xpower 内嵌电力轨道 顶柜玻璃：灰玻 | G97: 整体长度：2100mm/1800mm/1500mm 整体深度：480mm 整体高度：1980mm 顶柜长度：2100mm/1800mm/1500mm 顶柜深度：300mm 顶柜高度：490mm 立体收纳长度：2100mm/1800mm/1500mm 立体收纳深度：300mm 立体收纳高度：610mm 下柜长度：2100mm/1800mm/1500mm 下柜深度：480mm 下柜高度：880mm | H97: 5971.04 | I97: 4500 | J97: 0.48 | K97: =IFERROR(H97,0) | L97: 0.4668 | M97: 0.2105 | N97: 0.2007 | O97: 0.1804 | P97: =IFERROR(IF(K97=0,"待填成本",ROUND(K97/(1-L97),0)),"" ) | Q97: =IFERROR(IF(K97=0,"待填成本",ROUND(K97/(1-M97),0)),"" ) | R97: =IFERROR(IF(K97=0,"待填成本",ROUND(K97/(1-N97),0)),"" ) | S97: =IFERROR(IF(K97=0,"待填成本",ROUND(K97/(1-O97),0)),"" ) | T97: =IFERROR(IF(K97=0,"",(P97-K97)/P97),"" ) | U97: =IFERROR(IF(K97=0,"",(Q97-K97)/Q97),"" ) | V97: =IFERROR(IF(K97=0,"",(R97-K97)/R97),"" ) | W97: =IFERROR(IF(K97=0,"",(S97-K97)/S97),"" ) | AA97: 17.7675 | AB97: 10.35 | AC97: 20.355 | AD97: 300 | AE97: 150
A98: 2525009040199 | B98: 餐厅-柜 | C98: 樱桃木基础餐边柜 |樱桃木AA柱餐边柜 | D98: 基础柜-整柜AA柱背板-1.7米 | E98: 北美进口FAS级樱桃木 | F98: 抽屉围板：实木多层板 台面：12mm岩板 背板：实木多层板（AA柱）/亚克力洞洞板 内部赠送层板：实木多层板 电力轨道：xpower 内嵌电力轨道 顶柜玻璃：灰玻 | G98: 整体长度：2100mm/1800mm/1500mm 整体深度：480mm 整体高度：1980mm 顶柜长度：2100mm/1800mm/1500mm 顶柜深度：300mm 顶柜高度：490mm 立体收纳长度：2100mm/1800mm/1500mm 立体收纳深度：300mm 立体收纳高度：610mm 下柜长度：2100mm/1800mm/1500mm 下柜深度：480mm 下柜高度：880mm | H98: 5863.68 | I98: 4433.3333 | J98: 0.48 | K98: =IFERROR(H98,0) | L98: 0.4668 | M98: 0.2105 | N98: 0.2005 | O98: 0.1805 | P98: =IFERROR(IF(K98=0,"待填成本",ROUND(K98/(1-L98),0)),"" ) | Q98: =IFERROR(IF(K98=0,"待填成本",ROUND(K98/(1-M98),0)),"" ) | R98: =IFERROR(IF(K98=0,"待填成本",ROUND(K98/(1-N98),0)),"" ) | S98: =IFERROR(IF(K98=0,"待填成本",ROUND(K98/(1-O98),0)),"" ) | T98: =IFERROR(IF(K98=0,"",(P98-K98)/P98),"" ) | U98: =IFERROR(IF(K98=0,"",(Q98-K98)/Q98),"" ) | V98: =IFERROR(IF(K98=0,"",(R98-K98)/R98),"" ) | W98: =IFERROR(IF(K98=0,"",(S98-K98)/S98),"" ) | AA98: 17.067917 | AB98: 9.91875 | AC98: 20.0675 | AD98: 300 | AE98: 150
A99: 2525009040199 | B99: 餐厅-柜 | C99: 樱桃木基础餐边柜 |樱桃木AA柱餐边柜 | D99: 基础柜-整柜AA柱背板-1.6米 | E99: 北美进口FAS级樱桃木 | F99: 抽屉围板：实木多层板 台面：12mm岩板 背板：实木多层板（AA柱）/亚克力洞洞板 内部赠送层板：实木多层板 电力轨道：xpower 内嵌电力轨道 顶柜玻璃：灰玻 | G99: 整体长度：2100mm/1800mm/1500mm 整体深度：480mm 整体高度：1980mm 顶柜长度：2100mm/1800mm/1500mm 顶柜深度：300mm 顶柜高度：490mm 立体收纳长度：2100mm/1800mm/1500mm 立体收纳深度：300mm 立体收纳高度：610mm 下柜长度：2100mm/1800mm/1500mm 下柜深度：480mm 下柜高度：880mm | H99: 5756.32 | I99: 4366.6667 | J99: 0.48 | K99: =IFERROR(H99,0) | L99: 0.4668 | M99: 0.2105 | N99: 0.2003 | O99: 0.1805 | P99: =IFERROR(IF(K99=0,"待填成本",ROUND(K99/(1-L99),0)),"" ) | Q99: =IFERROR(IF(K99=0,"待填成本",ROUND(K99/(1-M99),0)),"" ) | R99: =IFERROR(IF(K99=0,"待填成本",ROUND(K99/(1-N99),0)),"" ) | S99: =IFERROR(IF(K99=0,"待填成本",ROUND(K99/(1-O99),0)),"" ) | T99: =IFERROR(IF(K99=0,"",(P99-K99)/P99),"" ) | U99: =IFERROR(IF(K99=0,"",(Q99-K99)/Q99),"" ) | V99: =IFERROR(IF(K99=0,"",(R99-K99)/R99),"" ) | W99: =IFERROR(IF(K99=0,"",(S99-K99)/S99),"" ) | AA99: 16.368333 | AB99: 9.4875 | AC99: 19.78 | AD99: 300 | AE99: 150
A100: 2525009040199 | B100: 餐厅-柜 | C100: 樱桃木基础餐边柜 |樱桃木AA柱餐边柜 | D100: 基础柜-整柜AA柱背板-1.5米 | E100: 北美进口FAS级樱桃木 | F100: 抽屉围板：实木多层板 台面：12mm岩板 背板：实木多层板（AA柱）/亚克力洞洞板 内部赠送层板：实木多层板 电力轨道：xpower 内嵌电力轨道 顶柜玻璃：灰玻 | G100: 整体长度：2100mm/1800mm/1500mm 整体深度：480mm 整体高度：1980mm 顶柜长度：2100mm/1800mm/1500mm 顶柜深度：300mm 顶柜高度：490mm 立体收纳长度：2100mm/1800mm/1500mm 立体收纳深度：300mm 立体收纳高度：610mm 下柜长度：2100mm/1800mm/1500mm 下柜深度：480mm 下柜高度：880mm | H100: 5648.96 | I100: 4300 | J100: 0.48 | K100: =IFERROR(H100,0) | L100: 0.4667 | M100: 0.2105 | N100: 0.2001 | O100: 0.1805 | P100: =IFERROR(IF(K100=0,"待填成本",ROUND(K100/(1-L100),0)),"" ) | Q100: =IFERROR(IF(K100=0,"待填成本",ROUND(K100/(1-M100),0)),"" ) | R100: =IFERROR(IF(K100=0,"待填成本",ROUND(K100/(1-N100),0)),"" ) | S100: =IFERROR(IF(K100=0,"待填成本",ROUND(K100/(1-O100),0)),"" ) | T100: =IFERROR(IF(K100=0,"",(P100-K100)/P100),"" ) | U100: =IFERROR(IF(K100=0,"",(Q100-K100)/Q100),"" ) | V100: =IFERROR(IF(K100=0,"",(R100-K100)/R100),"" ) | W100: =IFERROR(IF(K100=0,"",(S100-K100)/S100),"" ) | AA100: 15.66875 | AB100: 9.05625 | AC100: 19.4925 | AD100: 300 | AE100: 150
A101: 2525009040199 | B101: 餐厅-柜 | C101: 樱桃木基础餐边柜 |樱桃木AA柱餐边柜 | D101: 基础柜-整柜AA柱背板-1.4米 | E101: 北美进口FAS级樱桃木 | F101: 抽屉围板：实木多层板 台面：12mm岩板 背板：实木多层板（AA柱）/亚克力洞洞板 内部赠送层板：实木多层板 电力轨道：xpower 内嵌电力轨道 顶柜玻璃：灰玻 | G101: 整体长度：2100mm/1800mm/1500mm 整体深度：480mm 整体高度：1980mm 顶柜长度：2100mm/1800mm/1500mm 顶柜深度：300mm 顶柜高度：490mm 立体收纳长度：2100mm/1800mm/1500mm 立体收纳深度：300mm 立体收纳高度：610mm 下柜长度：2100mm/1800mm/1500mm 下柜深度：480mm 下柜高度：880mm | H101: 5521.9867 | I101: 4233.3333 | J101: 0.48 | K101: =IFERROR(H101,0) | L101: 0.4668 | M101: 0.2106 | N101: 0.2003 | O101: 0.1807 | P101: =IFERROR(IF(K101=0,"待填成本",ROUND(K101/(1-L101),0)),"" ) | Q101: =IFERROR(IF(K101=0,"待填成本",ROUND(K101/(1-M101),0)),"" ) | R101: =IFERROR(IF(K101=0,"待填成本",ROUND(K101/(1-N101),0)),"" ) | S101: =IFERROR(IF(K101=0,"待填成本",ROUND(K101/(1-O101),0)),"" ) | T101: =IFERROR(IF(K101=0,"",(P101-K101)/P101),"" ) | U101: =IFERROR(IF(K101=0,"",(Q101-K101)/Q101),"" ) | V101: =IFERROR(IF(K101=0,"",(R101-K101)/R101),"" ) | W101: =IFERROR(IF(K101=0,"",(S101-K101)/S101),"" ) | AA101: 15.3525 | AB101: 8.625 | AC101: 19.205 | AD101: 300 | AE101: 150
A102: 2525009040199 | B102: 餐厅-柜 | C102: 樱桃木基础餐边柜 |樱桃木AA柱餐边柜 | D102: 基础柜-整柜AA柱背板-1.3米 | E102: 北美进口FAS级樱桃木 | F102: 抽屉围板：实木多层板 台面：12mm岩板 背板：实木多层板（AA柱）/亚克力洞洞板 内部赠送层板：实木多层板 电力轨道：xpower 内嵌电力轨道 顶柜玻璃：灰玻 | G102: 整体长度：2100mm/1800mm/1500mm 整体深度：480mm 整体高度：1980mm 顶柜长度：2100mm/1800mm/1500mm 顶柜深度：300mm 顶柜高度：490mm 立体收纳长度：2100mm/1800mm/1500mm 立体收纳深度：300mm 立体收纳高度：610mm 下柜长度：2100mm/1800mm/1500mm 下柜深度：480mm 下柜高度：880mm | H102: 5395.0133 | I102: 4166.6667 | J102: 0.48 | K102: =IFERROR(H102,0) | L102: 0.4668 | M102: 0.2107 | N102: 0.2006 | O102: 0.1809 | P102: =IFERROR(IF(K102=0,"待填成本",ROUND(K102/(1-L102),0)),"" ) | Q102: =IFERROR(IF(K102=0,"待填成本",ROUND(K102/(1-M102),0)),"" ) | R102: =IFERROR(IF(K102=0,"待填成本",ROUND(K102/(1-N102),0)),"" ) | S102: =IFERROR(IF(K102=0,"待填成本",ROUND(K102/(1-O102),0)),"" ) | T102: =IFERROR(IF(K102=0,"",(P102-K102)/P102),"" ) | U102: =IFERROR(IF(K102=0,"",(Q102-K102)/Q102),"" ) | V102: =IFERROR(IF(K102=0,"",(R102-K102)/R102),"" ) | W102: =IFERROR(IF(K102=0,"",(S102-K102)/S102),"" ) | AA102: 15.03625 | AB102: 8.19375 | AC102: 18.9175 | AD102: 300 | AE102: 150
A103: 2525009040199 | B103: 餐厅-柜 | C103: 樱桃木基础餐边柜 |樱桃木AA柱餐边柜 | D103: 基础柜-整柜AA柱背板-1.2米 | E103: 北美进口FAS级樱桃木 | F103: 抽屉围板：实木多层板 台面：12mm岩板 背板：实木多层板（AA柱）/亚克力洞洞板 内部赠送层板：实木多层板 电力轨道：xpower 内嵌电力轨道 顶柜玻璃：灰玻 | G103: 整体长度：2100mm/1800mm/1500mm 整体深度：480mm 整体高度：1980mm 顶柜长度：2100mm/1800mm/1500mm 顶柜深度：300mm 顶柜高度：490mm 立体收纳长度：2100mm/1800mm/1500mm 立体收纳深度：300mm 立体收纳高度：610mm 下柜长度：2100mm/1800mm/1500mm 下柜深度：480mm 下柜高度：880mm | H103: 5268.04 | I103: 4100 | J103: 0.48 | K103: =IFERROR(H103,0) | L103: 0.4669 | M103: 0.2109 | N103: 0.2008 | O103: 0.181 | P103: =IFERROR(IF(K103=0,"待填成本",ROUND(K103/(1-L103),0)),"" ) | Q103: =IFERROR(IF(K103=0,"待填成本",ROUND(K103/(1-M103),0)),"" ) | R103: =IFERROR(IF(K103=0,"待填成本",ROUND(K103/(1-N103),0)),"" ) | S103: =IFERROR(IF(K103=0,"待填成本",ROUND(K103/(1-O103),0)),"" ) | T103: =IFERROR(IF(K103=0,"",(P103-K103)/P103),"" ) | U103: =IFERROR(IF(K103=0,"",(Q103-K103)/Q103),"" ) | V103: =IFERROR(IF(K103=0,"",(R103-K103)/R103),"" ) | W103: =IFERROR(IF(K103=0,"",(S103-K103)/S103),"" ) | AA103: 14.72 | AB103: 7.7625 | AC103: 18.63 | AD103: 300 | AE103: 150
A104: 2525009040199 | B104: 餐厅-柜 | C104: 樱桃木基础餐边柜 |樱桃木AA柱餐边柜 | D104: 基础柜-整柜AA柱背板-1.1米 | E104: 北美进口FAS级樱桃木 | F104: 抽屉围板：实木多层板 台面：12mm岩板 背板：实木多层板（AA柱）/亚克力洞洞板 内部赠送层板：实木多层板 电力轨道：xpower 内嵌电力轨道 顶柜玻璃：灰玻 | G104: 整体长度：2100mm/1800mm/1500mm 整体深度：480mm 整体高度：1980mm 顶柜长度：2100mm/1800mm/1500mm 顶柜深度：300mm 顶柜高度：490mm 立体收纳长度：2100mm/1800mm/1500mm 立体收纳深度：300mm 立体收纳高度：610mm 下柜长度：2100mm/1800mm/1500mm 下柜深度：480mm 下柜高度：880mm | H104: 5141.0667 | I104: 4033.3333 | J104: 0.48 | K104: =IFERROR(H104,0) | L104: 0.467 | M104: 0.211 | N104: 0.2011 | O104: 0.1812 | P104: =IFERROR(IF(K104=0,"待填成本",ROUND(K104/(1-L104),0)),"" ) | Q104: =IFERROR(IF(K104=0,"待填成本",ROUND(K104/(1-M104),0)),"" ) | R104: =IFERROR(IF(K104=0,"待填成本",ROUND(K104/(1-N104),0)),"" ) | S104: =IFERROR(IF(K104=0,"待填成本",ROUND(K104/(1-O104),0)),"" ) | T104: =IFERROR(IF(K104=0,"",(P104-K104)/P104),"" ) | U104: =IFERROR(IF(K104=0,"",(Q104-K104)/Q104),"" ) | V104: =IFERROR(IF(K104=0,"",(R104-K104)/R104),"" ) | W104: =IFERROR(IF(K104=0,"",(S104-K104)/S104),"" ) | AA104: 14.40375 | AB104: 7.33125 | AC104: 18.3425 | AD104: 300 | AE104: 150
A105: 2525009040199 | B105: 餐厅-柜 | C105: 樱桃木基础餐边柜 |樱桃木AA柱餐边柜 | D105: 基础柜-整柜AA柱背板-1.0米 | E105: 北美进口FAS级樱桃木 | F105: 抽屉围板：实木多层板 台面：12mm岩板 背板：实木多层板（AA柱）/亚克力洞洞板 内部赠送层板：实木多层板 电力轨道：xpower 内嵌电力轨道 顶柜玻璃：灰玻 | G105: 整体长度：2100mm/1800mm/1500mm 整体深度：480mm 整体高度：1980mm 顶柜长度：2100mm/1800mm/1500mm 顶柜深度：300mm 顶柜高度：490mm 立体收纳长度：2100mm/1800mm/1500mm 立体收纳深度：300mm 立体收纳高度：610mm 下柜长度：2100mm/1800mm/1500mm 下柜深度：480mm 下柜高度：880mm | H105: 5014.0933 | I105: 3966.6667 | J105: 0.48 | K105: =IFERROR(H105,0) | L105: 0.467 | M105: 0.2112 | N105: 0.2014 | O105: 0.1814 | P105: =IFERROR(IF(K105=0,"待填成本",ROUND(K105/(1-L105),0)),"" ) | Q105: =IFERROR(IF(K105=0,"待填成本",ROUND(K105/(1-M105),0)),"" ) | R105: =IFERROR(IF(K105=0,"待填成本",ROUND(K105/(1-N105),0)),"" ) | S105: =IFERROR(IF(K105=0,"待填成本",ROUND(K105/(1-O105),0)),"" ) | T105: =IFERROR(IF(K105=0,"",(P105-K105)/P105),"" ) | U105: =IFERROR(IF(K105=0,"",(Q105-K105)/Q105),"" ) | V105: =IFERROR(IF(K105=0,"",(R105-K105)/R105),"" ) | W105: =IFERROR(IF(K105=0,"",(S105-K105)/S105),"" ) | AA105: 14.0875 | AB105: 6.9 | AC105: 18.055 | AD105: 300 | AE105: 150
... A131: 2525010040599 | B131: 餐厅-柜 | C131: 樱桃木窄柜 |樱桃木1米餐边柜 | D131: 窄柜-整柜洞洞板背板-0.8米 | E131: 北美进口FAS级樱桃木 | F131: 抽屉围板：新西兰松木 台面：洞石岩板 背板：洞石纹理背板 电力轨道：xpower 内嵌电力轨道 顶柜玻璃：超透玻璃 | G131: 整体长度：1200mm/1000mm/800mm 整体深度：450mm 整体高度：1900mm 顶柜长度：1200mm/1000mm/800mm 顶柜深度：400mm 顶柜高度：325mm 立体收纳长度：1200mm/1000mm/800mm 立体收纳深度：400mm 立体收纳高度：655mm 下柜长度：1200mm/1000mm/800mm 下柜深度：450mm 下柜高度：910mm | H131: 3653.455 | I131: 2700 | J131: 0.44 | K131: =IFERROR(H131,0) | L131: 0.4668 | M131: 0.1208 | N131: 0.151 | O131: 0.1208 | P131: =IFERROR(IF(K131=0,"待填成本",ROUND(K131/(1-L131),0)),"" ) | Q131: =IFERROR(IF(K131=0,"待填成本",ROUND(K131/(1-M131),0)),"" ) | R131: =IFERROR(IF(K131=0,"待填成本",ROUND(K131/(1-N131),0)),"" ) | S131: =IFERROR(IF(K131=0,"待填成本",ROUND(K131/(1-O131),0)),"" ) | T131: =IFERROR(IF(K131=0,"",(P131-K131)/P131),"" ) | U131: =IFERROR(IF(K131=0,"",(Q131-K131)/Q131),"" ) | V131: =IFERROR(IF(K131=0,"",(R131-K131)/R131),"" ) | W131: =IFERROR(IF(K131=0,"",(S131-K131)/S131),"" ) | AA131: 10.58 | AB131: 7.0725 | AC131: 13.685 | AD131: 300 | AE131: 150
A132: 2525011041099 | B132: 餐厅-柜 | C132: 樱桃木旋转柜2025版 | D132: 旋转柜-仅餐桌-1.6米 | E132: 北美进口FAS级樱桃木 | H132: 0 | I132: 0 | J132: 0.48 | K132: =IFERROR(H132,0) | P132: =IFERROR(IF(K132=0,"待填成本",ROUND(K132/(1-L132),0)),"" ) | Q132: =IFERROR(IF(K132=0,"待填成本",ROUND(K132/(1-M132),0)),"" ) | R132: =IFERROR(IF(K132=0,"待填成本",ROUND(K132/(1-N132),0)),"" ) | S132: =IFERROR(IF(K132=0,"待填成本",ROUND(K132/(1-O132),0)),"" ) | T132: =IFERROR(IF(K132=0,"",(P132-K132)/P132),"" ) | U132: =IFERROR(IF(K132=0,"",(Q132-K132)/Q132),"" ) | V132: =IFERROR(IF(K132=0,"",(R132-K132)/R132),"" ) | W132: =IFERROR(IF(K132=0,"",(S132-K132)/S132),"" )
A133: 2525011041099 | B133: 餐厅-柜 | C133: 樱桃木旋转柜2025版 | D133: 旋转柜-仅餐桌-1.5米 | E133: 北美进口FAS级樱桃木 | H133: 0 | I133: 0 | J133: 0.48 | K133: =IFERROR(H133,0) | P133: =IFERROR(IF(K133=0,"待填成本",ROUND(K133/(1-L133),0)),"" ) | Q133: =IFERROR(IF(K133=0,"待填成本",ROUND(K133/(1-M133),0)),"" ) | R133: =IFERROR(IF(K133=0,"待填成本",ROUND(K133/(1-N133),0)),"" ) | S133: =IFERROR(IF(K133=0,"待填成本",ROUND(K133/(1-O133),0)),"" ) | T133: =IFERROR(IF(K133=0,"",(P133-K133)/P133),"" ) | U133: =IFERROR(IF(K133=0,"",(Q133-K133)/Q133),"" ) | V133: =IFERROR(IF(K133=0,"",(R133-K133)/R133),"" ) | W133: =IFERROR(IF(K133=0,"",(S133-K133)/S133),"" )
A134: 2525011041099 | B134: 餐厅-柜 | C134: 樱桃木旋转柜2025版 | D134: 旋转柜-仅餐桌-1.4米 | E134: 北美进口FAS级樱桃木 | H134: 0 | I134: 0 | J134: 0.48 | K134: =IFERROR(H134,0) | P134: =IFERROR(IF(K134=0,"待填成本",ROUND(K134/(1-L134),0)),"" ) | Q134: =IFERROR(IF(K134=0,"待填成本",ROUND(K134/(1-M134),0)),"" ) | R134: =IFERROR(IF(K134=0,"待填成本",ROUND(K134/(1-N134),0)),"" ) | S134: =IFERROR(IF(K134=0,"待填成本",ROUND(K134/(1-O134),0)),"" ) | T134: =IFERROR(IF(K134=0,"",(P134-K134)/P134),"" ) | U134: =IFERROR(IF(K134=0,"",(Q134-K134)/Q134),"" ) | V134: =IFERROR(IF(K134=0,"",(R134-K134)/R134),"" ) | W134: =IFERROR(IF(K134=0,"",(S134-K134)/S134),"" )
A135: 2525011041099 | B135: 餐厅-柜 | C135: 樱桃木旋转柜2025版 | D135: 旋转柜-仅餐桌-1.3米 | E135: 北美进口FAS级樱桃木 | H135: 0 | I135: 0 | J135: 0.48 | K135: =IFERROR(H135,0) | P135: =IFERROR(IF(K135=0,"待填成本",ROUND(K135/(1-L135),0)),"" ) | Q135: =IFERROR(IF(K135=0,"待填成本",ROUND(K135/(1-M135),0)),"" ) | R135: =IFERROR(IF(K135=0,"待填成本",ROUND(K135/(1-N135),0)),"" ) | S135: =IFERROR(IF(K135=0,"待填成本",ROUND(K135/(1-O135),0)),"" ) | T135: =IFERROR(IF(K135=0,"",(P135-K135)/P135),"" ) | U135: =IFERROR(IF(K135=0,"",(Q135-K135)/Q135),"" ) | V135: =IFERROR(IF(K135=0,"",(R135-K135)/R135),"" ) | W135: =IFERROR(IF(K135=0,"",(S135-K135)/S135),"" )
A136: 2525011041099 | B136: 餐厅-柜 | C136: 樱桃木旋转柜2025版 | D136: 旋转柜-仅餐桌-1.2米 | E136: 北美进口FAS级樱桃木 | H136: 0 | I136: 0 | J136: 0.48 | K136: =IFERROR(H136,0) | P136: =IFERROR(IF(K136=0,"待填成本",ROUND(K136/(1-L136),0)),"" ) | Q136: =IFERROR(IF(K136=0,"待填成本",ROUND(K136/(1-M136),0)),"" ) | R136: =IFERROR(IF(K136=0,"待填成本",ROUND(K136/(1-N136),0)),"" ) | S136: =IFERROR(IF(K136=0,"待填成本",ROUND(K136/(1-O136),0)),"" ) | T136: =IFERROR(IF(K136=0,"",(P136-K136)/P136),"" ) | U136: =IFERROR(IF(K136=0,"",(Q136-K136)/Q136),"" ) | V136: =IFERROR(IF(K136=0,"",(R136-K136)/R136),"" ) | W136: =IFERROR(IF(K136=0,"",(S136-K136)/S136),"" )
A137: 2525011041099 | B137: 餐厅-柜 | C137: 樱桃木旋转柜2025版 | D137: 旋转柜-仅餐桌-1.1米 | E137: 北美进口FAS级樱桃木 | H137: 0 | I137: 0 | J137: 0.48 | K137: =IFERROR(H137,0) | P137: =IFERROR(IF(K137=0,"待填成本",ROUND(K137/(1-L137),0)),"" ) | Q137: =IFERROR(IF(K137=0,"待填成本",ROUND(K137/(1-M137),0)),"" ) | R137: =IFERROR(IF(K137=0,"待填成本",ROUND(K137/(1-N137),0)),"" ) | S137: =IFERROR(IF(K137=0,"待填成本",ROUND(K137/(1-O137),0)),"" ) | T137: =IFERROR(IF(K137=0,"",(P137-K137)/P137),"" ) | U137: =IFERROR(IF(K137=0,"",(Q137-K137)/Q137),"" ) | V137: =IFERROR(IF(K137=0,"",(R137-K137)/R137),"" ) | W137: =IFERROR(IF(K137=0,"",(S137-K137)/S137),"" )
A138: 2525011041099 | B138: 餐厅-柜 | C138: 樱桃木旋转柜2025版 | D138: 旋转柜-仅餐桌-1.0米 | E138: 北美进口FAS级樱桃木 | H138: 0 | I138: 0 | J138: 0.48 | K138: =IFERROR(H138,0) | P138: =IFERROR(IF(K138=0,"待填成本",ROUND(K138/(1-L138),0)),"" ) | Q138: =IFERROR(IF(K138=0,"待填成本",ROUND(K138/(1-M138),0)),"" ) | R138: =IFERROR(IF(K138=0,"待填成本",ROUND(K138/(1-N138),0)),"" ) | S138: =IFERROR(IF(K138=0,"待填成本",ROUND(K138/(1-O138),0)),"" ) | T138: =IFERROR(IF(K138=0,"",(P138-K138)/P138),"" ) | U138: =IFERROR(IF(K138=0,"",(Q138-K138)/Q138),"" ) | V138: =IFERROR(IF(K138=0,"",(R138-K138)/R138),"" ) | W138: =IFERROR(IF(K138=0,"",(S138-K138)/S138),"" )
A139: 2525011041099 | B139: 餐厅-柜 | C139: 樱桃木旋转柜2025版 | D139: 旋转柜-仅餐桌-0.9米 | E139: 北美进口FAS级樱桃木 | H139: 0 | I139: 0 | J139: 0.48 | K139: =IFERROR(H139,0) | P139: =IFERROR(IF(K139=0,"待填成本",ROUND(K139/(1-L139),0)),"" ) | Q139: =IFERROR(IF(K139=0,"待填成本",ROUND(K139/(1-M139),0)),"" ) | R139: =IFERROR(IF(K139=0,"待填成本",ROUND(K139/(1-N139),0)),"" ) | S139: =IFERROR(IF(K139=0,"待填成本",ROUND(K139/(1-O139),0)),"" ) | T139: =IFERROR(IF(K139=0,"",(P139-K139)/P139),"" ) | U139: =IFERROR(IF(K139=0,"",(Q139-K139)/Q139),"" ) | V139: =IFERROR(IF(K139=0,"",(R139-K139)/R139),"" ) | W139: =IFERROR(IF(K139=0,"",(S139-K139)/S139),"" )
A140: 2525011041099 | B140: 餐厅-柜 | C140: 樱桃木旋转柜2025版 | D140: 旋转柜-仅餐桌-0.8米 | E140: 北美进口FAS级樱桃木 | H140: 0 | I140: 0 | J140: 0.48 | K140: =IFERROR(H140,0) | P140: =IFERROR(IF(K140=0,"待填成本",ROUND(K140/(1-L140),0)),"" ) | Q140: =IFERROR(IF(K140=0,"待填成本",ROUND(K140/(1-M140),0)),"" ) | R140: =IFERROR(IF(K140=0,"待填成本",ROUND(K140/(1-N140),0)),"" ) | S140: =IFERROR(IF(K140=0,"待填成本",ROUND(K140/(1-O140),0)),"" ) | T140: =IFERROR(IF(K140=0,"",(P140-K140)/P140),"" ) | U140: =IFERROR(IF(K140=0,"",(Q140-K140)/Q140),"" ) | V140: =IFERROR(IF(K140=0,"",(R140-K140)/R140),"" ) | W140: =IFERROR(IF(K140=0,"",(S140-K140)/S140),"" )
A141: 2525011041099 | B141: 餐厅-柜 | C141: 樱桃木旋转柜2025版 | D141: 旋转柜-下柜-2.1米+1.6米餐桌 | E141: 北美进口FAS级樱桃木 | H141: 0 | I141: 0 | J141: 0.48 | K141: =IFERROR(H141,0) | P141: =IFERROR(IF(K141=0,"待填成本",ROUND(K141/(1-L141),0)),"" ) | Q141: =IFERROR(IF(K141=0,"待填成本",ROUND(K141/(1-M141),0)),"" ) | R141: =IFERROR(IF(K141=0,"待填成本",ROUND(K141/(1-N141),0)),"" ) | S141: =IFERROR(IF(K141=0,"待填成本",ROUND(K141/(1-O141),0)),"" ) | T141: =IFERROR(IF(K141=0,"",(P141-K141)/P141),"" ) | U141: =IFERROR(IF(K141=0,"",(Q141-K141)/Q141),"" ) | V141: =IFERROR(IF(K141=0,"",(R141-K141)/R141),"" ) | W141: =IFERROR(IF(K141=0,"",(S141-K141)/S141),"" )
A142: 2525011041099 | B142: 餐厅-柜 | C142: 樱桃木旋转柜2025版 | D142: 旋转柜-下柜-2.0米+1.6米餐桌 | E142: 北美进口FAS级樱桃木 | H142: 0 | I142: 0 | J142: 0.48 | K142: =IFERROR(H142,0) | P142: =IFERROR(IF(K142=0,"待填成本",ROUND(K142/(1-L142),0)),"" ) | Q142: =IFERROR(IF(K142=0,"待填成本",ROUND(K142/(1-M142),0)),"" ) | R142: =IFERROR(IF(K142=0,"待填成本",ROUND(K142/(1-N142),0)),"" ) | S142: =IFERROR(IF(K142=0,"待填成本",ROUND(K142/(1-O142),0)),"" ) | T142: =IFERROR(IF(K142=0,"",(P142-K142)/P142),"" ) | U142: =IFERROR(IF(K142=0,"",(Q142-K142)/Q142),"" ) | V142: =IFERROR(IF(K142=0,"",(R142-K142)/R142),"" ) | W142: =IFERROR(IF(K142=0,"",(S142-K142)/S142),"" )
A143: 2525011041099 | B143: 餐厅-柜 | C143: 樱桃木旋转柜2025版 | D143: 旋转柜-下柜-1.9米+1.5米餐桌 | E143: 北美进口FAS级樱桃木 | H143: 0 | I143: 0 | J143: 0.48 | K143: =IFERROR(H143,0) | P143: =IFERROR(IF(K143=0,"待填成本",ROUND(K143/(1-L143),0)),"" ) | Q143: =IFERROR(IF(K143=0,"待填成本",ROUND(K143/(1-M143),0)),"" ) | R143: =IFERROR(IF(K143=0,"待填成本",ROUND(K143/(1-N143),0)),"" ) | S143: =IFERROR(IF(K143=0,"待填成本",ROUND(K143/(1-O143),0)),"" ) | T143: =IFERROR(IF(K143=0,"",(P143-K143)/P143),"" ) | U143: =IFERROR(IF(K143=0,"",(Q143-K143)/Q143),"" ) | V143: =IFERROR(IF(K143=0,"",(R143-K143)/R143),"" ) | W143: =IFERROR(IF(K143=0,"",(S143-K143)/S143),"" )
... A176: 2525011041099 | B176: 餐厅-柜 | C176: 樱桃木旋转柜2025版 | D176: 旋转柜-榉木整柜1.0米+1.0米餐桌 | E176: 北美进口FAS级樱桃木 | H176: 0 | I176: 0 | J176: 0.48 | K176: =IFERROR(H176,0) | P176: =IFERROR(IF(K176=0,"待填成本",ROUND(K176/(1-L176),0)),"" ) | Q176: =IFERROR(IF(K176=0,"待填成本",ROUND(K176/(1-M176),0)),"" ) | R176: =IFERROR(IF(K176=0,"待填成本",ROUND(K176/(1-N176),0)),"" ) | S176: =IFERROR(IF(K176=0,"待填成本",ROUND(K176/(1-O176),0)),"" ) | T176: =IFERROR(IF(K176=0,"",(P176-K176)/P176),"" ) | U176: =IFERROR(IF(K176=0,"",(Q176-K176)/Q176),"" ) | V176: =IFERROR(IF(K176=0,"",(R176-K176)/R176),"" ) | W176: =IFERROR(IF(K176=0,"",(S176-K176)/S176),"" )
A177: 2525012041599 | B177: 餐厅-柜 | C177: 黑胡桃木基础餐边柜 |黑胡桃木鎏金餐边柜 | D177: 鎏金柜-下柜-2.1米 | E177: 北美进口FAS级黑胡桃木 | F177: 抽屉围板：实木多层板 台面：黑色岩板 背板：鎏金板 电力轨道：xpower 内嵌电力轨道 顶柜玻璃：灰玻 | G177: 整体长度：1200mm/1000mm/800mm 整体深度：480mm 整体高度：1900mm 顶柜长度：1200mm/1000mm/800mm 顶柜深度：380mm 顶柜高度：420mm 立体收纳长度：1200mm/1000mm/800mm 立体收纳深度：380mm 立体收纳高度：650mm 下柜长度：1200mm/1000mm/800mm 下柜深度：480mm 下柜高度：880mm | H177: 0 | I177: 0 | J177: 0.48 | K177: =IFERROR(H177,0) | P177: =IFERROR(IF(K177=0,"待填成本",ROUND(K177/(1-L177),0)),"" ) | Q177: =IFERROR(IF(K177=0,"待填成本",ROUND(K177/(1-M177),0)),"" ) | R177: =IFERROR(IF(K177=0,"待填成本",ROUND(K177/(1-N177),0)),"" ) | S177: =IFERROR(IF(K177=0,"待填成本",ROUND(K177/(1-O177),0)),"" ) | T177: =IFERROR(IF(K177=0,"",(P177-K177)/P177),"" ) | U177: =IFERROR(IF(K177=0,"",(Q177-K177)/Q177),"" ) | V177: =IFERROR(IF(K177=0,"",(R177-K177)/R177),"" ) | W177: =IFERROR(IF(K177=0,"",(S177-K177)/S177),"" )
A178: 2525012041599 | B178: 餐厅-柜 | C178: 黑胡桃木基础餐边柜 |黑胡桃木鎏金餐边柜 | D178: 鎏金柜-下柜-2.0米 | E178: 北美进口FAS级黑胡桃木 | F178: 抽屉围板：实木多层板 台面：黑色岩板 背板：鎏金板 电力轨道：xpower 内嵌电力轨道 顶柜玻璃：灰玻 | G178: 整体长度：1200mm/1000mm/800mm 整体深度：480mm 整体高度：1900mm 顶柜长度：1200mm/1000mm/800mm 顶柜深度：380mm 顶柜高度：420mm 立体收纳长度：1200mm/1000mm/800mm 立体收纳深度：380mm 立体收纳高度：650mm 下柜长度：1200mm/1000mm/800mm 下柜深度：480mm 下柜高度：880mm | H178: 0 | I178: 0 | J178: 0.48 | K178: =IFERROR(H178,0) | P178: =IFERROR(IF(K178=0,"待填成本",ROUND(K178/(1-L178),0)),"" ) | Q178: =IFERROR(IF(K178=0,"待填成本",ROUND(K178/(1-M178),0)),"" ) | R178: =IFERROR(IF(K178=0,"待填成本",ROUND(K178/(1-N178),0)),"" ) | S178: =IFERROR(IF(K178=0,"待填成本",ROUND(K178/(1-O178),0)),"" ) | T178: =IFERROR(IF(K178=0,"",(P178-K178)/P178),"" ) | U178: =IFERROR(IF(K178=0,"",(Q178-K178)/Q178),"" ) | V178: =IFERROR(IF(K178=0,"",(R178-K178)/R178),"" ) | W178: =IFERROR(IF(K178=0,"",(S178-K178)/S178),"" )
A179: 2525012041599 | B179: 餐厅-柜 | C179: 黑胡桃木基础餐边柜 |黑胡桃木鎏金餐边柜 | D179: 鎏金柜-下柜-1.9米 | E179: 北美进口FAS级黑胡桃木 | F179: 抽屉围板：实木多层板 台面：黑色岩板 背板：鎏金板 电力轨道：xpower 内嵌电力轨道 顶柜玻璃：灰玻 | G179: 整体长度：1200mm/1000mm/800mm 整体深度：480mm 整体高度：1900mm 顶柜长度：1200mm/1000mm/800mm 顶柜深度：380mm 顶柜高度：420mm 立体收纳长度：1200mm/1000mm/800mm 立体收纳深度：380mm 立体收纳高度：650mm 下柜长度：1200mm/1000mm/800mm 下柜深度：480mm 下柜高度：880mm | H179: 0 | I179: 0 | J179: 0.48 | K179: =IFERROR(H179,0) | P179: =IFERROR(IF(K179=0,"待填成本",ROUND(K179/(1-L179),0)),"" ) | Q179: =IFERROR(IF(K179=0,"待填成本",ROUND(K179/(1-M179),0)),"" ) | R179: =IFERROR(IF(K179=0,"待填成本",ROUND(K179/(1-N179),0)),"" ) | S179: =IFERROR(IF(K179=0,"待填成本",ROUND(K179/(1-O179),0)),"" ) | T179: =IFERROR(IF(K179=0,"",(P179-K179)/P179),"" ) | U179: =IFERROR(IF(K179=0,"",(Q179-K179)/Q179),"" ) | V179: =IFERROR(IF(K179=0,"",(R179-K179)/R179),"" ) | W179: =IFERROR(IF(K179=0,"",(S179-K179)/S179),"" )
A180: 2525012041599 | B180: 餐厅-柜 | C180: 黑胡桃木基础餐边柜 |黑胡桃木鎏金餐边柜 | D180: 鎏金柜-下柜-1.8米 | E180: 北美进口FAS级黑胡桃木 | F180: 抽屉围板：实木多层板 台面：黑色岩板 背板：鎏金板 电力轨道：xpower 内嵌电力轨道 顶柜玻璃：灰玻 | G180: 整体长度：1200mm/1000mm/800mm 整体深度：480mm 整体高度：1900mm 顶柜长度：1200mm/1000mm/800mm 顶柜深度：380mm 顶柜高度：420mm 立体收纳长度：1200mm/1000mm/800mm 立体收纳深度：380mm 立体收纳高度：650mm 下柜长度：1200mm/1000mm/800mm 下柜深度：480mm 下柜高度：880mm | H180: 0 | I180: 0 | J180: 0.48 | K180: =IFERROR(H180,0) | P180: =IFERROR(IF(K180=0,"待填成本",ROUND(K180/(1-L180),0)),"" ) | Q180: =IFERROR(IF(K180=0,"待填成本",ROUND(K180/(1-M180),0)),"" ) | R180: =IFERROR(IF(K180=0,"待填成本",ROUND(K180/(1-N180),0)),"" ) | S180: =IFERROR(IF(K180=0,"待填成本",ROUND(K180/(1-O180),0)),"" ) | T180: =IFERROR(IF(K180=0,"",(P180-K180)/P180),"" ) | U180: =IFERROR(IF(K180=0,"",(Q180-K180)/Q180),"" ) | V180: =IFERROR(IF(K180=0,"",(R180-K180)/R180),"" ) | W180: =IFERROR(IF(K180=0,"",(S180-K180)/S180),"" )
A181: 2525012041599 | B181: 餐厅-柜 | C181: 黑胡桃木基础餐边柜 |黑胡桃木鎏金餐边柜 | D181: 鎏金柜-下柜-1.7米 | E181: 北美进口FAS级黑胡桃木 | F181: 抽屉围板：实木多层板 台面：黑色岩板 背板：鎏金板 电力轨道：xpower 内嵌电力轨道 顶柜玻璃：灰玻 | G181: 整体长度：1200mm/1000mm/800mm 整体深度：480mm 整体高度：1900mm 顶柜长度：1200mm/1000mm/800mm 顶柜深度：380mm 顶柜高度：420mm 立体收纳长度：1200mm/1000mm/800mm 立体收纳深度：380mm 立体收纳高度：650mm 下柜长度：1200mm/1000mm/800mm 下柜深度：480mm 下柜高度：880mm | H181: 0 | I181: 0 | J181: 0.48 | K181: =IFERROR(H181,0) | P181: =IFERROR(IF(K181=0,"待填成本",ROUND(K181/(1-L181),0)),"" ) | Q181: =IFERROR(IF(K181=0,"待填成本",ROUND(K181/(1-M181),0)),"" ) | R181: =IFERROR(IF(K181=0,"待填成本",ROUND(K181/(1-N181),0)),"" ) | S181: =IFERROR(IF(K181=0,"待填成本",ROUND(K181/(1-O181),0)),"" ) | T181: =IFERROR(IF(K181=0,"",(P181-K181)/P181),"" ) | U181: =IFERROR(IF(K181=0,"",(Q181-K181)/Q181),"" ) | V181: =IFERROR(IF(K181=0,"",(R181-K181)/R181),"" ) | W181: =IFERROR(IF(K181=0,"",(S181-K181)/S181),"" )
A182: 2525012041599 | B182: 餐厅-柜 | C182: 黑胡桃木基础餐边柜 |黑胡桃木鎏金餐边柜 | D182: 鎏金柜-下柜-1.6米 | E182: 北美进口FAS级黑胡桃木 | F182: 抽屉围板：实木多层板 台面：黑色岩板 背板：鎏金板 电力轨道：xpower 内嵌电力轨道 顶柜玻璃：灰玻 | G182: 整体长度：1200mm/1000mm/800mm 整体深度：480mm 整体高度：1900mm 顶柜长度：1200mm/1000mm/800mm 顶柜深度：380mm 顶柜高度：420mm 立体收纳长度：1200mm/1000mm/800mm 立体收纳深度：380mm 立体收纳高度：650mm 下柜长度：1200mm/1000mm/800mm 下柜深度：480mm 下柜高度：880mm | H182: 0 | I182: 0 | J182: 0.48 | K182: =IFERROR(H182,0) | P182: =IFERROR(IF(K182=0,"待填成本",ROUND(K182/(1-L182),0)),"" ) | Q182: =IFERROR(IF(K182=0,"待填成本",ROUND(K182/(1-M182),0)),"" ) | R182: =IFERROR(IF(K182=0,"待填成本",ROUND(K182/(1-N182),0)),"" ) | S182: =IFERROR(IF(K182=0,"待填成本",ROUND(K182/(1-O182),0)),"" ) | T182: =IFERROR(IF(K182=0,"",(P182-K182)/P182),"" ) | U182: =IFERROR(IF(K182=0,"",(Q182-K182)/Q182),"" ) | V182: =IFERROR(IF(K182=0,"",(R182-K182)/R182),"" ) | W182: =IFERROR(IF(K182=0,"",(S182-K182)/S182),"" )
A183: 2525012041599 | B183: 餐厅-柜 | C183: 黑胡桃木基础餐边柜 |黑胡桃木鎏金餐边柜 | D183: 鎏金柜-下柜-1.5米 | E183: 北美进口FAS级黑胡桃木 | F183: 抽屉围板：实木多层板 台面：黑色岩板 背板：鎏金板 电力轨道：xpower 内嵌电力轨道 顶柜玻璃：灰玻 | G183: 整体长度：1200mm/1000mm/800mm 整体深度：480mm 整体高度：1900mm 顶柜长度：1200mm/1000mm/800mm 顶柜深度：380mm 顶柜高度：420mm 立体收纳长度：1200mm/1000mm/800mm 立体收纳深度：380mm 立体收纳高度：650mm 下柜长度：1200mm/1000mm/800mm 下柜深度：480mm 下柜高度：880mm | H183: 0 | I183: 0 | J183: 0.48 | K183: =IFERROR(H183,0) | P183: =IFERROR(IF(K183=0,"待填成本",ROUND(K183/(1-L183),0)),"" ) | Q183: =IFERROR(IF(K183=0,"待填成本",ROUND(K183/(1-M183),0)),"" ) | R183: =IFERROR(IF(K183=0,"待填成本",ROUND(K183/(1-N183),0)),"" ) | S183: =IFERROR(IF(K183=0,"待填成本",ROUND(K183/(1-O183),0)),"" ) | T183: =IFERROR(IF(K183=0,"",(P183-K183)/P183),"" ) | U183: =IFERROR(IF(K183=0,"",(Q183-K183)/Q183),"" ) | V183: =IFERROR(IF(K183=0,"",(R183-K183)/R183),"" ) | W183: =IFERROR(IF(K183=0,"",(S183-K183)/S183),"" )
A184: 2525012041599 | B184: 餐厅-柜 | C184: 黑胡桃木基础餐边柜 |黑胡桃木鎏金餐边柜 | D184: 鎏金柜-下柜-1.4米 | E184: 北美进口FAS级黑胡桃木 | F184: 抽屉围板：实木多层板 台面：黑色岩板 背板：鎏金板 电力轨道：xpower 内嵌电力轨道 顶柜玻璃：灰玻 | G184: 整体长度：1200mm/1000mm/800mm 整体深度：480mm 整体高度：1900mm 顶柜长度：1200mm/1000mm/800mm 顶柜深度：380mm 顶柜高度：420mm 立体收纳长度：1200mm/1000mm/800mm 立体收纳深度：380mm 立体收纳高度：650mm 下柜长度：1200mm/1000mm/800mm 下柜深度：480mm 下柜高度：880mm | H184: 0 | I184: 0 | J184: 0.48 | K184: =IFERROR(H184,0) | P184: =IFERROR(IF(K184=0,"待填成本",ROUND(K184/(1-L184),0)),"" ) | Q184: =IFERROR(IF(K184=0,"待填成本",ROUND(K184/(1-M184),0)),"" ) | R184: =IFERROR(IF(K184=0,"待填成本",ROUND(K184/(1-N184),0)),"" ) | S184: =IFERROR(IF(K184=0,"待填成本",ROUND(K184/(1-O184),0)),"" ) | T184: =IFERROR(IF(K184=0,"",(P184-K184)/P184),"" ) | U184: =IFERROR(IF(K184=0,"",(Q184-K184)/Q184),"" ) | V184: =IFERROR(IF(K184=0,"",(R184-K184)/R184),"" ) | W184: =IFERROR(IF(K184=0,"",(S184-K184)/S184),"" )
A185: 2525012041599 | B185: 餐厅-柜 | C185: 黑胡桃木基础餐边柜 |黑胡桃木鎏金餐边柜 | D185: 鎏金柜-下柜-1.3米 | E185: 北美进口FAS级黑胡桃木 | F185: 抽屉围板：实木多层板 台面：黑色岩板 背板：鎏金板 电力轨道：xpower 内嵌电力轨道 顶柜玻璃：灰玻 | G185: 整体长度：1200mm/1000mm/800mm 整体深度：480mm 整体高度：1900mm 顶柜长度：1200mm/1000mm/800mm 顶柜深度：380mm 顶柜高度：420mm 立体收纳长度：1200mm/1000mm/800mm 立体收纳深度：380mm 立体收纳高度：650mm 下柜长度：1200mm/1000mm/800mm 下柜深度：480mm 下柜高度：880mm | H185: 0 | I185: 0 | J185: 0.48 | K185: =IFERROR(H185,0) | P185: =IFERROR(IF(K185=0,"待填成本",ROUND(K185/(1-L185),0)),"" ) | Q185: =IFERROR(IF(K185=0,"待填成本",ROUND(K185/(1-M185),0)),"" ) | R185: =IFERROR(IF(K185=0,"待填成本",ROUND(K185/(1-N185),0)),"" ) | S185: =IFERROR(IF(K185=0,"待填成本",ROUND(K185/(1-O185),0)),"" ) | T185: =IFERROR(IF(K185=0,"",(P185-K185)/P185),"" ) | U185: =IFERROR(IF(K185=0,"",(Q185-K185)/Q185),"" ) | V185: =IFERROR(IF(K185=0,"",(R185-K185)/R185),"" ) | W185: =IFERROR(IF(K185=0,"",(S185-K185)/S185),"" )
A186: 2525012041599 | B186: 餐厅-柜 | C186: 黑胡桃木基础餐边柜 |黑胡桃木鎏金餐边柜 | D186: 鎏金柜-下柜-1.2米 | E186: 北美进口FAS级黑胡桃木 | F186: 抽屉围板：实木多层板 台面：黑色岩板 背板：鎏金板 电力轨道：xpower 内嵌电力轨道 顶柜玻璃：灰玻 | G186: 整体长度：1200mm/1000mm/800mm 整体深度：480mm 整体高度：1900mm 顶柜长度：1200mm/1000mm/800mm 顶柜深度：380mm 顶柜高度：420mm 立体收纳长度：1200mm/1000mm/800mm 立体收纳深度：380mm 立体收纳高度：650mm 下柜长度：1200mm/1000mm/800mm 下柜深度：480mm 下柜高度：880mm | H186: 0 | I186: 0 | J186: 0.48 | K186: =IFERROR(H186,0) | P186: =IFERROR(IF(K186=0,"待填成本",ROUND(K186/(1-L186),0)),"" ) | Q186: =IFERROR(IF(K186=0,"待填成本",ROUND(K186/(1-M186),0)),"" ) | R186: =IFERROR(IF(K186=0,"待填成本",ROUND(K186/(1-N186),0)),"" ) | S186: =IFERROR(IF(K186=0,"待填成本",ROUND(K186/(1-O186),0)),"" ) | T186: =IFERROR(IF(K186=0,"",(P186-K186)/P186),"" ) | U186: =IFERROR(IF(K186=0,"",(Q186-K186)/Q186),"" ) | V186: =IFERROR(IF(K186=0,"",(R186-K186)/R186),"" ) | W186: =IFERROR(IF(K186=0,"",(S186-K186)/S186),"" )
A187: 2525012041599 | B187: 餐厅-柜 | C187: 黑胡桃木基础餐边柜 |黑胡桃木鎏金餐边柜 | D187: 鎏金柜-整柜-2.1米 | E187: 北美进口FAS级黑胡桃木 | F187: 抽屉围板：实木多层板 台面：黑色岩板 背板：鎏金板 电力轨道：xpower 内嵌电力轨道 顶柜玻璃：灰玻 | G187: 整体长度：1200mm/1000mm/800mm 整体深度：480mm 整体高度：1900mm 顶柜长度：1200mm/1000mm/800mm 顶柜深度：380mm 顶柜高度：420mm 立体收纳长度：1200mm/1000mm/800mm 立体收纳深度：380mm 立体收纳高度：650mm 下柜长度：1200mm/1000mm/800mm 下柜深度：480mm 下柜高度：880mm | H187: 9959.9633 | I187: 7900 | J187: 0.48 | K187: =IFERROR(H187,0) | L187: 0.4669 | M187: 0.2701 | N187: 0.2801 | O187: 0.2403 | P187: =IFERROR(IF(K187=0,"待填成本",ROUND(K187/(1-L187),0)),"" ) | Q187: =IFERROR(IF(K187=0,"待填成本",ROUND(K187/(1-M187),0)),"" ) | R187: =IFERROR(IF(K187=0,"待填成本",ROUND(K187/(1-N187),0)),"" ) | S187: =IFERROR(IF(K187=0,"待填成本",ROUND(K187/(1-O187),0)),"" ) | T187: =IFERROR(IF(K187=0,"",(P187-K187)/P187),"" ) | U187: =IFERROR(IF(K187=0,"",(Q187-K187)/Q187),"" ) | V187: =IFERROR(IF(K187=0,"",(R187-K187)/R187),"" ) | W187: =IFERROR(IF(K187=0,"",(S187-K187)/S187),"" ) | AA187: 25.32875 | AB187: 10.95375 | AC187: 31.3375 | AD187: 300 | AE187: 150
A188: 2525012041599 | B188: 餐厅-柜 | C188: 黑胡桃木基础餐边柜 |黑胡桃木鎏金餐边柜 | D188: 鎏金柜-整柜-2.0米 | E188: 北美进口FAS级黑胡桃木 | F188: 抽屉围板：实木多层板 台面：黑色岩板 背板：鎏金板 电力轨道：xpower 内嵌电力轨道 顶柜玻璃：灰玻 | G188: 整体长度：1200mm/1000mm/800mm 整体深度：480mm 整体高度：1900mm 顶柜长度：1200mm/1000mm/800mm 顶柜深度：380mm 顶柜高度：420mm 立体收纳长度：1200mm/1000mm/800mm 立体收纳深度：380mm 立体收纳高度：650mm 下柜长度：1200mm/1000mm/800mm 下柜深度：480mm 下柜高度：880mm | H188: 9772.9633 | I188: 7800 | J188: 0.48 | K188: =IFERROR(H188,0) | L188: 0.4668 | M188: 0.2701 | N188: 0.2802 | O188: 0.2402 | P188: =IFERROR(IF(K188=0,"待填成本",ROUND(K188/(1-L188),0)),"" ) | Q188: =IFERROR(IF(K188=0,"待填成本",ROUND(K188/(1-M188),0)),"" ) | R188: =IFERROR(IF(K188=0,"待填成本",ROUND(K188/(1-N188),0)),"" ) | S188: =IFERROR(IF(K188=0,"待填成本",ROUND(K188/(1-O188),0)),"" ) | T188: =IFERROR(IF(K188=0,"",(P188-K188)/P188),"" ) | U188: =IFERROR(IF(K188=0,"",(Q188-K188)/Q188),"" ) | V188: =IFERROR(IF(K188=0,"",(R188-K188)/R188),"" ) | W188: =IFERROR(IF(K188=0,"",(S188-K188)/S188),"" ) | AA188: 24.533333 | AB188: 10.6375 | AC188: 31.05 | AD188: 300 | AE188: 150
A189: 2525012041599 | B189: 餐厅-柜 | C189: 黑胡桃木基础餐边柜 |黑胡桃木鎏金餐边柜 | D189: 鎏金柜-整柜-1.9米 | E189: 北美进口FAS级黑胡桃木 | F189: 抽屉围板：实木多层板 台面：黑色岩板 背板：鎏金板 电力轨道：xpower 内嵌电力轨道 顶柜玻璃：灰玻 | G189: 整体长度：1200mm/1000mm/800mm 整体深度：480mm 整体高度：1900mm 顶柜长度：1200mm/1000mm/800mm 顶柜深度：380mm 顶柜高度：420mm 立体收纳长度：1200mm/1000mm/800mm 立体收纳深度：380mm 立体收纳高度：650mm 下柜长度：1200mm/1000mm/800mm 下柜深度：480mm 下柜高度：880mm | H189: 9585.9633 | I189: 7700 | J189: 0.48 | K189: =IFERROR(H189,0) | L189: 0.4668 | M189: 0.2701 | N189: 0.2802 | O189: 0.2402 | P189: =IFERROR(IF(K189=0,"待填成本",ROUND(K189/(1-L189),0)),"" ) | Q189: =IFERROR(IF(K189=0,"待填成本",ROUND(K189/(1-M189),0)),"" ) | R189: =IFERROR(IF(K189=0,"待填成本",ROUND(K189/(1-N189),0)),"" ) | S189: =IFERROR(IF(K189=0,"待填成本",ROUND(K189/(1-O189),0)),"" ) | T189: =IFERROR(IF(K189=0,"",(P189-K189)/P189),"" ) | U189: =IFERROR(IF(K189=0,"",(Q189-K189)/Q189),"" ) | V189: =IFERROR(IF(K189=0,"",(R189-K189)/R189),"" ) | W189: =IFERROR(IF(K189=0,"",(S189-K189)/S189),"" ) | AA189: 23.737917 | AB189: 10.32125 | AC189: 30.7625 | AD189: 300 | AE189: 150
A190: 2525012041599 | B190: 餐厅-柜 | C190: 黑胡桃木基础餐边柜 |黑胡桃木鎏金餐边柜 | D190: 鎏金柜-整柜-1.8米 | E190: 北美进口FAS级黑胡桃木 | F190: 抽屉围板：实木多层板 台面：黑色岩板 背板：鎏金板 电力轨道：xpower 内嵌电力轨道 顶柜玻璃：灰玻 | G190: 整体长度：1200mm/1000mm/800mm 整体深度：480mm 整体高度：1900mm 顶柜长度：1200mm/1000mm/800mm 顶柜深度：380mm 顶柜高度：420mm 立体收纳长度：1200mm/1000mm/800mm 立体收纳深度：380mm 立体收纳高度：650mm 下柜长度：1200mm/1000mm/800mm 下柜深度：480mm 下柜高度：880mm | H190: 9398.9633 | I190: 7600 | J190: 0.48 | K190: =IFERROR(H190,0) | L190: 0.4668 | M190: 0.2702 | N190: 0.2803 | O190: 0.2401 | P190: =IFERROR(IF(K190=0,"待填成本",ROUND(K190/(1-L190),0)),"" ) | Q190: =IFERROR(IF(K190=0,"待填成本",ROUND(K190/(1-M190),0)),"" ) | R190: =IFERROR(IF(K190=0,"待填成本",ROUND(K190/(1-N190),0)),"" ) | S190: =IFERROR(IF(K190=0,"待填成本",ROUND(K190/(1-O190),0)),"" ) | T190: =IFERROR(IF(K190=0,"",(P190-K190)/P190),"" ) | U190: =IFERROR(IF(K190=0,"",(Q190-K190)/Q190),"" ) | V190: =IFERROR(IF(K190=0,"",(R190-K190)/R190),"" ) | W190: =IFERROR(IF(K190=0,"",(S190-K190)/S190),"" ) | AA190: 22.9425 | AB190: 10.005 | AC190: 30.475 | AD190: 300 | AE190: 150
A191: 2525012041599 | B191: 餐厅-柜 | C191: 黑胡桃木基础餐边柜 |黑胡桃木鎏金餐边柜 | D191: 鎏金柜-整柜-1.7米 | E191: 北美进口FAS级黑胡桃木 | F191: 抽屉围板：实木多层板 台面：黑色岩板 背板：鎏金板 电力轨道：xpower 内嵌电力轨道 顶柜玻璃：灰玻 | G191: 整体长度：1200mm/1000mm/800mm 整体深度：480mm 整体高度：1900mm 顶柜长度：1200mm/1000mm/800mm 顶柜深度：380mm 顶柜高度：420mm 立体收纳长度：1200mm/1000mm/800mm 立体收纳深度：380mm 立体收纳高度：650mm 下柜长度：1200mm/1000mm/800mm 下柜深度：480mm 下柜高度：880mm | H191: 9244.9367 | I191: 7500 | J191: 0.48 | K191: =IFERROR(H191,0) | L191: 0.4668 | M191: 0.2702 | N191: 0.2803 | O191: 0.2401 | P191: =IFERROR(IF(K191=0,"待填成本",ROUND(K191/(1-L191),0)),"" ) | Q191: =IFERROR(IF(K191=0,"待填成本",ROUND(K191/(1-M191),0)),"" ) | R191: =IFERROR(IF(K191=0,"待填成本",ROUND(K191/(1-N191),0)),"" ) | S191: =IFERROR(IF(K191=0,"待填成本",ROUND(K191/(1-O191),0)),"" ) | T191: =IFERROR(IF(K191=0,"",(P191-K191)/P191),"" ) | U191: =IFERROR(IF(K191=0,"",(Q191-K191)/Q191),"" ) | V191: =IFERROR(IF(K191=0,"",(R191-K191)/R191),"" ) | W191: =IFERROR(IF(K191=0,"",(S191-K191)/S191),"" ) | AA191: 22.147083 | AB191: 9.68875 | AC191: 30.1875 | AD191: 300 | AE191: 150
A192: 2525012041599 | B192: 餐厅-柜 | C192: 黑胡桃木基础餐边柜 |黑胡桃木鎏金餐边柜 | D192: 鎏金柜-整柜-1.6米 | E192: 北美进口FAS级黑胡桃木 | F192: 抽屉围板：实木多层板 台面：黑色岩板 背板：鎏金板 电力轨道：xpower 内嵌电力轨道 顶柜玻璃：灰玻 | G192: 整体长度：1200mm/1000mm/800mm 整体深度：480mm 整体高度：1900mm 顶柜长度：1200mm/1000mm/800mm 顶柜深度：380mm 顶柜高度：420mm 立体收纳长度：1200mm/1000mm/800mm 立体收纳深度：380mm 立体收纳高度：650mm 下柜长度：1200mm/1000mm/800mm 下柜深度：480mm 下柜高度：880mm | H192: 9090.91 | I192: 7400 | J192: 0.48 | K192: =IFERROR(H192,0) | L192: 0.4668 | M192: 0.2701 | N192: 0.2804 | O192: 0.2401 | P192: =IFERROR(IF(K192=0,"待填成本",ROUND(K192/(1-L192),0)),"" ) | Q192: =IFERROR(IF(K192=0,"待填成本",ROUND(K192/(1-M192),0)),"" ) | R192: =IFERROR(IF(K192=0,"待填成本",ROUND(K192/(1-N192),0)),"" ) | S192: =IFERROR(IF(K192=0,"待填成本",ROUND(K192/(1-O192),0)),"" ) | T192: =IFERROR(IF(K192=0,"",(P192-K192)/P192),"" ) | U192: =IFERROR(IF(K192=0,"",(Q192-K192)/Q192),"" ) | V192: =IFERROR(IF(K192=0,"",(R192-K192)/R192),"" ) | W192: =IFERROR(IF(K192=0,"",(S192-K192)/S192),"" ) | AA192: 21.351667 | AB192: 9.3725 | AC192: 29.9 | AD192: 300 | AE192: 150
A193: 2525012041599 | B193: 餐厅-柜 | C193: 黑胡桃木基础餐边柜 |黑胡桃木鎏金餐边柜 | D193: 鎏金柜-整柜-1.5米 | E193: 北美进口FAS级黑胡桃木 | F193: 抽屉围板：实木多层板 台面：黑色岩板 背板：鎏金板 电力轨道：xpower 内嵌电力轨道 顶柜玻璃：灰玻 | G193: 整体长度：1200mm/1000mm/800mm 整体深度：480mm 整体高度：1900mm 顶柜长度：1200mm/1000mm/800mm 顶柜深度：380mm 顶柜高度：420mm 立体收纳长度：1200mm/1000mm/800mm 立体收纳深度：380mm 立体收纳高度：650mm 下柜长度：1200mm/1000mm/800mm 下柜深度：480mm 下柜高度：880mm | H193: 8936.8833 | I193: 7300 | J193: 0.48 | K193: =IFERROR(H193,0) | L193: 0.4668 | M193: 0.2701 | N193: 0.2805 | O193: 0.2402 | P193: =IFERROR(IF(K193=0,"待填成本",ROUND(K193/(1-L193),0)),"" ) | Q193: =IFERROR(IF(K193=0,"待填成本",ROUND(K193/(1-M193),0)),"" ) | R193: =IFERROR(IF(K193=0,"待填成本",ROUND(K193/(1-N193),0)),"" ) | S193: =IFERROR(IF(K193=0,"待填成本",ROUND(K193/(1-O193),0)),"" ) | T193: =IFERROR(IF(K193=0,"",(P193-K193)/P193),"" ) | U193: =IFERROR(IF(K193=0,"",(Q193-K193)/Q193),"" ) | V193: =IFERROR(IF(K193=0,"",(R193-K193)/R193),"" ) | W193: =IFERROR(IF(K193=0,"",(S193-K193)/S193),"" ) | AA193: 20.55625 | AB193: 9.05625 | AC193: 29.6125 | AD193: 300 | AE193: 150
A194: 2525012041599 | B194: 餐厅-柜 | C194: 黑胡桃木基础餐边柜 |黑胡桃木鎏金餐边柜 | D194: 鎏金柜-整柜-1.4米 | E194: 北美进口FAS级黑胡桃木 | F194: 抽屉围板：实木多层板 台面：黑色岩板 背板：鎏金板 电力轨道：xpower 内嵌电力轨道 顶柜玻璃：灰玻 | G194: 整体长度：1200mm/1000mm/800mm 整体深度：480mm 整体高度：1900mm 顶柜长度：1200mm/1000mm/800mm 顶柜深度：380mm 顶柜高度：420mm 立体收纳长度：1200mm/1000mm/800mm 立体收纳深度：380mm 立体收纳高度：650mm 下柜长度：1200mm/1000mm/800mm 下柜深度：480mm 下柜高度：880mm | H194: 8773.2433 | I194: 7200 | J194: 0.48 | K194: =IFERROR(H194,0) | L194: 0.4668 | M194: 0.2702 | N194: 0.2804 | O194: 0.2402 | P194: =IFERROR(IF(K194=0,"待填成本",ROUND(K194/(1-L194),0)),"" ) | Q194: =IFERROR(IF(K194=0,"待填成本",ROUND(K194/(1-M194),0)),"" ) | R194: =IFERROR(IF(K194=0,"待填成本",ROUND(K194/(1-N194),0)),"" ) | S194: =IFERROR(IF(K194=0,"待填成本",ROUND(K194/(1-O194),0)),"" ) | T194: =IFERROR(IF(K194=0,"",(P194-K194)/P194),"" ) | U194: =IFERROR(IF(K194=0,"",(Q194-K194)/Q194),"" ) | V194: =IFERROR(IF(K194=0,"",(R194-K194)/R194),"" ) | W194: =IFERROR(IF(K194=0,"",(S194-K194)/S194),"" ) | AA194: 20.24 | AB194: 8.74 | AC194: 29.325 | AD194: 300 | AE194: 150
A195: 2525012041599 | B195: 餐厅-柜 | C195: 黑胡桃木基础餐边柜 |黑胡桃木鎏金餐边柜 | D195: 鎏金柜-整柜-1.3米 | E195: 北美进口FAS级黑胡桃木 | F195: 抽屉围板：实木多层板 台面：黑色岩板 背板：鎏金板 电力轨道：xpower 内嵌电力轨道 顶柜玻璃：灰玻 | G195: 整体长度：1200mm/1000mm/800mm 整体深度：480mm 整体高度：1900mm 顶柜长度：1200mm/1000mm/800mm 顶柜深度：380mm 顶柜高度：420mm 立体收纳长度：1200mm/1000mm/800mm 立体收纳深度：380mm 立体收纳高度：650mm 下柜长度：1200mm/1000mm/800mm 下柜深度：480mm 下柜高度：880mm | H195: 8609.6033 | I195: 7100 | J195: 0.48 | K195: =IFERROR(H195,0) | L195: 0.4669 | M195: 0.2703 | N195: 0.2803 | O195: 0.2401 | P195: =IFERROR(IF(K195=0,"待填成本",ROUND(K195/(1-L195),0)),"" ) | Q195: =IFERROR(IF(K195=0,"待填成本",ROUND(K195/(1-M195),0)),"" ) | R195: =IFERROR(IF(K195=0,"待填成本",ROUND(K195/(1-N195),0)),"" ) | S195: =IFERROR(IF(K195=0,"待填成本",ROUND(K195/(1-O195),0)),"" ) | T195: =IFERROR(IF(K195=0,"",(P195-K195)/P195),"" ) | U195: =IFERROR(IF(K195=0,"",(Q195-K195)/Q195),"" ) | V195: =IFERROR(IF(K195=0,"",(R195-K195)/R195),"" ) | W195: =IFERROR(IF(K195=0,"",(S195-K195)/S195),"" ) | AA195: 19.92375 | AB195: 8.42375 | AC195: 29.0375 | AD195: 300 | AE195: 150
A196: 2525012041599 | B196: 餐厅-柜 | C196: 黑胡桃木基础餐边柜 |黑胡桃木鎏金餐边柜 | D196: 鎏金柜-整柜-1.2米 | E196: 北美进口FAS级黑胡桃木 | F196: 抽屉围板：实木多层板 台面：黑色岩板 背板：鎏金板 电力轨道：xpower 内嵌电力轨道 顶柜玻璃：灰玻 | G196: 整体长度：1200mm/1000mm/800mm 整体深度：480mm 整体高度：1900mm 顶柜长度：1200mm/1000mm/800mm 顶柜深度：380mm 顶柜高度：420mm 立体收纳长度：1200mm/1000mm/800mm 立体收纳深度：380mm 立体收纳高度：650mm 下柜长度：1200mm/1000mm/800mm 下柜深度：480mm 下柜高度：880mm | H196: 8445.9633 | I196: 7000 | J196: 0.48 | K196: =IFERROR(H196,0) | L196: 0.4669 | M196: 0.2703 | N196: 0.2802 | O196: 0.2401 | P196: =IFERROR(IF(K196=0,"待填成本",ROUND(K196/(1-L196),0)),"" ) | Q196: =IFERROR(IF(K196=0,"待填成本",ROUND(K196/(1-M196),0)),"" ) | R196: =IFERROR(IF(K196=0,"待填成本",ROUND(K196/(1-N196),0)),"" ) | S196: =IFERROR(IF(K196=0,"待填成本",ROUND(K196/(1-O196),0)),"" ) | T196: =IFERROR(IF(K196=0,"",(P196-K196)/P196),"" ) | U196: =IFERROR(IF(K196=0,"",(Q196-K196)/Q196),"" ) | V196: =IFERROR(IF(K196=0,"",(R196-K196)/R196),"" ) | W196: =IFERROR(IF(K196=0,"",(S196-K196)/S196),"" ) | AA196: 19.6075 | AB196: 8.1075 | AC196: 28.75 | AD196: 300 | AE196: 150
A197: 2525013042099 | B197: 餐厅-柜 | C197: 黑胡桃木太空舱餐边柜 |黑胡桃木曜黑餐边柜 | D197: 曜黑柜-下柜-2.1米 | E197: 北美进口FAS级黑胡桃木 | F197: 抽屉围板：实木多层板 台面：黑色岩板 背板：鎏金板 电力轨道：xpower 内嵌电力轨道 顶柜玻璃：灰玻 | G197: 整体长度：1200mm/1000mm/800mm 整体深度：480mm 整体高度：1900mm 顶柜长度：1200mm/1000mm/800mm 顶柜深度：400mm 顶柜高度：355mm 立体收纳长度：1200mm/1000mm/800mm 立体收纳深度：400mm 立体收纳高度：675mm 下柜长度：1200mm/1000mm/800mm 下柜深度：480mm 下柜高度：880mm | H197: 0 | I197: 0 | J197: 0.48 | K197: =IFERROR(H197,0) | P197: =IFERROR(IF(K197=0,"待填成本",ROUND(K197/(1-L197),0)),"" ) | Q197: =IFERROR(IF(K197=0,"待填成本",ROUND(K197/(1-M197),0)),"" ) | R197: =IFERROR(IF(K197=0,"待填成本",ROUND(K197/(1-N197),0)),"" ) | S197: =IFERROR(IF(K197=0,"待填成本",ROUND(K197/(1-O197),0)),"" ) | T197: =IFERROR(IF(K197=0,"",(P197-K197)/P197),"" ) | U197: =IFERROR(IF(K197=0,"",(Q197-K197)/Q197),"" ) | V197: =IFERROR(IF(K197=0,"",(R197-K197)/R197),"" ) | W197: =IFERROR(IF(K197=0,"",(S197-K197)/S197),"" )
A198: 2525013042099 | B198: 餐厅-柜 | C198: 黑胡桃木太空舱餐边柜 |黑胡桃木曜黑餐边柜 | D198: 曜黑柜-下柜-2.0米 | E198: 北美进口FAS级黑胡桃木 | F198: 抽屉围板：实木多层板 台面：黑色岩板 背板：鎏金板 电力轨道：xpower 内嵌电力轨道 顶柜玻璃：灰玻 | G198: 整体长度：1200mm/1000mm/800mm 整体深度：480mm 整体高度：1900mm 顶柜长度：1200mm/1000mm/800mm 顶柜深度：400mm 顶柜高度：355mm 立体收纳长度：1200mm/1000mm/800mm 立体收纳深度：400mm 立体收纳高度：675mm 下柜长度：1200mm/1000mm/800mm 下柜深度：480mm 下柜高度：880mm | H198: 0 | I198: 0 | J198: 0.48 | K198: =IFERROR(H198,0) | P198: =IFERROR(IF(K198=0,"待填成本",ROUND(K198/(1-L198),0)),"" ) | Q198: =IFERROR(IF(K198=0,"待填成本",ROUND(K198/(1-M198),0)),"" ) | R198: =IFERROR(IF(K198=0,"待填成本",ROUND(K198/(1-N198),0)),"" ) | S198: =IFERROR(IF(K198=0,"待填成本",ROUND(K198/(1-O198),0)),"" ) | T198: =IFERROR(IF(K198=0,"",(P198-K198)/P198),"" ) | U198: =IFERROR(IF(K198=0,"",(Q198-K198)/Q198),"" ) | V198: =IFERROR(IF(K198=0,"",(R198-K198)/R198),"" ) | W198: =IFERROR(IF(K198=0,"",(S198-K198)/S198),"" )
A199: 2525013042099 | B199: 餐厅-柜 | C199: 黑胡桃木太空舱餐边柜 |黑胡桃木曜黑餐边柜 | D199: 曜黑柜-下柜-1.9米 | E199: 北美进口FAS级黑胡桃木 | F199: 抽屉围板：实木多层板 台面：黑色岩板 背板：鎏金板 电力轨道：xpower 内嵌电力轨道 顶柜玻璃：灰玻 | G199: 整体长度：1200mm/1000mm/800mm 整体深度：480mm 整体高度：1900mm 顶柜长度：1200mm/1000mm/800mm 顶柜深度：400mm 顶柜高度：355mm 立体收纳长度：1200mm/1000mm/800mm 立体收纳深度：400mm 立体收纳高度：675mm 下柜长度：1200mm/1000mm/800mm 下柜深度：480mm 下柜高度：880mm | H199: 0 | I199: 0 | J199: 0.48 | K199: =IFERROR(H199,0) | P199: =IFERROR(IF(K199=0,"待填成本",ROUND(K199/(1-L199),0)),"" ) | Q199: =IFERROR(IF(K199=0,"待填成本",ROUND(K199/(1-M199),0)),"" ) | R199: =IFERROR(IF(K199=0,"待填成本",ROUND(K199/(1-N199),0)),"" ) | S199: =IFERROR(IF(K199=0,"待填成本",ROUND(K199/(1-O199),0)),"" ) | T199: =IFERROR(IF(K199=0,"",(P199-K199)/P199),"" ) | U199: =IFERROR(IF(K199=0,"",(Q199-K199)/Q199),"" ) | V199: =IFERROR(IF(K199=0,"",(R199-K199)/R199),"" ) | W199: =IFERROR(IF(K199=0,"",(S199-K199)/S199),"" )
A200: 2525013042099 | B200: 餐厅-柜 | C200: 黑胡桃木太空舱餐边柜 |黑胡桃木曜黑餐边柜 | D200: 曜黑柜-下柜-1.8米 | E200: 北美进口FAS级黑胡桃木 | F200: 抽屉围板：实木多层板 台面：黑色岩板 背板：鎏金板 电力轨道：xpower 内嵌电力轨道 顶柜玻璃：灰玻 | G200: 整体长度：1200mm/1000mm/800mm 整体深度：480mm 整体高度：1900mm 顶柜长度：1200mm/1000mm/800mm 顶柜深度：400mm 顶柜高度：355mm 立体收纳长度：1200mm/1000mm/800mm 立体收纳深度：400mm 立体收纳高度：675mm 下柜长度：1200mm/1000mm/800mm 下柜深度：480mm 下柜高度：880mm | H200: 0 | I200: 0 | J200: 0.48 | K200: =IFERROR(H200,0) | P200: =IFERROR(IF(K200=0,"待填成本",ROUND(K200/(1-L200),0)),"" ) | Q200: =IFERROR(IF(K200=0,"待填成本",ROUND(K200/(1-M200),0)),"" ) | R200: =IFERROR(IF(K200=0,"待填成本",ROUND(K200/(1-N200),0)),"" ) | S200: =IFERROR(IF(K200=0,"待填成本",ROUND(K200/(1-O200),0)),"" ) | T200: =IFERROR(IF(K200=0,"",(P200-K200)/P200),"" ) | U200: =IFERROR(IF(K200=0,"",(Q200-K200)/Q200),"" ) | V200: =IFERROR(IF(K200=0,"",(R200-K200)/R200),"" ) | W200: =IFERROR(IF(K200=0,"",(S200-K200)/S200),"" )
A201: 2525013042099 | B201: 餐厅-柜 | C201: 黑胡桃木太空舱餐边柜 |黑胡桃木曜黑餐边柜 | D201: 曜黑柜-下柜-1.7米 | E201: 北美进口FAS级黑胡桃木 | F201: 抽屉围板：实木多层板 台面：黑色岩板 背板：鎏金板 电力轨道：xpower 内嵌电力轨道 顶柜玻璃：灰玻 | G201: 整体长度：1200mm/1000mm/800mm 整体深度：480mm 整体高度：1900mm 顶柜长度：1200mm/1000mm/800mm 顶柜深度：400mm 顶柜高度：355mm 立体收纳长度：1200mm/1000mm/800mm 立体收纳深度：400mm 立体收纳高度：675mm 下柜长度：1200mm/1000mm/800mm 下柜深度：480mm 下柜高度：880mm | H201: 0 | I201: 0 | J201: 0.48 | K201: =IFERROR(H201,0) | P201: =IFERROR(IF(K201=0,"待填成本",ROUND(K201/(1-L201),0)),"" ) | Q201: =IFERROR(IF(K201=0,"待填成本",ROUND(K201/(1-M201),0)),"" ) | R201: =IFERROR(IF(K201=0,"待填成本",ROUND(K201/(1-N201),0)),"" ) | S201: =IFERROR(IF(K201=0,"待填成本",ROUND(K201/(1-O201),0)),"" ) | T201: =IFERROR(IF(K201=0,"",(P201-K201)/P201),"" ) | U201: =IFERROR(IF(K201=0,"",(Q201-K201)/Q201),"" ) | V201: =IFERROR(IF(K201=0,"",(R201-K201)/R201),"" ) | W201: =IFERROR(IF(K201=0,"",(S201-K201)/S201),"" )
A202: 2525013042099 | B202: 餐厅-柜 | C202: 黑胡桃木太空舱餐边柜 |黑胡桃木曜黑餐边柜 | D202: 曜黑柜-下柜-1.6米 | E202: 北美进口FAS级黑胡桃木 | F202: 抽屉围板：实木多层板 台面：黑色岩板 背板：鎏金板 电力轨道：xpower 内嵌电力轨道 顶柜玻璃：灰玻 | G202: 整体长度：1200mm/1000mm/800mm 整体深度：480mm 整体高度：1900mm 顶柜长度：1200mm/1000mm/800mm 顶柜深度：400mm 顶柜高度：355mm 立体收纳长度：1200mm/1000mm/800mm 立体收纳深度：400mm 立体收纳高度：675mm 下柜长度：1200mm/1000mm/800mm 下柜深度：480mm 下柜高度：880mm | H202: 0 | I202: 0 | J202: 0.48 | K202: =IFERROR(H202,0) | P202: =IFERROR(IF(K202=0,"待填成本",ROUND(K202/(1-L202),0)),"" ) | Q202: =IFERROR(IF(K202=0,"待填成本",ROUND(K202/(1-M202),0)),"" ) | R202: =IFERROR(IF(K202=0,"待填成本",ROUND(K202/(1-N202),0)),"" ) | S202: =IFERROR(IF(K202=0,"待填成本",ROUND(K202/(1-O202),0)),"" ) | T202: =IFERROR(IF(K202=0,"",(P202-K202)/P202),"" ) | U202: =IFERROR(IF(K202=0,"",(Q202-K202)/Q202),"" ) | V202: =IFERROR(IF(K202=0,"",(R202-K202)/R202),"" ) | W202: =IFERROR(IF(K202=0,"",(S202-K202)/S202),"" )
A203: 2525013042099 | B203: 餐厅-柜 | C203: 黑胡桃木太空舱餐边柜 |黑胡桃木曜黑餐边柜 | D203: 曜黑柜-下柜-1.5米 | E203: 北美进口FAS级黑胡桃木 | F203: 抽屉围板：实木多层板 台面：黑色岩板 背板：鎏金板 电力轨道：xpower 内嵌电力轨道 顶柜玻璃：灰玻 | G203: 整体长度：1200mm/1000mm/800mm 整体深度：480mm 整体高度：1900mm 顶柜长度：1200mm/1000mm/800mm 顶柜深度：400mm 顶柜高度：355mm 立体收纳长度：1200mm/1000mm/800mm 立体收纳深度：400mm 立体收纳高度：675mm 下柜长度：1200mm/1000mm/800mm 下柜深度：480mm 下柜高度：880mm | H203: 0 | I203: 0 | J203: 0.48 | K203: =IFERROR(H203,0) | P203: =IFERROR(IF(K203=0,"待填成本",ROUND(K203/(1-L203),0)),"" ) | Q203: =IFERROR(IF(K203=0,"待填成本",ROUND(K203/(1-M203),0)),"" ) | R203: =IFERROR(IF(K203=0,"待填成本",ROUND(K203/(1-N203),0)),"" ) | S203: =IFERROR(IF(K203=0,"待填成本",ROUND(K203/(1-O203),0)),"" ) | T203: =IFERROR(IF(K203=0,"",(P203-K203)/P203),"" ) | U203: =IFERROR(IF(K203=0,"",(Q203-K203)/Q203),"" ) | V203: =IFERROR(IF(K203=0,"",(R203-K203)/R203),"" ) | W203: =IFERROR(IF(K203=0,"",(S203-K203)/S203),"" )
A204: 2525013042099 | B204: 餐厅-柜 | C204: 黑胡桃木太空舱餐边柜 |黑胡桃木曜黑餐边柜 | D204: 曜黑柜-下柜-1.4米 | E204: 北美进口FAS级黑胡桃木 | F204: 抽屉围板：实木多层板 台面：黑色岩板 背板：鎏金板 电力轨道：xpower 内嵌电力轨道 顶柜玻璃：灰玻 | G204: 整体长度：1200mm/1000mm/800mm 整体深度：480mm 整体高度：1900mm 顶柜长度：1200mm/1000mm/800mm 顶柜深度：400mm 顶柜高度：355mm 立体收纳长度：1200mm/1000mm/800mm 立体收纳深度：400mm 立体收纳高度：675mm 下柜长度：1200mm/1000mm/800mm 下柜深度：480mm 下柜高度：880mm | H204: 0 | I204: 0 | J204: 0.48 | K204: =IFERROR(H204,0) | P204: =IFERROR(IF(K204=0,"待填成本",ROUND(K204/(1-L204),0)),"" ) | Q204: =IFERROR(IF(K204=0,"待填成本",ROUND(K204/(1-M204),0)),"" ) | R204: =IFERROR(IF(K204=0,"待填成本",ROUND(K204/(1-N204),0)),"" ) | S204: =IFERROR(IF(K204=0,"待填成本",ROUND(K204/(1-O204),0)),"" ) | T204: =IFERROR(IF(K204=0,"",(P204-K204)/P204),"" ) | U204: =IFERROR(IF(K204=0,"",(Q204-K204)/Q204),"" ) | V204: =IFERROR(IF(K204=0,"",(R204-K204)/R204),"" ) | W204: =IFERROR(IF(K204=0,"",(S204-K204)/S204),"" )
A205: 2525013042099 | B205: 餐厅-柜 | C205: 黑胡桃木太空舱餐边柜 |黑胡桃木曜黑餐边柜 | D205: 曜黑柜-下柜-1.3米 | E205: 北美进口FAS级黑胡桃木 | F205: 抽屉围板：实木多层板 台面：黑色岩板 背板：鎏金板 电力轨道：xpower 内嵌电力轨道 顶柜玻璃：灰玻 | G205: 整体长度：1200mm/1000mm/800mm 整体深度：480mm 整体高度：1900mm 顶柜长度：1200mm/1000mm/800mm 顶柜深度：400mm 顶柜高度：355mm 立体收纳长度：1200mm/1000mm/800mm 立体收纳深度：400mm 立体收纳高度：675mm 下柜长度：1200mm/1000mm/800mm 下柜深度：480mm 下柜高度：880mm | H205: 0 | I205: 0 | J205: 0.48 | K205: =IFERROR(H205,0) | P205: =IFERROR(IF(K205=0,"待填成本",ROUND(K205/(1-L205),0)),"" ) | Q205: =IFERROR(IF(K205=0,"待填成本",ROUND(K205/(1-M205),0)),"" ) | R205: =IFERROR(IF(K205=0,"待填成本",ROUND(K205/(1-N205),0)),"" ) | S205: =IFERROR(IF(K205=0,"待填成本",ROUND(K205/(1-O205),0)),"" ) | T205: =IFERROR(IF(K205=0,"",(P205-K205)/P205),"" ) | U205: =IFERROR(IF(K205=0,"",(Q205-K205)/Q205),"" ) | V205: =IFERROR(IF(K205=0,"",(R205-K205)/R205),"" ) | W205: =IFERROR(IF(K205=0,"",(S205-K205)/S205),"" )
A206: 2525013042099 | B206: 餐厅-柜 | C206: 黑胡桃木太空舱餐边柜 |黑胡桃木曜黑餐边柜 | D206: 曜黑柜-下柜-1.2米 | E206: 北美进口FAS级黑胡桃木 | F206: 抽屉围板：实木多层板 台面：黑色岩板 背板：鎏金板 电力轨道：xpower 内嵌电力轨道 顶柜玻璃：灰玻 | G206: 整体长度：1200mm/1000mm/800mm 整体深度：480mm 整体高度：1900mm 顶柜长度：1200mm/1000mm/800mm 顶柜深度：400mm 顶柜高度：355mm 立体收纳长度：1200mm/1000mm/800mm 立体收纳深度：400mm 立体收纳高度：675mm 下柜长度：1200mm/1000mm/800mm 下柜深度：480mm 下柜高度：880mm | H206: 0 | I206: 0 | J206: 0.48 | K206: =IFERROR(H206,0) | P206: =IFERROR(IF(K206=0,"待填成本",ROUND(K206/(1-L206),0)),"" ) | Q206: =IFERROR(IF(K206=0,"待填成本",ROUND(K206/(1-M206),0)),"" ) | R206: =IFERROR(IF(K206=0,"待填成本",ROUND(K206/(1-N206),0)),"" ) | S206: =IFERROR(IF(K206=0,"待填成本",ROUND(K206/(1-O206),0)),"" ) | T206: =IFERROR(IF(K206=0,"",(P206-K206)/P206),"" ) | U206: =IFERROR(IF(K206=0,"",(Q206-K206)/Q206),"" ) | V206: =IFERROR(IF(K206=0,"",(R206-K206)/R206),"" ) | W206: =IFERROR(IF(K206=0,"",(S206-K206)/S206),"" )
A207: 2525013042099 | B207: 餐厅-柜 | C207: 黑胡桃木太空舱餐边柜 |黑胡桃木曜黑餐边柜 | D207: 曜黑柜-整柜-2.1米 | E207: 北美进口FAS级黑胡桃木 | F207: 抽屉围板：实木多层板 台面：黑色岩板 背板：鎏金板 电力轨道：xpower 内嵌电力轨道 顶柜玻璃：灰玻 | G207: 整体长度：1200mm/1000mm/800mm 整体深度：480mm 整体高度：1900mm 顶柜长度：1200mm/1000mm/800mm 顶柜深度：400mm 顶柜高度：355mm 立体收纳长度：1200mm/1000mm/800mm 立体收纳深度：400mm 立体收纳高度：675mm 下柜长度：1200mm/1000mm/800mm 下柜深度：480mm 下柜高度：880mm | H207: 10568.488 | I207: 8500 | J207: 0.48 | K207: =IFERROR(H207,0) | L207: 0.4668 | M207: 0.2101 | N207: 0.2402 | O207: 0.2202 | P207: =IFERROR(IF(K207=0,"待填成本",ROUND(K207/(1-L207),0)),"" ) | Q207: =IFERROR(IF(K207=0,"待填成本",ROUND(K207/(1-M207),0)),"" ) | R207: =IFERROR(IF(K207=0,"待填成本",ROUND(K207/(1-N207),0)),"" ) | S207: =IFERROR(IF(K207=0,"待填成本",ROUND(K207/(1-O207),0)),"" ) | T207: =IFERROR(IF(K207=0,"",(P207-K207)/P207),"" ) | U207: =IFERROR(IF(K207=0,"",(Q207-K207)/Q207),"" ) | V207: =IFERROR(IF(K207=0,"",(R207-K207)/R207),"" ) | W207: =IFERROR(IF(K207=0,"",(S207-K207)/S207),"" ) | AA207: 30.36 | AB207: 10.95375 | AC207: 31.3375 | AD207: 300 | AE207: 150
A208: 2525013042099 | B208: 餐厅-柜 | C208: 黑胡桃木太空舱餐边柜 |黑胡桃木曜黑餐边柜 | D208: 曜黑柜-整柜-2.0米 | E208: 北美进口FAS级黑胡桃木 | F208: 抽屉围板：实木多层板 台面：黑色岩板 背板：鎏金板 电力轨道：xpower 内嵌电力轨道 顶柜玻璃：灰玻 | G208: 整体长度：1200mm/1000mm/800mm 整体深度：480mm 整体高度：1900mm 顶柜长度：1200mm/1000mm/800mm 顶柜深度：400mm 顶柜高度：355mm 立体收纳长度：1200mm/1000mm/800mm 立体收纳深度：400mm 立体收纳高度：675mm 下柜长度：1200mm/1000mm/800mm 下柜深度：480mm 下柜高度：880mm | H208: 10381.988 | I208: 8400 | J208: 0.48 | K208: =IFERROR(H208,0) | L208: 0.4668 | M208: 0.2101 | N208: 0.2402 | O208: 0.2202 | P208: =IFERROR(IF(K208=0,"待填成本",ROUND(K208/(1-L208),0)),"" ) | Q208: =IFERROR(IF(K208=0,"待填成本",ROUND(K208/(1-M208),0)),"" ) | R208: =IFERROR(IF(K208=0,"待填成本",ROUND(K208/(1-N208),0)),"" ) | S208: =IFERROR(IF(K208=0,"待填成本",ROUND(K208/(1-O208),0)),"" ) | T208: =IFERROR(IF(K208=0,"",(P208-K208)/P208),"" ) | U208: =IFERROR(IF(K208=0,"",(Q208-K208)/Q208),"" ) | V208: =IFERROR(IF(K208=0,"",(R208-K208)/R208),"" ) | W208: =IFERROR(IF(K208=0,"",(S208-K208)/S208),"" ) | AA208: 29.325 | AB208: 10.6375 | AC208: 31.05 | AD208: 300 | AE208: 150
A209: 2525013042099 | B209: 餐厅-柜 | C209: 黑胡桃木太空舱餐边柜 |黑胡桃木曜黑餐边柜 | D209: 曜黑柜-整柜-1.9米 | E209: 北美进口FAS级黑胡桃木 | F209: 抽屉围板：实木多层板 台面：黑色岩板 背板：鎏金板 电力轨道：xpower 内嵌电力轨道 顶柜玻璃：灰玻 | G209: 整体长度：1200mm/1000mm/800mm 整体深度：480mm 整体高度：1900mm 顶柜长度：1200mm/1000mm/800mm 顶柜深度：400mm 顶柜高度：355mm 立体收纳长度：1200mm/1000mm/800mm 立体收纳深度：400mm 立体收纳高度：675mm 下柜长度：1200mm/1000mm/800mm 下柜深度：480mm 下柜高度：880mm | H209: 10195.488 | I209: 8300 | J209: 0.48 | K209: =IFERROR(H209,0) | L209: 0.4668 | M209: 0.2101 | N209: 0.2403 | O209: 0.2203 | P209: =IFERROR(IF(K209=0,"待填成本",ROUND(K209/(1-L209),0)),"" ) | Q209: =IFERROR(IF(K209=0,"待填成本",ROUND(K209/(1-M209),0)),"" ) | R209: =IFERROR(IF(K209=0,"待填成本",ROUND(K209/(1-N209),0)),"" ) | S209: =IFERROR(IF(K209=0,"待填成本",ROUND(K209/(1-O209),0)),"" ) | T209: =IFERROR(IF(K209=0,"",(P209-K209)/P209),"" ) | U209: =IFERROR(IF(K209=0,"",(Q209-K209)/Q209),"" ) | V209: =IFERROR(IF(K209=0,"",(R209-K209)/R209),"" ) | W209: =IFERROR(IF(K209=0,"",(S209-K209)/S209),"" ) | AA209: 28.29 | AB209: 10.32125 | AC209: 30.7625 | AD209: 300 | AE209: 150
A210: 2525013042099 | B210: 餐厅-柜 | C210: 黑胡桃木太空舱餐边柜 |黑胡桃木曜黑餐边柜 | D210: 曜黑柜-整柜-1.8米 | E210: 北美进口FAS级黑胡桃木 | F210: 抽屉围板：实木多层板 台面：黑色岩板 背板：鎏金板 电力轨道：xpower 内嵌电力轨道 顶柜玻璃：灰玻 | G210: 整体长度：1200mm/1000mm/800mm 整体深度：480mm 整体高度：1900mm 顶柜长度：1200mm/1000mm/800mm 顶柜深度：400mm 顶柜高度：355mm 立体收纳长度：1200mm/1000mm/800mm 立体收纳深度：400mm 立体收纳高度：675mm 下柜长度：1200mm/1000mm/800mm 下柜深度：480mm 下柜高度：880mm | H210: 10008.988 | I210: 8200 | J210: 0.48 | K210: =IFERROR(H210,0) | L210: 0.4668 | M210: 0.2101 | N210: 0.2404 | O210: 0.2203 | P210: =IFERROR(IF(K210=0,"待填成本",ROUND(K210/(1-L210),0)),"" ) | Q210: =IFERROR(IF(K210=0,"待填成本",ROUND(K210/(1-M210),0)),"" ) | R210: =IFERROR(IF(K210=0,"待填成本",ROUND(K210/(1-N210),0)),"" ) | S210: =IFERROR(IF(K210=0,"待填成本",ROUND(K210/(1-O210),0)),"" ) | T210: =IFERROR(IF(K210=0,"",(P210-K210)/P210),"" ) | U210: =IFERROR(IF(K210=0,"",(Q210-K210)/Q210),"" ) | V210: =IFERROR(IF(K210=0,"",(R210-K210)/R210),"" ) | W210: =IFERROR(IF(K210=0,"",(S210-K210)/S210),"" ) | AA210: 27.255 | AB210: 10.005 | AC210: 30.475 | AD210: 300 | AE210: 150
A211: 2525013042099 | B211: 餐厅-柜 | C211: 黑胡桃木太空舱餐边柜 |黑胡桃木曜黑餐边柜 | D211: 曜黑柜-整柜-1.7米 | E211: 北美进口FAS级黑胡桃木 | F211: 抽屉围板：实木多层板 台面：黑色岩板 背板：鎏金板 电力轨道：xpower 内嵌电力轨道 顶柜玻璃：灰玻 | G211: 整体长度：1200mm/1000mm/800mm 整体深度：480mm 整体高度：1900mm 顶柜长度：1200mm/1000mm/800mm 顶柜深度：400mm 顶柜高度：355mm 立体收纳长度：1200mm/1000mm/800mm 立体收纳深度：400mm 立体收纳高度：675mm 下柜长度：1200mm/1000mm/800mm 下柜深度：480mm 下柜高度：880mm | H211: 9903.795 | I211: 8133.3333 | J211: 0.48 | K211: =IFERROR(H211,0) | L211: 0.4668 | M211: 0.2103 | N211: 0.2372 | O211: 0.2172 | P211: =IFERROR(IF(K211=0,"待填成本",ROUND(K211/(1-L211),0)),"" ) | Q211: =IFERROR(IF(K211=0,"待填成本",ROUND(K211/(1-M211),0)),"" ) | R211: =IFERROR(IF(K211=0,"待填成本",ROUND(K211/(1-N211),0)),"" ) | S211: =IFERROR(IF(K211=0,"待填成本",ROUND(K211/(1-O211),0)),"" ) | T211: =IFERROR(IF(K211=0,"",(P211-K211)/P211),"" ) | U211: =IFERROR(IF(K211=0,"",(Q211-K211)/Q211),"" ) | V211: =IFERROR(IF(K211=0,"",(R211-K211)/R211),"" ) | W211: =IFERROR(IF(K211=0,"",(S211-K211)/S211),"" ) | AA211: 26.22 | AB211: 9.68875 | AC211: 30.1875 | AD211: 300 | AE211: 150
A212: 2525013042099 | B212: 餐厅-柜 | C212: 黑胡桃木太空舱餐边柜 |黑胡桃木曜黑餐边柜 | D212: 曜黑柜-整柜-1.6米 | E212: 北美进口FAS级黑胡桃木 | F212: 抽屉围板：实木多层板 台面：黑色岩板 背板：鎏金板 电力轨道：xpower 内嵌电力轨道 顶柜玻璃：灰玻 | G212: 整体长度：1200mm/1000mm/800mm 整体深度：480mm 整体高度：1900mm 顶柜长度：1200mm/1000mm/800mm 顶柜深度：400mm 顶柜高度：355mm 立体收纳长度：1200mm/1000mm/800mm 立体收纳深度：400mm 立体收纳高度：675mm 下柜长度：1200mm/1000mm/800mm 下柜深度：480mm 下柜高度：880mm | H212: 9798.6017 | I212: 8066.6667 | J212: 0.48 | K212: =IFERROR(H212,0) | L212: 0.4668 | M212: 0.2104 | N212: 0.2339 | O212: 0.2139 | P212: =IFERROR(IF(K212=0,"待填成本",ROUND(K212/(1-L212),0)),"" ) | Q212: =IFERROR(IF(K212=0,"待填成本",ROUND(K212/(1-M212),0)),"" ) | R212: =IFERROR(IF(K212=0,"待填成本",ROUND(K212/(1-N212),0)),"" ) | S212: =IFERROR(IF(K212=0,"待填成本",ROUND(K212/(1-O212),0)),"" ) | T212: =IFERROR(IF(K212=0,"",(P212-K212)/P212),"" ) | U212: =IFERROR(IF(K212=0,"",(Q212-K212)/Q212),"" ) | V212: =IFERROR(IF(K212=0,"",(R212-K212)/R212),"" ) | W212: =IFERROR(IF(K212=0,"",(S212-K212)/S212),"" ) | AA212: 25.185 | AB212: 9.3725 | AC212: 29.9 | AD212: 300 | AE212: 150
A213: 2525013042099 | B213: 餐厅-柜 | C213: 黑胡桃木太空舱餐边柜 |黑胡桃木曜黑餐边柜 | D213: 曜黑柜-整柜-1.5米 | E213: 北美进口FAS级黑胡桃木 | F213: 抽屉围板：实木多层板 台面：黑色岩板 背板：鎏金板 电力轨道：xpower 内嵌电力轨道 顶柜玻璃：灰玻 | G213: 整体长度：1200mm/1000mm/800mm 整体深度：480mm 整体高度：1900mm 顶柜长度：1200mm/1000mm/800mm 顶柜深度：400mm 顶柜高度：355mm 立体收纳长度：1200mm/1000mm/800mm 立体收纳深度：400mm 立体收纳高度：675mm 下柜长度：1200mm/1000mm/800mm 下柜深度：480mm 下柜高度：880mm | H213: 9693.4083 | I213: 8000 | J213: 0.48 | K213: =IFERROR(H213,0) | L213: 0.4667 | M213: 0.2105 | N213: 0.2305 | O213: 0.2105 | P213: =IFERROR(IF(K213=0,"待填成本",ROUND(K213/(1-L213),0)),"" ) | Q213: =IFERROR(IF(K213=0,"待填成本",ROUND(K213/(1-M213),0)),"" ) | R213: =IFERROR(IF(K213=0,"待填成本",ROUND(K213/(1-N213),0)),"" ) | S213: =IFERROR(IF(K213=0,"待填成本",ROUND(K213/(1-O213),0)),"" ) | T213: =IFERROR(IF(K213=0,"",(P213-K213)/P213),"" ) | U213: =IFERROR(IF(K213=0,"",(Q213-K213)/Q213),"" ) | V213: =IFERROR(IF(K213=0,"",(R213-K213)/R213),"" ) | W213: =IFERROR(IF(K213=0,"",(S213-K213)/S213),"" ) | AA213: 24.15 | AB213: 9.05625 | AC213: 29.6125 | AD213: 300 | AE213: 150
A214: 2525013042099 | B214: 餐厅-柜 | C214: 黑胡桃木太空舱餐边柜 |黑胡桃木曜黑餐边柜 | D214: 曜黑柜-整柜-1.4米 | E214: 北美进口FAS级黑胡桃木 | F214: 抽屉围板：实木多层板 台面：黑色岩板 背板：鎏金板 电力轨道：xpower 内嵌电力轨道 顶柜玻璃：灰玻 | G214: 整体长度：1200mm/1000mm/800mm 整体深度：480mm 整体高度：1900mm 顶柜长度：1200mm/1000mm/800mm 顶柜深度：400mm 顶柜高度：355mm 立体收纳长度：1200mm/1000mm/800mm 立体收纳深度：400mm 立体收纳高度：675mm 下柜长度：1200mm/1000mm/800mm 下柜深度：480mm 下柜高度：880mm | H214: 9568.2683 | I214: 7933.3333 | J214: 0.48 | K214: =IFERROR(H214,0) | L214: 0.4667 | M214: 0.2104 | N214: 0.2241 | O214: 0.204 | P214: =IFERROR(IF(K214=0,"待填成本",ROUND(K214/(1-L214),0)),"" ) | Q214: =IFERROR(IF(K214=0,"待填成本",ROUND(K214/(1-M214),0)),"" ) | R214: =IFERROR(IF(K214=0,"待填成本",ROUND(K214/(1-N214),0)),"" ) | S214: =IFERROR(IF(K214=0,"待填成本",ROUND(K214/(1-O214),0)),"" ) | T214: =IFERROR(IF(K214=0,"",(P214-K214)/P214),"" ) | U214: =IFERROR(IF(K214=0,"",(Q214-K214)/Q214),"" ) | V214: =IFERROR(IF(K214=0,"",(R214-K214)/R214),"" ) | W214: =IFERROR(IF(K214=0,"",(S214-K214)/S214),"" ) | AA214: 23.83375 | AB214: 8.74 | AC214: 29.325 | AD214: 300 | AE214: 150
...

Sheet ② 高定报价单
A1: 畔色 高定报价单 — 全新定制，逐部位填写材料和尺寸，自动出报价
A2: ↓ 填写订单基本信息后，在下方按部位逐行录入材料和尺寸，底部自动汇总出报价
A3: 客户名称 | C3: 订单日期
A4: 产品类目 | C4: 家具大小等级 | D4: 小型 / 中型 / 大型
A5: 主材 | C5: 制作件数 | D5: 1
A6: 产品名称
A7: 提示：「对应材料」填写名称后，「材料单价」会从⚙️参数设置自动查找。如未找到可手动填单价。尺寸单位：米(m)，数量为件/块/付等。
A8: 材料分类 | B8: 部位描述 | C8: 对应材料（名称与参数设置表一致） | D8: 材料单价（自动查，可手改） | E8: 长(m) | F8: 宽/高(m) | G8: 数量 | H8: 成本价（自动） | I8: 备注
D9: =IFERROR(VLOOKUP(C9,'⚙️ 参数设置'!$B:$D,3,0),"") | H9: =IFERROR(IF(OR(C9="",G9=""),0,D9*IF(E9="",1,E9)*IF(F9="",1,F9)*IF(G9="",1,G9)),0)
D10: =IFERROR(VLOOKUP(C10,'⚙️ 参数设置'!$B:$D,3,0),"") | H10: =IFERROR(IF(OR(C10="",G10=""),0,D10*IF(E10="",1,E10)*IF(F10="",1,F10)*IF(G10="",1,G10)),0)
D11: =IFERROR(VLOOKUP(C11,'⚙️ 参数设置'!$B:$D,3,0),"") | H11: =IFERROR(IF(OR(C11="",G11=""),0,D11*IF(E11="",1,E11)*IF(F11="",1,F11)*IF(G11="",1,G11)),0)
D12: =IFERROR(VLOOKUP(C12,'⚙️ 参数设置'!$B:$D,3,0),"") | H12: =IFERROR(IF(OR(C12="",G12=""),0,D12*IF(E12="",1,E12)*IF(F12="",1,F12)*IF(G12="",1,G12)),0)
D13: =IFERROR(VLOOKUP(C13,'⚙️ 参数设置'!$B:$D,3,0),"") | H13: =IFERROR(IF(OR(C13="",G13=""),0,D13*IF(E13="",1,E13)*IF(F13="",1,F13)*IF(G13="",1,G13)),0)
D14: =IFERROR(VLOOKUP(C14,'⚙️ 参数设置'!$B:$D,3,0),"") | H14: =IFERROR(IF(OR(C14="",G14=""),0,D14*IF(E14="",1,E14)*IF(F14="",1,F14)*IF(G14="",1,G14)),0)
D15: =IFERROR(VLOOKUP(C15,'⚙️ 参数设置'!$B:$D,3,0),"") | H15: =IFERROR(IF(OR(C15="",G15=""),0,D15*IF(E15="",1,E15)*IF(F15="",1,F15)*IF(G15="",1,G15)),0)
D16: =IFERROR(VLOOKUP(C16,'⚙️ 参数设置'!$B:$D,3,0),"") | H16: =IFERROR(IF(OR(C16="",G16=""),0,D16*IF(E16="",1,E16)*IF(F16="",1,F16)*IF(G16="",1,G16)),0)
D17: =IFERROR(VLOOKUP(C17,'⚙️ 参数设置'!$B:$D,3,0),"") | H17: =IFERROR(IF(OR(C17="",G17=""),0,D17*IF(E17="",1,E17)*IF(F17="",1,F17)*IF(G17="",1,G17)),0)
D18: =IFERROR(VLOOKUP(C18,'⚙️ 参数设置'!$B:$D,3,0),"") | H18: =IFERROR(IF(OR(C18="",G18=""),0,D18*IF(E18="",1,E18)*IF(F18="",1,F18)*IF(G18="",1,G18)),0)
D19: =IFERROR(VLOOKUP(C19,'⚙️ 参数设置'!$B:$D,3,0),"") | H19: =IFERROR(IF(OR(C19="",G19=""),0,D19*IF(E19="",1,E19)*IF(F19="",1,F19)*IF(G19="",1,G19)),0)
D20: =IFERROR(VLOOKUP(C20,'⚙️ 参数设置'!$B:$D,3,0),"") | H20: =IFERROR(IF(OR(C20="",G20=""),0,D20*IF(E20="",1,E20)*IF(F20="",1,F20)*IF(G20="",1,G20)),0)
... D43: =IFERROR(VLOOKUP(C43,'⚙️ 参数设置'!$B:$D,3,0),"") | H43: =IFERROR(IF(OR(C43="",G43=""),0,D43*IF(E43="",1,E43)*IF(F43="",1,F43)*IF(G43="",1,G43)),0)
E45: 厂内木材+人工成本 | H45: =SUMIF(A9:A43,"木材成本",H9:H43)+SUMIF(A9:A43,"工厂人工费用",H9:H43)
E46: 工厂利润 (系数×木材人工成本) | H46: =I45*'⚙️ 参数设置'!$H$3
E47: 工厂木作总成本 | H47: =I45+I46
E48: 配件材料成本（畔色采购） | H48: =SUMIF(A9:A43,"配件材料成本",H9:H43)
E49: 打包费 | H49: =IFERROR(VLOOKUP("打包费用-"&D4,'⚙️ 参数设置'!$B:$D,3,0)*D6,0)
E50: 运费 | H50: =IFERROR(VLOOKUP("运费-"&D4,'⚙️ 参数设置'!$B:$D,3,0)*D6,0)
E51: 安装费 | H51: =IFERROR(VLOOKUP("上门安装费-"&D4,'⚙️ 参数设置'!$B:$D,3,0)*D6,0)
E52: 畔色总成本 | H52: =I47+I48+I49+I50+I51
E54: 高定最终报价（含15%利润） | H54: =ROUND(I52/(1-'⚙️ 参数设置'!$H$4),0)
